Workbook

Sheet Cockpit
A1: Cockpit – Anforderungen Autostrom / LKW-Laden
A2: Status, Erfüllung und Dokumentationsqualität auf einen Blick
A3: Alle Kennzahlen rechnen direkt aus den Registern „Anforderungen“ und „Komponenten“ – inklusive des vollständigen Bieterfragenkatalogs.
A5: Kennzahl | B5: Wert
A6: Anforderungen gesamt | B6: =COUNTA(Anforderungen!$B$7:$B$2000) -> 1382
A7: Erfasst | B7: =COUNTIF(Anforderungen!$K$7:$K$2000,"erfasst") -> 1364
A8: Bewertet | B8: =COUNTIF(Anforderungen!$K$7:$K$2000,"bewertet") -> 3
A9: Erfüllt | B9: =COUNTIF(Anforderungen!$K$7:$K$2000,"erfüllt") -> 10
A10: davon vollständig dokumentiert | B10: =COUNTIFS(Anforderungen!$K$7:$K$2000,"erfüllt",Anforderungen!$L$7:$L$2000,"<>",Anforderungen!$M$7:$M$2000,"<>") -> 10
A11: Trifft nicht zu | B11: =COUNTIF(Anforderungen!$K$7:$K$2000,"trifft nicht zu") -> 5
A12: Erfüllt ohne Datum | B12: =COUNTIFS(Anforderungen!$K$7:$K$2000,"erfüllt",Anforderungen!$L$7:$L$2000,"") -> 0
A13: Erfüllt ohne Nachweis / Notiz | B13: =COUNTIFS(Anforderungen!$K$7:$K$2000,"erfüllt",Anforderungen!$M$7:$M$2000,"") -> 0
A14: Trifft nicht zu ohne Begründung | B14: =COUNTIFS(Anforderungen!$K$7:$K$2000,"trifft nicht zu",Anforderungen!$M$7:$M$2000,"") -> 2
A15: Erfüllungsgrad | B15: =IFERROR(COUNTIF(Anforderungen!$K$7:$K$2000,"erfüllt")/(COUNTA(Anforderungen!$B$7:$B$2000)-COUNTIF(Anforderungen!$K$7:$K$2000,"trifft nicht zu")),0) -> 0.0072621641
A16: Dokumentationsgrad erfüllt | B16: =IFERROR(COUNTIFS(Anforderungen!$K$7:$K$2000,"erfüllt",Anforderungen!$L$7:$L$2000,"<>",Anforderungen!$M$7:$M$2000,"<>")/COUNTIF(Anforderungen!$K$7:$K$2000,"erfüllt"),0) -> 1
A17: Komponenten/Schnittstellen erfüllt | B17: =COUNTIF(Komponenten!$J$6:$J$29,"erfüllt") -> 0
A18: Bieterfragen im Register | B18: =COUNTIF(Anforderungen!$C$7:$C$2000,"Bieterfragenkatalog") -> 663
A19: Offene Zuordnungen (Komponente/Partner) | B19: =COUNTIF(Anforderungen!$J$7:$J$2000,"Zuordnung prüfen")+COUNTIF(Anforderungen!$I$7:$I$2000,"Zuordnung prüfen") -> 460

Sheet Anforderungen
A1: Anforderungen – Autostrom / LKW-Laden
A2: Zentrales Anforderungsregister: Der Block „Erfüllung / Nachweis“ verbindet Status, tatsächliches Erfüllungsdatum und Dokumentation.
A3: Logik: erfasst → bewertet → erfüllt. Bei „erfüllt“ sind Datum und Nachweis/Notiz erforderlich, bei „trifft nicht zu“ eine Begründung. Gelb markierte Zuordnungen (Partner/Komponente) sind fachlich zu prüfen.
B5: Anforderung & Zuordnung | K5: Erfüllung / Nachweis (Konzept)
B6: ID | C6: Dokument | D6: Fundstelle | E6: Themenfeld | F6: Kernaussage | G6: Anforderung / Frage (Originaltext) | H6: Bemerkung | I6: Partner | J6: Komponente(n) | K6: Status | L6: Erfüllt am | M6: Nachweis / Notiz
B7: ANF-001 | C7: Betreibervertrag | D7: § 25 (1) | E7: Reservierung | F7: OCPI Schnittstelle | G7: Der Auftragnehmer stellt sicher, dass die Reservierung von Ladepunkten über Reservierungsplattformen während der Laufzeit dieses Vertrags möglich ist. Hierzu hält der Auftragnehmer eine auf OCPI (Open Charge Point Interface) basierende Schnittstelle vor, über die sich Reservierungsplattformen nach Maßgabe der folgenden Absätze anbinden können. | I7: eRound | J7: OCPI Buchungskalender | K7: erfasst
B8: ANF-002 | C8: Betreibervertrag | D8: § 25 (2) | E8: Reservierung | F8: OCPI Kostenfrei | G8: Der Auftragnehmer ist verpflichtet, jeder Reservierungsplattform die Anbindung über die in Absatz 1 genannte Schnittstelle kostenfrei zu ermöglichen, soweit die Reservierungsplattform die folgenden Mindestvoraussetzungen erfüllt: | I8: eRound | J8: OCPI Buchungskalender | K8: erfasst
B9: ANF-003 | C9: Betreibervertrag | D9: § 25 (2) a | E9: Reservierung | F9: OCPI Kostenfrei | G9: Die Reservierungsplattform stellt dem Auftragnehmer für die Anbindung der Reservierungsplattform keine Anbindungskosten in Rechnung | I9: eRound | J9: Anbindung | K9: erfasst
B10: ANF-004 | C10: Betreibervertrag | D10: § 25 (2) b | E10: Reservierung | F10: Anbindung verpflichtend, wenn alle AN angebunden werden oder AG2 auffordert | G10: Die Reservierungsplattform ermöglicht Endnutzern und Mobilitätsdienstleistern die Reservierung von Ladepunkten im gesamten Gebiet der Bundesrepublik Deutschland gegen ein angemessenes Entgelt. Ermöglicht eine Reservierungsplattform eine Reservierung von Ladepunkten nur in Teilen des Gebiets der Bundesrepublik Deutschland, ist der Auftragnehmer zur Anbindung nur verpflichtet, wenn der Auftraggeber 2 den Auftragnehmer hierzu auffordert. | I10: eRound | J10: OCPI Buchungskalender | K10: erfasst
B11: ANF-005 | C11: Betreibervertrag | D11: § 25 (2) c | E11: Reservierung | F11: Reservierung mit Vorlauf von max. 7 Tagen und min. 15 min. Kostenfreie Stornierung und Änderung bis 30min vorher. Kennzeichenabgleich zur Unterbindung von Doppelbuchungen. | G11: Die Reservierungsplattform ermöglicht eine Reservierung von Ladepunkten mit einer Vorlaufzeit von maximal 7 Kalendertagen und mindestens 15 Minuten. Eine kostenfreie Stornierung oder Änderung der Reservierung über die Reservierungsplattform muss, soweit möglich, bis zu 30 Minuten vor Beginn des in der Reservierung angegebenen Startzeitpunkts möglich sein. Die Reservierungsplattform stellt durch geeignete Vorkehrungen (z. B. durch einen Kennzeichenabgleich) sicher, dass für einen E-LKW in einem Zeitintervall nur ein Ladepunkt reserviert wird. | I11: eRound | J11: OCPI Buchungskalender | K11: erfasst
B12: ANF-006 | C12: Betreibervertrag | D12: § 25 (2) d | E12: Reservierung | F12: Entschädigung an AN von der Reservierungsplattform i.H.v. mind. 30€ nach 15/30 min Wartezeit bei No-Show. | G12: Die Reservierungsplattform entschädigt den Auftragnehmer in angemessener Höhe, wenn an der reservierten Ladeeinrichtung ab dem in der Reservierung angegebenen Startzeitpunkt und Ablauf einer Wartezeit von 15 Minuten bei Ladepunkten zum Zwischenladen, bzw. 30 Minuten bei Ladepunkten zum Übernachtladen (sog. „no-show“) kein Start eines Ladevorgangs erfolgt. Die Entschädigung des Auftragnehmers ist angemessen, wenn der Auftragnehmer im Fall eines „no-show“ mindestens € 30,00 erhält. | I12: eRound | J12: Abrechnungskomponente | K12: erfasst
B13: ANF-007 | C13: Betreibervertrag | D13: § 25 (3) | E13: Reservierung | F13: Anpassung an Marktstandards mit 2 Monaten Vorlauf. | G13: Der Auftraggeber 2 ist berechtigt, die in Absatz 2 definierten Mindestvoraussetzungen im Fall abweichender Marktstandards mit einer Vorlaufzeit von zwei Monaten anzupassen | I13: eRound | J13: OCPI Buchungskalender | K13: erfasst
B14: ANF-008 | C14: Betreibervertrag | D14: § 25 (4) | E14: Reservierung | F14: Ladepunkte an einem Standort können von der Reservierung ausgenommen werden. | G14: Der Auftragnehmer kann CCS- und MCS-Ladepunkten an einem Standort von der Reservierungsmöglichkeit ausnehmen. | I14: eRound | J14: OCPI Buchungskalender | K14: erfasst
B15: ANF-009 | C15: Betreibervertrag | D15: § 25 (5) | E15: Zufahrt & Schranke | F15: Bauliche Maßnahme zur Reservierung an jedem Ladepunkt. | G15: Der Auftragnehmer hat geeignete Vorkehrungen, insbesondere die in Vertragsanlage 4: Leistungsbeschreibung Errichtung vorgesehenen baulichen Maßnahmen, zu treffen, um ein anderweitiges Laden an dem Ladepunkt der Ladeeinrichtung während des reservierten Zeitraums zu verhindern. | H15: Schrankensteuerung | I15: Schrankenhersteller | J15: Schrankenanlage | K15: erfasst
B16: ANF-010 | C16: Betreibervertrag | D16: § 25 (6) | E16: Reservierung | F16: Mindestens 40% der Ladepunkte müssen reserviert werden können. | G16: Verstößt der Auftragnehmer gegen die Pflicht nach Absatz 1, wird für jeden Standort, an dem die Reservierung von Ladepunkten aufgrund des Verstoßes gegen die Pflicht nach Absatz 1 nicht möglich ist, eine Vertragsstrafe fällig. Die Reservierung von Ladepunkten an einem Standort gilt als nicht möglich, wenn mindestens 40 % der Ladepunkte an dem Standort nicht reserviert werden können. Die Höhe der Vertragsstrafe beträgt € 2.500,00 für jeden Kalendertag, an dem die Reservierung von Ladepunkten an einem Standort nicht möglich ist, höchstens jedoch € 40.000,00 pro Kalendermonat und pro Standort. | H16: 40% der Schranken offen lassen? | I16: eRound | J16: OCPI Buchungskalender | K16: erfasst
B17: ANF-011 | C17: Betreibervertrag | D17: § 31 (1) | E17: Authentifizierung & Zugang | F17: Es muss Adhoc geladen werden können | G17: Der Auftragnehmer ist verpflichtet, potenziellen Endnutzern diskriminierungsfrei zu angemessenen Bedingungen ein Ad-hoc-Laden (punktuelles Aufladen i. S. d. AFIR) zu ermöglichen, soweit es ihm zumutbar ist (z. B. mit Blick auf die Bonität des Endnutzers). | H17: Adhoc muss möglich sein -> Schranke -> wie? | I17: eRound / SCS | J17: Authentifizierungskomponente / Schrankensteuerung | K17: erfasst
B18: ANF-012 | C18: Betreibervertrag | D18: § 38 (1) | E18: Nutzungszeit & Entgelte | F18: Blockadeentgelte und maximale Nutzungsdauer | G18: Start- und zeitabhängige Entgelte dürfen nicht erhoben werden. Dies gilt nicht für vertraglich vereinbarte Blockadeentgelte, die nach Ablauf einer maximalen Nutzungszeit vom Endnutzer bzw. Mobilitätsdienstleister unabhängig davon, welches der Zugangsmodelle des § 30 Abs. 2 gewählt wird, erhoben werden. Die maximale Nutzungszeit beginnt mit Beginn des Ladevorgangs und beträgt | H18: Schnittstelle Nutzungszeit | I18: eRound | J18: OCPI Buchungskalender | K18: erfasst
B19: ANF-013 | C19: Betreibervertrag | D19: § 38 (1) a | E19: Nutzungszeit & Entgelte | F19: Maximale Nutzungsdauer Zwischenladen ist 1h. | G19: bei MCS-Ladepunkten und CCS-Ladepunkten zum Zwischenladen 1 Stunde. | H19: Schnittstelle Nutzungszeit | I19: eRound | J19: OCPI Buchungskalender | K19: erfasst
B20: ANF-014 | C20: Betreibervertrag | D20: § 38 (1) b | E20: Nutzungszeit & Entgelte | F20: Maximale Nutzungsdauer Übernachtladen ist 12h. | G20: bei CCS-Ladepunkten zum Übernachtladen und MCS- oder CCS-Ladepunkte zum Zwischenladen, die zum Übernachtladen freigegeben wurden, 12 Stunden. | H20: Schnittstelle Nutzungszeit | I20: eRound | J20: OCPI Buchungskalender | K20: erfasst
B21: ANF-015 | C21: Betreibervertrag | D21: § 38 (2) | E21: Nutzungszeit & Entgelte | F21: Bei nidriger Auslastung kann die maximale Nutzungszeit vom AN verlängert werden. Bei nachfolgender Reservierung kann die maximale Nutzungszeit verkürzt werden. Bei Verkürzung zusätzliche Karenzzeit vor Blockadeentgeld von 5min. | G21: Der Auftragnehmer kann die maximalen Nutzungszeiten in Zeiten geringer Auslastung verlängern. Zudem kann er mit der Gestattung der Nutzung von MCS-Ladepunkten und CCS-Ladepunkten zum Zwischenladen dem Endnutzer bzw. Mobilitätsdienstleister auch ausdrücklich eine kürzere maximale Nutzungszeit einräumen, wenn wegen nachfolgender Reservierungen die maximale Nutzungszeit nach Absatz 1 lit. a nicht eingeräumt werden kann. In den Fällen des Satzes 2 ist dem Endnutzer bzw. Mobilitätsdienstleister zusätzlich eine Karenzzeit zum Verlassen des Ladeplatzes von 5 Minuten einzuräumen, nach deren Ablauf erst ein Blockadeentgelt erhoben werden darf | H21: SCS: Reaktionszeit System | I21: eRound | J21: OCPI Buchungskalender | K21: erfasst
B22: ANF-016 | C22: Betreibervertrag | D22: § 38 (3) | E22: Nutzungszeit & Entgelte | F22: Maximale Nutzungszeit endet mit Ablauf Reservierung. Maximale Nutzungsdauer kann vom AN verlängert werden. | G22: Hat ein Mobilitätsdienstleister einen Ladepunkt reserviert, so endet die maximale Nutzungszeit mit dem Ablauf des reservierten Zeitraums, auch wenn der Ladeplatz erst später belegt wurde, es sei denn, der Betreiber räumt ihm eine längere maximale Nutzungszeit ein. | I22: eRound | J22: OCPI Buchungskalender | K22: erfasst
B23: ANF-017 | C23: Betreibervertrag | D23: § 38 (4) | E23: Nutzungszeit & Entgelte | F23: Ladestart 15min Wartezeit Blockadeentgeld ggf. Pönalisierung Entfall maximale Nutzungsdauer | G23: Wird ein Ladevorgang nicht innerhalb von 15 Minuten nach Besetzung des Stellplatzes gestartet, entfällt die maximale Nutzungszeit und es kann ein Blockadeentgelt erhoben werden. | I23: eRound / SCS | J23: OCPI Buchungskalender / Abrechnungskomponente / Belegungsdetektion / Pönalisierungssystem | K23: erfasst
B24: ANF-018 | C24: Betreibervertrag | D24: § 38 (5) | E24: Nutzungszeit & Entgelte | F24: Kein Blockadeentgeld während Nachtruhezeiten, Sonn- und Feiertage der Bundesländer. | G24: An Sonn- und Feiertagen sowie zwischen 22 Uhr abends und 5 Uhr morgens (Nachtruhezeit) darf der Auftragnehmer für CCS-Ladepunkte zum Übernachtladen bzw. MCS- und CCS- Ladepunkten zum Zwischenladen, die zum Übernachtladen freigegeben wurden, keine Blockadeentgelte erheben. Hat der Ladevorgang bereits vor Beginn der Nachtruhezeiten begonnen und endet die maximale Nutzungszeit nach Absatz 1 während der Nachtruhezeit, so werden Blockadeentgelte mithin erst nach Ende der Nachtruhezeit berechnet. Satz 1 und 2 gelten entsprechend für Sonntage und gesetzliche Feiertage in dem Bundesland, in dem der jeweilige Standort gelegen ist. | H24: Einfluss auf Reservierung? | I24: eRound | J24: OCPI Buchungskalender | K24: erfasst
B25: ANF-019 | C25: Betreibervertrag | D25: § 38 (6) | E25: Nutzungszeit & Entgelte | F25: Blockadeentgeld Höhe 0,50€ / 0,15€ pro Min. | G25: Die Höhe des Blockadeentgelts darf bei MCS-Ladepunkten und bei CCS-Ladepunkten zum Zwischenladen maximal 0,50 €/Minute und bei CCS-Ladepunkten bzw. CCS- und MCS- Ladepunkten zum Zwischenladen, während des Zeitraums, für den sie zum Übernachtladen freigegeben wurden, maximal 0,15 €/Minute betragen. Das vereinnahmte Blockadeentgelt steht dem Auftragnehmer zu. | I25: eRound | J25: Abrechnungskomponente | K25: erfasst
B26: ANF-020 | C26: Betreibervertrag | D26: § 38 (7) | E26: Nutzungszeit & Entgelte | F26: Änderungen an maximaler Nutzungsdauer, Blockadeentgelt und Sperrzeiten mit Vorlauf möglich. | G26: Der Auftraggeber 2 kann die maximale Höhe der Blockadeentgelte nach Absatz 6 und die maximalen Nutzungszeiten bzw. Sperrzeiten für die Erhebung eines Blockadeentgeltes nach den Absätzen 1 bis 4 während der Laufzeit des Vertrags mit einer Frist von vier Monaten auf den Beginn eines Quartals schriftlich mit Wirkung gegenüber dem Auftragnehmer anpassen. Absenkungen der Höhe oder Verlängerungen die maximalen Nutzungszeiten bzw. Sperrzeiten sind nur mit Zustimmung des Auftragnehmers zulässig. Die Zustimmung gilt als erteilt, sofern der Auftragnehmer dem Auftraggeber 2 nicht innerhalb von zwei Wochen nach Mitteilung der geplanten Absenkung in Textform widerspricht. | I26: eRound | J26: Abrechnungskomponente | K26: erfasst
B27: ANF-021 | C27: Betreibervertrag | D27: § 38 (8) | E27: Nutzungszeit & Entgelte | F27: Mindestabnahmemenge und Vergütung bei Unterschreitung. | G27: Für jeden Übernachtladevorgang ist eine Mindestabnahmemenge von 150 kWh vorzusehen, dies gilt auch für MCS- und CCS-Ladepunkte, die nach Maßgabe dieses Vertrags zum Übernachtladen freigegeben werden. Wird die Mindestabnahmemenge nicht erreicht, so ist für die Differenz zwischen der tatsächlich abgenommenen Strommenge und der vertraglich vorgesehenen Mindestabnahmemenge vom Endnutzer bzw. Mobilitätsdienstleister eine Entschädigung in Höhe von 30 ct/kWh an den Auftragnehmer zu leisten. Die Entschädigungshöhe kann vom Auftraggeber 2 in Absprache mit dem Auftragnehmer zu einem späteren Zeitpunkt angepasst werden. | I27: eRound | J27: Abrechnungskomponente | K27: erfasst
B28: ANF-022 | C28: Betreibervertrag | D28: § 38 (9) | E28: Nutzungszeit & Entgelte | F28: Warnung NutzerIn vor Blockadeentgeld | G28: Endnutzer sind über eine gut sichtbare Beschilderung darauf hinzuweisen, dass der Stellplatz nach Abschluss des Ladevorgangs unverzüglich freizugeben ist; der Text der Beschilderung bedarf der Zustimmung des Auftraggebers 2. Zusätzlich soll der Endnutzer über eine App oder – falls er eine solche nicht nutzt – an der Ladeeinrichtung, vor Erhebung von Blockadeentgelt oder einer Vertragsstrafe einen Hinweis erhalten, dass der Ladevorgang beendet wurde und der Ladeplatz unverzüglich zu räumen ist | H28: ggf. Mitteilung? | I28: eRound | J28: Abrechnungskomponente / Beschilderung | K28: trifft nicht zu | L28: 46259 | M28: ggf. Thema für eRound ansonsten Beschilderung -> Bau GU
B29: ANF-023 | C29: Betreibervertrag | D29: § 42 (5) | E29: Betrieb & Auslastung | F29: Updates verpflichtend. | G29: Der Auftragnehmer ist auf Aufforderung des Auftraggebers 2 verpflichtet, die Ladeeinrichtungen technisch und/oder mit Blick auf die Software (insbesondere Schnittstellen und Protokolle) weiterzuentwickeln und zu verbessern. Die Erstattung der tatsächlich erforderlichen Kosten (zuzüglich angemessener Zuschläge für allgemeine Geschäftskosten, Wagnis und Gewinn) erfolgt nach den Regelungen über geänderte oder zusätzliche Leistungen nach § 40. | I29: Alpitronic | J29: Ladeeinrichtung | K29: trifft nicht zu | L29: 46260 | M29: Betrifft LIS
B30: ANF-024 | C30: Betreibervertrag | D30: § 22 (3) | E30: Betrieb & Auslastung | F30: Bei nidriger Auslastung: Zwischenladepunkte können zwischen 17 und 6 Uhr für Übernachtladen freigegeben werden. Aber mind. 40% Zwischenladepunkte, aber mind. 2 MCS und 1 CCS. | G30: CCS- und MCS-Ladepunkte zum Zwischenladen sind bei fehlender Auslastung ab 17:00 Uhr sowie an Wochenenden zum Übernachtladen freizugegeben. Es müssen jedoch auch in dieser Zeit 40 %, aber mindestens zwei MCS-Ladepunkte bzw. ein CCS-Ladepunkt, zum Zwischenladen für das Zwischenladen freigehalten werden. An Standorten, an denen nur ein MCS-Ladepunkt vorhanden ist, ist dieser für das Zwischenladen freizuhalten. Der Auftragnehmer hat sicherzustellen, dass die MCS- und CCS-Ladepunkte zum Zwischenladen ab 06:00 Uhr wieder für das Zwischenladen bereitstehen. Auftragnehmer und Auftraggeber 2 können sich je nach Auslastung der Ladepunkte auf abweichende Vorgaben zur Freigabe von Ladepunkten zum Zwischenladen einigen. | H30: 40% Zwischenladen | I30: eRound / SCS | J30: OCPI Buchungskalender / Dynamische Anzeige | K30: erfüllt | L30: 46259 | M30: eRound regelt - SCS zeigt an
B31: ANF-025 | C31: Betreibervertrag | D31: § 4 (52) | E31: Reservierung | F31: Mindestens AN plus ein weiterer. | G31: "Reservierungssystem“: Ein System zur Reservierung von Ladepunkten, das Mobilitätsdienstleistern ermöglicht, Ladepunkte bei dem Auftragnehmer und mindestens einem weiteren Ladepunktbetreiber zu reservieren. | H31: Mehr als 1 Anbieter | I31: Autostrom+ | J31: Anbindung | K31: bewertet
B32: ANF-026 | C32: Vertragsanlage 4 | D32: § 3.13.2 | E32: Zufahrt & Schranke | F32: Schrankenanlage auf Schrankeninsel | G32: Anforderungen an Lade-, Schrankeninseln und physische Zufahrtbeschränkungen | I32: Schrankenhersteller | J32: Schrankenanlage | K32: erfasst | L32: 46259 | M32: Schranke auf Schrankeninsel geplant
B33: ANF-027 | C33: Vertragsanlage 4 | D33: § 3.13.2 (1) | E33: Zufahrt & Schranke | F33: Schranke an Einfahrt Ladepunkt und Ausfahrt Ladepunkt. Bei Schrägparken Poller? | G33: Für den Zweck einer geordneten Zufahrt und Abfahrt sowie zur Sicherstellung der Verfügbarkeit der Ladeinfrastruktur sind Ladeinseln, Schrankeninseln sowie physische Zufahrtsbeschränkungen zu errichten. Diese dienen der Vermeidung unbefugter Inanspruchnahmen der Ladeplätze durch nichtladende Fahrzeuge aus allen Fahrtrichtungen und gewährleisten den bestimmungsgemäßen Betrieb der Ladeinfrastruktur. | H33: Schranke gefordert aus allen Richtungen | I33: Schrankenhersteller | J33: Schrankenanlage | K33: erfüllt | L33: 46259 | M33: Schranken auf beiden Seiten gepplant
B34: ANF-028 | C34: Vertragsanlage 4 | D34: § 3.13.4 | E34: Anzeige & Beschilderung | F34: Darstellung statischer und dynamischer Infos. | G34: Jeder Ladeplatz ist mit einer Kennzeichnung bzw. Anzeige mit folgenden Informationen auszurüsten: - Ladeplatznummer (Schild mit schwarzer Nummer auf weißem retroreflektierendem Hintergrund mit der Reflektionsklasse RA1 A) - Dynamische Anzeige mit - Typ des Ladeplatzes (MCS, CCS-Zwischenladen, CCS-Übernachtladen) - Leistung der Ladesäule - Status (verfügbar, reserviert ab XX:XX Uhr, belegt, außer Betrieb) - optional: Kennzeichen/Reservierungsnummer - Der Status des Ladeplatzes ist zusätzlich zur dynamischen Anzeige über eine farbcodierte Statuskennzeichnung darzustellen (Grün = verfügbar, Gelb = reserviert, Rot = belegt / außer Betrieb). Die farbcodierte Kennzeichnung dient der optischen Erkennbarkeit des Betriebszustands, insbesondere bei Ausfall der digitalen Anzeige. Die Platzierung der Kennzeichnung und Anzeigen hat bei Parkständen in Schrägaufstellung gut sichtbar auf der Schrankeninsel zu erfolgen. Die Platzierung der Kennzeichnung und Anzeigen hat bei Parkständen in Längsaufstellung gut sichtbar, dem entsprechenden Ladeplatz zugehörig im Bereich der Ladeinsel bzw. Ladesäule zu erfolgen. Weitere Anforderungen im Zusammenhang mit dynamischen Anzeigen sind der Vertragsanlage 6: Anforderungen an die Ladeinfrastruktur zu entnehmen. | H34: LED Anzeigen | I34: eRound / SCS | J34: Dynamische Anzeige | K34: erfüllt | L34: 46259 | M34: LIS zeigt Zustand an, Rest auf Anzeige
B35: ANF-029 | C35: Vertragsanlage 4 | D35: § 3.13.5 | E35: Zufahrt & Schranke | G35: Zur Gewährleistung eines sicheren und zuverlässigen Betriebs sind Schrankenanlagen und automatische Poller gemäß den folgenden technischen Anforderungen auszuführen: - robuste Witterungsbeständige und korrosionsgeschützte Ausführung für den ganzjährigen Einsatz im Außenbereich - automatisches Öffnen nach Abschluss des Ladevorgangs oder bei entsprechender Systemfreigabe - Erkennung der Fahrzeugposition sowie von Hindernissen vor dem Schließvorgang zur Vermeidung von Kollisionen - manuelle Notentriegelung durch autorisiertes Personal, um die Betriebsfähigkeit auch im Stör- oder Spannungsfall sicherzustellen - Integration in das zentrale Steuerungssystem (Backend oder lokales Steuergerät) zur Überwachung, Steuerung und Protokollierung der Schranken- und Pollerfunktionen - Schrankenbäume sind gemäß geltender Vorschriften mit rot-weißer Schraffierung zu kennzeichnen - Ausstattung von Schrankenbäumen und automatischen Pollern mit integrierter Beleuchtung zur Verbesserung der Sichtbarkeit und Betriebssicherheit; dabei sind die Vorgaben zur Blendwirkung gemäß ERS zu beachten Weitere Anforderungen für den Betrieb der Schranken sind der Vertragsanlage 6: Anforderungen an die Ladeinfrastruktur zu entnehmen. | H35: Öffnen bei Ladevorgangs-Ende wiederspricht sich mit Vertragsanlage 6 §10 Abs 2 Und funktioniert für Poller nicht -> da LKW darüber steht. Einheitliche Ansteuerung reduziert komplexität Bei Partnern | I35: Schrankenhersteller / SCS / eRound | J35: Schrankenanlage | K35: erfüllt | L35: 46260 | M35: Sicherheitseinrichtung geplant LED in Schrankenbaum geplant Integration des Schrankenstatus in eRound
B36: ANF-030 | C36: Vertragsanlage 4 | D36: § 3.13.2.2 | E36: Zufahrt & Schranke | G36: Bei Parkständen in Längsaufstellung sind automatisch versenkbare Poller zur Zufahrtsbeschränkung vorzusehen. Pro Parkstand sind drei Poller so anzuordnen, dass Fehlbelegungen ausgeschlossen sind. Die Abstände der Poller untereinander sowie zur Fahrgasse ergeben sich aus der Referenzplanung (Anhang 1a: Referenzplanung Längs- und Schrägparken). Das Ein- und Ausfahren zum Ladeplatz muss jederzeit gewährleistet bleiben, auch wenn die benachbarten Stellplätze durch ausgefahrene Poller gesichert sind. Die Dauer der Öffnungs- und Schließvorgänge ist auf das technisch mögliche Minimum zu begrenzen, um einen unterbrechungsarmen Verkehrsfluss sicherzustellen. Die Regelbreite der Parkstände muss 4,50 m betragen, die Länge entspricht den Vorgaben gemäß ERS für Längsparker von 25,00 m. Ergeben sich aufgrund der örtlichen Bestandsituation Abweichungen von der Regelbreite, ist die Befahrbarkeit stets durch einen Schleppkurvennachweis zu belegen. Die Poller sind elektrisch oder hydraulisch versenkbar auszuführen und müssen über eine automatische Höhenverstellung verfügen. Das Absenken erfolgt im Regelbetrieb ausschließlich bei autorisiertem Zugang (Ladevorgang oder Reservierung). Nach Beendigung des Ladevorgangs und nach erfolgter Ausfahrt des Fahrzeuges müssen sich Poller automatisch wieder heben. Eine Notabsenkung bei Ausfall muss durch autorisiertes Personal jederzeit möglich sein. Die Poller müssen widerstandsfähig gegen Anprall und sonstige auf Rastplätzen zu erwartende Einwirkungen sein sowie frost- und salzbeständig ausgeführt werden. Zudem ist ein Schutz gegen Fremdsteuerung und Manipulation sicherzustellen. Die Steuerung der Poller muss in das übergeordnete Zugangskontrollsystem integrierbar sein. Die Erkennbarkeit des Hindernissesist stets sicherzustellen. Die Poller sind zu beleuchten. Die Ladesäule ist im Randbereich des Stellplatzes in einem praktikablen Abstand zum fahrzeugseitigen Ladeanschluss zu positionieren. Die Fläche um die Ladesäule ist in Betonbauweise auszuführen und mit zweckdienlichen Mitteln gegen Anprall und sonstige übliche Einwirkungen auf Rastplätzen zu sichern. Befindet sich im Randbereich bereits eine Bordanlage, ist eine zusätzliche Hochbordabsicherung der Ladesäule nicht erforderlich. In allen übrigen Fällen ist, neben einem Anprallschutz, eine ausreichend dimensionierte Ladeinsel zum Schutz der Ladeinfrastruktur vorzusehen. | H36: Längsparken | I36: Autostrom+ | J36: – | K36: trifft nicht zu | L36: 45894 | M36: Los 2 hat keine Poller - betrifft nur längsparkplätze
B37: ANF-031 | C37: Vertragsanlage 4 | D37: § 3.6 | E37: Bau & Dokumentation | G37: Antrag auf Baufreigabe und Ausführungs-, Werk- und Montageplanung | H37: Mitwirkung an Planung und Freigabe | I37: Autostrom+ | J37: – | K37: bewertet
B38: ANF-032 | C38: Vertragsanlage 4 | D38: § 3.7 | E38: Bau & Dokumentation | G38: Bestandsunterlagen (As-Built) | H38: Verantwortlich für Dokumentation und Erstellung Unterlagen | I38: Autostrom+ | J38: – | K38: bewertet
B39: ANF-033 | C39: Vertragsanlage 6 | D39: § 8 | E39: Authentifizierung & Zugang | F39: Öffnung innerhalb von 45 Sekunden. | G39: Folgende Authentifizierungsoptionen (Anmeldung, Freischaltung der physischen Zufahrtsbeschränkungen und Start des Ladevorgangs etc.) müssen möglich sein: ▪ RFID-Token (Ladekarte etc.) von vertraglich angebundenen Mobilitätsdienstleister, ▪ App von vertraglich angebundenen Mobilitätsdienstleister, ▪ Ad hoc-Laden ohne Registrierung und ▪ ISO 15118 (nach Verfügbarkeit – s. o. Abschnitt 7.). Der Authentifizierungsvorgang zur Freigabe des Ladeplatzes muss innerhalb von maximal 45 Sekunden abgeschlossen sein und sollte so gestaltet sein, dass der Verkehrsfluss möglichst wenig beeinträchtigt wird. Die angegebene Zeitspanne umfasst alle praktische und technische Schritte der Authentifizierung bis zur Öffnung der Schranke bzw. des Pollers und gilt für alle vorgesehenen Zugangsarten | H39: 45 Sekunden (!) Wie (wer) Erfüllt das? Bieterfrage 441 nach Bezahlterminal ? | I39: eRound / SCS | J39: Authentifizierungskomponente / Schrankensteuerung | K39: erfasst
B40: ANF-034 | C40: Vertragsanlage 6 | D40: § 9 (1) | E40: Belegungsdetektion | F40: Belegungsdetektion ist gefordert. | G40: Jeder MCS- / CCS-Ladepunkt muss über eine Detektion verfügen. Die MCS- / CCSLadeplatzdetektion ist so auszustatten, dass Objekte auf dem zum MCS- / CCSLadepunkt gehörigen MCS- / CCS-Ladeplatz detektiert werden können. | H40: Deckensensoren Pönalisierung / Falschparker | I40: Schrankenhersteller / SCS | J40: Belegungsdetektion | K40: erfüllt | L40: 46259 | M40: Radarsensor stellt Belegung der Ladesäule bereit
B41: ANF-035 | C41: Vertragsanlage 6 | D41: § 9 (2) | E41: Belegungsdetektion | F41: Roaming-Infos müssen veröffentlicht werden Pönalisierung gefordert. Entfernung Falschparker gefordert. | G41: Die Information der Reservierung des MCS- / CCS-Ladepunkts muss dem IT-Backend der MCS- / CCS-Ladeeinrichtung zur Verfügung stehen und muss angebundenen Mobilitätsdienstleistern und Betreibern von Online-Plattformen zur Darstellung von Statusinformationen zur Verfügung gestellt werden. Zudem soll dem Betreiber die Pönalisierung und Entfernung von Falschparkern ermöglicht werden. | H41: Pönalisierung / Falschparker | I41: eRound / SCS | J41: OCPI Buchungskalender / Kennzeichenerfassung / Pönalisierungssystem | K41: erfasst
B42: ANF-036 | C42: Vertragsanlage 6 | D42: § 10 (1) | E42: Zufahrt & Schranke | F42: Einfahrtsschranke Ausfahrtsschranke Bei Nichtbelegung beide Schranken geschlossen. | G42: Jeder Ladeplatz ist mit einer Einfahrts- und einer Ausfahrtsschranke auszustatten. Die Schranken sind wie folgt zu betreiben: 1) Grundstellung: Beide Schranken sind bei Nichtbelegung des Ladeplatzes geschlossen. | I42: Schrankenhersteller | J42: Schrankensteuerung | K42: erfüllt | L42: 46259 | M42: Schranke wird konfiguriert, sodass diese zu ist
B43: ANF-037 | C43: Vertragsanlage 6 | D43: § 10 (2) | E43: Zufahrt & Schranke | F43: Einfahrtsschranke öffnet nach Authentifizierung. | G43: 2) Einfahrt: Die Einfahrtschranke öffnet sich nach erfolgreicher Authentifizierung und gewährt Zugang zum Ladeplatz. Sie bleibt während des gesamten Ladevorgangs geöffnet. | H43: Schnittstelle notwendig: Öffnen direkt nach Authentifizierung Schließen bei Ende Ladevorgang | I43: eRound / SCS | J43: Authentifizierungskomponente / Schrankensteuerung | K43: erfüllt | L43: 46259 | M43: Radarsensor erkennt Einfahrt bleibt geöffnet bis die Zone wieder frei ist.
B44: ANF-038 | C44: Vertragsanlage 6 | D44: § 10 (3) | E44: Zufahrt & Schranke | F44: Ausfahrtsschranke öffnet bei Ankunft LKW. | G44: 3) Ausfahrtsschaltung: Sobald der Lkw seine Parkposition auf dem Ladeplatz erreicht hat, öffnet sich die Ausfahrtsschranke. | H44: Ausfahrtsschranke also recht dumm -> komplett durch SCS möglich? | I44: Schrankenhersteller / SCS | J44: Schrankensteuerung | K44: erfüllt | L44: 46259 | M44: Die Schranke kann selbstständig öffnen und schließen
B45: ANF-039 | C45: Vertragsanlage 6 | D45: § 10 (4) | E45: Zufahrt & Schranke | F45: Ausfahrtsschranke schließt nach Verlassen des LKW. Fernsteuerung der Schranken. | G45: 4) Verlassen des Ladeplatzes: Nach Abschluss des Ladevorgangs und dem Verlassen des Ladeplatzes schließt sich die Ausfahrtsschranke wieder. Zudem ist dafür zu sorgen, dass die Einfahrts- und Ausfahrtsschranken im Notfall geöffnet werden können | H45: Schließen nach Ausfahrt -> Schranke selbst | I45: Schrankenhersteller | J45: Schrankensteuerung | K45: erfüllt | L45: 46259 | M45: Schranke schließt von alleine
B46: ANF-040 | C46: Vertragsanlage 6 | D46: § 4 | E46: Anzeige & Beschilderung | F46: Bezahlterminal für mehrere MCS/CCS Ladepunkte möglich. | G46: Display zur Anzeige von Informationen zum Ladevorgang (Ad hoc-Preis des CPO, geladene Energiemenge in kWh, Blockadeentgelt, Anweisungen zum Ablauf des Ladens). ▪ Das Display muss sowohl bei Tageslicht unter Sonneneinstrahlung als auch bei Dunkelheit gut ablesbar sein. ▪ Die Menüführung erfolgt mindestens in den Sprachen Deutsch und Englisch. ▪ RFID-Multireader zum Lesen von allen gängigen und zukünftig erwartbaren Ladekarten von Fahrstromanbietern (z.B. unter Berücksichtigung VDE-AR-E 2532-100) zum Authentifizieren und Starten von Ladevorgängen. Bezahlterminal für das Bezahlen von Ad hoc-Ladevorgängen (ohne Dauerschuldverhältnis). Dieses muss bargeldlose Zahlungen entsprechend den Vorgaben der AFIR ermöglichen. Zusätzliche Authentifizierungs- und Zahlungsmöglichkeiten können den Nutzern kostenlos eingeräumt werden. Dabei ist NFC-Technologie (Nahfeldkommunikation) und PinEingabe erforderlich. Von der Möglichkeit einer Pin-Eingabe kann abgesehen werden, wenn die Notwendigkeit der Pin-Eingabe dauerhaft bei allen relevanten Karten, insbesondere bei Präsentation einer physischen Karte zum Bezahlen von Fahrstrom entfällt. ▪ Ein Bezahlterminal kann auch zur Bezahlung von Ladevorgängen mehrerer MCS- bzw. CCS-Ladeeinrichtungen bzw. -Ladepunkten dienen | H46: Bezahlterminal kann für mehrere MCS / CCS genutzt werden | I46: eRound | J46: Authentifizierungskomponente | K46: erfüllt | L46: 46259 | M46: Jede LIS hat ein Display, rest in KANN-Anforderung
B47: ANF-041 | C47: Vertragsanlage 10 | D47: § 3.1 | E47: Monitoring & Reporting | F47: Benennung Datenpunkte zu Reservierungen im Monatsbericht. | G47: ab_total_reservations Anzahl Reservierungen je Ladepunkt ab_total_reservations_cancelled Anzahl stornierter Reservierungen je Ladepunkt ab_reservations_no-show Anzahl nicht eingehaltener Reservierungen je Ladepunkt | H47: Datentabelle Monatsbericht Verfügbarkeit | I47: eRound | J47: Monitoring | K47: erfasst
B48: ANF-042 | C48: Vertragsanlage 10 | D48: § 5 (d) | E48: Monitoring & Reporting | F48: Benennung Datenpunkte zu Reservierungen im Monatsbericht. | G48: total_reservation_cost Gesamtsumme aller Kosten im Zusammenhang mit der Reservierung eines Ladepunkts, einschließlich Festpreisbestandteilen (€) | H48: Datentabelle Reservierungskosten | I48: eRound | J48: Monitoring | K48: erfasst
B49: ANF-043 | C49: Vertragsanlage 13 | D49: § 8 (1) | E49: Reservierung | F49: Mehrfachbuchungen unterbinden | G49: Grundsätzlich möchte der Auftraggeber den Nutzern eine gewisse Flexibilität ermöglichen, da die Inanspruchnahme einer Reservierung z.B. aufgrund kurzfristiger Staus auch ohne Verschulden ggf. nicht wahrgenommen werden kann. Ein missbräuchliches Verhalten durch Nutzer, z.B. durch mehrfache Reservierungsbuchungen am gleichen Standort und am gleichen Tag, ist nicht im Interesse des Auftraggebers. Sollte sich ein solches Verhalten einstellen, besteht vor dem Hintergrund eines abweichenden Marktstandards nach §23 Abs. 3 des Betreibervertrags die Möglichkeit, die definierten Mindestvoraussetzungen an Reservierungsplattformen zu ändern. | H49: identisch zu Paragraph 38 - 1 | I49: eRound | J49: OCPI Buchungskalender | K49: erfasst
B50: ANF-044 | C50: Bieterfragenkatalog | D50: § 351 | E50: Belegungsdetektion | F50: Belegungsdetektion ist gefordert. | G50: Nein, auch bei installierten Zufahrtsbeschränkungen sind Sensoren als Redundanz zum Zweck der Detektion des Belegungsstatus des Ladeplatzes vorzusehen. | H50: // Antwort: Nein, auch bei installierten Zufahrtsbeschränkungen sind Sensoren als Redundanz zum Zweck der Detektion des Belegungsstatus des Ladeplatzes vorzusehen. | I50: SCS | J50: Belegungsdetektion | K50: erfasst
B51: ANF-045 | C51: Bieterfragenkatalog | D51: § 373 | E51: Reservierung | F51: OCPI Schnittstelle für Reservierungen ist gefordert. | G51: Frage: Laut Ziff. 3.4 im 4. Verfahrensbrief soll es nur ein zentrales Reservierungssystem geben. zugleich ist in § 23 Abs. 1 des Betreibervertrags von Reservierungsplattformen (Mehrzahl) die Rede. Wie passt dies zusammen? Antwort: Die überarbeitete Regelung im Betreibervertrag (§ 24) sieht vor, dass der Auftragnehmer eine Anbindung von Reservierungsplattformen über eine OCPI basierte Schnittstelle sicherstellt und Reservierungsplattformen über diese Schnittstelle ermöglicht, wenn sie die im Vertrag genannten Mindestvoraussetzungen erfüllt. | H51: OCPI Schnittstelle // Antwort: Die überarbeitete Regelung im Betreibervertrag (§ 24) sieht vor, dass der Auftragnehmer eine Anbindung von Reservierungsplattformen über eine OCPI basierte Schnittstelle sicherstellt und Reservierungsplattformen über diese Schnittstelle ermöglicht, wenn sie die im Vertrag genannten Mindestvoraussetzungen erfüllt. | I51: eRound | J51: OCPI Buchungskalender | K51: erfasst
B52: ANF-046 | C52: Bieterfragenkatalog | D52: § 374 | E52: Reservierung | F52: Anbindung muss deutschlandweit sichergestellt sein. | G52: Frage: Bei einer Reservierungsplattform handelt es sich um Software, die damit grundsätzlich weltweit verfügbar ist. Wie ist der Passus zu verstehen, dass die Plattform im gesamten Gebiet der Bundesrepublik Deutschland Reservierungen ermöglichen soll? Antwort: Es muss sichergestellt sein, dass die Reservierung für alle Rastanlagen mit Ladeinfrastruktur für E-LKW auf Bundesautobahnen möglich ist | H52: // Antwort: Es muss sichergestellt sein, dass die Reservierung für alle Rastanlagen mit Ladeinfrastruktur für E-LKW auf Bundesautobahnen möglich ist. | I52: Reservierungsplattform | J52: Anbindung | K52: erfasst
B53: ANF-047 | C53: Bieterfragenkatalog | D53: § 375 | E53: Nutzungszeit & Entgelte | G53: Es ist in Verbindung mit §36 das Erheben eines Blockadeentgeltes möglich, welches (bei Erscheinen) erst nach 75 min greift. Gehen wir recht in der Annahme, dass der CPO mit einer Belegung durch einen Reservierungsvorgang von 75 min rechnen muss, bevor er die Ladestation erneut als verfügbar meldet? | H53: leer 10.12.2025 // Antwort: Der Auftragnehmer muss nicht mit einer Belegung durch einen Reservierungsvorgang von 75min (beim Zwischenladen) rechnen. Der entsprechende Paragraph (jetzt §38) wurde im Betreibervertrag mit der Aufforderung zur Angebotsabge (Dezember 2025) überarbeitet. Die zuvor vorgesehene Wartezeit von 15 Minuten ist entfallen. Nach der neuen Regelung des § 38 Abs. 3 kann ein Blockadeentgelt im Fall einer Reservierung nach Ablauf des reservierten Zeitraums (ohne Wartezeit) erhoben werden. | I53: offen | J53: – | K53: erfasst
B54: ANF-048 | C54: Bieterfragenkatalog | D54: § 376 | E54: Nutzungszeit & Entgelte | G54: Frage: Der Vertrag sieht eine spätere mögliche Anpassung der Höhe des Blockadeentgeltes vor, aber keine Anpassungsoption hinsichtlich der Wartezeit. Gehen wir richtig in der Annahme, dass der AG nicht beabsichtigt, mögliche Optimierungspotenziale durch kürzere Wartezeiten während der Vertragslaufzeit zu realisieren? Antwort: Der Betreibervertrag wird mit der Aufforderung der Abgabe verbindlicher Angebote aktualisiert. | H54: Verweis Ausschreibungsunterlagen // Antwort: Der Betreibervertrag wird mit der Aufforderung der Abgabe verbindlicher Angebote aktualisiert. | I54: offen | J54: – | K54: erfasst
B55: ANF-049 | C55: Bieterfragenkatalog | D55: § 377 | E55: Reservierung | G55: Im In § 23 Abs. 4 BV heißt es, dass der Auftragnehmer verpflichtet ist, Endnutzern bzw. anderen Mobilitätsdienstleistern die Nutzung von MCS- oder CCS auch ohne vorherige Reservierung zu ermöglichen. Gehen wir recht in der Annahme, dass mit CCS nur Ladepunkte zum Zwischenladen gemeint sind und keine Ladepunkte zum Übernachtladen? Gehen wir weiter recht in der Annahme, dass sich dies auf die Ladepunkte eines Standortes bezieht und nicht auf jeden einzelnen Ladepunkt? Falls nein, heißt dies, dass es zulässig ist, ab weniger als 1h vor dem nächsten reservierten Lade Slot, keinen neuen Ladevorgang an dem betreffenden Ladepunkt mehr zuzulassen, da eine Blockiergebühr erst nach 60 min zulässig ist? Inwiefern sieht es die Vergabestelle als zulässig an, dass der adhoc-Nutzer einen spätesten Abfahrtzeitpunkt bestätigen muss, bei dessen Überschreiten eine Blockiergebühr erhoben werden darf? | H55: Verweis Ausschreibungsunterlagen // Antwort: Der Betreibervertrag wird mit der Aufforderung der Abgabe verbindlicher Angebote aktualisiert. | I55: offen | J55: – | K55: erfasst
B56: ANF-050 | C56: Bieterfragenkatalog | D56: § 378 | E56: Reservierung | F56: Anpassung möglich, bei ungewolltem Nutzerverhalten. | G56: Frage: Aus Sicht eines Kunden liegt es nahe, ggf. mehr als einen Standort zu reservieren, solange eine Buchung kostenlos storniert werden kann. Eine Stornierung und damit Freigabe eines Ladepunkts 30 Minuten vor dem geplanten Nutzungsbeginn führt jedoch dazu, dass die Wahrscheinlichkeit einer tatsächlichen Nutzung des zuvor reservierten Ladepunkts deutlich sinkt. Welche Maßnahmen sieht der AG vor, um ein derartiges Verhalten der Nutzer zu verhindern? Antwort: Grundsätzlich möchte der Auftraggeber den Nutzern eine gewisse Flexibilität ermöglichen, da die Inanspruchnahme einer Reservierung z.B. aufgrund kurzfristiger Staus auch ohne Verschulden ggf. nicht wahrgenommen werden kann. Ein missbräuchliches Verhalten durch Nutzer, z.B. durch mehrfache Reservierungsbuchungen am gleichen Standort und am gleichen Tag, ist nicht im Interesse des Auftraggebers. Sollte sich ein solches Verhalten einstellen, besteht vor dem Hintergrund eines abweichenden Marktstandards nach §23 Abs. 3 des Betreibervertrags die Möglichkeit, die definierten Mindestvoraussetzungen an Reservierungsplattformen zu ändern. | H56: // Antwort: Grundsätzlich möchte der Auftraggeber den Nutzern eine gewisse Flexibilität ermöglichen, da die Inanspruchnahme einer Reservierung z.B. aufgrund kurzfristiger Staus auch ohne Verschulden ggf. nicht wahrgenommen werden kann. Ein missbräuchliches Verhalten durch Nutzer, z.B. durch mehrfache Reservierungsbuchungen am gleichen Standort und am gleichen Tag, ist nicht im Interesse des Auftraggebers. Sollte sich ein solches Verhalten einstellen, besteht vor dem Hintergrund eines abweichenden Marktstandards nach §23 Abs. 3 des Betreibervertrags die Möglichkeit, die definierten Mindestvoraussetzungen an Reservierungsplattformen zu ändern. | I56: eRound | J56: OCPI Buchungskalender | K56: erfasst
B57: ANF-051 | C57: Bieterfragenkatalog | D57: § 455 | E57: Reservierung | F57: Reservierungsplattform ist nicht Teil der Ausschreibung. | G57: Frage: Im vierten Verfahrensbrief findet sich folgende Aussage unter 3.4.: „Die Vorgaben zum Reservierungssystem wurden dahingehend angepasst, dass es nunmehr ein zentrales Reservierungssystem geben wird.“ Im Betreibervertrag unter § 23, 2. Lesen wir allerdings: „Der Auftragnehmer ist verpflichtet, jeder Reservierungsplattform die Anbindung über die in Absatz 1 genannte Schnittstelle kostenfrei zu ermöglichen, soweit die Reservierungsplattform die folgenden Mindestvoraussetzungen erfüllt: (…)“ Dies stellt aus unserer Sicht ggf. einen Widerspruch dar. Wir bitten darum, die geplante Architektur des Reservierungsökosystems einmal zu erläutern. Antwort: Der Vertrag gilt. Sobald Reservierungsplattformen die im Vertrag genannten Mindestvoraussetzungen erfüllen, werden sie als anbindungsfähig und als zentral angesehen. In diesem Fall hat der Auftragnehmer auf Wunsch der externen Reservierungsplattformen eine Anbindung über eine OCPI-basierte Schnittstelle zu gewährleisten. Ein durch den Auftraggeber (z.B. per Vergabeverfahren) organisiertes, zentrales Reservierungssystem ist nicht in Planung. | H57: Zentrales Reservierungssystem // Antwort: Der Vertrag gilt. Sobald Reservierungsplattformen die im Vertrag genannten Mindestvoraussetzungen erfüllen, werden sie als anbindungsfähig und als zentral angesehen. In diesem Fall hat der Auftragnehmer auf Wunsch der externen Reservierungsplattformen eine Anbindung über eine OCPI-basierte Schnittstelle zu gewährleisten. Ein durch den Auftraggeber (z.B. per Vergabeverfahren) organisiertes, zentrales Reservierungssystem ist nicht in Planung. | I57: Reservierungsplattform | J57: Reservierungsplattform | K57: erfasst
B58: ANF-052 | C58: Bieterfragenkatalog | D58: § 370 | E58: Reservierung | F58: Sämtliche Infos via gängigen Roamingprotokoll / Marktstandard zur verfügung stellen. | G58: Frage: Welche Informationen der Reservierung sollen MSP und sonstigen bereitgestellt werden? Antwort: Es ist vom AN sicherzustellen, dass sämtliche Statusinformationen der Reservierungen bereitgestellt werden, die mittels der gängigen Roamingprotokolle übermittelt werden können und dem gängigen Marktstandard entsprechen. | H58: // Antwort: Es ist vom AN sicherzustellen, dass sämtliche Statusinformationen der Reservierungen bereitgestellt werden, die mittels der gängigen Roamingprotokolle übermittelt werden können und dem gängigen Marktstandard entsprechen. | I58: eRound | J58: OCPI Buchungskalender | K58: erfasst
B59: ANF-053 | C59: Bieterfragenkatalog | D59: Nr. 1 / S. 1 | E59: Vergabeverfahren & Angebot | F59: Klarstellung: Der Zuschlag wird nicht bereits auf die Erstangebote erteilt. Eine auf die Erstangebote bezogene Bindefrist ist daher gegenstandslos. | G59: Erster Verfahrensbrief, Formblatt A1, Fragenkatalog Nr. 61: In der Antwort auf Bieterfrage 61 ist ausgeführt, dass die Erstangebote indikativ sein werden und erst die Folgeangebote verbindlich. Unter Ziffer 3.1 des Ersten Verfahrensbriefs zum Verhandlungsverfahren heißt es entsprechend, dass der Auftraggeber den Zuschlag nicht auf das jeweils wirtschaftlichste Erstangebot erteilen wird. Unter Ziffer 4.6 des Ersten Verfahrensbriefs zum Verhandlungsverfahren heißt es allerdings, dass das Erstangebot zuschlagsfähig sein muss. Zudem soll der Bieter im Formblatt A1 – Angebotsschreiben erklären, sich bis zum Ablauf der Bindefrist an sein Erstangebot gebunden zu halten. Vor diesem Hintergrund bitten wir um Klarstellung: Ist unser Verständnis richtig, dass die Erstangebote rein indikativer Natur sind, also vom Auftraggeber unter keinen Umständen bezuschlagt werden können? Wie ist die Bindefrist zu verstehen? | H59: Bezug lt. Katalog: Erster Verfahrensvrief Katalogdatum: 08.01.2025 // Antwort: Der Zuschlag wird nicht bereits auf die Erstangeboite erteilt. Eine auf die Erstangebote bezogene Bindefrist ist daher gegenstandslos. | I59: Autostrom+ | J59: – | K59: trifft nicht zu
B60: ANF-054 | C60: Bieterfragenkatalog | D60: Nr. 2 / S. 1 | E60: Anzeige & Beschilderung | F60: Zusage / Ankündigung: Der AG beabsichtigt, die Unterlagen im weiteren Vergabeverfahren zur Verfügung zu stellen. | G60: Wann werden Anlage 04 Anhang 2 (Regelschnitt und Details für die Gestaltung der LKW- Ladeinfrastruktur) und Anlage 04 Anhang 3 (Markierungs- und Beschilderungsplan) zur Verfügung gestellt? | H60: Bezug lt. Katalog: LB Errichtung Katalogdatum: 08.01.2025 // Antwort: Der AG beabsichtigt, die Unterlagen im weiteren Vergabeverfahren zur Verfügung zu stellen. Die Erstellung eines Erstangebotes ist unabhängig davon auch ohne die genannten Unterlagen möglich. | I60: tbd | J60: Beschilderung | K60: erfasst
B61: ANF-055 | C61: Bieterfragenkatalog | D61: Nr. 3 / S. 1 | E61: Vertrag & Recht | F61: Klarstellung: Eine entsprechende Vertragsfassung wird allen für das Verhandlungsverfahren ausgewählten Bewerbern und Bewerbergemeinschaften mit Beantwortung zur Verfügung gestellt. | G61: Wir bitte zur besseren Nachverfolgung der Unterlagenfortschreibung um Zusendung einer ChangeVersion, um nachzuvollziehen in welchen Punkte das Vertragswerk angepasst wurde. | H61: Bezug lt. Katalog: Vertrag Katalogdatum: 09.01.2025 // Antwort: Eine entsprechende Vertragsfassung wird allen für das Verhandlungsverfahren ausgewählten Bewerbern und Bewerbergemeinschaften mit Beantwortung zur Verfügung gestellt. | I61: offen | J61: – | K61: erfasst
B62: ANF-056 | C62: Bieterfragenkatalog | D62: Nr. 4 / S. 1 | E62: Vertrag & Recht | F62: Zusage / Ankündigung: Anlage 9 zum Vertrag wird dem AN nach Vertragsschluss zu Verfügung gestellt (vgl. Vertragsanlage 4 LB Errichtung, S.13). | G62: Die für die zweite Phase der Ausschreibung geteilten Unterlagen enthalten NICHT die Vertragsanlagen 7 ("Logos") und 9 ("Ansprechpartner (losspezifisch)"). Wenn diese bewusst nicht geteilt werden - wann kann mit diesen gerechnet werden? | H62: Bezug lt. Katalog: Vertrag Katalogdatum: 09.01.2025 // Antwort: Anlage 9 zum Vertrag wird dem AN nach Vertragsschluss zu Verfügung gestellt (vgl. Vertragsanlage 4 LB Errichtung, S.13). Der AG beabsichtigt, die Anlage 7 im weiteren Vergabeverfahren zur Verfügung zu stellen. Die Erstellung eines Erstangebotes ist unabhängig davon auch ohne die genannten Unterlagen möglich. | I62: offen | J62: – | K62: erfasst
B63: ANF-057 | C63: Bieterfragenkatalog | D63: Nr. 5 / S. 1 | E63: Flächen & Genehmigungen | F63: Klarstellung: Die Unterlagen Vertragsanlage 2 ("Standortübersicht (losspezifisch)") und Anlage 2 zum Verfahrensbrief ("Gesamtübersicht über die Lose") wurden entsprechend aktualisiert und stehen Ihnen in der überarbeiteten Version zur … | G63: wir bitten um Klärung der folgenden Frage betreffend Anlage 2 zum Verfahrensbrief, Vertragsanlage 2_Standortübersicht und Vertragsanlage 3. In diesen Dokumenten ergeben sich teilweise Inkonsistenzen hinsichtlich der Anzahl der Ladepunkte je Standort. Könnten Sie diese bitte erläutern? Beispiel: Los 1, Standort Schwalenberg Ost: - laut Vertragsanlage 2_Standortübersicht, Los 1 und laut Anlage 2 zum Ersten Verfahrensbrief sollen an dem Standort 1 MCS-Ladepunkt, 1 CCS (Zwischenladepunkt) aufgebaut werden - laut Anlage 3 Los 1 (Vorplanungsdokument) sollen an dem Standort 6 MCS-Ladepunkte und 30 CCS Ladepunkt aufgebaut werden (keine Unterscheidung von Zwischenladen und Übernachtladen) | H63: Bezug lt. Katalog: Anlage 2/3 Katalogdatum: 09.01.2025 // Antwort: Die Unterlagen Vertragsanlage 2 ("Standortübersicht (losspezifisch)") und Anlage 2 zum Verfahrensbrief ("Gesamtübersicht über die Lose") wurden entsprechend aktualisiert und stehen Ihnen in der überarbeiteten Version zur Verfügung. Diese aktualisierten Dokumente sind dem Erstangebot zu Grunde zu legen. In den unverbindlichen Vorplanungen (Vertragsanlage 3 "Angaben und Informationen zu den Standorten (losspezifisch)") wird nicht zwischen CCS 400 und CCS 100 Ladepunkten unterschieden, da von gleichen baulichen Anforderungen auszugehen ist. Etwaige Unterschiede bei z. B. Kabelquerschnitten und anderen Komponenten sind zu berücksichtigen. | I63: offen | J63: – | K63: erfasst
B64: ANF-058 | C64: Bieterfragenkatalog | D64: Nr. 6 / S. 1 | E64: Netzanschluss & Energie | F64: Klarstellung: Die Unterlagen Vertragsanlage 2 ("Standortübersicht (losspezifish)") und Anlage 2 zum Verfahrensbrief ("Gesamtübersicht über die Lose") wurden entsprechend aktualisiert und stehen Ihnen in der überarbeiteten Version zur Verfügung. | G64: Es ist aufgefallen, dass in den Standortübersichten sowie in der Gesamtübersicht über die Lose (Anlagen 02) die Angaben in den Spalten "Nr. BAB" sowie "Geogr. Länge" und "Geogr. Breite" in weiten Teilen nicht mit der jeweiligen Kennung und Bezeichnung der Rastanlage (PWC-Anlage) zusammenpassen. Wir bitten um Überprüfung. Darüber hinaus unterscheiden sich die Angaben zur jeweiligen Anzahl der Ladepunkte in den Dokumenten der Vertragsanlagen 02 und der Vertragsanlage 05. Wir bitten um Überprüfung dieses Widerspruchs. Des Weiteren bitten wir um Überprüfung der Unterlagen in "Vertragsanlage 3 - Angaben und Informationen zu den einzelnen Standorten (losspezifisch)", da die dort enthaltenen Angaben teilweise nicht mit den vorgenannten Dokumenten aus "Anlage 2" übereinstimmen. Außerdem scheint in "Anlage 3" bei der "lfd. Nr." 74 die Angabe der "Nr. BAB" fehlerhaft zu sein. | H64: Bezug lt. Katalog: Vertragsanlage 02 Standortübersicht (losspezifisch) - Stand 06.01.2025 / Anlage 02_zum Verfahrensbrief_Gesamtübersich t über die Lose - Stand 06.01.2025 / Vertragsanlage 3 - Angaben und Informationen zu den einzelnen Standorten (losspezifisch) - Stand 06.01.2025 / Vertragsanlage 5 - Details zum Netzanschluss - Stand 06.01.25 Katalogdatum: 10.01.2025 // Antwort: Die Unterlagen Vertragsanlage 2 ("Standortübersicht (losspezifish)") und Anlage 2 zum Verfahrensbrief ("Gesamtübersicht über die Lose") wurden entsprechend aktualisiert und stehen Ihnen in der überarbeiteten Version zur Verfügung. Diese aktualisierten Dokumente sind dem Erstangebot zu Grunde zu legen. Die Angaben der Vertragsanlage 05 (Stand 06.01.2025) sind korrekt. | I64: offen | J64: – | K64: erfasst
B65: ANF-059 | C65: Bieterfragenkatalog | D65: Nr. 7 / S. 2 | E65: Vergabeverfahren & Angebot | F65: Klarstellung: Die Unterlagen Anlage 5 zum Verfahrensbrief wurden entsprechend aktualisiert und stehen Ihnen in der überarbeiteten Version zur Verfügung. | G65: Es ist aufgefallen, dass die Karte der Standorte fälschlicherweise als "Anlage 4 zum Verfahrensbrief" betitelt ist, während die Dateibezeichnung "Anlage 05..." ist. Wir bitten um Überprüfung. Des Weiteren bitten wir um Überprüfung der dargestellten Standorte, da mindestens 3 Standorte aus Los 4 nicht dargestellt sind. | H65: Bezug lt. Katalog: Anlage 05 zum Verfahrensbrief - Karte zur Losaufteilung - Stand 06.01.2025 Katalogdatum: 10.01.2025 // Antwort: Die Unterlagen Anlage 5 zum Verfahrensbrief wurden entsprechend aktualisiert und stehen Ihnen in der überarbeiteten Version zur Verfügung. Diese aktualisierte Dokumente ist dem Erstangebot zu Grunde zu legen. | I65: offen | J65: – | K65: erfasst
B66: ANF-060 | C66: Bieterfragenkatalog | D66: Nr. 8 / S. 2 | E66: Vergabeverfahren & Angebot | F66: Zusage / Ankündigung: Siehe die Antwort auf Frage 1. Die Bieter sind dennoch aufgefordert ein zuschlagsfähiges Erstangebot abzugeben. | G66: Bindung an Erstangebot: Im ersten Verfahrensbrief ist in 4.6 von der Abgabe eines "zuschlagsfähigen" Erstangebots die Rede. Wird somit in der Verhandlungsphase nur das verhandelt, was als "Verhandlungsbedarf" im Formblatt A6 explizit angemeldet wird und der Rest ist bereits bindend im Falle eines Zuschlags? | H66: Bezug lt. Katalog: Verfahrensbrief in 4.6 Katalogdatum: 14.01.2025 // Antwort: Siehe die Antwort auf Frage 1. Die Bieter sind dennoch aufgefordert ein zuschlagsfähiges Erstangebot abzugeben. In den Verhandlungen wird der von den Bietern im Formblatt A6 addressierte Verhandlungsbedarf behandelt. Im Anschluss an die Verhandlungen werden den Bietern entsprechend der Ergebnisse der Verhandlungen überarbeitete Vergabeunterlagen zur Verfügung gestellt. Auf der Grundlage dieser überarbeiteten Vergabeunterlagen werden die Bieter aufgefordert werden ein verbindliches Angbeot abzugeben. Dieses verbindliche Angbeot, auf das der AG beabsichtigt den Zuschlag zu erteilen, wird vollständig neu einzureichen sein und nicht auf Bestandteile des Erstangebots bezunehmen. | I66: offen | J66: – | K66: erfasst
B67: ANF-061 | C67: Bieterfragenkatalog | D67: Nr. 9 / S. 2 | E67: Netzanschluss & Energie | F67: Klarstellung: Die Pflicht, mit allen Mobilitätsdienstleistern diskriminierungsfrei Verträge zu schließen ist in §27(1) des Hauptvertrags geregelt. | G67: Müssen die Teilnehmer einen Vertrag mit jedem möglichen Mobilitätsdienstleister für das Durchleitungsmodell abschließen oder kann dies von einem einzelnen Akteur aggregiert werden? Vergleichbar mit einer Roaming-Plattform im MSP-Geschäft. | H67: Bezug lt. Katalog: BYOP Katalogdatum: 14.01.2025 // Antwort: Die Pflicht, mit allen Mobilitätsdienstleistern diskriminierungsfrei Verträge zu schließen ist in §27(1) des Hauptvertrags geregelt. Der Mobilitätsdienstleister kann dabei optional das Durchleitungsmodell wählen und den Strom bilanziell bereitstellen (§28 des Hauptvertrags). Erforderlich ist auch bei Wahl des Durchleitungsmodells der Abschluss einer Vereinbarung zwischen Ladepunktbetreiber und Mobilitätsdienstleister (vgl. Anlage 14 ). Es entstehen also bilaterale Verträge zur Durchleitung. Eine vertragliche Plattform-Lösung ist nicht zwingend vorgesehen, aber denkbar. | I67: eRound | J67: OCPI Buchungskalender | K67: erfasst
... B1388: ANF-1382 | C1388: Vertragsanlage 13 | D1388: § 15 (6) | E1388: Technik Ladeinfrastruktur | F1388: Ansprechpartner und Marktpartner Identifikationsnummer Als Ansprechpartner sind folgende Personen benannt: Ansprechpartner auf Seiten des Ladepunktbetreibers: ______________ Tel.: ______________ … | G1388: Ansprechpartner und Marktpartner Identifikationsnummer Als Ansprechpartner sind folgende Personen benannt: Ansprechpartner auf Seiten des Ladepunktbetreibers: ______________ Tel.: ______________ E-Mail: ______________ Marktpartner-Identifikationsnummer(n) (ggf. Felder ergänzen) ______________ ______________ Ansprechpartner auf Seiten des Bilanzkreisverantwortlichen: ______________ Tel.: ______________ E-Mail: ______________ Marktpartner-Identifikationsnummer ______________ ........................, den ............................ ..........................., den .............................. ....................................................... …….......................................................... (Ladepunktbetreiber) (Bilanzkreisverantwortlicher) Anhang: Ansprechpartner und Marktpartner-Identifikationsnummer Als Ansprechpartner sind folgende Personen benannt: Ansprechpartner auf Seiten des Ladepunktbetreibers: ______________ Tel.: ______________ E-Mail: ______________ Marktpartner-Identifikationsnummer(n) (ggf. Felder ergänzen) ______________ ______________ Ansprechpartner auf Seiten des Mobilitätsdienstleisters: ______________ Tel.: ______________ E-Mail: ______________ Soweit der Mobilitätsdienstleister auch Bilanzkreisverantwortlicher ist: Marktpartner-Identifikationsnummer ______________ | H1388: Kapitel: Anhänge Fundstelle im PDF: Seite 12 Zuordnung prüfen (Komponente/Partner nicht eindeutig) | I1388: Zuordnung prüfen | J1388: Zuordnung prüfen | K1388: erfasst

Sheet Auswertung
A1: Auswertung – Anforderungen
A2: Automatische Auswertung des Statusprozesses erfasst → bewertet → erfüllt bzw. trifft nicht zu – inklusive Bieterfragenkatalog.
A3: Erfüllungsgrad = erfüllte Anforderungen / anwendbare Anforderungen (Status „trifft nicht zu“ wird aus dem Nenner ausgeschlossen).
A5: 1 Nach Themenfeld
A6: Merkmal | B6: Gesamt | C6: Erfasst | D6: Bewertet | E6: Erfüllt | F6: Trifft nicht zu | G6: Erfüllungsgrad
A7: Anzeige & Beschilderung | B7: =COUNTIF(Anforderungen!$E$7:$E$2000,$A7) -> 14 | C7: =COUNTIFS(Anforderungen!$E$7:$E$2000,$A7,Anforderungen!$K$7:$K$2000,"erfasst") -> 12 | D7: =COUNTIFS(Anforderungen!$E$7:$E$2000,$A7,Anforderungen!$K$7:$K$2000,"bewertet") -> 0 | E7: =COUNTIFS(Anforderungen!$E$7:$E$2000,$A7,Anforderungen!$K$7:$K$2000,"erfüllt") -> 2 | F7: =COUNTIFS(Anforderungen!$E$7:$E$2000,$A7,Anforderungen!$K$7:$K$2000,"trifft nicht zu") -> 0 | G7: =IFERROR(E7/(B7-F7),0) -> 0.14285714
A8: Authentifizierung & Zugang | B8: =COUNTIF(Anforderungen!$E$7:$E$2000,$A8) -> 51 | C8: =COUNTIFS(Anforderungen!$E$7:$E$2000,$A8,Anforderungen!$K$7:$K$2000,"erfasst") -> 51 | D8: =COUNTIFS(Anforderungen!$E$7:$E$2000,$A8,Anforderungen!$K$7:$K$2000,"bewertet") -> 0 | E8: =COUNTIFS(Anforderungen!$E$7:$E$2000,$A8,Anforderungen!$K$7:$K$2000,"erfüllt") -> 0 | F8: =COUNTIFS(Anforderungen!$E$7:$E$2000,$A8,Anforderungen!$K$7:$K$2000,"trifft nicht zu") -> 0 | G8: =IFERROR(E8/(B8-F8),0) -> 0
A9: Bau & Dokumentation | B9: =COUNTIF(Anforderungen!$E$7:$E$2000,$A9) -> 98 | C9: =COUNTIFS(Anforderungen!$E$7:$E$2000,$A9,Anforderungen!$K$7:$K$2000,"erfasst") -> 96 | D9: =COUNTIFS(Anforderungen!$E$7:$E$2000,$A9,Anforderungen!$K$7:$K$2000,"bewertet") -> 2 | E9: =COUNTIFS(Anforderungen!$E$7:$E$2000,$A9,Anforderungen!$K$7:$K$2000,"erfüllt") -> 0 | F9: =COUNTIFS(Anforderungen!$E$7:$E$2000,$A9,Anforderungen!$K$7:$K$2000,"trifft nicht zu") -> 0 | G9: =IFERROR(E9/(B9-F9),0) -> 0
A10: Belegungsdetektion | B10: =COUNTIF(Anforderungen!$E$7:$E$2000,$A10) -> 4 | C10: =COUNTIFS(Anforderungen!$E$7:$E$2000,$A10,Anforderungen!$K$7:$K$2000,"erfasst") -> 3 | D10: =COUNTIFS(Anforderungen!$E$7:$E$2000,$A10,Anforderungen!$K$7:$K$2000,"bewertet") -> 0 | E10: =COUNTIFS(Anforderungen!$E$7:$E$2000,$A10,Anforderungen!$K$7:$K$2000,"erfüllt") -> 1 | F10: =COUNTIFS(Anforderungen!$E$7:$E$2000,$A10,Anforderungen!$K$7:$K$2000,"trifft nicht zu") -> 0 | G10: =IFERROR(E10/(B10-F10),0) -> 0.25
A11: Betrieb & Auslastung | B11: =COUNTIF(Anforderungen!$E$7:$E$2000,$A11) -> 76 | C11: =COUNTIFS(Anforderungen!$E$7:$E$2000,$A11,Anforderungen!$K$7:$K$2000,"erfasst") -> 74 | D11: =COUNTIFS(Anforderungen!$E$7:$E$2000,$A11,Anforderungen!$K$7:$K$2000,"bewertet") -> 0 | E11: =COUNTIFS(Anforderungen!$E$7:$E$2000,$A11,Anforderungen!$K$7:$K$2000,"erfüllt") -> 1 | F11: =COUNTIFS(Anforderungen!$E$7:$E$2000,$A11,Anforderungen!$K$7:$K$2000,"trifft nicht zu") -> 1 | G11: =IFERROR(E11/(B11-F11),0) -> 0.013333333
A12: Flächen & Genehmigungen | B12: =COUNTIF(Anforderungen!$E$7:$E$2000,$A12) -> 94 | C12: =COUNTIFS(Anforderungen!$E$7:$E$2000,$A12,Anforderungen!$K$7:$K$2000,"erfasst") -> 94 | D12: =COUNTIFS(Anforderungen!$E$7:$E$2000,$A12,Anforderungen!$K$7:$K$2000,"bewertet") -> 0 | E12: =COUNTIFS(Anforderungen!$E$7:$E$2000,$A12,Anforderungen!$K$7:$K$2000,"erfüllt") -> 0 | F12: =COUNTIFS(Anforderungen!$E$7:$E$2000,$A12,Anforderungen!$K$7:$K$2000,"trifft nicht zu") -> 0 | G12: =IFERROR(E12/(B12-F12),0) -> 0
A13: Monitoring & Reporting | B13: =COUNTIF(Anforderungen!$E$7:$E$2000,$A13) -> 34 | C13: =COUNTIFS(Anforderungen!$E$7:$E$2000,$A13,Anforderungen!$K$7:$K$2000,"erfasst") -> 34 | D13: =COUNTIFS(Anforderungen!$E$7:$E$2000,$A13,Anforderungen!$K$7:$K$2000,"bewertet") -> 0 | E13: =COUNTIFS(Anforderungen!$E$7:$E$2000,$A13,Anforderungen!$K$7:$K$2000,"erfüllt") -> 0 | F13: =COUNTIFS(Anforderungen!$E$7:$E$2000,$A13,Anforderungen!$K$7:$K$2000,"trifft nicht zu") -> 0 | G13: =IFERROR(E13/(B13-F13),0) -> 0
A14: Netzanschluss & Energie | B14: =COUNTIF(Anforderungen!$E$7:$E$2000,$A14) -> 228 | C14: =COUNTIFS(Anforderungen!$E$7:$E$2000,$A14,Anforderungen!$K$7:$K$2000,"erfasst") -> 227 | D14: =COUNTIFS(Anforderungen!$E$7:$E$2000,$A14,Anforderungen!$K$7:$K$2000,"bewertet") -> 0 | E14: =COUNTIFS(Anforderungen!$E$7:$E$2000,$A14,Anforderungen!$K$7:$K$2000,"erfüllt") -> 0 | F14: =COUNTIFS(Anforderungen!$E$7:$E$2000,$A14,Anforderungen!$K$7:$K$2000,"trifft nicht zu") -> 1 | G14: =IFERROR(E14/(B14-F14),0) -> 0
A15: Nutzungszeit & Entgelte | B15: =COUNTIF(Anforderungen!$E$7:$E$2000,$A15) -> 44 | C15: =COUNTIFS(Anforderungen!$E$7:$E$2000,$A15,Anforderungen!$K$7:$K$2000,"erfasst") -> 43 | D15: =COUNTIFS(Anforderungen!$E$7:$E$2000,$A15,Anforderungen!$K$7:$K$2000,"bewertet") -> 0 | E15: =COUNTIFS(Anforderungen!$E$7:$E$2000,$A15,Anforderungen!$K$7:$K$2000,"erfüllt") -> 0 | F15: =COUNTIFS(Anforderungen!$E$7:$E$2000,$A15,Anforderungen!$K$7:$K$2000,"trifft nicht zu") -> 1 | G15: =IFERROR(E15/(B15-F15),0) -> 0
A16: Reservierung | B16: =COUNTIF(Anforderungen!$E$7:$E$2000,$A16) -> 74 | C16: =COUNTIFS(Anforderungen!$E$7:$E$2000,$A16,Anforderungen!$K$7:$K$2000,"erfasst") -> 73 | D16: =COUNTIFS(Anforderungen!$E$7:$E$2000,$A16,Anforderungen!$K$7:$K$2000,"bewertet") -> 1 | E16: =COUNTIFS(Anforderungen!$E$7:$E$2000,$A16,Anforderungen!$K$7:$K$2000,"erfüllt") -> 0 | F16: =COUNTIFS(Anforderungen!$E$7:$E$2000,$A16,Anforderungen!$K$7:$K$2000,"trifft nicht zu") -> 0 | G16: =IFERROR(E16/(B16-F16),0) -> 0
A17: Sonstiges / Zuordnung prüfen | B17: =COUNTIF(Anforderungen!$E$7:$E$2000,$A17) -> 98 | C17: =COUNTIFS(Anforderungen!$E$7:$E$2000,$A17,Anforderungen!$K$7:$K$2000,"erfasst") -> 98 | D17: =COUNTIFS(Anforderungen!$E$7:$E$2000,$A17,Anforderungen!$K$7:$K$2000,"bewertet") -> 0 | E17: =COUNTIFS(Anforderungen!$E$7:$E$2000,$A17,Anforderungen!$K$7:$K$2000,"erfüllt") -> 0 | F17: =COUNTIFS(Anforderungen!$E$7:$E$2000,$A17,Anforderungen!$K$7:$K$2000,"trifft nicht zu") -> 0 | G17: =IFERROR(E17/(B17-F17),0) -> 0
A18: Technik Ladeinfrastruktur | B18: =COUNTIF(Anforderungen!$E$7:$E$2000,$A18) -> 153 | C18: =COUNTIFS(Anforderungen!$E$7:$E$2000,$A18,Anforderungen!$K$7:$K$2000,"erfasst") -> 153 | D18: =COUNTIFS(Anforderungen!$E$7:$E$2000,$A18,Anforderungen!$K$7:$K$2000,"bewertet") -> 0 | E18: =COUNTIFS(Anforderungen!$E$7:$E$2000,$A18,Anforderungen!$K$7:$K$2000,"erfüllt") -> 0 | F18: =COUNTIFS(Anforderungen!$E$7:$E$2000,$A18,Anforderungen!$K$7:$K$2000,"trifft nicht zu") -> 0 | G18: =IFERROR(E18/(B18-F18),0) -> 0
... A21: Zufahrt & Schranke | B21: =COUNTIF(Anforderungen!$E$7:$E$2000,$A21) -> 30 | C21: =COUNTIFS(Anforderungen!$E$7:$E$2000,$A21,Anforderungen!$K$7:$K$2000,"erfasst") -> 23 | D21: =COUNTIFS(Anforderungen!$E$7:$E$2000,$A21,Anforderungen!$K$7:$K$2000,"bewertet") -> 0 | E21: =COUNTIFS(Anforderungen!$E$7:$E$2000,$A21,Anforderungen!$K$7:$K$2000,"erfüllt") -> 6 | F21: =COUNTIFS(Anforderungen!$E$7:$E$2000,$A21,Anforderungen!$K$7:$K$2000,"trifft nicht zu") -> 1 | G21: =IFERROR(E21/(B21-F21),0) -> 0.20689655
A24: 2 Nach Partner
A25: Merkmal | B25: Gesamt | C25: Erfasst | D25: Bewertet | E25: Erfüllt | F25: Trifft nicht zu | G25: Erfüllungsgrad
A26: Aplitronic | B26: =SUMPRODUCT(ISNUMBER(SEARCH($A26,Anforderungen!$I$7:$I$2000))*(Anforderungen!$B$7:$B$2000<>"")) -> 104 | C26: =SUMPRODUCT(ISNUMBER(SEARCH($A26,Anforderungen!$I$7:$I$2000))*(Anforderungen!$K$7:$K$2000="erfasst")) -> 104 | D26: =SUMPRODUCT(ISNUMBER(SEARCH($A26,Anforderungen!$I$7:$I$2000))*(Anforderungen!$K$7:$K$2000="bewertet")) -> 0 | E26: =SUMPRODUCT(ISNUMBER(SEARCH($A26,Anforderungen!$I$7:$I$2000))*(Anforderungen!$K$7:$K$2000="erfüllt")) -> 0 | F26: =SUMPRODUCT(ISNUMBER(SEARCH($A26,Anforderungen!$I$7:$I$2000))*(Anforderungen!$K$7:$K$2000="trifft nicht zu")) -> 0 | G26: =IFERROR(E26/(B26-F26),0) -> 0
A27: eRound | B27: =SUMPRODUCT(ISNUMBER(SEARCH($A27,Anforderungen!$I$7:$I$2000))*(Anforderungen!$B$7:$B$2000<>"")) -> 225 | C27: =SUMPRODUCT(ISNUMBER(SEARCH($A27,Anforderungen!$I$7:$I$2000))*(Anforderungen!$K$7:$K$2000="erfasst")) -> 219 | D27: =SUMPRODUCT(ISNUMBER(SEARCH($A27,Anforderungen!$I$7:$I$2000))*(Anforderungen!$K$7:$K$2000="bewertet")) -> 0 | E27: =SUMPRODUCT(ISNUMBER(SEARCH($A27,Anforderungen!$I$7:$I$2000))*(Anforderungen!$K$7:$K$2000="erfüllt")) -> 5 | F27: =SUMPRODUCT(ISNUMBER(SEARCH($A27,Anforderungen!$I$7:$I$2000))*(Anforderungen!$K$7:$K$2000="trifft nicht zu")) -> 1 | G27: =IFERROR(E27/(B27-F27),0) -> 0.022321429
A28: SCS | B28: =SUMPRODUCT(ISNUMBER(SEARCH($A28,Anforderungen!$I$7:$I$2000))*(Anforderungen!$B$7:$B$2000<>"")) -> 76 | C28: =SUMPRODUCT(ISNUMBER(SEARCH($A28,Anforderungen!$I$7:$I$2000))*(Anforderungen!$K$7:$K$2000="erfasst")) -> 70 | D28: =SUMPRODUCT(ISNUMBER(SEARCH($A28,Anforderungen!$I$7:$I$2000))*(Anforderungen!$K$7:$K$2000="bewertet")) -> 0 | E28: =SUMPRODUCT(ISNUMBER(SEARCH($A28,Anforderungen!$I$7:$I$2000))*(Anforderungen!$K$7:$K$2000="erfüllt")) -> 6 | F28: =SUMPRODUCT(ISNUMBER(SEARCH($A28,Anforderungen!$I$7:$I$2000))*(Anforderungen!$K$7:$K$2000="trifft nicht zu")) -> 0 | G28: =IFERROR(E28/(B28-F28),0) -> 0.078947368
A29: Reservierungsplattform | B29: =SUMPRODUCT(ISNUMBER(SEARCH($A29,Anforderungen!$I$7:$I$2000))*(Anforderungen!$B$7:$B$2000<>"")) -> 13 | C29: =SUMPRODUCT(ISNUMBER(SEARCH($A29,Anforderungen!$I$7:$I$2000))*(Anforderungen!$K$7:$K$2000="erfasst")) -> 13 | D29: =SUMPRODUCT(ISNUMBER(SEARCH($A29,Anforderungen!$I$7:$I$2000))*(Anforderungen!$K$7:$K$2000="bewertet")) -> 0 | E29: =SUMPRODUCT(ISNUMBER(SEARCH($A29,Anforderungen!$I$7:$I$2000))*(Anforderungen!$K$7:$K$2000="erfüllt")) -> 0 | F29: =SUMPRODUCT(ISNUMBER(SEARCH($A29,Anforderungen!$I$7:$I$2000))*(Anforderungen!$K$7:$K$2000="trifft nicht zu")) -> 0 | G29: =IFERROR(E29/(B29-F29),0) -> 0
A30: tbd | B30: =SUMPRODUCT(ISNUMBER(SEARCH($A30,Anforderungen!$I$7:$I$2000))*(Anforderungen!$B$7:$B$2000<>"")) -> 29 | C30: =SUMPRODUCT(ISNUMBER(SEARCH($A30,Anforderungen!$I$7:$I$2000))*(Anforderungen!$K$7:$K$2000="erfasst")) -> 29 | D30: =SUMPRODUCT(ISNUMBER(SEARCH($A30,Anforderungen!$I$7:$I$2000))*(Anforderungen!$K$7:$K$2000="bewertet")) -> 0 | E30: =SUMPRODUCT(ISNUMBER(SEARCH($A30,Anforderungen!$I$7:$I$2000))*(Anforderungen!$K$7:$K$2000="erfüllt")) -> 0 | F30: =SUMPRODUCT(ISNUMBER(SEARCH($A30,Anforderungen!$I$7:$I$2000))*(Anforderungen!$K$7:$K$2000="trifft nicht zu")) -> 0 | G30: =IFERROR(E30/(B30-F30),0) -> 0
A31: offen | B31: =SUMPRODUCT(ISNUMBER(SEARCH($A31,Anforderungen!$I$7:$I$2000))*(Anforderungen!$B$7:$B$2000<>"")) -> 731 | C31: =SUMPRODUCT(ISNUMBER(SEARCH($A31,Anforderungen!$I$7:$I$2000))*(Anforderungen!$K$7:$K$2000="erfasst")) -> 730 | D31: =SUMPRODUCT(ISNUMBER(SEARCH($A31,Anforderungen!$I$7:$I$2000))*(Anforderungen!$K$7:$K$2000="bewertet")) -> 0 | E31: =SUMPRODUCT(ISNUMBER(SEARCH($A31,Anforderungen!$I$7:$I$2000))*(Anforderungen!$K$7:$K$2000="erfüllt")) -> 0 | F31: =SUMPRODUCT(ISNUMBER(SEARCH($A31,Anforderungen!$I$7:$I$2000))*(Anforderungen!$K$7:$K$2000="trifft nicht zu")) -> 1 | G31: =IFERROR(E31/(B31-F31),0) -> 0
A32: Zuordnung prüfen | B32: =SUMPRODUCT(ISNUMBER(SEARCH($A32,Anforderungen!$I$7:$I$2000))*(Anforderungen!$B$7:$B$2000<>"")) -> 230 | C32: =SUMPRODUCT(ISNUMBER(SEARCH($A32,Anforderungen!$I$7:$I$2000))*(Anforderungen!$K$7:$K$2000="erfasst")) -> 230 | D32: =SUMPRODUCT(ISNUMBER(SEARCH($A32,Anforderungen!$I$7:$I$2000))*(Anforderungen!$K$7:$K$2000="bewertet")) -> 0 | E32: =SUMPRODUCT(ISNUMBER(SEARCH($A32,Anforderungen!$I$7:$I$2000))*(Anforderungen!$K$7:$K$2000="erfüllt")) -> 0 | F32: =SUMPRODUCT(ISNUMBER(SEARCH($A32,Anforderungen!$I$7:$I$2000))*(Anforderungen!$K$7:$K$2000="trifft nicht zu")) -> 0 | G32: =IFERROR(E32/(B32-F32),0) -> 0
A35: 3 Nach Komponente
A36: Merkmal | B36: Gesamt | C36: Erfasst | D36: Bewertet | E36: Erfüllt | F36: Trifft nicht zu | G36: Erfüllungsgrad
A37: Ladeeinrichtung | B37: =SUMPRODUCT(ISNUMBER(SEARCH($A37,Anforderungen!$J$7:$J$2000))*(Anforderungen!$B$7:$B$2000<>"")) -> 171 | C37: =SUMPRODUCT(ISNUMBER(SEARCH($A37,Anforderungen!$J$7:$J$2000))*(Anforderungen!$K$7:$K$2000="erfasst")) -> 170 | D37: =SUMPRODUCT(ISNUMBER(SEARCH($A37,Anforderungen!$J$7:$J$2000))*(Anforderungen!$K$7:$K$2000="bewertet")) -> 0 | E37: =SUMPRODUCT(ISNUMBER(SEARCH($A37,Anforderungen!$J$7:$J$2000))*(Anforderungen!$K$7:$K$2000="erfüllt")) -> 0 | F37: =SUMPRODUCT(ISNUMBER(SEARCH($A37,Anforderungen!$J$7:$J$2000))*(Anforderungen!$K$7:$K$2000="trifft nicht zu")) -> 1 | G37: =IFERROR(E37/(B37-F37),0) -> 0
A38: Abrechnungskomponente | B38: =SUMPRODUCT(ISNUMBER(SEARCH($A38,Anforderungen!$J$7:$J$2000))*(Anforderungen!$B$7:$B$2000<>"")) -> 50 | C38: =SUMPRODUCT(ISNUMBER(SEARCH($A38,Anforderungen!$J$7:$J$2000))*(Anforderungen!$K$7:$K$2000="erfasst")) -> 49 | D38: =SUMPRODUCT(ISNUMBER(SEARCH($A38,Anforderungen!$J$7:$J$2000))*(Anforderungen!$K$7:$K$2000="bewertet")) -> 0 | E38: =SUMPRODUCT(ISNUMBER(SEARCH($A38,Anforderungen!$J$7:$J$2000))*(Anforderungen!$K$7:$K$2000="erfüllt")) -> 0 | F38: =SUMPRODUCT(ISNUMBER(SEARCH($A38,Anforderungen!$J$7:$J$2000))*(Anforderungen!$K$7:$K$2000="trifft nicht zu")) -> 1 | G38: =IFERROR(E38/(B38-F38),0) -> 0
A39: Authentifizierungskomponente | B39: =SUMPRODUCT(ISNUMBER(SEARCH($A39,Anforderungen!$J$7:$J$2000))*(Anforderungen!$B$7:$B$2000<>"")) -> 66 | C39: =SUMPRODUCT(ISNUMBER(SEARCH($A39,Anforderungen!$J$7:$J$2000))*(Anforderungen!$K$7:$K$2000="erfasst")) -> 64 | D39: =SUMPRODUCT(ISNUMBER(SEARCH($A39,Anforderungen!$J$7:$J$2000))*(Anforderungen!$K$7:$K$2000="bewertet")) -> 0 | E39: =SUMPRODUCT(ISNUMBER(SEARCH($A39,Anforderungen!$J$7:$J$2000))*(Anforderungen!$K$7:$K$2000="erfüllt")) -> 2 | F39: =SUMPRODUCT(ISNUMBER(SEARCH($A39,Anforderungen!$J$7:$J$2000))*(Anforderungen!$K$7:$K$2000="trifft nicht zu")) -> 0 | G39: =IFERROR(E39/(B39-F39),0) -> 0.03030303
A40: Monitoring | B40: =SUMPRODUCT(ISNUMBER(SEARCH($A40,Anforderungen!$J$7:$J$2000))*(Anforderungen!$B$7:$B$2000<>"")) -> 44 | C40: =SUMPRODUCT(ISNUMBER(SEARCH($A40,Anforderungen!$J$7:$J$2000))*(Anforderungen!$K$7:$K$2000="erfasst")) -> 44 | D40: =SUMPRODUCT(ISNUMBER(SEARCH($A40,Anforderungen!$J$7:$J$2000))*(Anforderungen!$K$7:$K$2000="bewertet")) -> 0 | E40: =SUMPRODUCT(ISNUMBER(SEARCH($A40,Anforderungen!$J$7:$J$2000))*(Anforderungen!$K$7:$K$2000="erfüllt")) -> 0 | F40: =SUMPRODUCT(ISNUMBER(SEARCH($A40,Anforderungen!$J$7:$J$2000))*(Anforderungen!$K$7:$K$2000="trifft nicht zu")) -> 0 | G40: =IFERROR(E40/(B40-F40),0) -> 0
A41: OCPI Buchungskalender | B41: =SUMPRODUCT(ISNUMBER(SEARCH($A41,Anforderungen!$J$7:$J$2000))*(Anforderungen!$B$7:$B$2000<>"")) -> 102 | C41: =SUMPRODUCT(ISNUMBER(SEARCH($A41,Anforderungen!$J$7:$J$2000))*(Anforderungen!$K$7:$K$2000="erfasst")) -> 101 | D41: =SUMPRODUCT(ISNUMBER(SEARCH($A41,Anforderungen!$J$7:$J$2000))*(Anforderungen!$K$7:$K$2000="bewertet")) -> 0 | E41: =SUMPRODUCT(ISNUMBER(SEARCH($A41,Anforderungen!$J$7:$J$2000))*(Anforderungen!$K$7:$K$2000="erfüllt")) -> 1 | F41: =SUMPRODUCT(ISNUMBER(SEARCH($A41,Anforderungen!$J$7:$J$2000))*(Anforderungen!$K$7:$K$2000="trifft nicht zu")) -> 0 | G41: =IFERROR(E41/(B41-F41),0) -> 0.0098039216
A42: Anbindung | B42: =SUMPRODUCT(ISNUMBER(SEARCH($A42,Anforderungen!$J$7:$J$2000))*(Anforderungen!$B$7:$B$2000<>"")) -> 3 | C42: =SUMPRODUCT(ISNUMBER(SEARCH($A42,Anforderungen!$J$7:$J$2000))*(Anforderungen!$K$7:$K$2000="erfasst")) -> 2 | D42: =SUMPRODUCT(ISNUMBER(SEARCH($A42,Anforderungen!$J$7:$J$2000))*(Anforderungen!$K$7:$K$2000="bewertet")) -> 1 | E42: =SUMPRODUCT(ISNUMBER(SEARCH($A42,Anforderungen!$J$7:$J$2000))*(Anforderungen!$K$7:$K$2000="erfüllt")) -> 0 | F42: =SUMPRODUCT(ISNUMBER(SEARCH($A42,Anforderungen!$J$7:$J$2000))*(Anforderungen!$K$7:$K$2000="trifft nicht zu")) -> 0 | G42: =IFERROR(E42/(B42-F42),0) -> 0
A43: Reservierungsplattform | B43: =SUMPRODUCT(ISNUMBER(SEARCH($A43,Anforderungen!$J$7:$J$2000))*(Anforderungen!$B$7:$B$2000<>"")) -> 12 | C43: =SUMPRODUCT(ISNUMBER(SEARCH($A43,Anforderungen!$J$7:$J$2000))*(Anforderungen!$K$7:$K$2000="erfasst")) -> 12 | D43: =SUMPRODUCT(ISNUMBER(SEARCH($A43,Anforderungen!$J$7:$J$2000))*(Anforderungen!$K$7:$K$2000="bewertet")) -> 0 | E43: =SUMPRODUCT(ISNUMBER(SEARCH($A43,Anforderungen!$J$7:$J$2000))*(Anforderungen!$K$7:$K$2000="erfüllt")) -> 0 | F43: =SUMPRODUCT(ISNUMBER(SEARCH($A43,Anforderungen!$J$7:$J$2000))*(Anforderungen!$K$7:$K$2000="trifft nicht zu")) -> 0 | G43: =IFERROR(E43/(B43-F43),0) -> 0
A44: Belegungsdetektion | B44: =SUMPRODUCT(ISNUMBER(SEARCH($A44,Anforderungen!$J$7:$J$2000))*(Anforderungen!$B$7:$B$2000<>"")) -> 5 | C44: =SUMPRODUCT(ISNUMBER(SEARCH($A44,Anforderungen!$J$7:$J$2000))*(Anforderungen!$K$7:$K$2000="erfasst")) -> 4 | D44: =SUMPRODUCT(ISNUMBER(SEARCH($A44,Anforderungen!$J$7:$J$2000))*(Anforderungen!$K$7:$K$2000="bewertet")) -> 0 | E44: =SUMPRODUCT(ISNUMBER(SEARCH($A44,Anforderungen!$J$7:$J$2000))*(Anforderungen!$K$7:$K$2000="erfüllt")) -> 1 | F44: =SUMPRODUCT(ISNUMBER(SEARCH($A44,Anforderungen!$J$7:$J$2000))*(Anforderungen!$K$7:$K$2000="trifft nicht zu")) -> 0 | G44: =IFERROR(E44/(B44-F44),0) -> 0.2
A45: Dynamische Anzeige | B45: =SUMPRODUCT(ISNUMBER(SEARCH($A45,Anforderungen!$J$7:$J$2000))*(Anforderungen!$B$7:$B$2000<>"")) -> 12 | C45: =SUMPRODUCT(ISNUMBER(SEARCH($A45,Anforderungen!$J$7:$J$2000))*(Anforderungen!$K$7:$K$2000="erfasst")) -> 10 | D45: =SUMPRODUCT(ISNUMBER(SEARCH($A45,Anforderungen!$J$7:$J$2000))*(Anforderungen!$K$7:$K$2000="bewertet")) -> 0 | E45: =SUMPRODUCT(ISNUMBER(SEARCH($A45,Anforderungen!$J$7:$J$2000))*(Anforderungen!$K$7:$K$2000="erfüllt")) -> 2 | F45: =SUMPRODUCT(ISNUMBER(SEARCH($A45,Anforderungen!$J$7:$J$2000))*(Anforderungen!$K$7:$K$2000="trifft nicht zu")) -> 0 | G45: =IFERROR(E45/(B45-F45),0) -> 0.16666667
A46: Kennzeichenerfassung | B46: =SUMPRODUCT(ISNUMBER(SEARCH($A46,Anforderungen!$J$7:$J$2000))*(Anforderungen!$B$7:$B$2000<>"")) -> 8 | C46: =SUMPRODUCT(ISNUMBER(SEARCH($A46,Anforderungen!$J$7:$J$2000))*(Anforderungen!$K$7:$K$2000="erfasst")) -> 8 | D46: =SUMPRODUCT(ISNUMBER(SEARCH($A46,Anforderungen!$J$7:$J$2000))*(Anforderungen!$K$7:$K$2000="bewertet")) -> 0 | E46: =SUMPRODUCT(ISNUMBER(SEARCH($A46,Anforderungen!$J$7:$J$2000))*(Anforderungen!$K$7:$K$2000="erfüllt")) -> 0 | F46: =SUMPRODUCT(ISNUMBER(SEARCH($A46,Anforderungen!$J$7:$J$2000))*(Anforderungen!$K$7:$K$2000="trifft nicht zu")) -> 0 | G46: =IFERROR(E46/(B46-F46),0) -> 0
A47: Pönalisierungssystem | B47: =SUMPRODUCT(ISNUMBER(SEARCH($A47,Anforderungen!$J$7:$J$2000))*(Anforderungen!$B$7:$B$2000<>"")) -> 35 | C47: =SUMPRODUCT(ISNUMBER(SEARCH($A47,Anforderungen!$J$7:$J$2000))*(Anforderungen!$K$7:$K$2000="erfasst")) -> 35 | D47: =SUMPRODUCT(ISNUMBER(SEARCH($A47,Anforderungen!$J$7:$J$2000))*(Anforderungen!$K$7:$K$2000="bewertet")) -> 0 | E47: =SUMPRODUCT(ISNUMBER(SEARCH($A47,Anforderungen!$J$7:$J$2000))*(Anforderungen!$K$7:$K$2000="erfüllt")) -> 0 | F47: =SUMPRODUCT(ISNUMBER(SEARCH($A47,Anforderungen!$J$7:$J$2000))*(Anforderungen!$K$7:$K$2000="trifft nicht zu")) -> 0 | G47: =IFERROR(E47/(B47-F47),0) -> 0
A48: Schrankensteuerung | B48: =SUMPRODUCT(ISNUMBER(SEARCH($A48,Anforderungen!$J$7:$J$2000))*(Anforderungen!$B$7:$B$2000<>"")) -> 25 | C48: =SUMPRODUCT(ISNUMBER(SEARCH($A48,Anforderungen!$J$7:$J$2000))*(Anforderungen!$K$7:$K$2000="erfasst")) -> 21 | D48: =SUMPRODUCT(ISNUMBER(SEARCH($A48,Anforderungen!$J$7:$J$2000))*(Anforderungen!$K$7:$K$2000="bewertet")) -> 0 | E48: =SUMPRODUCT(ISNUMBER(SEARCH($A48,Anforderungen!$J$7:$J$2000))*(Anforderungen!$K$7:$K$2000="erfüllt")) -> 4 | F48: =SUMPRODUCT(ISNUMBER(SEARCH($A48,Anforderungen!$J$7:$J$2000))*(Anforderungen!$K$7:$K$2000="trifft nicht zu")) -> 0 | G48: =IFERROR(E48/(B48-F48),0) -> 0.16
... A51: Zuordnung prüfen | B51: =SUMPRODUCT(ISNUMBER(SEARCH($A51,Anforderungen!$J$7:$J$2000))*(Anforderungen!$B$7:$B$2000<>"")) -> 230 | C51: =SUMPRODUCT(ISNUMBER(SEARCH($A51,Anforderungen!$J$7:$J$2000))*(Anforderungen!$K$7:$K$2000="erfasst")) -> 230 | D51: =SUMPRODUCT(ISNUMBER(SEARCH($A51,Anforderungen!$J$7:$J$2000))*(Anforderungen!$K$7:$K$2000="bewertet")) -> 0 | E51: =SUMPRODUCT(ISNUMBER(SEARCH($A51,Anforderungen!$J$7:$J$2000))*(Anforderungen!$K$7:$K$2000="erfüllt")) -> 0 | F51: =SUMPRODUCT(ISNUMBER(SEARCH($A51,Anforderungen!$J$7:$J$2000))*(Anforderungen!$K$7:$K$2000="trifft nicht zu")) -> 0 | G51: =IFERROR(E51/(B51-F51),0) -> 0
A54: 4 Nach Dokument
A55: Merkmal | B55: Gesamt | C55: Erfasst | D55: Bewertet | E55: Erfüllt | F55: Trifft nicht zu | G55: Erfüllungsgrad
A56: Vertragsanlage 13 | B56: =COUNTIF(Anforderungen!$C$7:$C$2000,$A56) -> 52 | C56: =COUNTIFS(Anforderungen!$C$7:$C$2000,$A56,Anforderungen!$K$7:$K$2000,"erfasst") -> 52 | D56: =COUNTIFS(Anforderungen!$C$7:$C$2000,$A56,Anforderungen!$K$7:$K$2000,"bewertet") -> 0 | E56: =COUNTIFS(Anforderungen!$C$7:$C$2000,$A56,Anforderungen!$K$7:$K$2000,"erfüllt") -> 0 | F56: =COUNTIFS(Anforderungen!$C$7:$C$2000,$A56,Anforderungen!$K$7:$K$2000,"trifft nicht zu") -> 0 | G56: =IFERROR(E56/(B56-F56),0) -> 0
A57: Betreibervertrag | B57: =COUNTIF(Anforderungen!$C$7:$C$2000,$A57) -> 471 | C57: =COUNTIFS(Anforderungen!$C$7:$C$2000,$A57,Anforderungen!$K$7:$K$2000,"erfasst") -> 467 | D57: =COUNTIFS(Anforderungen!$C$7:$C$2000,$A57,Anforderungen!$K$7:$K$2000,"bewertet") -> 1 | E57: =COUNTIFS(Anforderungen!$C$7:$C$2000,$A57,Anforderungen!$K$7:$K$2000,"erfüllt") -> 1 | F57: =COUNTIFS(Anforderungen!$C$7:$C$2000,$A57,Anforderungen!$K$7:$K$2000,"trifft nicht zu") -> 2 | G57: =IFERROR(E57/(B57-F57),0) -> 0.0021321962
A58: Bieterfragenkatalog | B58: =COUNTIF(Anforderungen!$C$7:$C$2000,$A58) -> 663 | C58: =COUNTIFS(Anforderungen!$C$7:$C$2000,$A58,Anforderungen!$K$7:$K$2000,"erfasst") -> 661 | D58: =COUNTIFS(Anforderungen!$C$7:$C$2000,$A58,Anforderungen!$K$7:$K$2000,"bewertet") -> 0 | E58: =COUNTIFS(Anforderungen!$C$7:$C$2000,$A58,Anforderungen!$K$7:$K$2000,"erfüllt") -> 0 | F58: =COUNTIFS(Anforderungen!$C$7:$C$2000,$A58,Anforderungen!$K$7:$K$2000,"trifft nicht zu") -> 2 | G58: =IFERROR(E58/(B58-F58),0) -> 0
A59: Vertragsanlage 10 | B59: =COUNTIF(Anforderungen!$C$7:$C$2000,$A59) -> 107 | C59: =COUNTIFS(Anforderungen!$C$7:$C$2000,$A59,Anforderungen!$K$7:$K$2000,"erfasst") -> 107 | D59: =COUNTIFS(Anforderungen!$C$7:$C$2000,$A59,Anforderungen!$K$7:$K$2000,"bewertet") -> 0 | E59: =COUNTIFS(Anforderungen!$C$7:$C$2000,$A59,Anforderungen!$K$7:$K$2000,"erfüllt") -> 0 | F59: =COUNTIFS(Anforderungen!$C$7:$C$2000,$A59,Anforderungen!$K$7:$K$2000,"trifft nicht zu") -> 0 | G59: =IFERROR(E59/(B59-F59),0) -> 0
A60: Vertragsanlage 4 | B60: =COUNTIF(Anforderungen!$C$7:$C$2000,$A60) -> 7 | C60: =COUNTIFS(Anforderungen!$C$7:$C$2000,$A60,Anforderungen!$K$7:$K$2000,"erfasst") -> 1 | D60: =COUNTIFS(Anforderungen!$C$7:$C$2000,$A60,Anforderungen!$K$7:$K$2000,"bewertet") -> 2 | E60: =COUNTIFS(Anforderungen!$C$7:$C$2000,$A60,Anforderungen!$K$7:$K$2000,"erfüllt") -> 3 | F60: =COUNTIFS(Anforderungen!$C$7:$C$2000,$A60,Anforderungen!$K$7:$K$2000,"trifft nicht zu") -> 1 | G60: =IFERROR(E60/(B60-F60),0) -> 0.5
A61: Vertragsanlage 6 | B61: =COUNTIF(Anforderungen!$C$7:$C$2000,$A61) -> 82 | C61: =COUNTIFS(Anforderungen!$C$7:$C$2000,$A61,Anforderungen!$K$7:$K$2000,"erfasst") -> 76 | D61: =COUNTIFS(Anforderungen!$C$7:$C$2000,$A61,Anforderungen!$K$7:$K$2000,"bewertet") -> 0 | E61: =COUNTIFS(Anforderungen!$C$7:$C$2000,$A61,Anforderungen!$K$7:$K$2000,"erfüllt") -> 6 | F61: =COUNTIFS(Anforderungen!$C$7:$C$2000,$A61,Anforderungen!$K$7:$K$2000,"trifft nicht zu") -> 0 | G61: =IFERROR(E61/(B61-F61),0) -> 0.073170732
A64: 5 Gesamtstatus
A65: Status | B65: Anforderungen | C65: Anteil
A66: erfasst | B66: =COUNTIF(Anforderungen!$K$7:$K$2000,A66) -> 1364 | C66: =IFERROR(B66/COUNTA(Anforderungen!$B$7:$B$2000),0) -> 0.9869754
A67: bewertet | B67: =COUNTIF(Anforderungen!$K$7:$K$2000,A67) -> 3 | C67: =IFERROR(B67/COUNTA(Anforderungen!$B$7:$B$2000),0) -> 0.002170767
A68: erfüllt | B68: =COUNTIF(Anforderungen!$K$7:$K$2000,A68) -> 10 | C68: =IFERROR(B68/COUNTA(Anforderungen!$B$7:$B$2000),0) -> 0.00723589
A69: trifft nicht zu | B69: =COUNTIF(Anforderungen!$K$7:$K$2000,A69) -> 5 | C69: =IFERROR(B69/COUNTA(Anforderungen!$B$7:$B$2000),0) -> 0.003617945
A71: 6 Vollständigkeit Erfüllung / Nachweis
A72: Prüfung | B72: Anforderungen | C72: Hinweis
A73: Erfüllt + Datum + Nachweis | B73: =COUNTIFS(Anforderungen!$K$7:$K$2000,"erfüllt",Anforderungen!$L$7:$L$2000,"<>",Anforderungen!$M$7:$M$2000,"<>") -> 10 | C73: vollständig dokumentiert
A74: Erfüllt ohne Datum | B74: =COUNTIFS(Anforderungen!$K$7:$K$2000,"erfüllt",Anforderungen!$L$7:$L$2000,"") -> 0 | C74: Datum in „Erfüllt am“ ergänzen
A75: Erfüllt ohne Nachweis / Notiz | B75: =COUNTIFS(Anforderungen!$K$7:$K$2000,"erfüllt",Anforderungen!$M$7:$M$2000,"") -> 0 | C75: Nachweis oder kurze Notiz ergänzen
A76: Trifft nicht zu ohne Begründung | B76: =COUNTIFS(Anforderungen!$K$7:$K$2000,"trifft nicht zu",Anforderungen!$M$7:$M$2000,"") -> 2 | C76: Begründung in „Nachweis / Notiz“ ergänzen
A77: Anwendbare Anforderungen | B77: =COUNTA(Anforderungen!$B$7:$B$2000)-COUNTIF(Anforderungen!$K$7:$K$2000,"trifft nicht zu") -> 1377 | C77: Gesamt abzüglich „trifft nicht zu“
A78: Offene Zuordnung Komponente | B78: =COUNTIF(Anforderungen!$J$7:$J$2000,"Zuordnung prüfen") -> 230 | C78: Komponente fachlich zuordnen
A79: Offene Zuordnung Partner | B79: =COUNTIF(Anforderungen!$I$7:$I$2000,"Zuordnung prüfen") -> 230 | C79: Partner fachlich zuordnen

Sheet Komponenten
A1: Komponenten & Schnittstellen
A2: Struktur Vergabeeinheit → Partner → Art → Komponente. Anzahl und Status der Anforderungen werden automatisch aus dem Register „Anforderungen“ abgeleitet.
A3: Statuslogik: erfasst hat Vorrang vor bewertet; erst wenn keine offenen Vorstufen mehr vorhanden sind, wird erfüllt bzw. trifft nicht zu angezeigt. Nur die Felder Vergabeeinheit, Partner, Art, Komponente und Bemerkung werden gepflegt – alles Übrige rechnet sich selbst.
A5: Vergabeeinheit | B5: Partner | C5: Art | D5: Komponente | E5: Anforderungen | F5: erfasst | G5: bewertet | H5: erfüllt | I5: trifft nicht zu | J5: Status | K5: Bemerkung / Schnittstelle | N5: Partner
A6: LIS | B6: Alpitronic | C6: Komponente | D6: Ladeeinrichtung | E6: =IF($D6="","",SUMPRODUCT(ISNUMBER(SEARCH($D6,Anforderungen!$J$7:$J$2000))*(Anforderungen!$B$7:$B$2000<>""))) -> 171 | F6: =IF($D6="","",SUMPRODUCT(ISNUMBER(SEARCH($D6,Anforderungen!$J$7:$J$2000))*(Anforderungen!$K$7:$K$2000="erfasst"))) -> 170 | G6: =IF($D6="","",SUMPRODUCT(ISNUMBER(SEARCH($D6,Anforderungen!$J$7:$J$2000))*(Anforderungen!$K$7:$K$2000="bewertet"))) -> 0 | H6: =IF($D6="","",SUMPRODUCT(ISNUMBER(SEARCH($D6,Anforderungen!$J$7:$J$2000))*(Anforderungen!$K$7:$K$2000="erfüllt"))) -> 0 | I6: =IF($D6="","",SUMPRODUCT(ISNUMBER(SEARCH($D6,Anforderungen!$J$7:$J$2000))*(Anforderungen!$K$7:$K$2000="trifft nicht zu"))) -> 1 | J6: =IF($D6="","",IF($E6=0,"keine Anforderungen",IF($F6>0,"erfasst",IF($G6>0,"bewertet",IF($H6>0,"erfüllt","trifft nicht zu"))))) -> erfasst | N6: Alpitronic
A7: WWL | B7: eRound | C7: Komponente | D7: Abrechnungskomponente | E7: =IF($D7="","",SUMPRODUCT(ISNUMBER(SEARCH($D7,Anforderungen!$J$7:$J$2000))*(Anforderungen!$B$7:$B$2000<>""))) -> 50 | F7: =IF($D7="","",SUMPRODUCT(ISNUMBER(SEARCH($D7,Anforderungen!$J$7:$J$2000))*(Anforderungen!$K$7:$K$2000="erfasst"))) -> 49 | G7: =IF($D7="","",SUMPRODUCT(ISNUMBER(SEARCH($D7,Anforderungen!$J$7:$J$2000))*(Anforderungen!$K$7:$K$2000="bewertet"))) -> 0 | H7: =IF($D7="","",SUMPRODUCT(ISNUMBER(SEARCH($D7,Anforderungen!$J$7:$J$2000))*(Anforderungen!$K$7:$K$2000="erfüllt"))) -> 0 | I7: =IF($D7="","",SUMPRODUCT(ISNUMBER(SEARCH($D7,Anforderungen!$J$7:$J$2000))*(Anforderungen!$K$7:$K$2000="trifft nicht zu"))) -> 1 | J7: =IF($D7="","",IF($E7=0,"keine Anforderungen",IF($F7>0,"erfasst",IF($G7>0,"bewertet",IF($H7>0,"erfüllt","trifft nicht zu"))))) -> erfasst | N7: eRound
A8: WWL | B8: eRound | C8: Komponente | D8: Authentifizierungskomponente | E8: =IF($D8="","",SUMPRODUCT(ISNUMBER(SEARCH($D8,Anforderungen!$J$7:$J$2000))*(Anforderungen!$B$7:$B$2000<>""))) -> 66 | F8: =IF($D8="","",SUMPRODUCT(ISNUMBER(SEARCH($D8,Anforderungen!$J$7:$J$2000))*(Anforderungen!$K$7:$K$2000="erfasst"))) -> 64 | G8: =IF($D8="","",SUMPRODUCT(ISNUMBER(SEARCH($D8,Anforderungen!$J$7:$J$2000))*(Anforderungen!$K$7:$K$2000="bewertet"))) -> 0 | H8: =IF($D8="","",SUMPRODUCT(ISNUMBER(SEARCH($D8,Anforderungen!$J$7:$J$2000))*(Anforderungen!$K$7:$K$2000="erfüllt"))) -> 2 | I8: =IF($D8="","",SUMPRODUCT(ISNUMBER(SEARCH($D8,Anforderungen!$J$7:$J$2000))*(Anforderungen!$K$7:$K$2000="trifft nicht zu"))) -> 0 | J8: =IF($D8="","",IF($E8=0,"keine Anforderungen",IF($F8>0,"erfasst",IF($G8>0,"bewertet",IF($H8>0,"erfüllt","trifft nicht zu"))))) -> erfasst | N8: Reservierungsplattform
A9: WWL | B9: eRound | C9: Komponente | D9: Monitoring | E9: =IF($D9="","",SUMPRODUCT(ISNUMBER(SEARCH($D9,Anforderungen!$J$7:$J$2000))*(Anforderungen!$B$7:$B$2000<>""))) -> 44 | F9: =IF($D9="","",SUMPRODUCT(ISNUMBER(SEARCH($D9,Anforderungen!$J$7:$J$2000))*(Anforderungen!$K$7:$K$2000="erfasst"))) -> 44 | G9: =IF($D9="","",SUMPRODUCT(ISNUMBER(SEARCH($D9,Anforderungen!$J$7:$J$2000))*(Anforderungen!$K$7:$K$2000="bewertet"))) -> 0 | H9: =IF($D9="","",SUMPRODUCT(ISNUMBER(SEARCH($D9,Anforderungen!$J$7:$J$2000))*(Anforderungen!$K$7:$K$2000="erfüllt"))) -> 0 | I9: =IF($D9="","",SUMPRODUCT(ISNUMBER(SEARCH($D9,Anforderungen!$J$7:$J$2000))*(Anforderungen!$K$7:$K$2000="trifft nicht zu"))) -> 0 | J9: =IF($D9="","",IF($E9=0,"keine Anforderungen",IF($F9>0,"erfasst",IF($G9>0,"bewertet",IF($H9>0,"erfüllt","trifft nicht zu"))))) -> erfasst | N9: SCS
A10: WWL | B10: eRound | C10: Komponente | D10: OCPI Buchungskalender | E10: =IF($D10="","",SUMPRODUCT(ISNUMBER(SEARCH($D10,Anforderungen!$J$7:$J$2000))*(Anforderungen!$B$7:$B$2000<>""))) -> 102 | F10: =IF($D10="","",SUMPRODUCT(ISNUMBER(SEARCH($D10,Anforderungen!$J$7:$J$2000))*(Anforderungen!$K$7:$K$2000="erfasst"))) -> 101 | G10: =IF($D10="","",SUMPRODUCT(ISNUMBER(SEARCH($D10,Anforderungen!$J$7:$J$2000))*(Anforderungen!$K$7:$K$2000="bewertet"))) -> 0 | H10: =IF($D10="","",SUMPRODUCT(ISNUMBER(SEARCH($D10,Anforderungen!$J$7:$J$2000))*(Anforderungen!$K$7:$K$2000="erfüllt"))) -> 1 | I10: =IF($D10="","",SUMPRODUCT(ISNUMBER(SEARCH($D10,Anforderungen!$J$7:$J$2000))*(Anforderungen!$K$7:$K$2000="trifft nicht zu"))) -> 0 | J10: =IF($D10="","",IF($E10=0,"keine Anforderungen",IF($F10>0,"erfasst",IF($G10>0,"bewertet",IF($H10>0,"erfüllt","trifft nicht zu"))))) -> erfasst | N10: Schrankenhersteller
A11: SmartInfra | B11: Reservierungsplattform | C11: Komponente | D11: Anbindung | E11: =IF($D11="","",SUMPRODUCT(ISNUMBER(SEARCH($D11,Anforderungen!$J$7:$J$2000))*(Anforderungen!$B$7:$B$2000<>""))) -> 3 | F11: =IF($D11="","",SUMPRODUCT(ISNUMBER(SEARCH($D11,Anforderungen!$J$7:$J$2000))*(Anforderungen!$K$7:$K$2000="erfasst"))) -> 2 | G11: =IF($D11="","",SUMPRODUCT(ISNUMBER(SEARCH($D11,Anforderungen!$J$7:$J$2000))*(Anforderungen!$K$7:$K$2000="bewertet"))) -> 1 | H11: =IF($D11="","",SUMPRODUCT(ISNUMBER(SEARCH($D11,Anforderungen!$J$7:$J$2000))*(Anforderungen!$K$7:$K$2000="erfüllt"))) -> 0 | I11: =IF($D11="","",SUMPRODUCT(ISNUMBER(SEARCH($D11,Anforderungen!$J$7:$J$2000))*(Anforderungen!$K$7:$K$2000="trifft nicht zu"))) -> 0 | J11: =IF($D11="","",IF($E11=0,"keine Anforderungen",IF($F11>0,"erfasst",IF($G11>0,"bewertet",IF($H11>0,"erfüllt","trifft nicht zu"))))) -> erfasst | N11: WWL
A12: SmartInfra | B12: Reservierungsplattform | C12: Komponente | D12: Reservierungsplattform | E12: =IF($D12="","",SUMPRODUCT(ISNUMBER(SEARCH($D12,Anforderungen!$J$7:$J$2000))*(Anforderungen!$B$7:$B$2000<>""))) -> 12 | F12: =IF($D12="","",SUMPRODUCT(ISNUMBER(SEARCH($D12,Anforderungen!$J$7:$J$2000))*(Anforderungen!$K$7:$K$2000="erfasst"))) -> 12 | G12: =IF($D12="","",SUMPRODUCT(ISNUMBER(SEARCH($D12,Anforderungen!$J$7:$J$2000))*(Anforderungen!$K$7:$K$2000="bewertet"))) -> 0 | H12: =IF($D12="","",SUMPRODUCT(ISNUMBER(SEARCH($D12,Anforderungen!$J$7:$J$2000))*(Anforderungen!$K$7:$K$2000="erfüllt"))) -> 0 | I12: =IF($D12="","",SUMPRODUCT(ISNUMBER(SEARCH($D12,Anforderungen!$J$7:$J$2000))*(Anforderungen!$K$7:$K$2000="trifft nicht zu"))) -> 0 | J12: =IF($D12="","",IF($E12=0,"keine Anforderungen",IF($F12>0,"erfasst",IF($G12>0,"bewertet",IF($H12>0,"erfüllt","trifft nicht zu"))))) -> erfasst | N12: Autostrom+
A13: SmartInfra | B13: SCS | C13: Komponente | D13: Belegungsdetektion | E13: =IF($D13="","",SUMPRODUCT(ISNUMBER(SEARCH($D13,Anforderungen!$J$7:$J$2000))*(Anforderungen!$B$7:$B$2000<>""))) -> 5 | F13: =IF($D13="","",SUMPRODUCT(ISNUMBER(SEARCH($D13,Anforderungen!$J$7:$J$2000))*(Anforderungen!$K$7:$K$2000="erfasst"))) -> 4 | G13: =IF($D13="","",SUMPRODUCT(ISNUMBER(SEARCH($D13,Anforderungen!$J$7:$J$2000))*(Anforderungen!$K$7:$K$2000="bewertet"))) -> 0 | H13: =IF($D13="","",SUMPRODUCT(ISNUMBER(SEARCH($D13,Anforderungen!$J$7:$J$2000))*(Anforderungen!$K$7:$K$2000="erfüllt"))) -> 1 | I13: =IF($D13="","",SUMPRODUCT(ISNUMBER(SEARCH($D13,Anforderungen!$J$7:$J$2000))*(Anforderungen!$K$7:$K$2000="trifft nicht zu"))) -> 0 | J13: =IF($D13="","",IF($E13=0,"keine Anforderungen",IF($F13>0,"erfasst",IF($G13>0,"bewertet",IF($H13>0,"erfüllt","trifft nicht zu"))))) -> erfasst | N13: eRound / SCS
A14: SmartInfra | B14: SCS | C14: Komponente | D14: Dynamische Anzeige | E14: =IF($D14="","",SUMPRODUCT(ISNUMBER(SEARCH($D14,Anforderungen!$J$7:$J$2000))*(Anforderungen!$B$7:$B$2000<>""))) -> 12 | F14: =IF($D14="","",SUMPRODUCT(ISNUMBER(SEARCH($D14,Anforderungen!$J$7:$J$2000))*(Anforderungen!$K$7:$K$2000="erfasst"))) -> 10 | G14: =IF($D14="","",SUMPRODUCT(ISNUMBER(SEARCH($D14,Anforderungen!$J$7:$J$2000))*(Anforderungen!$K$7:$K$2000="bewertet"))) -> 0 | H14: =IF($D14="","",SUMPRODUCT(ISNUMBER(SEARCH($D14,Anforderungen!$J$7:$J$2000))*(Anforderungen!$K$7:$K$2000="erfüllt"))) -> 2 | I14: =IF($D14="","",SUMPRODUCT(ISNUMBER(SEARCH($D14,Anforderungen!$J$7:$J$2000))*(Anforderungen!$K$7:$K$2000="trifft nicht zu"))) -> 0 | J14: =IF($D14="","",IF($E14=0,"keine Anforderungen",IF($F14>0,"erfasst",IF($G14>0,"bewertet",IF($H14>0,"erfüllt","trifft nicht zu"))))) -> erfasst | N14: Schrankenhersteller / SCS
A15: SmartInfra | B15: SCS | C15: Komponente | D15: Kennzeichenerfassung | E15: =IF($D15="","",SUMPRODUCT(ISNUMBER(SEARCH($D15,Anforderungen!$J$7:$J$2000))*(Anforderungen!$B$7:$B$2000<>""))) -> 8 | F15: =IF($D15="","",SUMPRODUCT(ISNUMBER(SEARCH($D15,Anforderungen!$J$7:$J$2000))*(Anforderungen!$K$7:$K$2000="erfasst"))) -> 8 | G15: =IF($D15="","",SUMPRODUCT(ISNUMBER(SEARCH($D15,Anforderungen!$J$7:$J$2000))*(Anforderungen!$K$7:$K$2000="bewertet"))) -> 0 | H15: =IF($D15="","",SUMPRODUCT(ISNUMBER(SEARCH($D15,Anforderungen!$J$7:$J$2000))*(Anforderungen!$K$7:$K$2000="erfüllt"))) -> 0 | I15: =IF($D15="","",SUMPRODUCT(ISNUMBER(SEARCH($D15,Anforderungen!$J$7:$J$2000))*(Anforderungen!$K$7:$K$2000="trifft nicht zu"))) -> 0 | J15: =IF($D15="","",IF($E15=0,"keine Anforderungen",IF($F15>0,"erfasst",IF($G15>0,"bewertet",IF($H15>0,"erfüllt","trifft nicht zu"))))) -> erfasst | N15: Schrankenhersteller / SCS / eRound
A16: SmartInfra | B16: SCS | C16: Komponente | D16: Pönalisierungssystem | E16: =IF($D16="","",SUMPRODUCT(ISNUMBER(SEARCH($D16,Anforderungen!$J$7:$J$2000))*(Anforderungen!$B$7:$B$2000<>""))) -> 35 | F16: =IF($D16="","",SUMPRODUCT(ISNUMBER(SEARCH($D16,Anforderungen!$J$7:$J$2000))*(Anforderungen!$K$7:$K$2000="erfasst"))) -> 35 | G16: =IF($D16="","",SUMPRODUCT(ISNUMBER(SEARCH($D16,Anforderungen!$J$7:$J$2000))*(Anforderungen!$K$7:$K$2000="bewertet"))) -> 0 | H16: =IF($D16="","",SUMPRODUCT(ISNUMBER(SEARCH($D16,Anforderungen!$J$7:$J$2000))*(Anforderungen!$K$7:$K$2000="erfüllt"))) -> 0 | I16: =IF($D16="","",SUMPRODUCT(ISNUMBER(SEARCH($D16,Anforderungen!$J$7:$J$2000))*(Anforderungen!$K$7:$K$2000="trifft nicht zu"))) -> 0 | J16: =IF($D16="","",IF($E16=0,"keine Anforderungen",IF($F16>0,"erfasst",IF($G16>0,"bewertet",IF($H16>0,"erfüllt","trifft nicht zu"))))) -> erfasst
A17: SmartInfra | B17: SCS | C17: Komponente | D17: Schrankensteuerung | E17: =IF($D17="","",SUMPRODUCT(ISNUMBER(SEARCH($D17,Anforderungen!$J$7:$J$2000))*(Anforderungen!$B$7:$B$2000<>""))) -> 25 | F17: =IF($D17="","",SUMPRODUCT(ISNUMBER(SEARCH($D17,Anforderungen!$J$7:$J$2000))*(Anforderungen!$K$7:$K$2000="erfasst"))) -> 21 | G17: =IF($D17="","",SUMPRODUCT(ISNUMBER(SEARCH($D17,Anforderungen!$J$7:$J$2000))*(Anforderungen!$K$7:$K$2000="bewertet"))) -> 0 | H17: =IF($D17="","",SUMPRODUCT(ISNUMBER(SEARCH($D17,Anforderungen!$J$7:$J$2000))*(Anforderungen!$K$7:$K$2000="erfüllt"))) -> 4 | I17: =IF($D17="","",SUMPRODUCT(ISNUMBER(SEARCH($D17,Anforderungen!$J$7:$J$2000))*(Anforderungen!$K$7:$K$2000="trifft nicht zu"))) -> 0 | J17: =IF($D17="","",IF($E17=0,"keine Anforderungen",IF($F17>0,"erfasst",IF($G17>0,"bewertet",IF($H17>0,"erfüllt","trifft nicht zu"))))) -> erfasst
A18: AUP | B18: tbd | C18: Komponente | D18: Beschilderung | E18: =IF($D18="","",SUMPRODUCT(ISNUMBER(SEARCH($D18,Anforderungen!$J$7:$J$2000))*(Anforderungen!$B$7:$B$2000<>""))) -> 11 | F18: =IF($D18="","",SUMPRODUCT(ISNUMBER(SEARCH($D18,Anforderungen!$J$7:$J$2000))*(Anforderungen!$K$7:$K$2000="erfasst"))) -> 10 | G18: =IF($D18="","",SUMPRODUCT(ISNUMBER(SEARCH($D18,Anforderungen!$J$7:$J$2000))*(Anforderungen!$K$7:$K$2000="bewertet"))) -> 0 | H18: =IF($D18="","",SUMPRODUCT(ISNUMBER(SEARCH($D18,Anforderungen!$J$7:$J$2000))*(Anforderungen!$K$7:$K$2000="erfüllt"))) -> 0 | I18: =IF($D18="","",SUMPRODUCT(ISNUMBER(SEARCH($D18,Anforderungen!$J$7:$J$2000))*(Anforderungen!$K$7:$K$2000="trifft nicht zu"))) -> 1 | J18: =IF($D18="","",IF($E18=0,"keine Anforderungen",IF($F18>0,"erfasst",IF($G18>0,"bewertet",IF($H18>0,"erfüllt","trifft nicht zu"))))) -> erfasst
A19: SmartInfra | B19: CAME | C19: Komponente | D19: Schrankenanlage | E19: =IF($D19="","",SUMPRODUCT(ISNUMBER(SEARCH($D19,Anforderungen!$J$7:$J$2000))*(Anforderungen!$B$7:$B$2000<>""))) -> 23 | F19: =IF($D19="","",SUMPRODUCT(ISNUMBER(SEARCH($D19,Anforderungen!$J$7:$J$2000))*(Anforderungen!$K$7:$K$2000="erfasst"))) -> 21 | G19: =IF($D19="","",SUMPRODUCT(ISNUMBER(SEARCH($D19,Anforderungen!$J$7:$J$2000))*(Anforderungen!$K$7:$K$2000="bewertet"))) -> 0 | H19: =IF($D19="","",SUMPRODUCT(ISNUMBER(SEARCH($D19,Anforderungen!$J$7:$J$2000))*(Anforderungen!$K$7:$K$2000="erfüllt"))) -> 2 | I19: =IF($D19="","",SUMPRODUCT(ISNUMBER(SEARCH($D19,Anforderungen!$J$7:$J$2000))*(Anforderungen!$K$7:$K$2000="trifft nicht zu"))) -> 0 | J19: =IF($D19="","",IF($E19=0,"keine Anforderungen",IF($F19>0,"erfasst",IF($G19>0,"bewertet",IF($H19>0,"erfüllt","trifft nicht zu"))))) -> erfasst
A20: Zuordnung prüfen | B20: eRound / SCS | C20: Schnittstelle | D20: OCPI Buchungskalender / Abrechnungskomponente / Belegungsdetektion / Pönalisierungssystem | E20: =IF($D20="","",SUMPRODUCT(ISNUMBER(SEARCH("OCPI Buchungskalender",Anforderungen!$J$7:$J$2000))*ISNUMBER(SEARCH("Abrechnungskomponente",Anforderungen!$J$7:$J$2000))*ISNUMBER(SEARCH("Belegungsdetektion",Anforderungen!$J$7:$J$2000))*ISNUMBER(SEARCH("Pönalisierungssystem",Anforderungen!$J$7:$J$2000))*(Anforderungen!$B$7:$B$2000<>""))) -> 1 | F20: =IF($D20="","",SUMPRODUCT(ISNUMBER(SEARCH("OCPI Buchungskalender",Anforderungen!$J$7:$J$2000))*ISNUMBER(SEARCH("Abrechnungskomponente",Anforderungen!$J$7:$J$2000))*ISNUMBER(SEARCH("Belegungsdetektion",Anforderungen!$J$7:$J$2000))*ISNUMBER(SEARCH("Pönalisierungssystem",Anforderungen!$J$7:$J$2000))*(Anforderungen!$K$7:$K$2000="erfasst"))) -> 1 | G20: =IF($D20="","",SUMPRODUCT(ISNUMBER(SEARCH("OCPI Buchungskalender",Anforderungen!$J$7:$J$2000))*ISNUMBER(SEARCH("Abrechnungskomponente",Anforderungen!$J$7:$J$2000))*ISNUMBER(SEARCH("Belegungsdetektion",Anforderungen!$J$7:$J$2000))*ISNUMBER(SEARCH("Pönalisierungssystem",Anforderungen!$J$7:$J$2000))*(Anforderungen!$K$7:$K$2000="bewertet"))) -> 0 | H20: =IF($D20="","",SUMPRODUCT(ISNUMBER(SEARCH("OCPI Buchungskalender",Anforderungen!$J$7:$J$2000))*ISNUMBER(SEARCH("Abrechnungskomponente",Anforderungen!$J$7:$J$2000))*ISNUMBER(SEARCH("Belegungsdetektion",Anforderungen!$J$7:$J$2000))*ISNUMBER(SEARCH("Pönalisierungssystem",Anforderungen!$J$7:$J$2000))*(Anforderungen!$K$7:$K$2000="erfüllt"))) -> 0 | I20: =IF($D20="","",SUMPRODUCT(ISNUMBER(SEARCH("OCPI Buchungskalender",Anforderungen!$J$7:$J$2000))*ISNUMBER(SEARCH("Abrechnungskomponente",Anforderungen!$J$7:$J$2000))*ISNUMBER(SEARCH("Belegungsdetektion",Anforderungen!$J$7:$J$2000))*ISNUMBER(SEARCH("Pönalisierungssystem",Anforderungen!$J$7:$J$2000))*(Anforderungen!$K$7:$K$2000="trifft nicht zu"))) -> 0 | J20: =IF($D20="","",IF($E20=0,"keine Anforderungen",IF($F20>0,"erfasst",IF($G20>0,"bewertet",IF($H20>0,"erfüllt","trifft nicht zu"))))) -> erfasst | K20: Schnittstelle: zählt Anforderungen, die alle genannten Komponenten betreffen.
A21: Zuordnung prüfen | B21: eRound / SCS | C21: Schnittstelle | D21: OCPI Buchungskalender / Dynamische Anzeige | E21: =IF($D21="","",SUMPRODUCT(ISNUMBER(SEARCH("OCPI Buchungskalender",Anforderungen!$J$7:$J$2000))*ISNUMBER(SEARCH("Dynamische Anzeige",Anforderungen!$J$7:$J$2000))*(Anforderungen!$B$7:$B$2000<>""))) -> 5 | F21: =IF($D21="","",SUMPRODUCT(ISNUMBER(SEARCH("OCPI Buchungskalender",Anforderungen!$J$7:$J$2000))*ISNUMBER(SEARCH("Dynamische Anzeige",Anforderungen!$J$7:$J$2000))*(Anforderungen!$K$7:$K$2000="erfasst"))) -> 4 | G21: =IF($D21="","",SUMPRODUCT(ISNUMBER(SEARCH("OCPI Buchungskalender",Anforderungen!$J$7:$J$2000))*ISNUMBER(SEARCH("Dynamische Anzeige",Anforderungen!$J$7:$J$2000))*(Anforderungen!$K$7:$K$2000="bewertet"))) -> 0 | H21: =IF($D21="","",SUMPRODUCT(ISNUMBER(SEARCH("OCPI Buchungskalender",Anforderungen!$J$7:$J$2000))*ISNUMBER(SEARCH("Dynamische Anzeige",Anforderungen!$J$7:$J$2000))*(Anforderungen!$K$7:$K$2000="erfüllt"))) -> 1 | I21: =IF($D21="","",SUMPRODUCT(ISNUMBER(SEARCH("OCPI Buchungskalender",Anforderungen!$J$7:$J$2000))*ISNUMBER(SEARCH("Dynamische Anzeige",Anforderungen!$J$7:$J$2000))*(Anforderungen!$K$7:$K$2000="trifft nicht zu"))) -> 0 | J21: =IF($D21="","",IF($E21=0,"keine Anforderungen",IF($F21>0,"erfasst",IF($G21>0,"bewertet",IF($H21>0,"erfüllt","trifft nicht zu"))))) -> erfasst | K21: Schnittstelle: zählt Anforderungen, die alle genannten Komponenten betreffen.
A22: Zuordnung prüfen | B22: eRound / SCS | C22: Schnittstelle | D22: OCPI Buchungskalender / Kennzeichenerfassung / Pönalisierungssystem | E22: =IF($D22="","",SUMPRODUCT(ISNUMBER(SEARCH("OCPI Buchungskalender",Anforderungen!$J$7:$J$2000))*ISNUMBER(SEARCH("Kennzeichenerfassung",Anforderungen!$J$7:$J$2000))*ISNUMBER(SEARCH("Pönalisierungssystem",Anforderungen!$J$7:$J$2000))*(Anforderungen!$B$7:$B$2000<>""))) -> 2 | F22: =IF($D22="","",SUMPRODUCT(ISNUMBER(SEARCH("OCPI Buchungskalender",Anforderungen!$J$7:$J$2000))*ISNUMBER(SEARCH("Kennzeichenerfassung",Anforderungen!$J$7:$J$2000))*ISNUMBER(SEARCH("Pönalisierungssystem",Anforderungen!$J$7:$J$2000))*(Anforderungen!$K$7:$K$2000="erfasst"))) -> 2 | G22: =IF($D22="","",SUMPRODUCT(ISNUMBER(SEARCH("OCPI Buchungskalender",Anforderungen!$J$7:$J$2000))*ISNUMBER(SEARCH("Kennzeichenerfassung",Anforderungen!$J$7:$J$2000))*ISNUMBER(SEARCH("Pönalisierungssystem",Anforderungen!$J$7:$J$2000))*(Anforderungen!$K$7:$K$2000="bewertet"))) -> 0 | H22: =IF($D22="","",SUMPRODUCT(ISNUMBER(SEARCH("OCPI Buchungskalender",Anforderungen!$J$7:$J$2000))*ISNUMBER(SEARCH("Kennzeichenerfassung",Anforderungen!$J$7:$J$2000))*ISNUMBER(SEARCH("Pönalisierungssystem",Anforderungen!$J$7:$J$2000))*(Anforderungen!$K$7:$K$2000="erfüllt"))) -> 0 | I22: =IF($D22="","",SUMPRODUCT(ISNUMBER(SEARCH("OCPI Buchungskalender",Anforderungen!$J$7:$J$2000))*ISNUMBER(SEARCH("Kennzeichenerfassung",Anforderungen!$J$7:$J$2000))*ISNUMBER(SEARCH("Pönalisierungssystem",Anforderungen!$J$7:$J$2000))*(Anforderungen!$K$7:$K$2000="trifft nicht zu"))) -> 0 | J22: =IF($D22="","",IF($E22=0,"keine Anforderungen",IF($F22>0,"erfasst",IF($G22>0,"bewertet",IF($H22>0,"erfüllt","trifft nicht zu"))))) -> erfasst | K22: Schnittstelle: zählt Anforderungen, die alle genannten Komponenten betreffen.
A23: Zuordnung prüfen | B23: eRound / SCS | C23: Schnittstelle | D23: Authentifizierungskomponente / Schrankensteuerung | E23: =IF($D23="","",SUMPRODUCT(ISNUMBER(SEARCH("Authentifizierungskomponente",Anforderungen!$J$7:$J$2000))*ISNUMBER(SEARCH("Schrankensteuerung",Anforderungen!$J$7:$J$2000))*(Anforderungen!$B$7:$B$2000<>""))) -> 8 | F23: =IF($D23="","",SUMPRODUCT(ISNUMBER(SEARCH("Authentifizierungskomponente",Anforderungen!$J$7:$J$2000))*ISNUMBER(SEARCH("Schrankensteuerung",Anforderungen!$J$7:$J$2000))*(Anforderungen!$K$7:$K$2000="erfasst"))) -> 7 | G23: =IF($D23="","",SUMPRODUCT(ISNUMBER(SEARCH("Authentifizierungskomponente",Anforderungen!$J$7:$J$2000))*ISNUMBER(SEARCH("Schrankensteuerung",Anforderungen!$J$7:$J$2000))*(Anforderungen!$K$7:$K$2000="bewertet"))) -> 0 | H23: =IF($D23="","",SUMPRODUCT(ISNUMBER(SEARCH("Authentifizierungskomponente",Anforderungen!$J$7:$J$2000))*ISNUMBER(SEARCH("Schrankensteuerung",Anforderungen!$J$7:$J$2000))*(Anforderungen!$K$7:$K$2000="erfüllt"))) -> 1 | I23: =IF($D23="","",SUMPRODUCT(ISNUMBER(SEARCH("Authentifizierungskomponente",Anforderungen!$J$7:$J$2000))*ISNUMBER(SEARCH("Schrankensteuerung",Anforderungen!$J$7:$J$2000))*(Anforderungen!$K$7:$K$2000="trifft nicht zu"))) -> 0 | J23: =IF($D23="","",IF($E23=0,"keine Anforderungen",IF($F23>0,"erfasst",IF($G23>0,"bewertet",IF($H23>0,"erfüllt","trifft nicht zu"))))) -> erfasst | K23: Schnittstelle: zählt Anforderungen, die alle genannten Komponenten betreffen.
E24: =IF($D24="","",SUMPRODUCT(ISNUMBER(SEARCH($D24,Anforderungen!$J$7:$J$2000))*(Anforderungen!$B$7:$B$2000<>""))) | F24: =IF($D24="","",SUMPRODUCT(ISNUMBER(SEARCH($D24,Anforderungen!$J$7:$J$2000))*(Anforderungen!$K$7:$K$2000="erfasst"))) | G24: =IF($D24="","",SUMPRODUCT(ISNUMBER(SEARCH($D24,Anforderungen!$J$7:$J$2000))*(Anforderungen!$K$7:$K$2000="bewertet"))) | H24: =IF($D24="","",SUMPRODUCT(ISNUMBER(SEARCH($D24,Anforderungen!$J$7:$J$2000))*(Anforderungen!$K$7:$K$2000="erfüllt"))) | I24: =IF($D24="","",SUMPRODUCT(ISNUMBER(SEARCH($D24,Anforderungen!$J$7:$J$2000))*(Anforderungen!$K$7:$K$2000="trifft nicht zu"))) | J24: =IF($D24="","",IF($E24=0,"keine Anforderungen",IF($F24>0,"erfasst",IF($G24>0,"bewertet",IF($H24>0,"erfüllt","trifft nicht zu")))))
E25: =IF($D25="","",SUMPRODUCT(ISNUMBER(SEARCH($D25,Anforderungen!$J$7:$J$2000))*(Anforderungen!$B$7:$B$2000<>""))) | F25: =IF($D25="","",SUMPRODUCT(ISNUMBER(SEARCH($D25,Anforderungen!$J$7:$J$2000))*(Anforderungen!$K$7:$K$2000="erfasst"))) | G25: =IF($D25="","",SUMPRODUCT(ISNUMBER(SEARCH($D25,Anforderungen!$J$7:$J$2000))*(Anforderungen!$K$7:$K$2000="bewertet"))) | H25: =IF($D25="","",SUMPRODUCT(ISNUMBER(SEARCH($D25,Anforderungen!$J$7:$J$2000))*(Anforderungen!$K$7:$K$2000="erfüllt"))) | I25: =IF($D25="","",SUMPRODUCT(ISNUMBER(SEARCH($D25,Anforderungen!$J$7:$J$2000))*(Anforderungen!$K$7:$K$2000="trifft nicht zu"))) | J25: =IF($D25="","",IF($E25=0,"keine Anforderungen",IF($F25>0,"erfasst",IF($G25>0,"bewertet",IF($H25>0,"erfüllt","trifft nicht zu")))))
E26: =IF($D26="","",SUMPRODUCT(ISNUMBER(SEARCH($D26,Anforderungen!$J$7:$J$2000))*(Anforderungen!$B$7:$B$2000<>""))) | F26: =IF($D26="","",SUMPRODUCT(ISNUMBER(SEARCH($D26,Anforderungen!$J$7:$J$2000))*(Anforderungen!$K$7:$K$2000="erfasst"))) | G26: =IF($D26="","",SUMPRODUCT(ISNUMBER(SEARCH($D26,Anforderungen!$J$7:$J$2000))*(Anforderungen!$K$7:$K$2000="bewertet"))) | H26: =IF($D26="","",SUMPRODUCT(ISNUMBER(SEARCH($D26,Anforderungen!$J$7:$J$2000))*(Anforderungen!$K$7:$K$2000="erfüllt"))) | I26: =IF($D26="","",SUMPRODUCT(ISNUMBER(SEARCH($D26,Anforderungen!$J$7:$J$2000))*(Anforderungen!$K$7:$K$2000="trifft nicht zu"))) | J26: =IF($D26="","",IF($E26=0,"keine Anforderungen",IF($F26>0,"erfasst",IF($G26>0,"bewertet",IF($H26>0,"erfüllt","trifft nicht zu")))))
E27: =IF($D27="","",SUMPRODUCT(ISNUMBER(SEARCH($D27,Anforderungen!$J$7:$J$2000))*(Anforderungen!$B$7:$B$2000<>""))) | F27: =IF($D27="","",SUMPRODUCT(ISNUMBER(SEARCH($D27,Anforderungen!$J$7:$J$2000))*(Anforderungen!$K$7:$K$2000="erfasst"))) | G27: =IF($D27="","",SUMPRODUCT(ISNUMBER(SEARCH($D27,Anforderungen!$J$7:$J$2000))*(Anforderungen!$K$7:$K$2000="bewertet"))) | H27: =IF($D27="","",SUMPRODUCT(ISNUMBER(SEARCH($D27,Anforderungen!$J$7:$J$2000))*(Anforderungen!$K$7:$K$2000="erfüllt"))) | I27: =IF($D27="","",SUMPRODUCT(ISNUMBER(SEARCH($D27,Anforderungen!$J$7:$J$2000))*(Anforderungen!$K$7:$K$2000="trifft nicht zu"))) | J27: =IF($D27="","",IF($E27=0,"keine Anforderungen",IF($F27>0,"erfasst",IF($G27>0,"bewertet",IF($H27>0,"erfüllt","trifft nicht zu")))))
E28: =IF($D28="","",SUMPRODUCT(ISNUMBER(SEARCH($D28,Anforderungen!$J$7:$J$2000))*(Anforderungen!$B$7:$B$2000<>""))) | F28: =IF($D28="","",SUMPRODUCT(ISNUMBER(SEARCH($D28,Anforderungen!$J$7:$J$2000))*(Anforderungen!$K$7:$K$2000="erfasst"))) | G28: =IF($D28="","",SUMPRODUCT(ISNUMBER(SEARCH($D28,Anforderungen!$J$7:$J$2000))*(Anforderungen!$K$7:$K$2000="bewertet"))) | H28: =IF($D28="","",SUMPRODUCT(ISNUMBER(SEARCH($D28,Anforderungen!$J$7:$J$2000))*(Anforderungen!$K$7:$K$2000="erfüllt"))) | I28: =IF($D28="","",SUMPRODUCT(ISNUMBER(SEARCH($D28,Anforderungen!$J$7:$J$2000))*(Anforderungen!$K$7:$K$2000="trifft nicht zu"))) | J28: =IF($D28="","",IF($E28=0,"keine Anforderungen",IF($F28>0,"erfasst",IF($G28>0,"bewertet",IF($H28>0,"erfüllt","trifft nicht zu")))))
E29: =IF($D29="","",SUMPRODUCT(ISNUMBER(SEARCH($D29,Anforderungen!$J$7:$J$2000))*(Anforderungen!$B$7:$B$2000<>""))) | F29: =IF($D29="","",SUMPRODUCT(ISNUMBER(SEARCH($D29,Anforderungen!$J$7:$J$2000))*(Anforderungen!$K$7:$K$2000="erfasst"))) | G29: =IF($D29="","",SUMPRODUCT(ISNUMBER(SEARCH($D29,Anforderungen!$J$7:$J$2000))*(Anforderungen!$K$7:$K$2000="bewertet"))) | H29: =IF($D29="","",SUMPRODUCT(ISNUMBER(SEARCH($D29,Anforderungen!$J$7:$J$2000))*(Anforderungen!$K$7:$K$2000="erfüllt"))) | I29: =IF($D29="","",SUMPRODUCT(ISNUMBER(SEARCH($D29,Anforderungen!$J$7:$J$2000))*(Anforderungen!$K$7:$K$2000="trifft nicht zu"))) | J29: =IF($D29="","",IF($E29=0,"keine Anforderungen",IF($F29>0,"erfasst",IF($G29>0,"bewertet",IF($H29>0,"erfüllt","trifft nicht zu"))))) | N29: tbd
A31: Organigramm – Vergabe- und Komponentenstruktur | M31: Textquellen Organigramm (Formeln – bitte nicht löschen)
A32: SmartInfra → Vergabeeinheit → Partner → Art → Komponente. Die Beschriftung jeder Box ist mit einer Formelzelle verknüpft (Spalte M) und aktualisiert sich automatisch, sobald sich Name, Anzahl oder Status in der Tabelle oberhalb ändern.
M34: ="SMARTINFRA"&CHAR(10)&COUNTA($D$6:$D$29)&" Komponenten / Schnittstellen" -> SMARTINFRA 18 Komponenten / Schnittstellen
M35: =$A6&CHAR(10)&COUNTIF($A$6:$A$29,$A6)&IF(COUNTIF($A$6:$A$29,$A6)=1," Komponente"," Komponenten") -> LIS 1 Komponente
M36: =$A7&CHAR(10)&COUNTIF($A$6:$A$29,$A7)&IF(COUNTIF($A$6:$A$29,$A7)=1," Komponente"," Komponenten") -> WWL 4 Komponenten
M37: =$A11&CHAR(10)&COUNTIF($A$6:$A$29,$A11)&IF(COUNTIF($A$6:$A$29,$A11)=1," Komponente"," Komponenten") -> SmartInfra 8 Komponenten
M38: =$A18&CHAR(10)&COUNTIF($A$6:$A$29,$A18)&IF(COUNTIF($A$6:$A$29,$A18)=1," Komponente"," Komponenten") -> AUP 1 Komponente
M39: =$A20&CHAR(10)&COUNTIF($A$6:$A$29,$A20)&IF(COUNTIF($A$6:$A$29,$A20)=1," Komponente"," Komponenten") -> Zuordnung prüfen 4 Komponenten
M40: =$B6&CHAR(10)&COUNTIFS($A$6:$A$29,$A6,$B$6:$B$29,$B6)&IF(COUNTIFS($A$6:$A$29,$A6,$B$6:$B$29,$B6)=1," Komponente"," Komponenten") -> Alpitronic 1 Komponente
M41: =$B7&CHAR(10)&COUNTIFS($A$6:$A$29,$A7,$B$6:$B$29,$B7)&IF(COUNTIFS($A$6:$A$29,$A7,$B$6:$B$29,$B7)=1," Komponente"," Komponenten") -> eRound 4 Komponenten
M42: =$B11&CHAR(10)&COUNTIFS($A$6:$A$29,$A11,$B$6:$B$29,$B11)&IF(COUNTIFS($A$6:$A$29,$A11,$B$6:$B$29,$B11)=1," Komponente"," Komponenten") -> Reservierungsplattform 2 Komponenten
M43: =$B13&CHAR(10)&COUNTIFS($A$6:$A$29,$A13,$B$6:$B$29,$B13)&IF(COUNTIFS($A$6:$A$29,$A13,$B$6:$B$29,$B13)=1," Komponente"," Komponenten") -> SCS 5 Komponenten
M44: =$B19&CHAR(10)&COUNTIFS($A$6:$A$29,$A19,$B$6:$B$29,$B19)&IF(COUNTIFS($A$6:$A$29,$A19,$B$6:$B$29,$B19)=1," Komponente"," Komponenten") -> CAME 1 Komponente
M45: =$B18&CHAR(10)&COUNTIFS($A$6:$A$29,$A18,$B$6:$B$29,$B18)&IF(COUNTIFS($A$6:$A$29,$A18,$B$6:$B$29,$B18)=1," Komponente"," Komponenten") -> tbd 1 Komponente
M46: =$B20&CHAR(10)&COUNTIFS($A$6:$A$29,$A20,$B$6:$B$29,$B20)&IF(COUNTIFS($A$6:$A$29,$A20,$B$6:$B$29,$B20)=1," Komponente"," Komponenten") -> eRound / SCS 4 Komponenten
M47: =$C6&CHAR(10)&COUNTIFS($A$6:$A$29,$A6,$B$6:$B$29,$B6,$C$6:$C$29,$C6)&IF(COUNTIFS($A$6:$A$29,$A6,$B$6:$B$29,$B6,$C$6:$C$29,$C6)=1," Eintrag"," Einträge") -> Komponente 1 Eintrag
M48: =$C7&CHAR(10)&COUNTIFS($A$6:$A$29,$A7,$B$6:$B$29,$B7,$C$6:$C$29,$C7)&IF(COUNTIFS($A$6:$A$29,$A7,$B$6:$B$29,$B7,$C$6:$C$29,$C7)=1," Eintrag"," Einträge") -> Komponente 4 Einträge
M49: =$C11&CHAR(10)&COUNTIFS($A$6:$A$29,$A11,$B$6:$B$29,$B11,$C$6:$C$29,$C11)&IF(COUNTIFS($A$6:$A$29,$A11,$B$6:$B$29,$B11,$C$6:$C$29,$C11)=1," Eintrag"," Einträge") -> Komponente 2 Einträge
M50: =$C13&CHAR(10)&COUNTIFS($A$6:$A$29,$A13,$B$6:$B$29,$B13,$C$6:$C$29,$C13)&IF(COUNTIFS($A$6:$A$29,$A13,$B$6:$B$29,$B13,$C$6:$C$29,$C13)=1," Eintrag"," Einträge") -> Komponente 5 Einträge
M51: =$C19&CHAR(10)&COUNTIFS($A$6:$A$29,$A19,$B$6:$B$29,$B19,$C$6:$C$29,$C19)&IF(COUNTIFS($A$6:$A$29,$A19,$B$6:$B$29,$B19,$C$6:$C$29,$C19)=1," Eintrag"," Einträge") -> Komponente 1 Eintrag
M52: =$C18&CHAR(10)&COUNTIFS($A$6:$A$29,$A18,$B$6:$B$29,$B18,$C$6:$C$29,$C18)&IF(COUNTIFS($A$6:$A$29,$A18,$B$6:$B$29,$B18,$C$6:$C$29,$C18)=1," Eintrag"," Einträge") -> Komponente 1 Eintrag
M53: =$C20&CHAR(10)&COUNTIFS($A$6:$A$29,$A20,$B$6:$B$29,$B20,$C$6:$C$29,$C20)&IF(COUNTIFS($A$6:$A$29,$A20,$B$6:$B$29,$B20,$C$6:$C$29,$C20)=1," Eintrag"," Einträge") -> Schnittstelle 4 Einträge
M54: =IF($D6="","",$D6&CHAR(10)&$E6&IF($E6=1," Anforderung"," Anforderungen")&" · "&$H6&"/"&$E6&" erfüllt"&CHAR(10)&"Status: "&$J6) -> Ladeeinrichtung 171 Anforderungen · 0/171 erfüllt Status: erfasst
M55: =IF($D7="","",$D7&CHAR(10)&$E7&IF($E7=1," Anforderung"," Anforderungen")&" · "&$H7&"/"&$E7&" erfüllt"&CHAR(10)&"Status: "&$J7) -> Abrechnungskomponente 50 Anforderungen · 0/50 erfüllt Status: erfasst
M56: =IF($D8="","",$D8&CHAR(10)&$E8&IF($E8=1," Anforderung"," Anforderungen")&" · "&$H8&"/"&$E8&" erfüllt"&CHAR(10)&"Status: "&$J8) -> Authentifizierungskomponente 66 Anforderungen · 2/66 erfüllt Status: erfasst
M57: =IF($D9="","",$D9&CHAR(10)&$E9&IF($E9=1," Anforderung"," Anforderungen")&" · "&$H9&"/"&$E9&" erfüllt"&CHAR(10)&"Status: "&$J9) -> Monitoring 44 Anforderungen · 0/44 erfüllt Status: erfasst
M58: =IF($D10="","",$D10&CHAR(10)&$E10&IF($E10=1," Anforderung"," Anforderungen")&" · "&$H10&"/"&$E10&" erfüllt"&CHAR(10)&"Status: "&$J10) -> OCPI Buchungskalender 102 Anforderungen · 1/102 erfüllt Status: erfasst
M59: =IF($D11="","",$D11&CHAR(10)&$E11&IF($E11=1," Anforderung"," Anforderungen")&" · "&$H11&"/"&$E11&" erfüllt"&CHAR(10)&"Status: "&$J11) -> Anbindung 3 Anforderungen · 0/3 erfüllt Status: erfasst
M60: =IF($D12="","",$D12&CHAR(10)&$E12&IF($E12=1," Anforderung"," Anforderungen")&" · "&$H12&"/"&$E12&" erfüllt"&CHAR(10)&"Status: "&$J12) -> Reservierungsplattform 12 Anforderungen · 0/12 erfüllt Status: erfasst
M61: =IF($D13="","",$D13&CHAR(10)&$E13&IF($E13=1," Anforderung"," Anforderungen")&" · "&$H13&"/"&$E13&" erfüllt"&CHAR(10)&"Status: "&$J13) -> Belegungsdetektion 5 Anforderungen · 1/5 erfüllt Status: erfasst
M62: =IF($D14="","",$D14&CHAR(10)&$E14&IF($E14=1," Anforderung"," Anforderungen")&" · "&$H14&"/"&$E14&" erfüllt"&CHAR(10)&"Status: "&$J14) -> Dynamische Anzeige 12 Anforderungen · 2/12 erfüllt Status: erfasst
M63: =IF($D15="","",$D15&CHAR(10)&$E15&IF($E15=1," Anforderung"," Anforderungen")&" · "&$H15&"/"&$E15&" erfüllt"&CHAR(10)&"Status: "&$J15) -> Kennzeichenerfassung 8 Anforderungen · 0/8 erfüllt Status: erfasst
M64: =IF($D16="","",$D16&CHAR(10)&$E16&IF($E16=1," Anforderung"," Anforderungen")&" · "&$H16&"/"&$E16&" erfüllt"&CHAR(10)&"Status: "&$J16) -> Pönalisierungssystem 35 Anforderungen · 0/35 erfüllt Status: erfasst
M65: =IF($D17="","",$D17&CHAR(10)&$E17&IF($E17=1," Anforderung"," Anforderungen")&" · "&$H17&"/"&$E17&" erfüllt"&CHAR(10)&"Status: "&$J17) -> Schrankensteuerung 25 Anforderungen · 4/25 erfüllt Status: erfasst
A66: Statusansicht – dieselbe Struktur mit automatischer Statusfarbe | M66: =IF($D19="","",$D19&CHAR(10)&$E19&IF($E19=1," Anforderung"," Anforderungen")&" · "&$H19&"/"&$E19&" erfüllt"&CHAR(10)&"Status: "&$J19) -> Schrankenanlage 23 Anforderungen · 2/23 erfüllt Status: erfasst
A67: Ergänzung zum Organigramm: Diese Ansicht färbt sich über bedingte Formatierung automatisch nach dem Komponentenstatus und passt sich auch einer Umsortierung der Tabelle an. | M67: =IF($D18="","",$D18&CHAR(10)&$E18&IF($E18=1," Anforderung"," Anforderungen")&" · "&$H18&"/"&$E18&" erfüllt"&CHAR(10)&"Status: "&$J18) -> Beschilderung 11 Anforderungen · 0/11 erfüllt Status: erfasst
A68: =IF($D6="","",IF($A6=$A5,"",$A6&CHAR(10)&COUNTIF($A$6:$A$29,$A6)&" Komponenten")) -> LIS 1 Komponenten | B68: =IF($D6="","",IF(AND($A6=$A5,$B6=$B5),"","└ "&$B6&" ("&COUNTIFS($A$6:$A$29,$A6,$B$6:$B$29,$B6)&")")) -> └ Alpitronic (1) | C68: =IF($D6="","",IF(AND($A6=$A5,$B6=$B5,$C6=$C5),"","└ "&$C6&" ("&COUNTIFS($A$6:$A$29,$A6,$B$6:$B$29,$B6,$C$6:$C$29,$C6)&")")) -> └ Komponente (1) | D68: =IF($D6="","","└ "&$D6&CHAR(10)&$E6&" Anforderungen · "&$H6&"/"&$E6&" erfüllt"&CHAR(10)&"Status: "&$J6) -> └ Ladeeinrichtung 171 Anforderungen · 0/171 erfüllt Status: erfasst | M68: =IF($D20="","",$D20&CHAR(10)&$E20&IF($E20=1," Anforderung"," Anforderungen")&" · "&$H20&"/"&$E20&" erfüllt"&CHAR(10)&"Status: "&$J20) -> OCPI Buchungskalender / Abrechnungskomponente / Belegungsdetektion / Pönalisierungssystem 1 Anforderung · 0/1 erfüllt Status: erfasst
A69: =IF($D7="","",IF($A7=$A6,"",$A7&CHAR(10)&COUNTIF($A$6:$A$29,$A7)&" Komponenten")) -> WWL 4 Komponenten | B69: =IF($D7="","",IF(AND($A7=$A6,$B7=$B6),"","└ "&$B7&" ("&COUNTIFS($A$6:$A$29,$A7,$B$6:$B$29,$B7)&")")) -> └ eRound (4) | C69: =IF($D7="","",IF(AND($A7=$A6,$B7=$B6,$C7=$C6),"","└ "&$C7&" ("&COUNTIFS($A$6:$A$29,$A7,$B$6:$B$29,$B7,$C$6:$C$29,$C7)&")")) -> └ Komponente (4) | D69: =IF($D7="","","└ "&$D7&CHAR(10)&$E7&" Anforderungen · "&$H7&"/"&$E7&" erfüllt"&CHAR(10)&"Status: "&$J7) -> └ Abrechnungskomponente 50 Anforderungen · 0/50 erfüllt Status: erfasst | M69: =IF($D21="","",$D21&CHAR(10)&$E21&IF($E21=1," Anforderung"," Anforderungen")&" · "&$H21&"/"&$E21&" erfüllt"&CHAR(10)&"Status: "&$J21) -> OCPI Buchungskalender / Dynamische Anzeige 5 Anforderungen · 1/5 erfüllt Status: erfasst
A70: =IF($D8="","",IF($A8=$A7,"",$A8&CHAR(10)&COUNTIF($A$6:$A$29,$A8)&" Komponenten")) | B70: =IF($D8="","",IF(AND($A8=$A7,$B8=$B7),"","└ "&$B8&" ("&COUNTIFS($A$6:$A$29,$A8,$B$6:$B$29,$B8)&")")) | C70: =IF($D8="","",IF(AND($A8=$A7,$B8=$B7,$C8=$C7),"","└ "&$C8&" ("&COUNTIFS($A$6:$A$29,$A8,$B$6:$B$29,$B8,$C$6:$C$29,$C8)&")")) | D70: =IF($D8="","","└ "&$D8&CHAR(10)&$E8&" Anforderungen · "&$H8&"/"&$E8&" erfüllt"&CHAR(10)&"Status: "&$J8) -> └ Authentifizierungskomponente 66 Anforderungen · 2/66 erfüllt Status: erfasst | M70: =IF($D22="","",$D22&CHAR(10)&$E22&IF($E22=1," Anforderung"," Anforderungen")&" · "&$H22&"/"&$E22&" erfüllt"&CHAR(10)&"Status: "&$J22) -> OCPI Buchungskalender / Kennzeichenerfassung / Pönalisierungssystem 2 Anforderungen · 0/2 erfüllt Status: erfasst
A71: =IF($D9="","",IF($A9=$A8,"",$A9&CHAR(10)&COUNTIF($A$6:$A$29,$A9)&" Komponenten")) | B71: =IF($D9="","",IF(AND($A9=$A8,$B9=$B8),"","└ "&$B9&" ("&COUNTIFS($A$6:$A$29,$A9,$B$6:$B$29,$B9)&")")) | C71: =IF($D9="","",IF(AND($A9=$A8,$B9=$B8,$C9=$C8),"","└ "&$C9&" ("&COUNTIFS($A$6:$A$29,$A9,$B$6:$B$29,$B9,$C$6:$C$29,$C9)&")")) | D71: =IF($D9="","","└ "&$D9&CHAR(10)&$E9&" Anforderungen · "&$H9&"/"&$E9&" erfüllt"&CHAR(10)&"Status: "&$J9) -> └ Monitoring 44 Anforderungen · 0/44 erfüllt Status: erfasst | M71: =IF($D23="","",$D23&CHAR(10)&$E23&IF($E23=1," Anforderung"," Anforderungen")&" · "&$H23&"/"&$E23&" erfüllt"&CHAR(10)&"Status: "&$J23) -> Authentifizierungskomponente / Schrankensteuerung 8 Anforderungen · 1/8 erfüllt Status: erfasst
A72: =IF($D10="","",IF($A10=$A9,"",$A10&CHAR(10)&COUNTIF($A$6:$A$29,$A10)&" Komponenten")) | B72: =IF($D10="","",IF(AND($A10=$A9,$B10=$B9),"","└ "&$B10&" ("&COUNTIFS($A$6:$A$29,$A10,$B$6:$B$29,$B10)&")")) | C72: =IF($D10="","",IF(AND($A10=$A9,$B10=$B9,$C10=$C9),"","└ "&$C10&" ("&COUNTIFS($A$6:$A$29,$A10,$B$6:$B$29,$B10,$C$6:$C$29,$C10)&")")) | D72: =IF($D10="","","└ "&$D10&CHAR(10)&$E10&" Anforderungen · "&$H10&"/"&$E10&" erfüllt"&CHAR(10)&"Status: "&$J10) -> └ OCPI Buchungskalender 102 Anforderungen · 1/102 erfüllt Status: erfasst
A73: =IF($D11="","",IF($A11=$A10,"",$A11&CHAR(10)&COUNTIF($A$6:$A$29,$A11)&" Komponenten")) -> SmartInfra 8 Komponenten | B73: =IF($D11="","",IF(AND($A11=$A10,$B11=$B10),"","└ "&$B11&" ("&COUNTIFS($A$6:$A$29,$A11,$B$6:$B$29,$B11)&")")) -> └ Reservierungsplattform (2) | C73: =IF($D11="","",IF(AND($A11=$A10,$B11=$B10,$C11=$C10),"","└ "&$C11&" ("&COUNTIFS($A$6:$A$29,$A11,$B$6:$B$29,$B11,$C$6:$C$29,$C11)&")")) -> └ Komponente (2) | D73: =IF($D11="","","└ "&$D11&CHAR(10)&$E11&" Anforderungen · "&$H11&"/"&$E11&" erfüllt"&CHAR(10)&"Status: "&$J11) -> └ Anbindung 3 Anforderungen · 0/3 erfüllt Status: erfasst
A74: =IF($D12="","",IF($A12=$A11,"",$A12&CHAR(10)&COUNTIF($A$6:$A$29,$A12)&" Komponenten")) | B74: =IF($D12="","",IF(AND($A12=$A11,$B12=$B11),"","└ "&$B12&" ("&COUNTIFS($A$6:$A$29,$A12,$B$6:$B$29,$B12)&")")) | C74: =IF($D12="","",IF(AND($A12=$A11,$B12=$B11,$C12=$C11),"","└ "&$C12&" ("&COUNTIFS($A$6:$A$29,$A12,$B$6:$B$29,$B12,$C$6:$C$29,$C12)&")")) | D74: =IF($D12="","","└ "&$D12&CHAR(10)&$E12&" Anforderungen · "&$H12&"/"&$E12&" erfüllt"&CHAR(10)&"Status: "&$J12) -> └ Reservierungsplattform 12 Anforderungen · 0/12 erfüllt Status: erfasst
A75: =IF($D13="","",IF($A13=$A12,"",$A13&CHAR(10)&COUNTIF($A$6:$A$29,$A13)&" Komponenten")) | B75: =IF($D13="","",IF(AND($A13=$A12,$B13=$B12),"","└ "&$B13&" ("&COUNTIFS($A$6:$A$29,$A13,$B$6:$B$29,$B13)&")")) -> └ SCS (5) | C75: =IF($D13="","",IF(AND($A13=$A12,$B13=$B12,$C13=$C12),"","└ "&$C13&" ("&COUNTIFS($A$6:$A$29,$A13,$B$6:$B$29,$B13,$C$6:$C$29,$C13)&")")) -> └ Komponente (5) | D75: =IF($D13="","","└ "&$D13&CHAR(10)&$E13&" Anforderungen · "&$H13&"/"&$E13&" erfüllt"&CHAR(10)&"Status: "&$J13) -> └ Belegungsdetektion 5 Anforderungen · 1/5 erfüllt Status: erfasst
A76: =IF($D14="","",IF($A14=$A13,"",$A14&CHAR(10)&COUNTIF($A$6:$A$29,$A14)&" Komponenten")) | B76: =IF($D14="","",IF(AND($A14=$A13,$B14=$B13),"","└ "&$B14&" ("&COUNTIFS($A$6:$A$29,$A14,$B$6:$B$29,$B14)&")")) | C76: =IF($D14="","",IF(AND($A14=$A13,$B14=$B13,$C14=$C13),"","└ "&$C14&" ("&COUNTIFS($A$6:$A$29,$A14,$B$6:$B$29,$B14,$C$6:$C$29,$C14)&")")) | D76: =IF($D14="","","└ "&$D14&CHAR(10)&$E14&" Anforderungen · "&$H14&"/"&$E14&" erfüllt"&CHAR(10)&"Status: "&$J14) -> └ Dynamische Anzeige 12 Anforderungen · 2/12 erfüllt Status: erfasst
A77: =IF($D15="","",IF($A15=$A14,"",$A15&CHAR(10)&COUNTIF($A$6:$A$29,$A15)&" Komponenten")) | B77: =IF($D15="","",IF(AND($A15=$A14,$B15=$B14),"","└ "&$B15&" ("&COUNTIFS($A$6:$A$29,$A15,$B$6:$B$29,$B15)&")")) | C77: =IF($D15="","",IF(AND($A15=$A14,$B15=$B14,$C15=$C14),"","└ "&$C15&" ("&COUNTIFS($A$6:$A$29,$A15,$B$6:$B$29,$B15,$C$6:$C$29,$C15)&")")) | D77: =IF($D15="","","└ "&$D15&CHAR(10)&$E15&" Anforderungen · "&$H15&"/"&$E15&" erfüllt"&CHAR(10)&"Status: "&$J15) -> └ Kennzeichenerfassung 8 Anforderungen · 0/8 erfüllt Status: erfasst
A78: =IF($D16="","",IF($A16=$A15,"",$A16&CHAR(10)&COUNTIF($A$6:$A$29,$A16)&" Komponenten")) | B78: =IF($D16="","",IF(AND($A16=$A15,$B16=$B15),"","└ "&$B16&" ("&COUNTIFS($A$6:$A$29,$A16,$B$6:$B$29,$B16)&")")) | C78: =IF($D16="","",IF(AND($A16=$A15,$B16=$B15,$C16=$C15),"","└ "&$C16&" ("&COUNTIFS($A$6:$A$29,$A16,$B$6:$B$29,$B16,$C$6:$C$29,$C16)&")")) | D78: =IF($D16="","","└ "&$D16&CHAR(10)&$E16&" Anforderungen · "&$H16&"/"&$E16&" erfüllt"&CHAR(10)&"Status: "&$J16) -> └ Pönalisierungssystem 35 Anforderungen · 0/35 erfüllt Status: erfasst
A79: =IF($D17="","",IF($A17=$A16,"",$A17&CHAR(10)&COUNTIF($A$6:$A$29,$A17)&" Komponenten")) | B79: =IF($D17="","",IF(AND($A17=$A16,$B17=$B16),"","└ "&$B17&" ("&COUNTIFS($A$6:$A$29,$A17,$B$6:$B$29,$B17)&")")) | C79: =IF($D17="","",IF(AND($A17=$A16,$B17=$B16,$C17=$C16),"","└ "&$C17&" ("&COUNTIFS($A$6:$A$29,$A17,$B$6:$B$29,$B17,$C$6:$C$29,$C17)&")")) | D79: =IF($D17="","","└ "&$D17&CHAR(10)&$E17&" Anforderungen · "&$H17&"/"&$E17&" erfüllt"&CHAR(10)&"Status: "&$J17) -> └ Schrankensteuerung 25 Anforderungen · 4/25 erfüllt Status: erfasst
A80: =IF($D18="","",IF($A18=$A17,"",$A18&CHAR(10)&COUNTIF($A$6:$A$29,$A18)&" Komponenten")) -> AUP 1 Komponenten | B80: =IF($D18="","",IF(AND($A18=$A17,$B18=$B17),"","└ "&$B18&" ("&COUNTIFS($A$6:$A$29,$A18,$B$6:$B$29,$B18)&")")) -> └ tbd (1) | C80: =IF($D18="","",IF(AND($A18=$A17,$B18=$B17,$C18=$C17),"","└ "&$C18&" ("&COUNTIFS($A$6:$A$29,$A18,$B$6:$B$29,$B18,$C$6:$C$29,$C18)&")")) -> └ Komponente (1) | D80: =IF($D18="","","└ "&$D18&CHAR(10)&$E18&" Anforderungen · "&$H18&"/"&$E18&" erfüllt"&CHAR(10)&"Status: "&$J18) -> └ Beschilderung 11 Anforderungen · 0/11 erfüllt Status: erfasst
A81: =IF($D19="","",IF($A19=$A18,"",$A19&CHAR(10)&COUNTIF($A$6:$A$29,$A19)&" Komponenten")) -> SmartInfra 8 Komponenten | B81: =IF($D19="","",IF(AND($A19=$A18,$B19=$B18),"","└ "&$B19&" ("&COUNTIFS($A$6:$A$29,$A19,$B$6:$B$29,$B19)&")")) -> └ CAME (1) | C81: =IF($D19="","",IF(AND($A19=$A18,$B19=$B18,$C19=$C18),"","└ "&$C19&" ("&COUNTIFS($A$6:$A$29,$A19,$B$6:$B$29,$B19,$C$6:$C$29,$C19)&")")) -> └ Komponente (1) | D81: =IF($D19="","","└ "&$D19&CHAR(10)&$E19&" Anforderungen · "&$H19&"/"&$E19&" erfüllt"&CHAR(10)&"Status: "&$J19) -> └ Schrankenanlage 23 Anforderungen · 2/23 erfüllt Status: erfasst
A82: =IF($D20="","",IF($A20=$A19,"",$A20&CHAR(10)&COUNTIF($A$6:$A$29,$A20)&" Komponenten")) -> Zuordnung prüfen 4 Komponenten | B82: =IF($D20="","",IF(AND($A20=$A19,$B20=$B19),"","└ "&$B20&" ("&COUNTIFS($A$6:$A$29,$A20,$B$6:$B$29,$B20)&")")) -> └ eRound / SCS (4) | C82: =IF($D20="","",IF(AND($A20=$A19,$B20=$B19,$C20=$C19),"","└ "&$C20&" ("&COUNTIFS($A$6:$A$29,$A20,$B$6:$B$29,$B20,$C$6:$C$29,$C20)&")")) -> └ Schnittstelle (4) | D82: =IF($D20="","","└ "&$D20&CHAR(10)&$E20&" Anforderungen · "&$H20&"/"&$E20&" erfüllt"&CHAR(10)&"Status: "&$J20) -> └ OCPI Buchungskalender / Abrechnungskomponente / Belegungsdetektion / Pönalisierungssystem 1 Anforderungen · 0/1 erfüllt Status: erfasst
A83: =IF($D21="","",IF($A21=$A20,"",$A21&CHAR(10)&COUNTIF($A$6:$A$29,$A21)&" Komponenten")) | B83: =IF($D21="","",IF(AND($A21=$A20,$B21=$B20),"","└ "&$B21&" ("&COUNTIFS($A$6:$A$29,$A21,$B$6:$B$29,$B21)&")")) | C83: =IF($D21="","",IF(AND($A21=$A20,$B21=$B20,$C21=$C20),"","└ "&$C21&" ("&COUNTIFS($A$6:$A$29,$A21,$B$6:$B$29,$B21,$C$6:$C$29,$C21)&")")) | D83: =IF($D21="","","└ "&$D21&CHAR(10)&$E21&" Anforderungen · "&$H21&"/"&$E21&" erfüllt"&CHAR(10)&"Status: "&$J21) -> └ OCPI Buchungskalender / Dynamische Anzeige 5 Anforderungen · 1/5 erfüllt Status: erfasst
... A91: =IF($D29="","",IF($A29=$A28,"",$A29&CHAR(10)&COUNTIF($A$6:$A$29,$A29)&" Komponenten")) | B91: =IF($D29="","",IF(AND($A29=$A28,$B29=$B28),"","└ "&$B29&" ("&COUNTIFS($A$6:$A$29,$A29,$B$6:$B$29,$B29)&")")) | C91: =IF($D29="","",IF(AND($A29=$A28,$B29=$B28,$C29=$C28),"","└ "&$C29&" ("&COUNTIFS($A$6:$A$29,$A29,$B$6:$B$29,$B29,$C$6:$C$29,$C29)&")")) | D91: =IF($D29="","","└ "&$D29&CHAR(10)&$E29&" Anforderungen · "&$H29&"/"&$E29&" erfüllt"&CHAR(10)&"Status: "&$J29)
A93: Legende Statusfarben
A94: erfasst | B94: bewertet | C94: erfüllt | D94: trifft nicht zu | E94: keine Anforderungen
A96: Pflegehinweis: Es werden ausschließlich Vergabeeinheit, Partner, Art, Komponente und Bemerkung eingetragen. Anzahl, Statusverteilung, Gesamtstatus, die Beschriftung der Organigramm-Boxen und die Statusansicht aktualisieren sich daraus automatisch. Kommen Komponenten hinzu oder ändert sich die Gruppierung, muss die Boxenanordnung des Organigramms neu erzeugt werden. „Zuordnung prüfen“ bedeutet: aus den vorliegenden Unterlagen nicht eindeutig ableitbar.

Sheet Lesehilfe
A1: Lesehilfe – Anforderungen
A2: So wird die vereinfachte Anforderungsdatei verwendet
A5: Zweck | B5: Die Mappe bündelt die Anforderungen aus der Ausschreibung und verfolgt ihren fachlichen Status bis zur Erfüllung.
A6: Anforderungen | B6: Zentrales Arbeitsregister. Hier werden Status, Erfüllungsdatum sowie Nachweis / Notiz gepflegt.
A7: Komponenten | B7: Zeigt automatisch, wie viele Anforderungen an einer Komponente bzw. Schnittstelle hängen und welchen zusammengefassten Status sie hat.
A8: Auswertung | B8: Automatische Auswertung nach Themenfeld, Partner, Komponente, Dokument und Gesamtstatus.
A9: Cockpit | B9: Kompakte Kennzahlen zu Status, Erfüllungsgrad und fehlender Erfüllungsdokumentation.
A10: Anzeigekonzept | B10: Wurde aus dieser Mappe entfernt und steht als separate Excel-Datei zur Verfügung.
A12: Status „erfasst“ | B12: Die Anforderung ist aufgenommen, wurde aber noch nicht abschließend fachlich bewertet.
A13: Status „bewertet“ | B13: Status ist das steuernde Feld: erfasst → bewertet → erfüllt oder „trifft nicht zu“. Der Status bestimmt, welche Dokumentation erforderlich ist.
A14: Status „erfüllt“ | B14: „Erfüllt am“ ist ein normales Datumsfeld ohne Dropdown. Es wird nur bei Status „erfüllt“ befüllt und enthält das tatsächliche Erfüllungsdatum.
A15: Status „trifft nicht zu“ | B15: „Nachweis / Notiz“ gehört direkt zum Status: bei „erfüllt“ dient es als Nachweis/Prüfnotiz; bei „trifft nicht zu“ dokumentiert es die Begründung.
A16: Erfüllt am | B16: Die drei Felder Status + Erfüllt am + Nachweis / Notiz bilden gemeinsam den Erfüllungsblock. Fehlende oder widersprüchliche Eingaben werden farblich markiert.
A17: Nachweis / Notiz | B17: Kurzer Nachweis, Link-/Dokumenthinweis, Prüfergebnis oder Begründung, warum die Anforderung nicht zutrifft.
... A29: Statusansicht | B29: Unterhalb des Organigramms, gleiche Hierarchie in Zellen. Sie färbt sich über bedingte Formatierung automatisch nach dem Komponentenstatus und passt sich auch einer Umsortierung der Tabelle ohne Nacharbeit an.
