Workbook

Sheet Cockpit
A1: Cockpit – Anforderungen Autostrom / LKW-Laden
A2: Status, Erfüllung und Dokumentationsqualität auf einen Blick
A3: Alle Kennzahlen rechnen direkt aus den Registern „Anforderungen“ und „Komponenten“ – inklusive des vollständigen Bieterfragenkatalogs.
A5: Kennzahl | B5: Wert
A6: Anforderungen gesamt | B6: =COUNTA(Anforderungen!$B$7:$B$2000) -> 1382
A7: Erfasst | B7: =COUNTIF(Anforderungen!$K$7:$K$2000,"erfasst") -> 50
A8: Bewertet | B8: =COUNTIF(Anforderungen!$K$7:$K$2000,"bewertet") -> 3
A9: Erfüllt | B9: =COUNTIF(Anforderungen!$K$7:$K$2000,"erfüllt") -> 10
A10: davon vollständig dokumentiert | B10: =COUNTIFS(Anforderungen!$K$7:$K$2000,"erfüllt",Anforderungen!$L$7:$L$2000,"<>",Anforderungen!$M$7:$M$2000,"<>") -> 10
A11: Trifft nicht zu | B11: =COUNTIF(Anforderungen!$K$7:$K$2000,"trifft nicht zu") -> 1319
A12: Erfüllt ohne Datum | B12: =COUNTIFS(Anforderungen!$K$7:$K$2000,"erfüllt",Anforderungen!$L$7:$L$2000,"") -> 0
A13: Erfüllt ohne Nachweis / Notiz | B13: =COUNTIFS(Anforderungen!$K$7:$K$2000,"erfüllt",Anforderungen!$M$7:$M$2000,"") -> 0
A14: Trifft nicht zu ohne Begründung | B14: =COUNTIFS(Anforderungen!$K$7:$K$2000,"trifft nicht zu",Anforderungen!$M$7:$M$2000,"") -> 2
A15: Erfüllungsgrad | B15: =IFERROR(COUNTIF(Anforderungen!$K$7:$K$2000,"erfüllt")/(COUNTA(Anforderungen!$B$7:$B$2000)-COUNTIF(Anforderungen!$K$7:$K$2000,"trifft nicht zu")),0) -> 0.15873016
A16: Dokumentationsgrad erfüllt | B16: =IFERROR(COUNTIFS(Anforderungen!$K$7:$K$2000,"erfüllt",Anforderungen!$L$7:$L$2000,"<>",Anforderungen!$M$7:$M$2000,"<>")/COUNTIF(Anforderungen!$K$7:$K$2000,"erfüllt"),0) -> 1
A17: Komponenten/Schnittstellen erfüllt | B17: =COUNTIF(Komponenten!$J$6:$J$29,"erfüllt") -> 0
A18: Bieterfragen im Register | B18: =COUNTIF(Anforderungen!$C$7:$C$2000,"Bieterfragenkatalog") -> 663
A19: Offene Zuordnungen (Komponente/Partner) | B19: =COUNTIF(Anforderungen!$J$7:$J$2000,"Zuordnung prüfen")+COUNTIF(Anforderungen!$I$7:$I$2000,"Zuordnung prüfen") -> 460

Sheet Anforderungen
A1: Anforderungen – Autostrom / LKW-Laden
A2: Zentrales Anforderungsregister: Der Block „Erfüllung / Nachweis“ verbindet Status, tatsächliches Erfüllungsdatum und Dokumentation.
A3: Logik: erfasst → bewertet → erfüllt. Bei „erfüllt“ sind Datum und Nachweis/Notiz erforderlich, bei „trifft nicht zu“ eine Begründung. Gelb markierte Zuordnungen (Partner/Komponente) sind fachlich zu prüfen.
B5: Anforderung & Zuordnung | K5: Erfüllung / Nachweis (Konzept)
B6: ID | C6: Dokument | D6: Fundstelle | E6: Themenfeld | F6: Kernaussage | G6: Anforderung / Frage (Originaltext) | H6: Bemerkung | I6: Partner | J6: Komponente(n) | K6: Status | L6: Erfüllt am | M6: Nachweis / Notiz
B7: ANF-001 | C7: Betreibervertrag | D7: § 25 (1) | E7: Reservierung | F7: OCPI Schnittstelle | G7: Der Auftragnehmer stellt sicher, dass die Reservierung von Ladepunkten über Reservierungsplattformen während der Laufzeit dieses Vertrags möglich ist. Hierzu hält der Auftragnehmer eine auf OCPI (Open Charge Point Interface) basierende Schnittstelle vor, über die sich Reservierungsplattformen nach Maßgabe der folgenden Absätze anbinden können. | I7: eRound | J7: OCPI Buchungskalender | K7: trifft nicht zu | M7: Automatisch ausgewertet: Außerhalb des betrachteten Leistungsumfangs (Schranken, Kennzeichenerfassung, dynamische Anzeige).
B8: ANF-002 | C8: Betreibervertrag | D8: § 25 (2) | E8: Reservierung | F8: OCPI Kostenfrei | G8: Der Auftragnehmer ist verpflichtet, jeder Reservierungsplattform die Anbindung über die in Absatz 1 genannte Schnittstelle kostenfrei zu ermöglichen, soweit die Reservierungsplattform die folgenden Mindestvoraussetzungen erfüllt: | I8: eRound | J8: OCPI Buchungskalender | K8: trifft nicht zu | M8: Automatisch ausgewertet: Außerhalb des betrachteten Leistungsumfangs (Schranken, Kennzeichenerfassung, dynamische Anzeige).
B9: ANF-003 | C9: Betreibervertrag | D9: § 25 (2) a | E9: Reservierung | F9: OCPI Kostenfrei | G9: Die Reservierungsplattform stellt dem Auftragnehmer für die Anbindung der Reservierungsplattform keine Anbindungskosten in Rechnung | I9: eRound | J9: Anbindung | K9: trifft nicht zu | M9: Automatisch ausgewertet: Außerhalb des betrachteten Leistungsumfangs (Schranken, Kennzeichenerfassung, dynamische Anzeige).
B10: ANF-004 | C10: Betreibervertrag | D10: § 25 (2) b | E10: Reservierung | F10: Anbindung verpflichtend, wenn alle AN angebunden werden oder AG2 auffordert | G10: Die Reservierungsplattform ermöglicht Endnutzern und Mobilitätsdienstleistern die Reservierung von Ladepunkten im gesamten Gebiet der Bundesrepublik Deutschland gegen ein angemessenes Entgelt. Ermöglicht eine Reservierungsplattform eine Reservierung von Ladepunkten nur in Teilen des Gebiets der Bundesrepublik Deutschland, ist der Auftragnehmer zur Anbindung nur verpflichtet, wenn der Auftraggeber 2 den Auftragnehmer hierzu auffordert. | I10: eRound | J10: OCPI Buchungskalender | K10: trifft nicht zu | M10: Automatisch ausgewertet: Außerhalb des betrachteten Leistungsumfangs (Schranken, Kennzeichenerfassung, dynamische Anzeige).
B11: ANF-005 | C11: Betreibervertrag | D11: § 25 (2) c | E11: Reservierung | F11: Reservierung mit Vorlauf von max. 7 Tagen und min. 15 min. Kostenfreie Stornierung und Änderung bis 30min vorher. Kennzeichenabgleich zur Unterbindung von Doppelbuchungen. | G11: Die Reservierungsplattform ermöglicht eine Reservierung von Ladepunkten mit einer Vorlaufzeit von maximal 7 Kalendertagen und mindestens 15 Minuten. Eine kostenfreie Stornierung oder Änderung der Reservierung über die Reservierungsplattform muss, soweit möglich, bis zu 30 Minuten vor Beginn des in der Reservierung angegebenen Startzeitpunkts möglich sein. Die Reservierungsplattform stellt durch geeignete Vorkehrungen (z. B. durch einen Kennzeichenabgleich) sicher, dass für einen E-LKW in einem Zeitintervall nur ein Ladepunkt reserviert wird. | I11: eRound | J11: OCPI Buchungskalender | K11: erfasst
B12: ANF-006 | C12: Betreibervertrag | D12: § 25 (2) d | E12: Reservierung | F12: Entschädigung an AN von der Reservierungsplattform i.H.v. mind. 30€ nach 15/30 min Wartezeit bei No-Show. | G12: Die Reservierungsplattform entschädigt den Auftragnehmer in angemessener Höhe, wenn an der reservierten Ladeeinrichtung ab dem in der Reservierung angegebenen Startzeitpunkt und Ablauf einer Wartezeit von 15 Minuten bei Ladepunkten zum Zwischenladen, bzw. 30 Minuten bei Ladepunkten zum Übernachtladen (sog. „no-show“) kein Start eines Ladevorgangs erfolgt. Die Entschädigung des Auftragnehmers ist angemessen, wenn der Auftragnehmer im Fall eines „no-show“ mindestens € 30,00 erhält. | I12: eRound | J12: Abrechnungskomponente | K12: trifft nicht zu | M12: Automatisch ausgewertet: Außerhalb des betrachteten Leistungsumfangs (Schranken, Kennzeichenerfassung, dynamische Anzeige).
B13: ANF-007 | C13: Betreibervertrag | D13: § 25 (3) | E13: Reservierung | F13: Anpassung an Marktstandards mit 2 Monaten Vorlauf. | G13: Der Auftraggeber 2 ist berechtigt, die in Absatz 2 definierten Mindestvoraussetzungen im Fall abweichender Marktstandards mit einer Vorlaufzeit von zwei Monaten anzupassen | I13: eRound | J13: OCPI Buchungskalender | K13: trifft nicht zu | M13: Automatisch ausgewertet: Außerhalb des betrachteten Leistungsumfangs (Schranken, Kennzeichenerfassung, dynamische Anzeige).
B14: ANF-008 | C14: Betreibervertrag | D14: § 25 (4) | E14: Reservierung | F14: Ladepunkte an einem Standort können von der Reservierung ausgenommen werden. | G14: Der Auftragnehmer kann CCS- und MCS-Ladepunkten an einem Standort von der Reservierungsmöglichkeit ausnehmen. | I14: eRound | J14: OCPI Buchungskalender | K14: trifft nicht zu | M14: Automatisch ausgewertet: Außerhalb des betrachteten Leistungsumfangs (Schranken, Kennzeichenerfassung, dynamische Anzeige).
B15: ANF-009 | C15: Betreibervertrag | D15: § 25 (5) | E15: Zufahrt & Schranke | F15: Bauliche Maßnahme zur Reservierung an jedem Ladepunkt. | G15: Der Auftragnehmer hat geeignete Vorkehrungen, insbesondere die in Vertragsanlage 4: Leistungsbeschreibung Errichtung vorgesehenen baulichen Maßnahmen, zu treffen, um ein anderweitiges Laden an dem Ladepunkt der Ladeeinrichtung während des reservierten Zeitraums zu verhindern. | H15: Schrankensteuerung | I15: Schrankenhersteller | J15: Schrankenanlage | K15: erfasst
B16: ANF-010 | C16: Betreibervertrag | D16: § 25 (6) | E16: Reservierung | F16: Mindestens 40% der Ladepunkte müssen reserviert werden können. | G16: Verstößt der Auftragnehmer gegen die Pflicht nach Absatz 1, wird für jeden Standort, an dem die Reservierung von Ladepunkten aufgrund des Verstoßes gegen die Pflicht nach Absatz 1 nicht möglich ist, eine Vertragsstrafe fällig. Die Reservierung von Ladepunkten an einem Standort gilt als nicht möglich, wenn mindestens 40 % der Ladepunkte an dem Standort nicht reserviert werden können. Die Höhe der Vertragsstrafe beträgt € 2.500,00 für jeden Kalendertag, an dem die Reservierung von Ladepunkten an einem Standort nicht möglich ist, höchstens jedoch € 40.000,00 pro Kalendermonat und pro Standort. | H16: 40% der Schranken offen lassen? | I16: eRound | J16: OCPI Buchungskalender | K16: erfasst
B17: ANF-011 | C17: Betreibervertrag | D17: § 31 (1) | E17: Authentifizierung & Zugang | F17: Es muss Adhoc geladen werden können | G17: Der Auftragnehmer ist verpflichtet, potenziellen Endnutzern diskriminierungsfrei zu angemessenen Bedingungen ein Ad-hoc-Laden (punktuelles Aufladen i. S. d. AFIR) zu ermöglichen, soweit es ihm zumutbar ist (z. B. mit Blick auf die Bonität des Endnutzers). | H17: Adhoc muss möglich sein -> Schranke -> wie? | I17: eRound / SCS | J17: Authentifizierungskomponente / Schrankensteuerung | K17: erfasst
B18: ANF-012 | C18: Betreibervertrag | D18: § 38 (1) | E18: Nutzungszeit & Entgelte | F18: Blockadeentgelte und maximale Nutzungsdauer | G18: Start- und zeitabhängige Entgelte dürfen nicht erhoben werden. Dies gilt nicht für vertraglich vereinbarte Blockadeentgelte, die nach Ablauf einer maximalen Nutzungszeit vom Endnutzer bzw. Mobilitätsdienstleister unabhängig davon, welches der Zugangsmodelle des § 30 Abs. 2 gewählt wird, erhoben werden. Die maximale Nutzungszeit beginnt mit Beginn des Ladevorgangs und beträgt | H18: Schnittstelle Nutzungszeit | I18: eRound | J18: OCPI Buchungskalender | K18: trifft nicht zu | M18: Automatisch ausgewertet: Außerhalb des betrachteten Leistungsumfangs (Schranken, Kennzeichenerfassung, dynamische Anzeige).
B19: ANF-013 | C19: Betreibervertrag | D19: § 38 (1) a | E19: Nutzungszeit & Entgelte | F19: Maximale Nutzungsdauer Zwischenladen ist 1h. | G19: bei MCS-Ladepunkten und CCS-Ladepunkten zum Zwischenladen 1 Stunde. | H19: Schnittstelle Nutzungszeit | I19: eRound | J19: OCPI Buchungskalender | K19: trifft nicht zu | M19: Automatisch ausgewertet: Außerhalb des betrachteten Leistungsumfangs (Schranken, Kennzeichenerfassung, dynamische Anzeige).
B20: ANF-014 | C20: Betreibervertrag | D20: § 38 (1) b | E20: Nutzungszeit & Entgelte | F20: Maximale Nutzungsdauer Übernachtladen ist 12h. | G20: bei CCS-Ladepunkten zum Übernachtladen und MCS- oder CCS-Ladepunkte zum Zwischenladen, die zum Übernachtladen freigegeben wurden, 12 Stunden. | H20: Schnittstelle Nutzungszeit | I20: eRound | J20: OCPI Buchungskalender | K20: trifft nicht zu | M20: Automatisch ausgewertet: Außerhalb des betrachteten Leistungsumfangs (Schranken, Kennzeichenerfassung, dynamische Anzeige).
B21: ANF-015 | C21: Betreibervertrag | D21: § 38 (2) | E21: Nutzungszeit & Entgelte | F21: Bei nidriger Auslastung kann die maximale Nutzungszeit vom AN verlängert werden. Bei nachfolgender Reservierung kann die maximale Nutzungszeit verkürzt werden. Bei Verkürzung zusätzliche Karenzzeit vor Blockadeentgeld von 5min. | G21: Der Auftragnehmer kann die maximalen Nutzungszeiten in Zeiten geringer Auslastung verlängern. Zudem kann er mit der Gestattung der Nutzung von MCS-Ladepunkten und CCS-Ladepunkten zum Zwischenladen dem Endnutzer bzw. Mobilitätsdienstleister auch ausdrücklich eine kürzere maximale Nutzungszeit einräumen, wenn wegen nachfolgender Reservierungen die maximale Nutzungszeit nach Absatz 1 lit. a nicht eingeräumt werden kann. In den Fällen des Satzes 2 ist dem Endnutzer bzw. Mobilitätsdienstleister zusätzlich eine Karenzzeit zum Verlassen des Ladeplatzes von 5 Minuten einzuräumen, nach deren Ablauf erst ein Blockadeentgelt erhoben werden darf | H21: SCS: Reaktionszeit System | I21: eRound | J21: OCPI Buchungskalender | K21: trifft nicht zu | M21: Automatisch ausgewertet: Außerhalb des betrachteten Leistungsumfangs (Schranken, Kennzeichenerfassung, dynamische Anzeige).
B22: ANF-016 | C22: Betreibervertrag | D22: § 38 (3) | E22: Nutzungszeit & Entgelte | F22: Maximale Nutzungszeit endet mit Ablauf Reservierung. Maximale Nutzungsdauer kann vom AN verlängert werden. | G22: Hat ein Mobilitätsdienstleister einen Ladepunkt reserviert, so endet die maximale Nutzungszeit mit dem Ablauf des reservierten Zeitraums, auch wenn der Ladeplatz erst später belegt wurde, es sei denn, der Betreiber räumt ihm eine längere maximale Nutzungszeit ein. | I22: eRound | J22: OCPI Buchungskalender | K22: trifft nicht zu | M22: Automatisch ausgewertet: Außerhalb des betrachteten Leistungsumfangs (Schranken, Kennzeichenerfassung, dynamische Anzeige).
B23: ANF-017 | C23: Betreibervertrag | D23: § 38 (4) | E23: Nutzungszeit & Entgelte | F23: Ladestart 15min Wartezeit Blockadeentgeld ggf. Pönalisierung Entfall maximale Nutzungsdauer | G23: Wird ein Ladevorgang nicht innerhalb von 15 Minuten nach Besetzung des Stellplatzes gestartet, entfällt die maximale Nutzungszeit und es kann ein Blockadeentgelt erhoben werden. | I23: eRound / SCS | J23: OCPI Buchungskalender / Abrechnungskomponente / Belegungsdetektion / Pönalisierungssystem | K23: trifft nicht zu | M23: Automatisch ausgewertet: Außerhalb des betrachteten Leistungsumfangs (Schranken, Kennzeichenerfassung, dynamische Anzeige).
B24: ANF-018 | C24: Betreibervertrag | D24: § 38 (5) | E24: Nutzungszeit & Entgelte | F24: Kein Blockadeentgeld während Nachtruhezeiten, Sonn- und Feiertage der Bundesländer. | G24: An Sonn- und Feiertagen sowie zwischen 22 Uhr abends und 5 Uhr morgens (Nachtruhezeit) darf der Auftragnehmer für CCS-Ladepunkte zum Übernachtladen bzw. MCS- und CCS- Ladepunkten zum Zwischenladen, die zum Übernachtladen freigegeben wurden, keine Blockadeentgelte erheben. Hat der Ladevorgang bereits vor Beginn der Nachtruhezeiten begonnen und endet die maximale Nutzungszeit nach Absatz 1 während der Nachtruhezeit, so werden Blockadeentgelte mithin erst nach Ende der Nachtruhezeit berechnet. Satz 1 und 2 gelten entsprechend für Sonntage und gesetzliche Feiertage in dem Bundesland, in dem der jeweilige Standort gelegen ist. | H24: Einfluss auf Reservierung? | I24: eRound | J24: OCPI Buchungskalender | K24: trifft nicht zu | M24: Automatisch ausgewertet: Außerhalb des betrachteten Leistungsumfangs (Schranken, Kennzeichenerfassung, dynamische Anzeige).
B25: ANF-019 | C25: Betreibervertrag | D25: § 38 (6) | E25: Nutzungszeit & Entgelte | F25: Blockadeentgeld Höhe 0,50€ / 0,15€ pro Min. | G25: Die Höhe des Blockadeentgelts darf bei MCS-Ladepunkten und bei CCS-Ladepunkten zum Zwischenladen maximal 0,50 €/Minute und bei CCS-Ladepunkten bzw. CCS- und MCS- Ladepunkten zum Zwischenladen, während des Zeitraums, für den sie zum Übernachtladen freigegeben wurden, maximal 0,15 €/Minute betragen. Das vereinnahmte Blockadeentgelt steht dem Auftragnehmer zu. | I25: eRound | J25: Abrechnungskomponente | K25: trifft nicht zu | M25: Automatisch ausgewertet: Außerhalb des betrachteten Leistungsumfangs (Schranken, Kennzeichenerfassung, dynamische Anzeige).
B26: ANF-020 | C26: Betreibervertrag | D26: § 38 (7) | E26: Nutzungszeit & Entgelte | F26: Änderungen an maximaler Nutzungsdauer, Blockadeentgelt und Sperrzeiten mit Vorlauf möglich. | G26: Der Auftraggeber 2 kann die maximale Höhe der Blockadeentgelte nach Absatz 6 und die maximalen Nutzungszeiten bzw. Sperrzeiten für die Erhebung eines Blockadeentgeltes nach den Absätzen 1 bis 4 während der Laufzeit des Vertrags mit einer Frist von vier Monaten auf den Beginn eines Quartals schriftlich mit Wirkung gegenüber dem Auftragnehmer anpassen. Absenkungen der Höhe oder Verlängerungen die maximalen Nutzungszeiten bzw. Sperrzeiten sind nur mit Zustimmung des Auftragnehmers zulässig. Die Zustimmung gilt als erteilt, sofern der Auftragnehmer dem Auftraggeber 2 nicht innerhalb von zwei Wochen nach Mitteilung der geplanten Absenkung in Textform widerspricht. | I26: eRound | J26: Abrechnungskomponente | K26: trifft nicht zu | M26: Automatisch ausgewertet: Außerhalb des betrachteten Leistungsumfangs (Schranken, Kennzeichenerfassung, dynamische Anzeige).
B27: ANF-021 | C27: Betreibervertrag | D27: § 38 (8) | E27: Nutzungszeit & Entgelte | F27: Mindestabnahmemenge und Vergütung bei Unterschreitung. | G27: Für jeden Übernachtladevorgang ist eine Mindestabnahmemenge von 150 kWh vorzusehen, dies gilt auch für MCS- und CCS-Ladepunkte, die nach Maßgabe dieses Vertrags zum Übernachtladen freigegeben werden. Wird die Mindestabnahmemenge nicht erreicht, so ist für die Differenz zwischen der tatsächlich abgenommenen Strommenge und der vertraglich vorgesehenen Mindestabnahmemenge vom Endnutzer bzw. Mobilitätsdienstleister eine Entschädigung in Höhe von 30 ct/kWh an den Auftragnehmer zu leisten. Die Entschädigungshöhe kann vom Auftraggeber 2 in Absprache mit dem Auftragnehmer zu einem späteren Zeitpunkt angepasst werden. | I27: eRound | J27: Abrechnungskomponente | K27: trifft nicht zu | M27: Automatisch ausgewertet: Außerhalb des betrachteten Leistungsumfangs (Schranken, Kennzeichenerfassung, dynamische Anzeige).
B28: ANF-022 | C28: Betreibervertrag | D28: § 38 (9) | E28: Nutzungszeit & Entgelte | F28: Warnung NutzerIn vor Blockadeentgeld | G28: Endnutzer sind über eine gut sichtbare Beschilderung darauf hinzuweisen, dass der Stellplatz nach Abschluss des Ladevorgangs unverzüglich freizugeben ist; der Text der Beschilderung bedarf der Zustimmung des Auftraggebers 2. Zusätzlich soll der Endnutzer über eine App oder – falls er eine solche nicht nutzt – an der Ladeeinrichtung, vor Erhebung von Blockadeentgelt oder einer Vertragsstrafe einen Hinweis erhalten, dass der Ladevorgang beendet wurde und der Ladeplatz unverzüglich zu räumen ist | H28: ggf. Mitteilung? | I28: eRound | J28: Abrechnungskomponente / Beschilderung | K28: trifft nicht zu | L28: 46259 | M28: ggf. Thema für eRound ansonsten Beschilderung -> Bau GU
B29: ANF-023 | C29: Betreibervertrag | D29: § 42 (5) | E29: Betrieb & Auslastung | F29: Updates verpflichtend. | G29: Der Auftragnehmer ist auf Aufforderung des Auftraggebers 2 verpflichtet, die Ladeeinrichtungen technisch und/oder mit Blick auf die Software (insbesondere Schnittstellen und Protokolle) weiterzuentwickeln und zu verbessern. Die Erstattung der tatsächlich erforderlichen Kosten (zuzüglich angemessener Zuschläge für allgemeine Geschäftskosten, Wagnis und Gewinn) erfolgt nach den Regelungen über geänderte oder zusätzliche Leistungen nach § 40. | I29: Alpitronic | J29: Ladeeinrichtung | K29: trifft nicht zu | L29: 46260 | M29: Betrifft LIS
B30: ANF-024 | C30: Betreibervertrag | D30: § 22 (3) | E30: Betrieb & Auslastung | F30: Bei nidriger Auslastung: Zwischenladepunkte können zwischen 17 und 6 Uhr für Übernachtladen freigegeben werden. Aber mind. 40% Zwischenladepunkte, aber mind. 2 MCS und 1 CCS. | G30: CCS- und MCS-Ladepunkte zum Zwischenladen sind bei fehlender Auslastung ab 17:00 Uhr sowie an Wochenenden zum Übernachtladen freizugegeben. Es müssen jedoch auch in dieser Zeit 40 %, aber mindestens zwei MCS-Ladepunkte bzw. ein CCS-Ladepunkt, zum Zwischenladen für das Zwischenladen freigehalten werden. An Standorten, an denen nur ein MCS-Ladepunkt vorhanden ist, ist dieser für das Zwischenladen freizuhalten. Der Auftragnehmer hat sicherzustellen, dass die MCS- und CCS-Ladepunkte zum Zwischenladen ab 06:00 Uhr wieder für das Zwischenladen bereitstehen. Auftragnehmer und Auftraggeber 2 können sich je nach Auslastung der Ladepunkte auf abweichende Vorgaben zur Freigabe von Ladepunkten zum Zwischenladen einigen. | H30: 40% Zwischenladen | I30: eRound / SCS | J30: OCPI Buchungskalender / Dynamische Anzeige | K30: erfüllt | L30: 46259 | M30: eRound regelt - SCS zeigt an
B31: ANF-025 | C31: Betreibervertrag | D31: § 4 (52) | E31: Reservierung | F31: Mindestens AN plus ein weiterer. | G31: "Reservierungssystem“: Ein System zur Reservierung von Ladepunkten, das Mobilitätsdienstleistern ermöglicht, Ladepunkte bei dem Auftragnehmer und mindestens einem weiteren Ladepunktbetreiber zu reservieren. | H31: Mehr als 1 Anbieter | I31: Autostrom+ | J31: Anbindung | K31: bewertet
B32: ANF-026 | C32: Vertragsanlage 4 | D32: § 3.13.2 | E32: Zufahrt & Schranke | F32: Schrankenanlage auf Schrankeninsel | G32: Anforderungen an Lade-, Schrankeninseln und physische Zufahrtbeschränkungen | I32: Schrankenhersteller | J32: Schrankenanlage | K32: erfasst | L32: 46259 | M32: Schranke auf Schrankeninsel geplant
B33: ANF-027 | C33: Vertragsanlage 4 | D33: § 3.13.2 (1) | E33: Zufahrt & Schranke | F33: Schranke an Einfahrt Ladepunkt und Ausfahrt Ladepunkt. Bei Schrägparken Poller? | G33: Für den Zweck einer geordneten Zufahrt und Abfahrt sowie zur Sicherstellung der Verfügbarkeit der Ladeinfrastruktur sind Ladeinseln, Schrankeninseln sowie physische Zufahrtsbeschränkungen zu errichten. Diese dienen der Vermeidung unbefugter Inanspruchnahmen der Ladeplätze durch nichtladende Fahrzeuge aus allen Fahrtrichtungen und gewährleisten den bestimmungsgemäßen Betrieb der Ladeinfrastruktur. | H33: Schranke gefordert aus allen Richtungen | I33: Schrankenhersteller | J33: Schrankenanlage | K33: erfüllt | L33: 46259 | M33: Schranken auf beiden Seiten gepplant
B34: ANF-028 | C34: Vertragsanlage 4 | D34: § 3.13.4 | E34: Anzeige & Beschilderung | F34: Darstellung statischer und dynamischer Infos. | G34: Jeder Ladeplatz ist mit einer Kennzeichnung bzw. Anzeige mit folgenden Informationen auszurüsten: - Ladeplatznummer (Schild mit schwarzer Nummer auf weißem retroreflektierendem Hintergrund mit der Reflektionsklasse RA1 A) - Dynamische Anzeige mit - Typ des Ladeplatzes (MCS, CCS-Zwischenladen, CCS-Übernachtladen) - Leistung der Ladesäule - Status (verfügbar, reserviert ab XX:XX Uhr, belegt, außer Betrieb) - optional: Kennzeichen/Reservierungsnummer - Der Status des Ladeplatzes ist zusätzlich zur dynamischen Anzeige über eine farbcodierte Statuskennzeichnung darzustellen (Grün = verfügbar, Gelb = reserviert, Rot = belegt / außer Betrieb). Die farbcodierte Kennzeichnung dient der optischen Erkennbarkeit des Betriebszustands, insbesondere bei Ausfall der digitalen Anzeige. Die Platzierung der Kennzeichnung und Anzeigen hat bei Parkständen in Schrägaufstellung gut sichtbar auf der Schrankeninsel zu erfolgen. Die Platzierung der Kennzeichnung und Anzeigen hat bei Parkständen in Längsaufstellung gut sichtbar, dem entsprechenden Ladeplatz zugehörig im Bereich der Ladeinsel bzw. Ladesäule zu erfolgen. Weitere Anforderungen im Zusammenhang mit dynamischen Anzeigen sind der Vertragsanlage 6: Anforderungen an die Ladeinfrastruktur zu entnehmen. | H34: LED Anzeigen | I34: eRound / SCS | J34: Dynamische Anzeige | K34: erfüllt | L34: 46259 | M34: LIS zeigt Zustand an, Rest auf Anzeige
B35: ANF-029 | C35: Vertragsanlage 4 | D35: § 3.13.5 | E35: Zufahrt & Schranke | G35: Zur Gewährleistung eines sicheren und zuverlässigen Betriebs sind Schrankenanlagen und automatische Poller gemäß den folgenden technischen Anforderungen auszuführen: - robuste Witterungsbeständige und korrosionsgeschützte Ausführung für den ganzjährigen Einsatz im Außenbereich - automatisches Öffnen nach Abschluss des Ladevorgangs oder bei entsprechender Systemfreigabe - Erkennung der Fahrzeugposition sowie von Hindernissen vor dem Schließvorgang zur Vermeidung von Kollisionen - manuelle Notentriegelung durch autorisiertes Personal, um die Betriebsfähigkeit auch im Stör- oder Spannungsfall sicherzustellen - Integration in das zentrale Steuerungssystem (Backend oder lokales Steuergerät) zur Überwachung, Steuerung und Protokollierung der Schranken- und Pollerfunktionen - Schrankenbäume sind gemäß geltender Vorschriften mit rot-weißer Schraffierung zu kennzeichnen - Ausstattung von Schrankenbäumen und automatischen Pollern mit integrierter Beleuchtung zur Verbesserung der Sichtbarkeit und Betriebssicherheit; dabei sind die Vorgaben zur Blendwirkung gemäß ERS zu beachten Weitere Anforderungen für den Betrieb der Schranken sind der Vertragsanlage 6: Anforderungen an die Ladeinfrastruktur zu entnehmen. | H35: Öffnen bei Ladevorgangs-Ende wiederspricht sich mit Vertragsanlage 6 §10 Abs 2 Und funktioniert für Poller nicht -> da LKW darüber steht. Einheitliche Ansteuerung reduziert komplexität Bei Partnern | I35: Schrankenhersteller / SCS / eRound | J35: Schrankenanlage | K35: erfüllt | L35: 46260 | M35: Sicherheitseinrichtung geplant LED in Schrankenbaum geplant Integration des Schrankenstatus in eRound
B36: ANF-030 | C36: Vertragsanlage 4 | D36: § 3.13.2.2 | E36: Zufahrt & Schranke | G36: Bei Parkständen in Längsaufstellung sind automatisch versenkbare Poller zur Zufahrtsbeschränkung vorzusehen. Pro Parkstand sind drei Poller so anzuordnen, dass Fehlbelegungen ausgeschlossen sind. Die Abstände der Poller untereinander sowie zur Fahrgasse ergeben sich aus der Referenzplanung (Anhang 1a: Referenzplanung Längs- und Schrägparken). Das Ein- und Ausfahren zum Ladeplatz muss jederzeit gewährleistet bleiben, auch wenn die benachbarten Stellplätze durch ausgefahrene Poller gesichert sind. Die Dauer der Öffnungs- und Schließvorgänge ist auf das technisch mögliche Minimum zu begrenzen, um einen unterbrechungsarmen Verkehrsfluss sicherzustellen. Die Regelbreite der Parkstände muss 4,50 m betragen, die Länge entspricht den Vorgaben gemäß ERS für Längsparker von 25,00 m. Ergeben sich aufgrund der örtlichen Bestandsituation Abweichungen von der Regelbreite, ist die Befahrbarkeit stets durch einen Schleppkurvennachweis zu belegen. Die Poller sind elektrisch oder hydraulisch versenkbar auszuführen und müssen über eine automatische Höhenverstellung verfügen. Das Absenken erfolgt im Regelbetrieb ausschließlich bei autorisiertem Zugang (Ladevorgang oder Reservierung). Nach Beendigung des Ladevorgangs und nach erfolgter Ausfahrt des Fahrzeuges müssen sich Poller automatisch wieder heben. Eine Notabsenkung bei Ausfall muss durch autorisiertes Personal jederzeit möglich sein. Die Poller müssen widerstandsfähig gegen Anprall und sonstige auf Rastplätzen zu erwartende Einwirkungen sein sowie frost- und salzbeständig ausgeführt werden. Zudem ist ein Schutz gegen Fremdsteuerung und Manipulation sicherzustellen. Die Steuerung der Poller muss in das übergeordnete Zugangskontrollsystem integrierbar sein. Die Erkennbarkeit des Hindernissesist stets sicherzustellen. Die Poller sind zu beleuchten. Die Ladesäule ist im Randbereich des Stellplatzes in einem praktikablen Abstand zum fahrzeugseitigen Ladeanschluss zu positionieren. Die Fläche um die Ladesäule ist in Betonbauweise auszuführen und mit zweckdienlichen Mitteln gegen Anprall und sonstige übliche Einwirkungen auf Rastplätzen zu sichern. Befindet sich im Randbereich bereits eine Bordanlage, ist eine zusätzliche Hochbordabsicherung der Ladesäule nicht erforderlich. In allen übrigen Fällen ist, neben einem Anprallschutz, eine ausreichend dimensionierte Ladeinsel zum Schutz der Ladeinfrastruktur vorzusehen. | H36: Längsparken | I36: Autostrom+ | J36: – | K36: trifft nicht zu | L36: 45894 | M36: Los 2 hat keine Poller - betrifft nur längsparkplätze
B37: ANF-031 | C37: Vertragsanlage 4 | D37: § 3.6 | E37: Bau & Dokumentation | G37: Antrag auf Baufreigabe und Ausführungs-, Werk- und Montageplanung | H37: Mitwirkung an Planung und Freigabe | I37: Autostrom+ | J37: – | K37: bewertet
B38: ANF-032 | C38: Vertragsanlage 4 | D38: § 3.7 | E38: Bau & Dokumentation | G38: Bestandsunterlagen (As-Built) | H38: Verantwortlich für Dokumentation und Erstellung Unterlagen | I38: Autostrom+ | J38: – | K38: bewertet
B39: ANF-033 | C39: Vertragsanlage 6 | D39: § 8 | E39: Authentifizierung & Zugang | F39: Öffnung innerhalb von 45 Sekunden. | G39: Folgende Authentifizierungsoptionen (Anmeldung, Freischaltung der physischen Zufahrtsbeschränkungen und Start des Ladevorgangs etc.) müssen möglich sein: ▪ RFID-Token (Ladekarte etc.) von vertraglich angebundenen Mobilitätsdienstleister, ▪ App von vertraglich angebundenen Mobilitätsdienstleister, ▪ Ad hoc-Laden ohne Registrierung und ▪ ISO 15118 (nach Verfügbarkeit – s. o. Abschnitt 7.). Der Authentifizierungsvorgang zur Freigabe des Ladeplatzes muss innerhalb von maximal 45 Sekunden abgeschlossen sein und sollte so gestaltet sein, dass der Verkehrsfluss möglichst wenig beeinträchtigt wird. Die angegebene Zeitspanne umfasst alle praktische und technische Schritte der Authentifizierung bis zur Öffnung der Schranke bzw. des Pollers und gilt für alle vorgesehenen Zugangsarten | H39: 45 Sekunden (!) Wie (wer) Erfüllt das? Bieterfrage 441 nach Bezahlterminal ? | I39: eRound / SCS | J39: Authentifizierungskomponente / Schrankensteuerung | K39: erfasst
B40: ANF-034 | C40: Vertragsanlage 6 | D40: § 9 (1) | E40: Belegungsdetektion | F40: Belegungsdetektion ist gefordert. | G40: Jeder MCS- / CCS-Ladepunkt muss über eine Detektion verfügen. Die MCS- / CCSLadeplatzdetektion ist so auszustatten, dass Objekte auf dem zum MCS- / CCSLadepunkt gehörigen MCS- / CCS-Ladeplatz detektiert werden können. | H40: Deckensensoren Pönalisierung / Falschparker | I40: Schrankenhersteller / SCS | J40: Belegungsdetektion | K40: erfüllt | L40: 46259 | M40: Radarsensor stellt Belegung der Ladesäule bereit
B41: ANF-035 | C41: Vertragsanlage 6 | D41: § 9 (2) | E41: Belegungsdetektion | F41: Roaming-Infos müssen veröffentlicht werden Pönalisierung gefordert. Entfernung Falschparker gefordert. | G41: Die Information der Reservierung des MCS- / CCS-Ladepunkts muss dem IT-Backend der MCS- / CCS-Ladeeinrichtung zur Verfügung stehen und muss angebundenen Mobilitätsdienstleistern und Betreibern von Online-Plattformen zur Darstellung von Statusinformationen zur Verfügung gestellt werden. Zudem soll dem Betreiber die Pönalisierung und Entfernung von Falschparkern ermöglicht werden. | H41: Pönalisierung / Falschparker | I41: eRound / SCS | J41: OCPI Buchungskalender / Kennzeichenerfassung / Pönalisierungssystem | K41: erfasst
B42: ANF-036 | C42: Vertragsanlage 6 | D42: § 10 (1) | E42: Zufahrt & Schranke | F42: Einfahrtsschranke Ausfahrtsschranke Bei Nichtbelegung beide Schranken geschlossen. | G42: Jeder Ladeplatz ist mit einer Einfahrts- und einer Ausfahrtsschranke auszustatten. Die Schranken sind wie folgt zu betreiben: 1) Grundstellung: Beide Schranken sind bei Nichtbelegung des Ladeplatzes geschlossen. | I42: Schrankenhersteller | J42: Schrankensteuerung | K42: erfüllt | L42: 46259 | M42: Schranke wird konfiguriert, sodass diese zu ist
B43: ANF-037 | C43: Vertragsanlage 6 | D43: § 10 (2) | E43: Zufahrt & Schranke | F43: Einfahrtsschranke öffnet nach Authentifizierung. | G43: 2) Einfahrt: Die Einfahrtschranke öffnet sich nach erfolgreicher Authentifizierung und gewährt Zugang zum Ladeplatz. Sie bleibt während des gesamten Ladevorgangs geöffnet. | H43: Schnittstelle notwendig: Öffnen direkt nach Authentifizierung Schließen bei Ende Ladevorgang | I43: eRound / SCS | J43: Authentifizierungskomponente / Schrankensteuerung | K43: erfüllt | L43: 46259 | M43: Radarsensor erkennt Einfahrt bleibt geöffnet bis die Zone wieder frei ist.
B44: ANF-038 | C44: Vertragsanlage 6 | D44: § 10 (3) | E44: Zufahrt & Schranke | F44: Ausfahrtsschranke öffnet bei Ankunft LKW. | G44: 3) Ausfahrtsschaltung: Sobald der Lkw seine Parkposition auf dem Ladeplatz erreicht hat, öffnet sich die Ausfahrtsschranke. | H44: Ausfahrtsschranke also recht dumm -> komplett durch SCS möglich? | I44: Schrankenhersteller / SCS | J44: Schrankensteuerung | K44: erfüllt | L44: 46259 | M44: Die Schranke kann selbstständig öffnen und schließen
B45: ANF-039 | C45: Vertragsanlage 6 | D45: § 10 (4) | E45: Zufahrt & Schranke | F45: Ausfahrtsschranke schließt nach Verlassen des LKW. Fernsteuerung der Schranken. | G45: 4) Verlassen des Ladeplatzes: Nach Abschluss des Ladevorgangs und dem Verlassen des Ladeplatzes schließt sich die Ausfahrtsschranke wieder. Zudem ist dafür zu sorgen, dass die Einfahrts- und Ausfahrtsschranken im Notfall geöffnet werden können | H45: Schließen nach Ausfahrt -> Schranke selbst | I45: Schrankenhersteller | J45: Schrankensteuerung | K45: erfüllt | L45: 46259 | M45: Schranke schließt von alleine
B46: ANF-040 | C46: Vertragsanlage 6 | D46: § 4 | E46: Anzeige & Beschilderung | F46: Bezahlterminal für mehrere MCS/CCS Ladepunkte möglich. | G46: Display zur Anzeige von Informationen zum Ladevorgang (Ad hoc-Preis des CPO, geladene Energiemenge in kWh, Blockadeentgelt, Anweisungen zum Ablauf des Ladens). ▪ Das Display muss sowohl bei Tageslicht unter Sonneneinstrahlung als auch bei Dunkelheit gut ablesbar sein. ▪ Die Menüführung erfolgt mindestens in den Sprachen Deutsch und Englisch. ▪ RFID-Multireader zum Lesen von allen gängigen und zukünftig erwartbaren Ladekarten von Fahrstromanbietern (z.B. unter Berücksichtigung VDE-AR-E 2532-100) zum Authentifizieren und Starten von Ladevorgängen. Bezahlterminal für das Bezahlen von Ad hoc-Ladevorgängen (ohne Dauerschuldverhältnis). Dieses muss bargeldlose Zahlungen entsprechend den Vorgaben der AFIR ermöglichen. Zusätzliche Authentifizierungs- und Zahlungsmöglichkeiten können den Nutzern kostenlos eingeräumt werden. Dabei ist NFC-Technologie (Nahfeldkommunikation) und PinEingabe erforderlich. Von der Möglichkeit einer Pin-Eingabe kann abgesehen werden, wenn die Notwendigkeit der Pin-Eingabe dauerhaft bei allen relevanten Karten, insbesondere bei Präsentation einer physischen Karte zum Bezahlen von Fahrstrom entfällt. ▪ Ein Bezahlterminal kann auch zur Bezahlung von Ladevorgängen mehrerer MCS- bzw. CCS-Ladeeinrichtungen bzw. -Ladepunkten dienen | H46: Bezahlterminal kann für mehrere MCS / CCS genutzt werden | I46: eRound | J46: Authentifizierungskomponente | K46: erfüllt | L46: 46259 | M46: Jede LIS hat ein Display, rest in KANN-Anforderung
B47: ANF-041 | C47: Vertragsanlage 10 | D47: § 3.1 | E47: Monitoring & Reporting | F47: Benennung Datenpunkte zu Reservierungen im Monatsbericht. | G47: ab_total_reservations Anzahl Reservierungen je Ladepunkt ab_total_reservations_cancelled Anzahl stornierter Reservierungen je Ladepunkt ab_reservations_no-show Anzahl nicht eingehaltener Reservierungen je Ladepunkt | H47: Datentabelle Monatsbericht Verfügbarkeit | I47: eRound | J47: Monitoring | K47: trifft nicht zu | M47: Automatisch ausgewertet: Außerhalb des betrachteten Leistungsumfangs (Schranken, Kennzeichenerfassung, dynamische Anzeige).
B48: ANF-042 | C48: Vertragsanlage 10 | D48: § 5 (d) | E48: Monitoring & Reporting | F48: Benennung Datenpunkte zu Reservierungen im Monatsbericht. | G48: total_reservation_cost Gesamtsumme aller Kosten im Zusammenhang mit der Reservierung eines Ladepunkts, einschließlich Festpreisbestandteilen (€) | H48: Datentabelle Reservierungskosten | I48: eRound | J48: Monitoring | K48: trifft nicht zu | M48: Automatisch ausgewertet: Außerhalb des betrachteten Leistungsumfangs (Schranken, Kennzeichenerfassung, dynamische Anzeige).
B49: ANF-043 | C49: Vertragsanlage 13 | D49: § 8 (1) | E49: Reservierung | F49: Mehrfachbuchungen unterbinden | G49: Grundsätzlich möchte der Auftraggeber den Nutzern eine gewisse Flexibilität ermöglichen, da die Inanspruchnahme einer Reservierung z.B. aufgrund kurzfristiger Staus auch ohne Verschulden ggf. nicht wahrgenommen werden kann. Ein missbräuchliches Verhalten durch Nutzer, z.B. durch mehrfache Reservierungsbuchungen am gleichen Standort und am gleichen Tag, ist nicht im Interesse des Auftraggebers. Sollte sich ein solches Verhalten einstellen, besteht vor dem Hintergrund eines abweichenden Marktstandards nach §23 Abs. 3 des Betreibervertrags die Möglichkeit, die definierten Mindestvoraussetzungen an Reservierungsplattformen zu ändern. | H49: identisch zu Paragraph 38 - 1 | I49: eRound | J49: OCPI Buchungskalender | K49: trifft nicht zu | M49: Automatisch ausgewertet: Außerhalb des betrachteten Leistungsumfangs (Schranken, Kennzeichenerfassung, dynamische Anzeige).
B50: ANF-044 | C50: Bieterfragenkatalog | D50: § 351 | E50: Belegungsdetektion | F50: Belegungsdetektion ist gefordert. | G50: Nein, auch bei installierten Zufahrtsbeschränkungen sind Sensoren als Redundanz zum Zweck der Detektion des Belegungsstatus des Ladeplatzes vorzusehen. | H50: // Antwort: Nein, auch bei installierten Zufahrtsbeschränkungen sind Sensoren als Redundanz zum Zweck der Detektion des Belegungsstatus des Ladeplatzes vorzusehen. | I50: SCS | J50: Belegungsdetektion | K50: erfasst
B51: ANF-045 | C51: Bieterfragenkatalog | D51: § 373 | E51: Reservierung | F51: OCPI Schnittstelle für Reservierungen ist gefordert. | G51: Frage: Laut Ziff. 3.4 im 4. Verfahrensbrief soll es nur ein zentrales Reservierungssystem geben. zugleich ist in § 23 Abs. 1 des Betreibervertrags von Reservierungsplattformen (Mehrzahl) die Rede. Wie passt dies zusammen? Antwort: Die überarbeitete Regelung im Betreibervertrag (§ 24) sieht vor, dass der Auftragnehmer eine Anbindung von Reservierungsplattformen über eine OCPI basierte Schnittstelle sicherstellt und Reservierungsplattformen über diese Schnittstelle ermöglicht, wenn sie die im Vertrag genannten Mindestvoraussetzungen erfüllt. | H51: OCPI Schnittstelle // Antwort: Die überarbeitete Regelung im Betreibervertrag (§ 24) sieht vor, dass der Auftragnehmer eine Anbindung von Reservierungsplattformen über eine OCPI basierte Schnittstelle sicherstellt und Reservierungsplattformen über diese Schnittstelle ermöglicht, wenn sie die im Vertrag genannten Mindestvoraussetzungen erfüllt. | I51: eRound | J51: OCPI Buchungskalender | K51: trifft nicht zu | M51: Automatisch ausgewertet: Außerhalb des betrachteten Leistungsumfangs (Schranken, Kennzeichenerfassung, dynamische Anzeige).
B52: ANF-046 | C52: Bieterfragenkatalog | D52: § 374 | E52: Reservierung | F52: Anbindung muss deutschlandweit sichergestellt sein. | G52: Frage: Bei einer Reservierungsplattform handelt es sich um Software, die damit grundsätzlich weltweit verfügbar ist. Wie ist der Passus zu verstehen, dass die Plattform im gesamten Gebiet der Bundesrepublik Deutschland Reservierungen ermöglichen soll? Antwort: Es muss sichergestellt sein, dass die Reservierung für alle Rastanlagen mit Ladeinfrastruktur für E-LKW auf Bundesautobahnen möglich ist | H52: // Antwort: Es muss sichergestellt sein, dass die Reservierung für alle Rastanlagen mit Ladeinfrastruktur für E-LKW auf Bundesautobahnen möglich ist. | I52: Reservierungsplattform | J52: Anbindung | K52: trifft nicht zu | M52: Automatisch ausgewertet: Außerhalb des betrachteten Leistungsumfangs (Schranken, Kennzeichenerfassung, dynamische Anzeige).
B53: ANF-047 | C53: Bieterfragenkatalog | D53: § 375 | E53: Nutzungszeit & Entgelte | G53: Es ist in Verbindung mit §36 das Erheben eines Blockadeentgeltes möglich, welches (bei Erscheinen) erst nach 75 min greift. Gehen wir recht in der Annahme, dass der CPO mit einer Belegung durch einen Reservierungsvorgang von 75 min rechnen muss, bevor er die Ladestation erneut als verfügbar meldet? | H53: leer 10.12.2025 // Antwort: Der Auftragnehmer muss nicht mit einer Belegung durch einen Reservierungsvorgang von 75min (beim Zwischenladen) rechnen. Der entsprechende Paragraph (jetzt §38) wurde im Betreibervertrag mit der Aufforderung zur Angebotsabge (Dezember 2025) überarbeitet. Die zuvor vorgesehene Wartezeit von 15 Minuten ist entfallen. Nach der neuen Regelung des § 38 Abs. 3 kann ein Blockadeentgelt im Fall einer Reservierung nach Ablauf des reservierten Zeitraums (ohne Wartezeit) erhoben werden. | I53: offen | J53: – | K53: trifft nicht zu | M53: Automatisch ausgewertet: Außerhalb des betrachteten Leistungsumfangs (Schranken, Kennzeichenerfassung, dynamische Anzeige).
B54: ANF-048 | C54: Bieterfragenkatalog | D54: § 376 | E54: Nutzungszeit & Entgelte | G54: Frage: Der Vertrag sieht eine spätere mögliche Anpassung der Höhe des Blockadeentgeltes vor, aber keine Anpassungsoption hinsichtlich der Wartezeit. Gehen wir richtig in der Annahme, dass der AG nicht beabsichtigt, mögliche Optimierungspotenziale durch kürzere Wartezeiten während der Vertragslaufzeit zu realisieren? Antwort: Der Betreibervertrag wird mit der Aufforderung der Abgabe verbindlicher Angebote aktualisiert. | H54: Verweis Ausschreibungsunterlagen // Antwort: Der Betreibervertrag wird mit der Aufforderung der Abgabe verbindlicher Angebote aktualisiert. | I54: offen | J54: – | K54: trifft nicht zu | M54: Automatisch ausgewertet: Außerhalb des betrachteten Leistungsumfangs (Schranken, Kennzeichenerfassung, dynamische Anzeige).
B55: ANF-049 | C55: Bieterfragenkatalog | D55: § 377 | E55: Reservierung | G55: Im In § 23 Abs. 4 BV heißt es, dass der Auftragnehmer verpflichtet ist, Endnutzern bzw. anderen Mobilitätsdienstleistern die Nutzung von MCS- oder CCS auch ohne vorherige Reservierung zu ermöglichen. Gehen wir recht in der Annahme, dass mit CCS nur Ladepunkte zum Zwischenladen gemeint sind und keine Ladepunkte zum Übernachtladen? Gehen wir weiter recht in der Annahme, dass sich dies auf die Ladepunkte eines Standortes bezieht und nicht auf jeden einzelnen Ladepunkt? Falls nein, heißt dies, dass es zulässig ist, ab weniger als 1h vor dem nächsten reservierten Lade Slot, keinen neuen Ladevorgang an dem betreffenden Ladepunkt mehr zuzulassen, da eine Blockiergebühr erst nach 60 min zulässig ist? Inwiefern sieht es die Vergabestelle als zulässig an, dass der adhoc-Nutzer einen spätesten Abfahrtzeitpunkt bestätigen muss, bei dessen Überschreiten eine Blockiergebühr erhoben werden darf? | H55: Verweis Ausschreibungsunterlagen // Antwort: Der Betreibervertrag wird mit der Aufforderung der Abgabe verbindlicher Angebote aktualisiert. | I55: offen | J55: – | K55: trifft nicht zu | M55: Automatisch ausgewertet: Außerhalb des betrachteten Leistungsumfangs (Schranken, Kennzeichenerfassung, dynamische Anzeige).
B56: ANF-050 | C56: Bieterfragenkatalog | D56: § 378 | E56: Reservierung | F56: Anpassung möglich, bei ungewolltem Nutzerverhalten. | G56: Frage: Aus Sicht eines Kunden liegt es nahe, ggf. mehr als einen Standort zu reservieren, solange eine Buchung kostenlos storniert werden kann. Eine Stornierung und damit Freigabe eines Ladepunkts 30 Minuten vor dem geplanten Nutzungsbeginn führt jedoch dazu, dass die Wahrscheinlichkeit einer tatsächlichen Nutzung des zuvor reservierten Ladepunkts deutlich sinkt. Welche Maßnahmen sieht der AG vor, um ein derartiges Verhalten der Nutzer zu verhindern? Antwort: Grundsätzlich möchte der Auftraggeber den Nutzern eine gewisse Flexibilität ermöglichen, da die Inanspruchnahme einer Reservierung z.B. aufgrund kurzfristiger Staus auch ohne Verschulden ggf. nicht wahrgenommen werden kann. Ein missbräuchliches Verhalten durch Nutzer, z.B. durch mehrfache Reservierungsbuchungen am gleichen Standort und am gleichen Tag, ist nicht im Interesse des Auftraggebers. Sollte sich ein solches Verhalten einstellen, besteht vor dem Hintergrund eines abweichenden Marktstandards nach §23 Abs. 3 des Betreibervertrags die Möglichkeit, die definierten Mindestvoraussetzungen an Reservierungsplattformen zu ändern. | H56: // Antwort: Grundsätzlich möchte der Auftraggeber den Nutzern eine gewisse Flexibilität ermöglichen, da die Inanspruchnahme einer Reservierung z.B. aufgrund kurzfristiger Staus auch ohne Verschulden ggf. nicht wahrgenommen werden kann. Ein missbräuchliches Verhalten durch Nutzer, z.B. durch mehrfache Reservierungsbuchungen am gleichen Standort und am gleichen Tag, ist nicht im Interesse des Auftraggebers. Sollte sich ein solches Verhalten einstellen, besteht vor dem Hintergrund eines abweichenden Marktstandards nach §23 Abs. 3 des Betreibervertrags die Möglichkeit, die definierten Mindestvoraussetzungen an Reservierungsplattformen zu ändern. | I56: eRound | J56: OCPI Buchungskalender | K56: trifft nicht zu | M56: Automatisch ausgewertet: Außerhalb des betrachteten Leistungsumfangs (Schranken, Kennzeichenerfassung, dynamische Anzeige).
B57: ANF-051 | C57: Bieterfragenkatalog | D57: § 455 | E57: Reservierung | F57: Reservierungsplattform ist nicht Teil der Ausschreibung. | G57: Frage: Im vierten Verfahrensbrief findet sich folgende Aussage unter 3.4.: „Die Vorgaben zum Reservierungssystem wurden dahingehend angepasst, dass es nunmehr ein zentrales Reservierungssystem geben wird.“ Im Betreibervertrag unter § 23, 2. Lesen wir allerdings: „Der Auftragnehmer ist verpflichtet, jeder Reservierungsplattform die Anbindung über die in Absatz 1 genannte Schnittstelle kostenfrei zu ermöglichen, soweit die Reservierungsplattform die folgenden Mindestvoraussetzungen erfüllt: (…)“ Dies stellt aus unserer Sicht ggf. einen Widerspruch dar. Wir bitten darum, die geplante Architektur des Reservierungsökosystems einmal zu erläutern. Antwort: Der Vertrag gilt. Sobald Reservierungsplattformen die im Vertrag genannten Mindestvoraussetzungen erfüllen, werden sie als anbindungsfähig und als zentral angesehen. In diesem Fall hat der Auftragnehmer auf Wunsch der externen Reservierungsplattformen eine Anbindung über eine OCPI-basierte Schnittstelle zu gewährleisten. Ein durch den Auftraggeber (z.B. per Vergabeverfahren) organisiertes, zentrales Reservierungssystem ist nicht in Planung. | H57: Zentrales Reservierungssystem // Antwort: Der Vertrag gilt. Sobald Reservierungsplattformen die im Vertrag genannten Mindestvoraussetzungen erfüllen, werden sie als anbindungsfähig und als zentral angesehen. In diesem Fall hat der Auftragnehmer auf Wunsch der externen Reservierungsplattformen eine Anbindung über eine OCPI-basierte Schnittstelle zu gewährleisten. Ein durch den Auftraggeber (z.B. per Vergabeverfahren) organisiertes, zentrales Reservierungssystem ist nicht in Planung. | I57: Reservierungsplattform | J57: Reservierungsplattform | K57: trifft nicht zu | M57: Automatisch ausgewertet: Außerhalb des betrachteten Leistungsumfangs (Schranken, Kennzeichenerfassung, dynamische Anzeige).
B58: ANF-052 | C58: Bieterfragenkatalog | D58: § 370 | E58: Reservierung | F58: Sämtliche Infos via gängigen Roamingprotokoll / Marktstandard zur verfügung stellen. | G58: Frage: Welche Informationen der Reservierung sollen MSP und sonstigen bereitgestellt werden? Antwort: Es ist vom AN sicherzustellen, dass sämtliche Statusinformationen der Reservierungen bereitgestellt werden, die mittels der gängigen Roamingprotokolle übermittelt werden können und dem gängigen Marktstandard entsprechen. | H58: // Antwort: Es ist vom AN sicherzustellen, dass sämtliche Statusinformationen der Reservierungen bereitgestellt werden, die mittels der gängigen Roamingprotokolle übermittelt werden können und dem gängigen Marktstandard entsprechen. | I58: eRound | J58: OCPI Buchungskalender | K58: trifft nicht zu | M58: Automatisch ausgewertet: Außerhalb des betrachteten Leistungsumfangs (Schranken, Kennzeichenerfassung, dynamische Anzeige).
B59: ANF-053 | C59: Bieterfragenkatalog | D59: Nr. 1 / S. 1 | E59: Vergabeverfahren & Angebot | F59: Klarstellung: Der Zuschlag wird nicht bereits auf die Erstangebote erteilt. Eine auf die Erstangebote bezogene Bindefrist ist daher gegenstandslos. | G59: Erster Verfahrensbrief, Formblatt A1, Fragenkatalog Nr. 61: In der Antwort auf Bieterfrage 61 ist ausgeführt, dass die Erstangebote indikativ sein werden und erst die Folgeangebote verbindlich. Unter Ziffer 3.1 des Ersten Verfahrensbriefs zum Verhandlungsverfahren heißt es entsprechend, dass der Auftraggeber den Zuschlag nicht auf das jeweils wirtschaftlichste Erstangebot erteilen wird. Unter Ziffer 4.6 des Ersten Verfahrensbriefs zum Verhandlungsverfahren heißt es allerdings, dass das Erstangebot zuschlagsfähig sein muss. Zudem soll der Bieter im Formblatt A1 – Angebotsschreiben erklären, sich bis zum Ablauf der Bindefrist an sein Erstangebot gebunden zu halten. Vor diesem Hintergrund bitten wir um Klarstellung: Ist unser Verständnis richtig, dass die Erstangebote rein indikativer Natur sind, also vom Auftraggeber unter keinen Umständen bezuschlagt werden können? Wie ist die Bindefrist zu verstehen? | H59: Bezug lt. Katalog: Erster Verfahrensvrief Katalogdatum: 08.01.2025 // Antwort: Der Zuschlag wird nicht bereits auf die Erstangeboite erteilt. Eine auf die Erstangebote bezogene Bindefrist ist daher gegenstandslos. | I59: Autostrom+ | J59: – | K59: trifft nicht zu
B60: ANF-054 | C60: Bieterfragenkatalog | D60: Nr. 2 / S. 1 | E60: Anzeige & Beschilderung | F60: Zusage / Ankündigung: Der AG beabsichtigt, die Unterlagen im weiteren Vergabeverfahren zur Verfügung zu stellen. | G60: Wann werden Anlage 04 Anhang 2 (Regelschnitt und Details für die Gestaltung der LKW- Ladeinfrastruktur) und Anlage 04 Anhang 3 (Markierungs- und Beschilderungsplan) zur Verfügung gestellt? | H60: Bezug lt. Katalog: LB Errichtung Katalogdatum: 08.01.2025 // Antwort: Der AG beabsichtigt, die Unterlagen im weiteren Vergabeverfahren zur Verfügung zu stellen. Die Erstellung eines Erstangebotes ist unabhängig davon auch ohne die genannten Unterlagen möglich. | I60: tbd | J60: Beschilderung | K60: trifft nicht zu | M60: Automatisch ausgewertet: Außerhalb des betrachteten Leistungsumfangs (Schranken, Kennzeichenerfassung, dynamische Anzeige).
B61: ANF-055 | C61: Bieterfragenkatalog | D61: Nr. 3 / S. 1 | E61: Vertrag & Recht | F61: Klarstellung: Eine entsprechende Vertragsfassung wird allen für das Verhandlungsverfahren ausgewählten Bewerbern und Bewerbergemeinschaften mit Beantwortung zur Verfügung gestellt. | G61: Wir bitte zur besseren Nachverfolgung der Unterlagenfortschreibung um Zusendung einer ChangeVersion, um nachzuvollziehen in welchen Punkte das Vertragswerk angepasst wurde. | H61: Bezug lt. Katalog: Vertrag Katalogdatum: 09.01.2025 // Antwort: Eine entsprechende Vertragsfassung wird allen für das Verhandlungsverfahren ausgewählten Bewerbern und Bewerbergemeinschaften mit Beantwortung zur Verfügung gestellt. | I61: offen | J61: – | K61: trifft nicht zu | M61: Automatisch ausgewertet: Außerhalb des betrachteten Leistungsumfangs (Schranken, Kennzeichenerfassung, dynamische Anzeige).
B62: ANF-056 | C62: Bieterfragenkatalog | D62: Nr. 4 / S. 1 | E62: Vertrag & Recht | F62: Zusage / Ankündigung: Anlage 9 zum Vertrag wird dem AN nach Vertragsschluss zu Verfügung gestellt (vgl. Vertragsanlage 4 LB Errichtung, S.13). | G62: Die für die zweite Phase der Ausschreibung geteilten Unterlagen enthalten NICHT die Vertragsanlagen 7 ("Logos") und 9 ("Ansprechpartner (losspezifisch)"). Wenn diese bewusst nicht geteilt werden - wann kann mit diesen gerechnet werden? | H62: Bezug lt. Katalog: Vertrag Katalogdatum: 09.01.2025 // Antwort: Anlage 9 zum Vertrag wird dem AN nach Vertragsschluss zu Verfügung gestellt (vgl. Vertragsanlage 4 LB Errichtung, S.13). Der AG beabsichtigt, die Anlage 7 im weiteren Vergabeverfahren zur Verfügung zu stellen. Die Erstellung eines Erstangebotes ist unabhängig davon auch ohne die genannten Unterlagen möglich. | I62: offen | J62: – | K62: trifft nicht zu | M62: Automatisch ausgewertet: Außerhalb des betrachteten Leistungsumfangs (Schranken, Kennzeichenerfassung, dynamische Anzeige).
B63: ANF-057 | C63: Bieterfragenkatalog | D63: Nr. 5 / S. 1 | E63: Flächen & Genehmigungen | F63: Klarstellung: Die Unterlagen Vertragsanlage 2 ("Standortübersicht (losspezifisch)") und Anlage 2 zum Verfahrensbrief ("Gesamtübersicht über die Lose") wurden entsprechend aktualisiert und stehen Ihnen in der überarbeiteten Version zur … | G63: wir bitten um Klärung der folgenden Frage betreffend Anlage 2 zum Verfahrensbrief, Vertragsanlage 2_Standortübersicht und Vertragsanlage 3. In diesen Dokumenten ergeben sich teilweise Inkonsistenzen hinsichtlich der Anzahl der Ladepunkte je Standort. Könnten Sie diese bitte erläutern? Beispiel: Los 1, Standort Schwalenberg Ost: - laut Vertragsanlage 2_Standortübersicht, Los 1 und laut Anlage 2 zum Ersten Verfahrensbrief sollen an dem Standort 1 MCS-Ladepunkt, 1 CCS (Zwischenladepunkt) aufgebaut werden - laut Anlage 3 Los 1 (Vorplanungsdokument) sollen an dem Standort 6 MCS-Ladepunkte und 30 CCS Ladepunkt aufgebaut werden (keine Unterscheidung von Zwischenladen und Übernachtladen) | H63: Bezug lt. Katalog: Anlage 2/3 Katalogdatum: 09.01.2025 // Antwort: Die Unterlagen Vertragsanlage 2 ("Standortübersicht (losspezifisch)") und Anlage 2 zum Verfahrensbrief ("Gesamtübersicht über die Lose") wurden entsprechend aktualisiert und stehen Ihnen in der überarbeiteten Version zur Verfügung. Diese aktualisierten Dokumente sind dem Erstangebot zu Grunde zu legen. In den unverbindlichen Vorplanungen (Vertragsanlage 3 "Angaben und Informationen zu den Standorten (losspezifisch)") wird nicht zwischen CCS 400 und CCS 100 Ladepunkten unterschieden, da von gleichen baulichen Anforderungen auszugehen ist. Etwaige Unterschiede bei z. B. Kabelquerschnitten und anderen Komponenten sind zu berücksichtigen. | I63: offen | J63: – | K63: trifft nicht zu | M63: Automatisch ausgewertet: Außerhalb des betrachteten Leistungsumfangs (Schranken, Kennzeichenerfassung, dynamische Anzeige).
B64: ANF-058 | C64: Bieterfragenkatalog | D64: Nr. 6 / S. 1 | E64: Netzanschluss & Energie | F64: Klarstellung: Die Unterlagen Vertragsanlage 2 ("Standortübersicht (losspezifish)") und Anlage 2 zum Verfahrensbrief ("Gesamtübersicht über die Lose") wurden entsprechend aktualisiert und stehen Ihnen in der überarbeiteten Version zur Verfügung. | G64: Es ist aufgefallen, dass in den Standortübersichten sowie in der Gesamtübersicht über die Lose (Anlagen 02) die Angaben in den Spalten "Nr. BAB" sowie "Geogr. Länge" und "Geogr. Breite" in weiten Teilen nicht mit der jeweiligen Kennung und Bezeichnung der Rastanlage (PWC-Anlage) zusammenpassen. Wir bitten um Überprüfung. Darüber hinaus unterscheiden sich die Angaben zur jeweiligen Anzahl der Ladepunkte in den Dokumenten der Vertragsanlagen 02 und der Vertragsanlage 05. Wir bitten um Überprüfung dieses Widerspruchs. Des Weiteren bitten wir um Überprüfung der Unterlagen in "Vertragsanlage 3 - Angaben und Informationen zu den einzelnen Standorten (losspezifisch)", da die dort enthaltenen Angaben teilweise nicht mit den vorgenannten Dokumenten aus "Anlage 2" übereinstimmen. Außerdem scheint in "Anlage 3" bei der "lfd. Nr." 74 die Angabe der "Nr. BAB" fehlerhaft zu sein. | H64: Bezug lt. Katalog: Vertragsanlage 02 Standortübersicht (losspezifisch) - Stand 06.01.2025 / Anlage 02_zum Verfahrensbrief_Gesamtübersich t über die Lose - Stand 06.01.2025 / Vertragsanlage 3 - Angaben und Informationen zu den einzelnen Standorten (losspezifisch) - Stand 06.01.2025 / Vertragsanlage 5 - Details zum Netzanschluss - Stand 06.01.25 Katalogdatum: 10.01.2025 // Antwort: Die Unterlagen Vertragsanlage 2 ("Standortübersicht (losspezifish)") und Anlage 2 zum Verfahrensbrief ("Gesamtübersicht über die Lose") wurden entsprechend aktualisiert und stehen Ihnen in der überarbeiteten Version zur Verfügung. Diese aktualisierten Dokumente sind dem Erstangebot zu Grunde zu legen. Die Angaben der Vertragsanlage 05 (Stand 06.01.2025) sind korrekt. | I64: offen | J64: – | K64: trifft nicht zu | M64: Automatisch ausgewertet: Außerhalb des betrachteten Leistungsumfangs (Schranken, Kennzeichenerfassung, dynamische Anzeige).
B65: ANF-059 | C65: Bieterfragenkatalog | D65: Nr. 7 / S. 2 | E65: Vergabeverfahren & Angebot | F65: Klarstellung: Die Unterlagen Anlage 5 zum Verfahrensbrief wurden entsprechend aktualisiert und stehen Ihnen in der überarbeiteten Version zur Verfügung. | G65: Es ist aufgefallen, dass die Karte der Standorte fälschlicherweise als "Anlage 4 zum Verfahrensbrief" betitelt ist, während die Dateibezeichnung "Anlage 05..." ist. Wir bitten um Überprüfung. Des Weiteren bitten wir um Überprüfung der dargestellten Standorte, da mindestens 3 Standorte aus Los 4 nicht dargestellt sind. | H65: Bezug lt. Katalog: Anlage 05 zum Verfahrensbrief - Karte zur Losaufteilung - Stand 06.01.2025 Katalogdatum: 10.01.2025 // Antwort: Die Unterlagen Anlage 5 zum Verfahrensbrief wurden entsprechend aktualisiert und stehen Ihnen in der überarbeiteten Version zur Verfügung. Diese aktualisierte Dokumente ist dem Erstangebot zu Grunde zu legen. | I65: offen | J65: – | K65: trifft nicht zu | M65: Automatisch ausgewertet: Betrifft das Vergabeverfahren (Angebot, Wertung, Unterlagen), nicht die zu erbringende Leistung. Keiner Komponente zugeordnet.
B66: ANF-060 | C66: Bieterfragenkatalog | D66: Nr. 8 / S. 2 | E66: Vergabeverfahren & Angebot | F66: Zusage / Ankündigung: Siehe die Antwort auf Frage 1. Die Bieter sind dennoch aufgefordert ein zuschlagsfähiges Erstangebot abzugeben. | G66: Bindung an Erstangebot: Im ersten Verfahrensbrief ist in 4.6 von der Abgabe eines "zuschlagsfähigen" Erstangebots die Rede. Wird somit in der Verhandlungsphase nur das verhandelt, was als "Verhandlungsbedarf" im Formblatt A6 explizit angemeldet wird und der Rest ist bereits bindend im Falle eines Zuschlags? | H66: Bezug lt. Katalog: Verfahrensbrief in 4.6 Katalogdatum: 14.01.2025 // Antwort: Siehe die Antwort auf Frage 1. Die Bieter sind dennoch aufgefordert ein zuschlagsfähiges Erstangebot abzugeben. In den Verhandlungen wird der von den Bietern im Formblatt A6 addressierte Verhandlungsbedarf behandelt. Im Anschluss an die Verhandlungen werden den Bietern entsprechend der Ergebnisse der Verhandlungen überarbeitete Vergabeunterlagen zur Verfügung gestellt. Auf der Grundlage dieser überarbeiteten Vergabeunterlagen werden die Bieter aufgefordert werden ein verbindliches Angbeot abzugeben. Dieses verbindliche Angbeot, auf das der AG beabsichtigt den Zuschlag zu erteilen, wird vollständig neu einzureichen sein und nicht auf Bestandteile des Erstangebots bezunehmen. | I66: offen | J66: – | K66: trifft nicht zu | M66: Automatisch ausgewertet: Betrifft das Vergabeverfahren (Angebot, Wertung, Unterlagen), nicht die zu erbringende Leistung. Keiner Komponente zugeordnet.
B67: ANF-061 | C67: Bieterfragenkatalog | D67: Nr. 9 / S. 2 | E67: Netzanschluss & Energie | F67: Klarstellung: Die Pflicht, mit allen Mobilitätsdienstleistern diskriminierungsfrei Verträge zu schließen ist in §27(1) des Hauptvertrags geregelt. | G67: Müssen die Teilnehmer einen Vertrag mit jedem möglichen Mobilitätsdienstleister für das Durchleitungsmodell abschließen oder kann dies von einem einzelnen Akteur aggregiert werden? Vergleichbar mit einer Roaming-Plattform im MSP-Geschäft. | H67: Bezug lt. Katalog: BYOP Katalogdatum: 14.01.2025 // Antwort: Die Pflicht, mit allen Mobilitätsdienstleistern diskriminierungsfrei Verträge zu schließen ist in §27(1) des Hauptvertrags geregelt. Der Mobilitätsdienstleister kann dabei optional das Durchleitungsmodell wählen und den Strom bilanziell bereitstellen (§28 des Hauptvertrags). Erforderlich ist auch bei Wahl des Durchleitungsmodells der Abschluss einer Vereinbarung zwischen Ladepunktbetreiber und Mobilitätsdienstleister (vgl. Anlage 14 ). Es entstehen also bilaterale Verträge zur Durchleitung. Eine vertragliche Plattform-Lösung ist nicht zwingend vorgesehen, aber denkbar. | I67: eRound | J67: OCPI Buchungskalender | K67: trifft nicht zu | M67: Automatisch ausgewertet: Außerhalb des betrachteten Leistungsumfangs (Schranken, Kennzeichenerfassung, dynamische Anzeige).
B68: ANF-062 | C68: Bieterfragenkatalog | D68: Nr. 10 / S. 2 | E68: Vergabeverfahren & Angebot | F68: Bestätigt: der Rastplatz mit der Kennung DE-ST-001249 ist "Brockenblick Ost". | G68: Bezieht sich "Parkplatz Brockenblick Ost" (DE-ST-001249) tatsächlich auf "Parkplatz Brocken Nord"? | H68: Bezug lt. Katalog: Standortbezeichnung Katalogdatum: 14.01.2025 // Antwort: Ja, der Rastplatz mit der Kennung DE-ST-001249 ist "Brockenblick Ost". Für die Indentifikation der Standorte sind die angegebene Kennung und die in Anlage 2 zum Verfahrensbrief "Gesamtübersicht über die Lose" genannten Geokoordinaten maßgebend. Rastanalagenbezeichungen können in unterschiedlichen Kartensystemen (insb. von Drittanbietern) abweichen bzw. sind nicht immer aktuell. | I68: offen | J68: – | K68: trifft nicht zu | M68: Automatisch ausgewertet: Betrifft das Vergabeverfahren (Angebot, Wertung, Unterlagen), nicht die zu erbringende Leistung. Keiner Komponente zugeordnet.
B69: ANF-063 | C69: Bieterfragenkatalog | D69: Nr. 11 / S. 2 | E69: Netzanschluss & Energie | F69: Verweis des Auftraggebers auf die Antwort zu Bieterfrage 6. | G69: Die zur Verfügung gestellten standortspezifischen Dokumente bieten keine kongruenten Informationen. Die Anzahl der CCS/MCS-Ladepunkte pro Standort ist in den Unterlagen nicht konsistent: - 20250106_Vertragsanlage 02_Standortübersicht (losspezifisch) - 20250106_Vertragsanlage 05_Details zum Netzanschluss Bitte bestätigen Sie, welche Version korrekt ist und passen Sie die Dokumente entsprechend an. | H69: Bezug lt. Katalog: Ladeinfrastruktur je Standort Katalogdatum: 14.01.2025 // Antwort: siehe die Antwort auf Frage 6 | I69: offen | J69: – | K69: trifft nicht zu | M69: Automatisch ausgewertet: Die Antwort des Auftraggebers verweist ausschließlich auf Bieterfrage 6. Keine eigenständige Anforderung – der Inhalt ist unter der dort erfassten Zeile nachzuhalten.
B70: ANF-064 | C70: Bieterfragenkatalog | D70: Nr. 12 / S. 2 | E70: Bau & Dokumentation | F70: Klarstellung: Siehe Anlage 1 zum Verfahrensbrief - Betreibervertrag, §39 Abs. 3: "Das Errichtungsentgelt für den betreffenden Standort wird, sofern die jeweils nachfolgenden Zahlungsvoraussetzungen vorliegen, [...] gezahlt, […]." | G70: Sie schreiben: "Der Abschluss der Errichtungsphase wird mit der Verkehrsfreigabe des letzten Standortes im Los erreicht." Werden erst im Anschluss daran die ersten 50% der Errichtungskosten aller Standorte überwiesen, oder kann man nach jeder einzelnen Errichtung bereits 50% der Errichtungskosten anfordern? | H70: Bezug lt. Katalog: - Katalogdatum: 15.01.2024 // Antwort: Siehe Anlage 1 zum Verfahrensbrief - Betreibervertrag, §39 Abs. 3: "Das Errichtungsentgelt für den betreffenden Standort wird, sofern die jeweils nachfolgenden Zahlungsvoraussetzungen vorliegen, [...] gezahlt, […]." | I70: offen | J70: – | K70: trifft nicht zu | M70: Automatisch ausgewertet: Außerhalb des betrachteten Leistungsumfangs (Schranken, Kennzeichenerfassung, dynamische Anzeige).
B71: ANF-065 | C71: Bieterfragenkatalog | D71: Nr. 13 / S. 2 | E71: Vergabeverfahren & Angebot | F71: Verweis des Auftraggebers auf die Antwort zu Bieterfrage 1. | G71: Nach Ablauf der Angebotsfrist bleibt der Bieter bis zum Ablauf der vom öffentlichen Auftraggeber festgelegten Bindefrist an sein Angebot gebunden." Inwiefern ist damit das Erstangebot bindend? | H71: Bezug lt. Katalog: - Katalogdatum: 15.01.2024 // Antwort: siehe die Antwort auf Frage 1 | I71: offen | J71: – | K71: trifft nicht zu | M71: Automatisch ausgewertet: Die Antwort des Auftraggebers verweist ausschließlich auf Bieterfrage 1. Keine eigenständige Anforderung – der Inhalt ist unter der dort erfassten Zeile nachzuhalten.
... B74: ANF-068 | C74: Bieterfragenkatalog | D74: Nr. 16 / S. 2 | E74: Netzanschluss & Energie | F74: Klarstellung: Die bilanzielle Zuordnung der Energie im Durchleitungsmodell erfolgt über eine Zuordnungsermächtigung des EMP/MSP zu einem Bilanzkreis. | G74: In welchem Kostenposten werden Risikopositionen zu Lieferantenausfällen beim Durchleitungsmodell hinterlegt? Diese sind auslastungsabhängig und somit nicht prognostizierbar. | H74: Bezug lt. Katalog: - Katalogdatum: 15.01.2024 // Antwort: Die bilanzielle Zuordnung der Energie im Durchleitungsmodell erfolgt über eine Zuordnungsermächtigung des EMP/MSP zu einem Bilanzkreis. Diese Zuordnungsermächtigung kann solange durch den Betreiber genutzt werden, bis der Bilanzkreis, auf den sich die Zuordnungsermächtigung bezieht, gekündigt wurde. Der Betreiber muss - entsprechend einem normalen Netzbetreiber - also sicherstellen, dass nach Kündigung des Bilanzkreises (Veröffentlichung der ÜNB) keine Ladevorgänge mehr im Rahmen des Durchleitungsmodells erfolgen. "Lieferantenausfälle" führen beim Betreiber daher grundsätzlich nicht zu Kosten bezogen auf die im Rahmen des Durchleitungsmodells entnommenen Strommengen. | I74: offen | J74: – | K74: trifft nicht zu | M74: Automatisch ausgewertet: Außerhalb des betrachteten Leistungsumfangs (Schranken, Kennzeichenerfassung, dynamische Anzeige).
B75: ANF-069 | C75: Bieterfragenkatalog | D75: Nr. 17 / S. 2 | E75: Netzanschluss & Energie | F75: Klarstellung: Alle Standorte sind mit der ausgeschriebenen Anzahl an Ladepunkten zu errichten. Soweit die Netzanschlusskapazität an einzelnen Standorten nicht (rechtzeitig) vorliegt, kann der AG an diesen Standorten einen die … | G75: Sollen die Standorte mit dem Komplettsetup errichtet werden, ohne dass der endgültige Netzanschluss vorliegt? In diesem Fall können die Leistungsvorgaben der Ausschreibung nicht erfüllt werden. | H75: Bezug lt. Katalog: - Katalogdatum: 15.01.2024 // Antwort: Alle Standorte sind mit der ausgeschriebenen Anzahl an Ladepunkten zu errichten. Soweit die Netzanschlusskapazität an einzelnen Standorten nicht (rechtzeitig) vorliegt, kann der AG an diesen Standorten einen die Anschlusskapazität teilweise ersetzenden Speicher aufstellen (Anlage 1 zum Verfahrensbrief - Betreibervertrag, §44). | I75: offen | J75: – | K75: trifft nicht zu
B76: ANF-070 | C76: Bieterfragenkatalog | D76: Nr. 18 / S. 2 | E76: Nutzungszeit & Entgelte | F76: Klarstellung: Der Betreiber kann diese Kosten bei der Kalkulation seines EMP-Entgelts bzw. seines Ad hoc - Ladetarifs berücksichtigten. | G76: Wie wird im Zusammenhang mit Verlustenergien mit nicht absehbaren Veränderungen und damit einhergehenden regulatorischen Änderungen umgegangen (z.B. dynamische Netzentgelte oder neue Strompreiszonen)? Sollen diese Risiken im Angebot berücksichtigt werden oder können hier steigende Kosten auch im Laufe des Betriebes an den Bund weitergereicht werden? | H76: Bezug lt. Katalog: - Katalogdatum: 15.01.2024 // Antwort: Der Betreiber kann diese Kosten bei der Kalkulation seines EMP-Entgelts bzw. seines Ad hoc - Ladetarifs berücksichtigten. Beim Durchleitungsmodell können die Kosten der Netznutzung ebenfalls berücksichtigt werden. | I76: eRound | J76: Abrechnungskomponente | K76: trifft nicht zu | M76: Automatisch ausgewertet: Außerhalb des betrachteten Leistungsumfangs (Schranken, Kennzeichenerfassung, dynamische Anzeige).
B77: ANF-071 | C77: Bieterfragenkatalog | D77: Nr. 19 / S. 2 | E77: Vertrag & Recht | F77: Klarstellung: Eine Anpassung des Beginns der Vertragslaufzeit auf Zeitpunkt der Inbetriebnahme der Standorte ist nicht vorgesehen. | G77: Die Laufzeit beträgt weiterhin 8 Jahre ab Loszuschlag, also voraussichtlich bis 2033? Ein großteil der Standorte muss erst 2029 und 2030 gebaut werden. Die tatsächliche Laufzeit würde für diese Standorte nur 3-4 Jahre betragen. Erwägen Sie die Option, dass die Vertragslaufzeit ab Inbetriebnahme der Standorte startet? | H77: Bezug lt. Katalog: - Katalogdatum: 15.01.2024 // Antwort: Eine Anpassung des Beginns der Vertragslaufzeit auf Zeitpunkt der Inbetriebnahme der Standorte ist nicht vorgesehen. Der tatsächliche Zeitpunkt der Inbetriebnahme der einzelnen Standorte obliegt auch der Planung des AN (Vertragsanlage 4 - Kapitel 2.2.1). | I77: offen | J77: – | K77: trifft nicht zu | M77: Automatisch ausgewertet: Außerhalb des betrachteten Leistungsumfangs (Schranken, Kennzeichenerfassung, dynamische Anzeige).
B78: ANF-072 | C78: Bieterfragenkatalog | D78: Nr. 20 / S. 2 | E78: Vertrag & Recht | F78: Verweis des Auftraggebers auf die Antwort zu Bieterfrage 5. | G78: Viele der Geokoordinaten in Vertragsanlage 2 und Anlage 2 zum Verfahrensbrief stimmen nicht mit den Rastplätzen überein. Wir bitten Sie, zu spezifizieren welche Angabe massgeblich ist und die unzutreffenden Angaben zu korrigieren. | H78: Bezug lt. Katalog: – Katalogdatum: 15.01.2025 // Antwort: Siehe Antwort auf Frage 5 | I78: offen | J78: – | K78: trifft nicht zu | M78: Automatisch ausgewertet: Die Antwort des Auftraggebers verweist ausschließlich auf Bieterfrage 5. Keine eigenständige Anforderung – der Inhalt ist unter der dort erfassten Zeile nachzuhalten.
B79: ANF-073 | C79: Bieterfragenkatalog | D79: Nr. 21 / S. 2 | E79: Vertrag & Recht | F79: Klarstellung: Die Angaben der Vertragsanlage 03 sind im Fall des Rastplatzes DE-BW-006550 Eichhäuser Hof nicht korrekt. | G79: In Vertragsanlage 3 steht bei DE-BW-006550 Rastplatz Eichhäuser Hof, dass kein WC vorhanden ist. Jedoch sieht es in einschlägigen Karten-/Bewertungsdiensten danach aus, dass ein WC vorhanden und benutzbar ist. Liegt hier ein Fehler vor? Bitte spezifizieren Sie welche Information richtig ist. | H79: Bezug lt. Katalog: – Katalogdatum: 15.01.2025 // Antwort: Die Angaben der Vertragsanlage 03 sind im Fall des Rastplatzes DE-BW-006550 Eichhäuser Hof nicht korrekt. Es ist korrekt, dass auf der Anlage mittlerweile ein WC vorhanen ist. | I79: offen | J79: – | K79: trifft nicht zu | M79: Automatisch ausgewertet: Außerhalb des betrachteten Leistungsumfangs (Schranken, Kennzeichenerfassung, dynamische Anzeige).
B80: ANF-074 | C80: Bieterfragenkatalog | D80: Nr. 22 / S. 3 | E80: Bau & Dokumentation | F80: Klarstellung: Eine Freigabe aller Standorte soll bis zum 31.12.2030 erfolgen. Ein Unterschied zwischen der Inbetriebnahme und der Verkehrsfreigabe besteht nicht. | G80: In der aktuellsten Vertragsfassung vom 06.01. ist in §11.4 von einer vorgesehenen spätesten Inbetriebnahme zum 31.12.2028 die Rede. In Vertragsanlage 04 (Leistungsbeschreibung Errichtung) unter Punkt 2.2.1 ist dagegen von einer Verkehrsfreigabe von 100% der Standorte spätestens zum 31.12.2030 die Rede. Könnten Sie spezifizieren, welche Angabe korrekt ist? Könnten Sie darüber hinaus spezifizieren, ob zwischen Betriebs- und Verkehrsfreigabe ein Unterschied besteht? | H80: Bezug lt. Katalog: – Katalogdatum: 15.01.2025 // Antwort: Eine Freigabe aller Standorte soll bis zum 31.12.2030 erfolgen. Ein Unterschied zwischen der Inbetriebnahme und der Verkehrsfreigabe besteht nicht. Die Regelungen im Vertrag und der Vertragsanlage 4 werden vor Aufforderung zur Abgabe verbindlicher Angebote noch aufeinander abgestimmt. | I80: offen | J80: – | K80: trifft nicht zu | M80: Automatisch ausgewertet: Außerhalb des betrachteten Leistungsumfangs (Schranken, Kennzeichenerfassung, dynamische Anzeige).
B81: ANF-075 | C81: Bieterfragenkatalog | D81: Nr. 23 / S. 3 | E81: Flächen & Genehmigungen | F81: Klarstellung: Zu etwaigen weiteren Ausschreibungen können keine Angaben gemacht werden. | G81: Kann es basierend auf dem Ausgang dieser Ausschreibung Einschränkungen bei der Losvergabe der kommenden Ausschreibung (bemannte Rastanlagen) geben? Z.B. zur Vermeidung lokaler Monopole? | H81: Bezug lt. Katalog: – Katalogdatum: 15.01.2025 // Antwort: Zu etwaigen weiteren Ausschreibungen können keine Angaben gemacht werden. | I81: offen | J81: – | K81: trifft nicht zu | M81: Automatisch ausgewertet: Außerhalb des betrachteten Leistungsumfangs (Schranken, Kennzeichenerfassung, dynamische Anzeige).
B82: ANF-076 | C82: Bieterfragenkatalog | D82: Nr. 24 / S. 3 | E82: Vertrag & Recht | F82: Klarstellung: Das Betreiberentgelt als Vergütungsbestandteil richtet sich nach §40 des Vertrags (Anlage 01 zum Verfahrensbrief). | G82: Was ist im Detail unter dem "Betreiberentgelt" zu verstehen und aus welchen Bestandteilen setzt sich diese zusammen? | H82: Bezug lt. Katalog: Hauptvertrag Katalogdatum: 17.01.2025 // Antwort: Das Betreiberentgelt als Vergütungsbestandteil richtet sich nach §40 des Vertrags (Anlage 01 zum Verfahrensbrief). Es bezieht sich grundsätzlich auf den Betrieb der Ladeinfrastruktur. Die Kalkulation des Betreiberentgelts unterliegt der Kalkulationsfreiheit der Bieter. Der AG behält sich vor, sich von den Bietern eine Aufschlüsselung der Bestandteile des kalkulierten Betreiberentgelts mit Abgabe der verbindlichen Angabeote einreichen zu lassen. | I82: offen | J82: – | K82: trifft nicht zu | M82: Automatisch ausgewertet: Außerhalb des betrachteten Leistungsumfangs (Schranken, Kennzeichenerfassung, dynamische Anzeige).
B83: ANF-077 | C83: Bieterfragenkatalog | D83: Nr. 25 / S. 3 | E83: Reservierung | F83: Verneint: das Ad-hoc Entgelt soll nicht gemindert werden. § 19 Abs. | G83: § 19: Ist es gewollt, dass bei Nutzung des Reservierungssystems und Ad-hoc Ladung die Erlöse für den AN gemindert werden? | H83: Bezug lt. Katalog: Hauptvertrag Katalogdatum: 17.01.2025 // Antwort: Nein, das Ad-hoc Entgelt soll nicht gemindert werden. § 19 Abs. 6 sieht lediglich eine Anrechnung eines gzahlten Reservierungsentgelts vor. | I83: eRound / Reservierungsplattform | J83: Authentifizierungskomponente / OCPI Buchungskalender / Reservierungsplattform | K83: trifft nicht zu | M83: Automatisch ausgewertet: Außerhalb des betrachteten Leistungsumfangs (Schranken, Kennzeichenerfassung, dynamische Anzeige).
B84: ANF-078 | C84: Bieterfragenkatalog | D84: Nr. 26 / S. 3 | E84: Vergabeverfahren & Angebot | F84: Klarstellung: Die Angebotsfrist ist angemessen und auskömmlich. Eine Fristverlängerung erfolgt nicht. | G84: Es ist eine Abgabefrist des Erstangebots bis zum 27.02.2025, 12 Uhr vorgesehen. Die Klärung der Fragen als Basis für die Angebotskalkulation und Erstellung der Konzepte sowie die danach erforderlichen Prüfungs-, Freigabe und insbesondere hochrangigen Gremienbeteiligungen mit anschließender Finalisierung der Angebote sind bis zum 27.02.2025 ist terminlich nicht möglich. Wir bitten daher um Verlängerung der Abgabefrist für das Erstangebot bis zum 20.03.2025. | H84: Bezug lt. Katalog: Frist für Abgabe Erstangebote Katalogdatum: 17.01.2025 // Antwort: Die Angebotsfrist ist angemessen und auskömmlich. Eine Fristverlängerung erfolgt nicht. | I84: offen | J84: – | K84: trifft nicht zu | M84: Automatisch ausgewertet: Betrifft das Vergabeverfahren (Angebot, Wertung, Unterlagen), nicht die zu erbringende Leistung. Keiner Komponente zugeordnet.
B85: ANF-079 | C85: Bieterfragenkatalog | D85: Nr. 27 / S. 3 | E85: Flächen & Genehmigungen | F85: Klarstellung: Die ladeplatzbezogene Beleuchtung ist an die Niederspannungsanalage der Ladeinfrastruktur anzuschließen. | G85: In diesem Kapitel wird beschrieben, dass der Anschluss und die Abrechnung der Mastbeleuchtung über das Energienetz der Rastanlage erfolgt. Gleichzeitig soll die Beleuchtungsanlage an die Niederspannungsanlage der E-Mobilität angeschlossen werden. Wir bitten um Prüfung, welche der beiden Vorgaben tatsächlich zutrifft. | H85: Bezug lt. Katalog: LB Errichtung, Kapitl 3.10.1 Katalogdatum: 17.01.2025 Zuordnung prüfen (Komponente/Partner nicht eindeutig) // Antwort: Die ladeplatzbezogene Beleuchtung ist an die Niederspannungsanalage der Ladeinfrastruktur anzuschließen. | I85: Zuordnung prüfen | J85: Zuordnung prüfen | K85: trifft nicht zu | M85: Automatisch ausgewertet: Außerhalb des betrachteten Leistungsumfangs (Schranken, Kennzeichenerfassung, dynamische Anzeige).
B86: ANF-080 | C86: Bieterfragenkatalog | D86: Nr. 28 / S. 3 | E86: Netzanschluss & Energie | F86: Klarstellung: Die Endausbauleistung für jeden Standort finden Sie in der Vertragsanlage 5 "Details zum Netzanschluss" in der Spalte "beantragte Leistung 2035". | G86: Sämtliche Kabelführungen sind auf die Endausbauleistung im Jahr 2035 zu bemessen.Wir bitten um Angabe der Endausbauleistung für jeden Standort. | H86: Bezug lt. Katalog: LB Errichtung, Kapitel 4.11.6 Katalogdatum: 17.01.2025 // Antwort: Die Endausbauleistung für jeden Standort finden Sie in der Vertragsanlage 5 "Details zum Netzanschluss" in der Spalte "beantragte Leistung 2035". | I86: offen | J86: – | K86: trifft nicht zu | M86: Automatisch ausgewertet: Außerhalb des betrachteten Leistungsumfangs (Schranken, Kennzeichenerfassung, dynamische Anzeige).
B87: ANF-081 | C87: Bieterfragenkatalog | D87: Nr. 29 / S. 3 | E87: Vertrag & Recht | F87: Klarstellung: Es ist vorgesehen, dass das Infrastrukturentgelt über alle Standorte berechnet wird. | G87: Wird das Infrastrukturentgelt standortbezogen, losbezogen (und damit anbieterbezogen) oder über alle Standorte berechnet? | H87: Bezug lt. Katalog: Infrastrukturentgelt Katalogdatum: 17.01.2025 // Antwort: Es ist vorgesehen, dass das Infrastrukturentgelt über alle Standorte berechnet wird. | I87: offen | J87: – | K87: trifft nicht zu | M87: Automatisch ausgewertet: Außerhalb des betrachteten Leistungsumfangs (Schranken, Kennzeichenerfassung, dynamische Anzeige).
... B90: ANF-084 | C90: Bieterfragenkatalog | D90: Nr. 32 / S. 3 | E90: Netzanschluss & Energie | F90: Klarstellung: Die Installationsaktivitäten sind in den jeweiligen Kostengruppen mitzuberücksichtigen. | G90: Dokument: "20250106_Anlage 06_zum Verfahrensbrief_Aufschlüssel_Preise Errichtung" --> Sind alle Installationsaktivitäten (Ladehardware, CCTV, Trafo, Unterstation etc.) in Position 3.9 (Zeile 26) und Position 3.10 (Zeile 27) aufzuführen oder wird der gesamte Kostenpunkt "Installation" an anderer Stelle aufgeführt? | H90: Bezug lt. Katalog: Preise Errichtung Katalogdatum: 17.01.2025 // Antwort: Die Installationsaktivitäten sind in den jeweiligen Kostengruppen mitzuberücksichtigen. | I90: Alpitronic | J90: Ladeeinrichtung | K90: trifft nicht zu | M90: Automatisch ausgewertet: Außerhalb des betrachteten Leistungsumfangs (Schranken, Kennzeichenerfassung, dynamische Anzeige).
B91: ANF-085 | C91: Bieterfragenkatalog | D91: Nr. 33 / S. 3 | E91: Reservierung | F91: Zusage / Ankündigung: Die Möglichkeiten und Rahmenbedingungen der Reservierung werden Teil der Bieterverhandlungen sein, hierbei wird insbesondere auch zu erörtern sein, inwieweit die Reservierung von Energiemengen bzw. die Angabe des benötigten … | G91: Im Betriebskonzept ist es erforderlich, dass etwaiges Falschparken durch z.B. Diesel LKW nicht passieren kann. Müssen die Stellplätze eine Schranke aufweisen, also muss das Standortlayout Schranken integriert haben oder kann man in dem Betriebskonzept und Layout auch andere Lösungen aufzeigen? | H91: Bezug lt. Katalog: Betriebskonzept Katalogdatum: 17.01.2025 // Antwort: Die Möglichkeiten und Rahmenbedingungen der Reservierung werden Teil der Bieterverhandlungen sein, hierbei wird insbesondere auch zu erörtern sein, inwieweit die Reservierung von Energiemengen bzw. die Angabe des benötigten Energiebedarfs im Rahmen des Reservierungsprozesses möglich sein soll bzw. sinnvoll ist und wie ein Freihalten eines reservierten Ladepunktes sichergestellt werden kann. Für die Angebotsabgabe ist davon auszugehen, dass eine Reservierung von Ladepunkten und Ahndung von Falschparkern möglich ist. (vgl. Fußnote 3 zu §19 des Vertrags) Dementsprechend können im Betriebskonzept zum Erstangebot auch andere Lösungen aufgezeigt werden. Für die verbindlichen Angebote wird der AG einheitliche Rahmenbedingungen vorgeben. | I91: eRound / SCS | J91: Schrankensteuerung / OCPI Buchungskalender / Pönalisierungssystem | K91: erfasst
B92: ANF-086 | C92: Bieterfragenkatalog | D92: Nr. 34 / S. 3 | E92: Flächen & Genehmigungen | F92: Klarstellung: Sofern sich Ihre Frage auf die Dokumente Anlage 2 zum Verfahrensbrief "Gesamtübersicht über die Lose", Vertragsanlage 2 "Standortübersicht (losspezifisch)" und Anlage 5 zum Verfahrensbrief "Karte zur Losaufteilung" bezieht wurden … | G92: Aus der Bereitstellung der neuen Unterlagen am 17.01. geht nicht hervor, welche Änderungen im Vergleich zu den Originalversionen vorgenommen wurden. Kann das bitte kenntlich gemacht werden? | H92: Bezug lt. Katalog: Change Log Katalogdatum: 17.01.2025 // Antwort: Sofern sich Ihre Frage auf die Dokumente Anlage 2 zum Verfahrensbrief "Gesamtübersicht über die Lose", Vertragsanlage 2 "Standortübersicht (losspezifisch)" und Anlage 5 zum Verfahrensbrief "Karte zur Losaufteilung" bezieht wurden folgende Informationen aktualisert: Anlage 2 zum Verfahrensbrief "Gesamtübersicht über die Lose": Die Anzahl der Ladepunkte, die BAB-Nr., die Geogr. Länge und Breite sowie die Anzahl der Ladepunkte wurden korrigiert. Vertragsanlage 2 "Standortübersicht (losspezifisch)": Die Anzahl der Ladepunkte, die BAB-Nr., die Geogr. Länge und Breite, die Anzahl der Ladepunkte sowie die zusammenfassende Tabelle wurden korrigiert. Anlage 5 zum Verfahrensbrief "Karte zur Losaufteilung": Fehlende Standorte wurden ergänzt. | I92: offen | J92: – | K92: trifft nicht zu | M92: Automatisch ausgewertet: Außerhalb des betrachteten Leistungsumfangs (Schranken, Kennzeichenerfassung, dynamische Anzeige).
B93: ANF-087 | C93: Bieterfragenkatalog | D93: Nr. 35 / S. 3 | E93: Netzanschluss & Energie | F93: Verneint: es wurde - wie sich aus den §§ 27 ff. ergibt - nicht gestrichen. | G93: Ist das Durchleitungsmodell nicht mehr Grundvoraussetzung für ein Angebot? In den neuen Vertragsunterlagen wurde es unter §3 gestrichen. | H93: Bezug lt. Katalog: Vertrag Katalogdatum: 20.01.2025 // Antwort: Nein, es wurde - wie sich aus den §§ 27 ff. ergibt - nicht gestrichen. Mit der Streichung in § 3 des Vertrages wurde nur verdeutlicht, dass es sich beim Durchleitungsmodell um eine besondere Form des "EMP-Ladens", nämlich die Gewährung von Zugang ohne bilanzielle Bereitstellung von Strom, handelt. | I93: offen | J93: – | K93: trifft nicht zu | M93: Automatisch ausgewertet: Außerhalb des betrachteten Leistungsumfangs (Schranken, Kennzeichenerfassung, dynamische Anzeige).
B94: ANF-088 | C94: Bieterfragenkatalog | D94: Nr. 36 / S. 3 | E94: Flächen & Genehmigungen | F94: Vorgaben bleiben unverändert: Soweit nicht ausdrücklich etwas anderes geregelt wird, sind die Bieter an die Vorgaben der Vertragsanlage 4 (Leistungsbeschreibung Errichtung) gebunden. | G94: Warum sind gemäß Vorplanungen die MCS-Aufstellflächen 4 Meter breit und die CCS Aufstellflächen nur 3 Meter breit? Sind wir daran gebunden so zu bauen? | H94: Bezug lt. Katalog: Leistungsbeschreibung Katalogdatum: 20.01.2025 // Antwort: Soweit nicht ausdrücklich etwas anderes geregelt wird, sind die Bieter an die Vorgaben der Vertragsanlage 4 (Leistungsbeschreibung Errichtung) gebunden. Den Bietern steht es frei, anderweitige Aufstellflächen als Verhandlungsbedarf mit dem Erstangebot einzureichen. | I94: offen | J94: – | K94: trifft nicht zu | M94: Automatisch ausgewertet: Außerhalb des betrachteten Leistungsumfangs (Schranken, Kennzeichenerfassung, dynamische Anzeige).
B95: ANF-089 | C95: Bieterfragenkatalog | D95: Nr. 37 / S. 4 | E95: Vergabeverfahren & Angebot | F95: Klarstellung: Ein entsprechendes Vorgehen ist aktuell nicht vorgesehen. Gegenstand dieses Vergabeverfahrens ist ausschließlich LKW Ladeinfrastruktur. | G95: Ist es beabsichtigt, im weiteren Verlauf des Verfahrens den Bietern Zusagen darüber zu machen, dass an ausgewählten Standorten mit erfolgtem Zuschlag in der Zukunft per geplanter Erweiterung die Errichtung von zusätzlicher PKW-Ladeinfrastruktur gestattet werden wird, soweit dies technisch umsetzbar ist und bislang noch nicht durch vergangene Ausschreibungen des Bundes abgedeckt wurde bzw. könnte dies Gegenstand der Verhandlungen sein? | H95: Bezug lt. Katalog: – Katalogdatum: 20.01.2025 // Antwort: Ein entsprechendes Vorgehen ist aktuell nicht vorgesehen. Gegenstand dieses Vergabeverfahrens ist ausschließlich LKW Ladeinfrastruktur. | I95: offen | J95: – | K95: trifft nicht zu | M95: Automatisch ausgewertet: Betrifft das Vergabeverfahren (Angebot, Wertung, Unterlagen), nicht die zu erbringende Leistung. Keiner Komponente zugeordnet.
B96: ANF-090 | C96: Bieterfragenkatalog | D96: Nr. 38 / S. 4 | E96: Vergabeverfahren & Angebot | F96: Klarstellung: Da es sich bei der Angabe um Mindestmengen handelt, können die Mengengrudnsätzlich auch in den jeweiligen Jahren vorgezogen werden. | G96: Der Bau verteilt sich auf 2026 bis 2030, wobei hier die Mindestmenge angegeben wird. Können die Mengen in den jeweiligen Jahren vorgezogen werden? Wenn ja, bis zu welchem Maße? | H96: Bezug lt. Katalog: Leistungsbeschreibung Errichtung Katalogdatum: 20.01.2025 // Antwort: Da es sich bei der Angabe um Mindestmengen handelt, können die Mengengrudnsätzlich auch in den jeweiligen Jahren vorgezogen werden. Einzelheiten können zum Gegenstand der Bieterverhandlungen gemacht werden. | I96: offen | J96: – | K96: trifft nicht zu | M96: Automatisch ausgewertet: Betrifft das Vergabeverfahren (Angebot, Wertung, Unterlagen), nicht die zu erbringende Leistung. Keiner Komponente zugeordnet.
B97: ANF-091 | C97: Bieterfragenkatalog | D97: Nr. 39 / S. 4 | E97: Netzanschluss & Energie | F97: Klarstellung: Die entsprechenden Informationen werden den Bietern im weiteren Vergabeverfahren mitgeteilt, sobald sie dem AG von dem jeweilgien Netzbetreiber vorliegen. | G97: Wie und wann erhält man Info zur MSP-Ebene, 10/20 oder 30 kV macht einen großen Preisunterschied und ist für die Kalkulation wesentlich. | H97: Bezug lt. Katalog: – Katalogdatum: 20.01.2025 // Antwort: Die entsprechenden Informationen werden den Bietern im weiteren Vergabeverfahren mitgeteilt, sobald sie dem AG von dem jeweilgien Netzbetreiber vorliegen. | I97: offen | J97: – | K97: trifft nicht zu | M97: Automatisch ausgewertet: Außerhalb des betrachteten Leistungsumfangs (Schranken, Kennzeichenerfassung, dynamische Anzeige).
B98: ANF-092 | C98: Bieterfragenkatalog | D98: Nr. 40 / S. 4 | E98: Nutzungszeit & Entgelte | F98: Klarstellung: Es wird auf §24 Abs. 3 des Vertrages sowie Ziffer 10 der Vertragsanlage 06 "Anforderungen an die Ladeeinrichtung" verwiesen. | G98: An jedem Ladepunkt sollen CEE Steckdosen für die Trailer vorhanden sein, muss die Abrechnung eichrechtskonform erfolgen? Zu welchen Konditionen sind die Stromerlöse zwischen AG und AN zu kalkulieren? Sind festgelegte Preise vorgesehen? | H98: Bezug lt. Katalog: Vertragsanlage 06 Katalogdatum: 20.01.2025 // Antwort: Es wird auf §24 Abs. 3 des Vertrages sowie Ziffer 10 der Vertragsanlage 06 "Anforderungen an die Ladeeinrichtung" verwiesen. Einzelheiten können zum Gegenstand der Bieterverhandlungen gemacht werden. | I98: Alpitronic / eRound | J98: Abrechnungskomponente / Ladeeinrichtung | K98: trifft nicht zu | M98: Automatisch ausgewertet: Außerhalb des betrachteten Leistungsumfangs (Schranken, Kennzeichenerfassung, dynamische Anzeige).
B99: ANF-093 | C99: Bieterfragenkatalog | D99: Nr. 41 / S. 4 | E99: Sonstiges / Zuordnung prüfen | F99: Klarstellung: Der AG wird die Unterlagen im weiteren Vergabeverfahren zur Verfügung stellen. | G99: Kap. 3.1: Lt. Seite 16 ist die Tabelle von Seite 15 nur beispielhaft. Eine vollständige Liste der zu erstellenden und einzureichenden Unterlagen kann dem Anhang 8 entnommenen werden. Diese fehlt in den Ausschreibungsunterlagen. Bitte um Verteilung des Anhangs 8. | H99: Bezug lt. Katalog: Leistungsbeschreibung Errichtung Katalogdatum: 20.01.2025 Zuordnung prüfen (Komponente/Partner nicht eindeutig) // Antwort: Der AG wird die Unterlagen im weiteren Vergabeverfahren zur Verfügung stellen. | I99: Zuordnung prüfen | J99: Zuordnung prüfen | K99: trifft nicht zu | M99: Automatisch ausgewertet: Außerhalb des betrachteten Leistungsumfangs (Schranken, Kennzeichenerfassung, dynamische Anzeige).
B100: ANF-094 | C100: Bieterfragenkatalog | D100: Nr. 42 / S. 4 | E100: Bau & Dokumentation | F100: Klarstellung: Es ist nicht klar, was mit Sicherheitsaudits gemeint ist. Sofern Verkehrssicherheitsaudits gemeint sind, haben diese einmalig im Rahmen der Baufreigabefreigabe zu erfolgen. | G100: Sind Sicherheitsaudits durchzuführen? Wenn ja, sind die Leistungen vom AN zu erbringen und wie oft durchzuführen? | H100: Bezug lt. Katalog: Sicherheitsaudits Katalogdatum: 20.01.2025 // Antwort: Es ist nicht klar, was mit Sicherheitsaudits gemeint ist. Sofern Verkehrssicherheitsaudits gemeint sind, haben diese einmalig im Rahmen der Baufreigabefreigabe zu erfolgen. | I100: offen | J100: – | K100: trifft nicht zu | M100: Automatisch ausgewertet: Außerhalb des betrachteten Leistungsumfangs (Schranken, Kennzeichenerfassung, dynamische Anzeige).
B101: ANF-095 | C101: Bieterfragenkatalog | D101: Nr. 43 / S. 4 | E101: Flächen & Genehmigungen | F101: Klarstellung: Eine Kanalnetzberechnung ist erforderlich, sofern das Regenwassernetz angepasst/ verändert wird. | G101: Kap. 3.8.2: Den vorliegenden Unterlagen ist nicht zu entnehmen, ob eine Kanalnetzberechnung der gesamten Rastanlage erforderlich ist. Bitte um Präzisierung der erforderlichen Leistungen. | H101: Bezug lt. Katalog: – Katalogdatum: 20.01.2025 // Antwort: Eine Kanalnetzberechnung ist erforderlich, sofern das Regenwassernetz angepasst/ verändert wird. | I101: offen | J101: – | K101: trifft nicht zu | M101: Automatisch ausgewertet: Außerhalb des betrachteten Leistungsumfangs (Schranken, Kennzeichenerfassung, dynamische Anzeige).
B102: ANF-096 | C102: Bieterfragenkatalog | D102: Nr. 44 / S. 4 | E102: Vergabeverfahren & Angebot | F102: Klarstellung: Ein entsprechendes Vorgehen ist, soweit hinsichtlich der jeweiligen konkreten Unterlage sinnvoll, vorgesehen. | G102: Bereitstellung von ChangeVersion für sämtliche Unterlagen: Wir bitte darum, bei zukünftigen Änderung der Ausschreibungsunterlagen eine ChangeVersion des jeweiligen Dokuments bereitzustellen um ein Anpassung der Vergabeunterlagen nachvollziehen zu können. | H102: Bezug lt. Katalog: – Katalogdatum: 20.01.2025 // Antwort: Ein entsprechendes Vorgehen ist, soweit hinsichtlich der jeweiligen konkreten Unterlage sinnvoll, vorgesehen. | I102: offen | J102: – | K102: trifft nicht zu | M102: Automatisch ausgewertet: Betrifft das Vergabeverfahren (Angebot, Wertung, Unterlagen), nicht die zu erbringende Leistung. Keiner Komponente zugeordnet.
B103: ANF-097 | C103: Bieterfragenkatalog | D103: Nr. 45 / S. 4 | E103: Netzanschluss & Energie | F103: Klarstellung: Zu den Systemkosten wird aktuell im Vertrag keine ausdrückliche Aussage getroffen. Allerdings ist der Auftragnehmer nach § 44 Abs. | G103: § 44, Abs. 1.: Der AG kann an Standorten Speicher aufstellen. Wir bitten um Bestätigung, dass der AG auch die Kosten des Systemanschlusses trägt. | H103: Bezug lt. Katalog: Hauptvertrag Katalogdatum: 20.01.2025 // Antwort: Zu den Systemkosten wird aktuell im Vertrag keine ausdrückliche Aussage getroffen. Allerdings ist der Auftragnehmer nach § 44 Abs. 2 des Vertrages nur dafür verantwortlich, den Speicher instand zu halten und die für den Betrieb des Speichers erforderlichen Versicherungen abzuschließen. Im Umkehrschluss bedeutet dies: Der AG trägt die Kosten für Errichtung und Systemeinbindung. Die Thematik Speicher wird Gegenstand der Bietergespräche sein. | I103: offen | J103: – | K103: trifft nicht zu | M103: Automatisch ausgewertet: Außerhalb des betrachteten Leistungsumfangs (Schranken, Kennzeichenerfassung, dynamische Anzeige).
... B153: ANF-147 | C153: Bieterfragenkatalog | D153: Nr. 95 / S. 8 | E153: Netzanschluss & Energie | F153: Verweis des Auftraggebers auf die Antwort zu Bieterfrage 60. | G153: Details zum Netzanschluss: Die Anzahl der Ladepunkte und die geforderten Leistungen passen nicht zu den Aufbauanforderungen insbesondere hinsichtlich der geforderten (gleichzeitigen) Ladeleistungen (auch nicht zur Leistung 2035). Wie ist hiermit umzugehen? Beispiel: DE-BB-444901: gemäß Anforderungen an die Ladeleistungen wird u.M. eine NA-Leistung von 4682 kW benötigt. In der Anlage wird als beantragte NA-Leistung 2800 kW angegeben. | H153: Bezug lt. Katalog: Vertragsanlage 05 Katalogdatum: 31.01.2025 // Antwort: Siehe Antwort auf die Bieterfrage 60. | I153: offen | J153: – | K153: trifft nicht zu | M153: Automatisch ausgewertet: Die Antwort des Auftraggebers verweist ausschließlich auf Bieterfrage 60. Keine eigenständige Anforderung – der Inhalt ist unter der dort erfassten Zeile nachzuhalten.
B154: ANF-148 | C154: Bieterfragenkatalog | D154: Nr. 96 / S. 8 | E154: Reservierung | F154: Zusage / Ankündigung: Siehe Antwort auf die Bieterfrage 33. Danach werden die Möglichkeiten und Rahmenbedingungen der Reservierung Teil der Bieterverhandlungen sein. | G154: Ist die (a) Überwachung der Gesamtanlage und/oder (b) die Objektidentifikation und/oder (c) eine Kennzeichenidentifikation z.B. im Zusammenhang mit dem Reservierungssystem mittels Kameratechnik seitens des AG erlaubt und erwünscht? Wenn ja, welche zusätzlichen genehmigungs-/freigabetechnischen Schritte müssen hierfür angegangen grob angegangen werden? | H154: Bezug lt. Katalog: Überwachung, Kennzeichenidentifikation Katalogdatum: 31.01.2025 // Antwort: Siehe Antwort auf die Bieterfrage 33. Danach werden die Möglichkeiten und Rahmenbedingungen der Reservierung Teil der Bieterverhandlungen sein. Dazu gehört auch wie ein Freihalten/Überwachen eines reservierten Ladepunktes sichergestellt werden kann. Für die Angebotsabgabe ist davon auszugehen, dass eine Reservierung von Ladepunkten und Ahndung von Falschparkern möglich ist (vgl. Fußnote 3 zu §19 des Vertrags). Dementsprechend können im Betriebskonzept zum Erstangebot auch andere Lösungen aufgezeigt werden. Für die verbindlichen Angebote wird der AG einheitliche Rahmenbedingungen vorgeben. | I154: eRound / SCS / Reservierungsplattform | J154: Kennzeichenerfassung / OCPI Buchungskalender / Reservierungsplattform / Pönalisierungssystem | K154: erfasst
...

Sheet Filter
A1: Filter – Anforderungen gezielt anzeigen | V1: Auswahllisten (Grundlage der Dropdowns)
A2: Auswahl in den gelben Feldern treffen; die Liste unten aktualisiert sich sofort. „(alle)“ lässt das Feld unberücksichtigt. Komponente und Partner suchen als Teiltext, finden also auch Mehrfachzuordnungen. Gepflegt wird weiterhin nur im Register „Anforderungen“. | V2: (alle) | W2: (alle) | X2: (alle) | Y2: (alle) | Z2: (alle)
V3: bewertet | W3: Betreibervertrag | X3: Anzeige & Beschilderung | Y3: Abrechnungskomponente | Z3: Alpitronic
B4: Status | E4: Dokument | H4: Themenfeld | V4: erfasst | W4: Bieterfragenkatalog | X4: Authentifizierung & Zugang | Y4: Anbindung | Z4: Autostrom+
B5: (alle) | E5: (alle) | H5: (alle) | V5: erfüllt | W5: Vertragsanlage 10 | X5: Bau & Dokumentation | Y5: Authentifizierungskomponente | Z5: Reservierungsplattform
B6: Komponente | E6: Partner | H6: Suchbegriff | T6: Rang | V6: trifft nicht zu | W6: Vertragsanlage 13 | X6: Belegungsdetektion | Y6: Belegungsdetektion | Z6: SCS
B7: (alle) | E7: (alle) | T7: =IF(Anforderungen!$B7="","",IF(AND(OR($B5="(alle)",Anforderungen!$K7=$B5),OR($E5="(alle)",Anforderungen!$C7=$E5),OR($H5="(alle)",Anforderungen!$E7=$H5),OR($B7="(alle)",ISNUMBER(SEARCH($B7,Anforderungen!$J7))),OR($E7="(alle)",ISNUMBER(SEARCH($E7,Anforderungen!$I7))),OR($H7="",ISNUMBER(SEARCH($H7,Anforderungen!$F7&" "&Anforderungen!$G7)))),COUNT($T$6:$T6)+1,"")) -> 1 | W7: Vertragsanlage 4 | X7: Betrieb & Auslastung | Y7: Beschilderung | Z7: Schrankenhersteller
H8: Suchbegriff wirkt auf Kernaussage und Originaltext | T8: =IF(Anforderungen!$B8="","",IF(AND(OR($B5="(alle)",Anforderungen!$K8=$B5),OR($E5="(alle)",Anforderungen!$C8=$E5),OR($H5="(alle)",Anforderungen!$E8=$H5),OR($B7="(alle)",ISNUMBER(SEARCH($B7,Anforderungen!$J8))),OR($E7="(alle)",ISNUMBER(SEARCH($E7,Anforderungen!$I8))),OR($H7="",ISNUMBER(SEARCH($H7,Anforderungen!$F8&" "&Anforderungen!$G8)))),COUNT($T$6:$T7)+1,"")) -> 2 | W8: Vertragsanlage 6 | X8: Flächen & Genehmigungen | Y8: Dynamische Anzeige | Z8: Schrankenhersteller / SCS
T9: =IF(Anforderungen!$B9="","",IF(AND(OR($B5="(alle)",Anforderungen!$K9=$B5),OR($E5="(alle)",Anforderungen!$C9=$E5),OR($H5="(alle)",Anforderungen!$E9=$H5),OR($B7="(alle)",ISNUMBER(SEARCH($B7,Anforderungen!$J9))),OR($E7="(alle)",ISNUMBER(SEARCH($E7,Anforderungen!$I9))),OR($H7="",ISNUMBER(SEARCH($H7,Anforderungen!$F9&" "&Anforderungen!$G9)))),COUNT($T$6:$T8)+1,"")) -> 3 | X9: Monitoring & Reporting | Y9: Kennzeichenerfassung | Z9: Schrankenhersteller / SCS / eRound
A10: Treffer | B10: =COUNT($T$7:$T$2000) -> 1382 | D10: erfasst | E10: =SUMPRODUCT((ISNUMBER($T$7:$T$2000))*(Anforderungen!$K$7:$K$2000="erfasst")) -> 50 | F10: bewertet | G10: =SUMPRODUCT((ISNUMBER($T$7:$T$2000))*(Anforderungen!$K$7:$K$2000="bewertet")) -> 3 | H10: erfüllt | I10: =SUMPRODUCT((ISNUMBER($T$7:$T$2000))*(Anforderungen!$K$7:$K$2000="erfüllt")) -> 10 | J10: trifft nicht zu | K10: =SUMPRODUCT((ISNUMBER($T$7:$T$2000))*(Anforderungen!$K$7:$K$2000="trifft nicht zu")) -> 1319 | T10: =IF(Anforderungen!$B10="","",IF(AND(OR($B5="(alle)",Anforderungen!$K10=$B5),OR($E5="(alle)",Anforderungen!$C10=$E5),OR($H5="(alle)",Anforderungen!$E10=$H5),OR($B7="(alle)",ISNUMBER(SEARCH($B7,Anforderungen!$J10))),OR($E7="(alle)",ISNUMBER(SEARCH($E7,Anforderungen!$I10))),OR($H7="",ISNUMBER(SEARCH($H7,Anforderungen!$F10&" "&Anforderungen!$G10)))),COUNT($T$6:$T9)+1,"")) -> 4 | X10: Netzanschluss & Energie | Y10: Ladeeinrichtung | Z10: WWL
A11: Angezeigt werden die ersten 300 Treffer. Bei mehr Treffern die Auswahl weiter eingrenzen. | T11: =IF(Anforderungen!$B11="","",IF(AND(OR($B5="(alle)",Anforderungen!$K11=$B5),OR($E5="(alle)",Anforderungen!$C11=$E5),OR($H5="(alle)",Anforderungen!$E11=$H5),OR($B7="(alle)",ISNUMBER(SEARCH($B7,Anforderungen!$J11))),OR($E7="(alle)",ISNUMBER(SEARCH($E7,Anforderungen!$I11))),OR($H7="",ISNUMBER(SEARCH($H7,Anforderungen!$F11&" "&Anforderungen!$G11)))),COUNT($T$6:$T10)+1,"")) -> 5 | X11: Nutzungszeit & Entgelte | Y11: Monitoring | Z11: Zuordnung prüfen
T12: =IF(Anforderungen!$B12="","",IF(AND(OR($B5="(alle)",Anforderungen!$K12=$B5),OR($E5="(alle)",Anforderungen!$C12=$E5),OR($H5="(alle)",Anforderungen!$E12=$H5),OR($B7="(alle)",ISNUMBER(SEARCH($B7,Anforderungen!$J12))),OR($E7="(alle)",ISNUMBER(SEARCH($E7,Anforderungen!$I12))),OR($H7="",ISNUMBER(SEARCH($H7,Anforderungen!$F12&" "&Anforderungen!$G12)))),COUNT($T$6:$T11)+1,"")) -> 6 | X12: Reservierung | Y12: OCPI Buchungskalender | Z12: eRound
A13: ID | B13: Dokument | C13: Fundstelle | D13: Themenfeld | E13: Kernaussage | F13: Originaltext | G13: Partner | H13: Komponente(n) | I13: Status | J13: Erfüllt am | K13: Nachweis / Notiz | T13: =IF(Anforderungen!$B13="","",IF(AND(OR($B5="(alle)",Anforderungen!$K13=$B5),OR($E5="(alle)",Anforderungen!$C13=$E5),OR($H5="(alle)",Anforderungen!$E13=$H5),OR($B7="(alle)",ISNUMBER(SEARCH($B7,Anforderungen!$J13))),OR($E7="(alle)",ISNUMBER(SEARCH($E7,Anforderungen!$I13))),OR($H7="",ISNUMBER(SEARCH($H7,Anforderungen!$F13&" "&Anforderungen!$G13)))),COUNT($T$6:$T12)+1,"")) -> 7 | X13: Sonstiges / Zuordnung prüfen | Y13: Pönalisierungssystem | Z13: eRound / SCS
A14: =IF($R14="","",INDEX(Anforderungen!$B:$B,$R14)) -> ANF-001 | B14: =IF($R14="","",INDEX(Anforderungen!$C:$C,$R14)) -> Betreibervertrag | C14: =IF($R14="","",INDEX(Anforderungen!$D:$D,$R14)) -> § 25 (1) | D14: =IF($R14="","",INDEX(Anforderungen!$E:$E,$R14)) -> Reservierung | E14: =IF($R14="","",INDEX(Anforderungen!$F:$F,$R14)) -> OCPI Schnittstelle | F14: =IF($R14="","",INDEX(Anforderungen!$G:$G,$R14)) -> Der Auftragnehmer stellt sicher, dass die Reservierung von Ladepunkten über Reservierungsplattformen während der Laufzeit dieses Vertrags möglich ist. Hierzu hält der Auftragnehmer eine auf OCPI (Open Charge Point Interface) basierende Schnittstelle vor, über die sich Reservierungsplattformen nach Maßgabe der folgenden Absätze anbinden können. | G14: =IF($R14="","",INDEX(Anforderungen!$I:$I,$R14)) -> eRound | H14: =IF($R14="","",INDEX(Anforderungen!$J:$J,$R14)) -> OCPI Buchungskalender | I14: =IF($R14="","",INDEX(Anforderungen!$K:$K,$R14)) -> trifft nicht zu | J14: =IF($R14="","",INDEX(Anforderungen!$L:$L,$R14)) -> 0 | K14: =IF($R14="","",INDEX(Anforderungen!$M:$M,$R14)) -> Automatisch ausgewertet: Außerhalb des betrachteten Leistungsumfangs (Schranken, Kennzeichenerfassung, dynamische Anzeige). | R14: =IFERROR(MATCH(ROWS($A$14:$A14),$T$7:$T$2000,0)+6,"") -> 7 | T14: =IF(Anforderungen!$B14="","",IF(AND(OR($B5="(alle)",Anforderungen!$K14=$B5),OR($E5="(alle)",Anforderungen!$C14=$E5),OR($H5="(alle)",Anforderungen!$E14=$H5),OR($B7="(alle)",ISNUMBER(SEARCH($B7,Anforderungen!$J14))),OR($E7="(alle)",ISNUMBER(SEARCH($E7,Anforderungen!$I14))),OR($H7="",ISNUMBER(SEARCH($H7,Anforderungen!$F14&" "&Anforderungen!$G14)))),COUNT($T$6:$T13)+1,"")) -> 8 | X14: Technik Ladeinfrastruktur | Y14: Reservierungsplattform | Z14: offen
A15: =IF($R15="","",INDEX(Anforderungen!$B:$B,$R15)) -> ANF-002 | B15: =IF($R15="","",INDEX(Anforderungen!$C:$C,$R15)) -> Betreibervertrag | C15: =IF($R15="","",INDEX(Anforderungen!$D:$D,$R15)) -> § 25 (2) | D15: =IF($R15="","",INDEX(Anforderungen!$E:$E,$R15)) -> Reservierung | E15: =IF($R15="","",INDEX(Anforderungen!$F:$F,$R15)) -> OCPI Kostenfrei | F15: =IF($R15="","",INDEX(Anforderungen!$G:$G,$R15)) -> Der Auftragnehmer ist verpflichtet, jeder Reservierungsplattform die Anbindung über die in Absatz 1 genannte Schnittstelle kostenfrei zu ermöglichen, soweit die Reservierungsplattform die folgenden Mindestvoraussetzungen erfüllt: | G15: =IF($R15="","",INDEX(Anforderungen!$I:$I,$R15)) -> eRound | H15: =IF($R15="","",INDEX(Anforderungen!$J:$J,$R15)) -> OCPI Buchungskalender | I15: =IF($R15="","",INDEX(Anforderungen!$K:$K,$R15)) -> trifft nicht zu | J15: =IF($R15="","",INDEX(Anforderungen!$L:$L,$R15)) -> 0 | K15: =IF($R15="","",INDEX(Anforderungen!$M:$M,$R15)) -> Automatisch ausgewertet: Außerhalb des betrachteten Leistungsumfangs (Schranken, Kennzeichenerfassung, dynamische Anzeige). | R15: =IFERROR(MATCH(ROWS($A$14:$A15),$T$7:$T$2000,0)+6,"") -> 8 | T15: =IF(Anforderungen!$B15="","",IF(AND(OR($B5="(alle)",Anforderungen!$K15=$B5),OR($E5="(alle)",Anforderungen!$C15=$E5),OR($H5="(alle)",Anforderungen!$E15=$H5),OR($B7="(alle)",ISNUMBER(SEARCH($B7,Anforderungen!$J15))),OR($E7="(alle)",ISNUMBER(SEARCH($E7,Anforderungen!$I15))),OR($H7="",ISNUMBER(SEARCH($H7,Anforderungen!$F15&" "&Anforderungen!$G15)))),COUNT($T$6:$T14)+1,"")) -> 9 | X15: Vergabeverfahren & Angebot | Y15: Schrankenanlage | Z15: tbd
A16: =IF($R16="","",INDEX(Anforderungen!$B:$B,$R16)) -> ANF-003 | B16: =IF($R16="","",INDEX(Anforderungen!$C:$C,$R16)) -> Betreibervertrag | C16: =IF($R16="","",INDEX(Anforderungen!$D:$D,$R16)) -> § 25 (2) a | D16: =IF($R16="","",INDEX(Anforderungen!$E:$E,$R16)) -> Reservierung | E16: =IF($R16="","",INDEX(Anforderungen!$F:$F,$R16)) -> OCPI Kostenfrei | F16: =IF($R16="","",INDEX(Anforderungen!$G:$G,$R16)) -> Die Reservierungsplattform stellt dem Auftragnehmer für die Anbindung der Reservierungsplattform keine Anbindungskosten in Rechnung | G16: =IF($R16="","",INDEX(Anforderungen!$I:$I,$R16)) -> eRound | H16: =IF($R16="","",INDEX(Anforderungen!$J:$J,$R16)) -> Anbindung | I16: =IF($R16="","",INDEX(Anforderungen!$K:$K,$R16)) -> trifft nicht zu | J16: =IF($R16="","",INDEX(Anforderungen!$L:$L,$R16)) -> 0 | K16: =IF($R16="","",INDEX(Anforderungen!$M:$M,$R16)) -> Automatisch ausgewertet: Außerhalb des betrachteten Leistungsumfangs (Schranken, Kennzeichenerfassung, dynamische Anzeige). | R16: =IFERROR(MATCH(ROWS($A$14:$A16),$T$7:$T$2000,0)+6,"") -> 9 | T16: =IF(Anforderungen!$B16="","",IF(AND(OR($B5="(alle)",Anforderungen!$K16=$B5),OR($E5="(alle)",Anforderungen!$C16=$E5),OR($H5="(alle)",Anforderungen!$E16=$H5),OR($B7="(alle)",ISNUMBER(SEARCH($B7,Anforderungen!$J16))),OR($E7="(alle)",ISNUMBER(SEARCH($E7,Anforderungen!$I16))),OR($H7="",ISNUMBER(SEARCH($H7,Anforderungen!$F16&" "&Anforderungen!$G16)))),COUNT($T$6:$T15)+1,"")) -> 10 | X16: Vertrag & Recht | Y16: Schrankensteuerung
A17: =IF($R17="","",INDEX(Anforderungen!$B:$B,$R17)) -> ANF-004 | B17: =IF($R17="","",INDEX(Anforderungen!$C:$C,$R17)) -> Betreibervertrag | C17: =IF($R17="","",INDEX(Anforderungen!$D:$D,$R17)) -> § 25 (2) b | D17: =IF($R17="","",INDEX(Anforderungen!$E:$E,$R17)) -> Reservierung | E17: =IF($R17="","",INDEX(Anforderungen!$F:$F,$R17)) -> Anbindung verpflichtend, wenn alle AN angebunden werden oder AG2 auffordert | F17: =IF($R17="","",INDEX(Anforderungen!$G:$G,$R17)) -> Die Reservierungsplattform ermöglicht Endnutzern und Mobilitätsdienstleistern die Reservierung von Ladepunkten im gesamten Gebiet der Bundesrepublik Deutschland gegen ein angemessenes Entgelt. Ermöglicht eine Reservierungsplattform eine Reservierung von Ladepunkten nur in Teilen des Gebiets der Bundesrepublik Deutschland, ist der Auftragnehmer zur Anbindung nur verpflichtet, wenn der Auftraggeber 2 den Auftragnehmer hierzu auffordert. | G17: =IF($R17="","",INDEX(Anforderungen!$I:$I,$R17)) -> eRound | H17: =IF($R17="","",INDEX(Anforderungen!$J:$J,$R17)) -> OCPI Buchungskalender | I17: =IF($R17="","",INDEX(Anforderungen!$K:$K,$R17)) -> trifft nicht zu | J17: =IF($R17="","",INDEX(Anforderungen!$L:$L,$R17)) -> 0 | K17: =IF($R17="","",INDEX(Anforderungen!$M:$M,$R17)) -> Automatisch ausgewertet: Außerhalb des betrachteten Leistungsumfangs (Schranken, Kennzeichenerfassung, dynamische Anzeige). | R17: =IFERROR(MATCH(ROWS($A$14:$A17),$T$7:$T$2000,0)+6,"") -> 10 | T17: =IF(Anforderungen!$B17="","",IF(AND(OR($B5="(alle)",Anforderungen!$K17=$B5),OR($E5="(alle)",Anforderungen!$C17=$E5),OR($H5="(alle)",Anforderungen!$E17=$H5),OR($B7="(alle)",ISNUMBER(SEARCH($B7,Anforderungen!$J17))),OR($E7="(alle)",ISNUMBER(SEARCH($E7,Anforderungen!$I17))),OR($H7="",ISNUMBER(SEARCH($H7,Anforderungen!$F17&" "&Anforderungen!$G17)))),COUNT($T$6:$T16)+1,"")) -> 11 | X17: Zufahrt & Schranke | Y17: Zuordnung prüfen
A18: =IF($R18="","",INDEX(Anforderungen!$B:$B,$R18)) -> ANF-005 | B18: =IF($R18="","",INDEX(Anforderungen!$C:$C,$R18)) -> Betreibervertrag | C18: =IF($R18="","",INDEX(Anforderungen!$D:$D,$R18)) -> § 25 (2) c | D18: =IF($R18="","",INDEX(Anforderungen!$E:$E,$R18)) -> Reservierung | E18: =IF($R18="","",INDEX(Anforderungen!$F:$F,$R18)) -> Reservierung mit Vorlauf von max. 7 Tagen und min. 15 min. Kostenfreie Stornierung und Änderung bis 30min vorher. Kennzeichenabgleich zur Unterbindung von Doppelbuchungen. | F18: =IF($R18="","",INDEX(Anforderungen!$G:$G,$R18)) -> Die Reservierungsplattform ermöglicht eine Reservierung von Ladepunkten mit einer Vorlaufzeit von maximal 7 Kalendertagen und mindestens 15 Minuten. Eine kostenfreie Stornierung oder Änderung der Reservierung über die Reservierungsplattform muss, soweit möglich, bis zu 30 Minuten vor Beginn des in der Reservierung angegebenen Startzeitpunkts möglich sein. Die Reservierungsplattform stellt durch geeignete Vorkehrungen (z. B. durch einen Kennzeichenabgleich) sicher, dass für einen E-LKW in einem Zeitintervall nur ein Ladepunkt reserviert wird. | G18: =IF($R18="","",INDEX(Anforderungen!$I:$I,$R18)) -> eRound | H18: =IF($R18="","",INDEX(Anforderungen!$J:$J,$R18)) -> OCPI Buchungskalender | I18: =IF($R18="","",INDEX(Anforderungen!$K:$K,$R18)) -> erfasst | J18: =IF($R18="","",INDEX(Anforderungen!$L:$L,$R18)) -> 0 | K18: =IF($R18="","",INDEX(Anforderungen!$M:$M,$R18)) -> 0 | R18: =IFERROR(MATCH(ROWS($A$14:$A18),$T$7:$T$2000,0)+6,"") -> 11 | T18: =IF(Anforderungen!$B18="","",IF(AND(OR($B5="(alle)",Anforderungen!$K18=$B5),OR($E5="(alle)",Anforderungen!$C18=$E5),OR($H5="(alle)",Anforderungen!$E18=$H5),OR($B7="(alle)",ISNUMBER(SEARCH($B7,Anforderungen!$J18))),OR($E7="(alle)",ISNUMBER(SEARCH($E7,Anforderungen!$I18))),OR($H7="",ISNUMBER(SEARCH($H7,Anforderungen!$F18&" "&Anforderungen!$G18)))),COUNT($T$6:$T17)+1,"")) -> 12 | Y18: –
A19: =IF($R19="","",INDEX(Anforderungen!$B:$B,$R19)) -> ANF-006 | B19: =IF($R19="","",INDEX(Anforderungen!$C:$C,$R19)) -> Betreibervertrag | C19: =IF($R19="","",INDEX(Anforderungen!$D:$D,$R19)) -> § 25 (2) d | D19: =IF($R19="","",INDEX(Anforderungen!$E:$E,$R19)) -> Reservierung | E19: =IF($R19="","",INDEX(Anforderungen!$F:$F,$R19)) -> Entschädigung an AN von der Reservierungsplattform i.H.v. mind. 30€ nach 15/30 min Wartezeit bei No-Show. | F19: =IF($R19="","",INDEX(Anforderungen!$G:$G,$R19)) -> Die Reservierungsplattform entschädigt den Auftragnehmer in angemessener Höhe, wenn an der reservierten Ladeeinrichtung ab dem in der Reservierung angegebenen Startzeitpunkt und Ablauf einer Wartezeit von 15 Minuten bei Ladepunkten zum Zwischenladen, bzw. 30 Minuten bei Ladepunkten zum Übernachtladen (sog. „no-show“) kein Start eines Ladevorgangs erfolgt. Die Entschädigung des Auftragnehmers ist angemessen, wenn der Auftragnehmer im Fall eines „no-show“ mindestens € 30,00 erhält. | G19: =IF($R19="","",INDEX(Anforderungen!$I:$I,$R19)) -> eRound | H19: =IF($R19="","",INDEX(Anforderungen!$J:$J,$R19)) -> Abrechnungskomponente | I19: =IF($R19="","",INDEX(Anforderungen!$K:$K,$R19)) -> trifft nicht zu | J19: =IF($R19="","",INDEX(Anforderungen!$L:$L,$R19)) -> 0 | K19: =IF($R19="","",INDEX(Anforderungen!$M:$M,$R19)) -> Automatisch ausgewertet: Außerhalb des betrachteten Leistungsumfangs (Schranken, Kennzeichenerfassung, dynamische Anzeige). | R19: =IFERROR(MATCH(ROWS($A$14:$A19),$T$7:$T$2000,0)+6,"") -> 12 | T19: =IF(Anforderungen!$B19="","",IF(AND(OR($B5="(alle)",Anforderungen!$K19=$B5),OR($E5="(alle)",Anforderungen!$C19=$E5),OR($H5="(alle)",Anforderungen!$E19=$H5),OR($B7="(alle)",ISNUMBER(SEARCH($B7,Anforderungen!$J19))),OR($E7="(alle)",ISNUMBER(SEARCH($E7,Anforderungen!$I19))),OR($H7="",ISNUMBER(SEARCH($H7,Anforderungen!$F19&" "&Anforderungen!$G19)))),COUNT($T$6:$T18)+1,"")) -> 13
A20: =IF($R20="","",INDEX(Anforderungen!$B:$B,$R20)) -> ANF-007 | B20: =IF($R20="","",INDEX(Anforderungen!$C:$C,$R20)) -> Betreibervertrag | C20: =IF($R20="","",INDEX(Anforderungen!$D:$D,$R20)) -> § 25 (3) | D20: =IF($R20="","",INDEX(Anforderungen!$E:$E,$R20)) -> Reservierung | E20: =IF($R20="","",INDEX(Anforderungen!$F:$F,$R20)) -> Anpassung an Marktstandards mit 2 Monaten Vorlauf. | F20: =IF($R20="","",INDEX(Anforderungen!$G:$G,$R20)) -> Der Auftraggeber 2 ist berechtigt, die in Absatz 2 definierten Mindestvoraussetzungen im Fall abweichender Marktstandards mit einer Vorlaufzeit von zwei Monaten anzupassen | G20: =IF($R20="","",INDEX(Anforderungen!$I:$I,$R20)) -> eRound | H20: =IF($R20="","",INDEX(Anforderungen!$J:$J,$R20)) -> OCPI Buchungskalender | I20: =IF($R20="","",INDEX(Anforderungen!$K:$K,$R20)) -> trifft nicht zu | J20: =IF($R20="","",INDEX(Anforderungen!$L:$L,$R20)) -> 0 | K20: =IF($R20="","",INDEX(Anforderungen!$M:$M,$R20)) -> Automatisch ausgewertet: Außerhalb des betrachteten Leistungsumfangs (Schranken, Kennzeichenerfassung, dynamische Anzeige). | R20: =IFERROR(MATCH(ROWS($A$14:$A20),$T$7:$T$2000,0)+6,"") -> 13 | T20: =IF(Anforderungen!$B20="","",IF(AND(OR($B5="(alle)",Anforderungen!$K20=$B5),OR($E5="(alle)",Anforderungen!$C20=$E5),OR($H5="(alle)",Anforderungen!$E20=$H5),OR($B7="(alle)",ISNUMBER(SEARCH($B7,Anforderungen!$J20))),OR($E7="(alle)",ISNUMBER(SEARCH($E7,Anforderungen!$I20))),OR($H7="",ISNUMBER(SEARCH($H7,Anforderungen!$F20&" "&Anforderungen!$G20)))),COUNT($T$6:$T19)+1,"")) -> 14
A21: =IF($R21="","",INDEX(Anforderungen!$B:$B,$R21)) -> ANF-008 | B21: =IF($R21="","",INDEX(Anforderungen!$C:$C,$R21)) -> Betreibervertrag | C21: =IF($R21="","",INDEX(Anforderungen!$D:$D,$R21)) -> § 25 (4) | D21: =IF($R21="","",INDEX(Anforderungen!$E:$E,$R21)) -> Reservierung | E21: =IF($R21="","",INDEX(Anforderungen!$F:$F,$R21)) -> Ladepunkte an einem Standort können von der Reservierung ausgenommen werden. | F21: =IF($R21="","",INDEX(Anforderungen!$G:$G,$R21)) -> Der Auftragnehmer kann CCS- und MCS-Ladepunkten an einem Standort von der Reservierungsmöglichkeit ausnehmen. | G21: =IF($R21="","",INDEX(Anforderungen!$I:$I,$R21)) -> eRound | H21: =IF($R21="","",INDEX(Anforderungen!$J:$J,$R21)) -> OCPI Buchungskalender | I21: =IF($R21="","",INDEX(Anforderungen!$K:$K,$R21)) -> trifft nicht zu | J21: =IF($R21="","",INDEX(Anforderungen!$L:$L,$R21)) -> 0 | K21: =IF($R21="","",INDEX(Anforderungen!$M:$M,$R21)) -> Automatisch ausgewertet: Außerhalb des betrachteten Leistungsumfangs (Schranken, Kennzeichenerfassung, dynamische Anzeige). | R21: =IFERROR(MATCH(ROWS($A$14:$A21),$T$7:$T$2000,0)+6,"") -> 14 | T21: =IF(Anforderungen!$B21="","",IF(AND(OR($B5="(alle)",Anforderungen!$K21=$B5),OR($E5="(alle)",Anforderungen!$C21=$E5),OR($H5="(alle)",Anforderungen!$E21=$H5),OR($B7="(alle)",ISNUMBER(SEARCH($B7,Anforderungen!$J21))),OR($E7="(alle)",ISNUMBER(SEARCH($E7,Anforderungen!$I21))),OR($H7="",ISNUMBER(SEARCH($H7,Anforderungen!$F21&" "&Anforderungen!$G21)))),COUNT($T$6:$T20)+1,"")) -> 15
A22: =IF($R22="","",INDEX(Anforderungen!$B:$B,$R22)) -> ANF-009 | B22: =IF($R22="","",INDEX(Anforderungen!$C:$C,$R22)) -> Betreibervertrag | C22: =IF($R22="","",INDEX(Anforderungen!$D:$D,$R22)) -> § 25 (5) | D22: =IF($R22="","",INDEX(Anforderungen!$E:$E,$R22)) -> Zufahrt & Schranke | E22: =IF($R22="","",INDEX(Anforderungen!$F:$F,$R22)) -> Bauliche Maßnahme zur Reservierung an jedem Ladepunkt. | F22: =IF($R22="","",INDEX(Anforderungen!$G:$G,$R22)) -> Der Auftragnehmer hat geeignete Vorkehrungen, insbesondere die in Vertragsanlage 4: Leistungsbeschreibung Errichtung vorgesehenen baulichen Maßnahmen, zu treffen, um ein anderweitiges Laden an dem Ladepunkt der Ladeeinrichtung während des reservierten Zeitraums zu verhindern. | G22: =IF($R22="","",INDEX(Anforderungen!$I:$I,$R22)) -> Schrankenhersteller | H22: =IF($R22="","",INDEX(Anforderungen!$J:$J,$R22)) -> Schrankenanlage | I22: =IF($R22="","",INDEX(Anforderungen!$K:$K,$R22)) -> erfasst | J22: =IF($R22="","",INDEX(Anforderungen!$L:$L,$R22)) -> 0 | K22: =IF($R22="","",INDEX(Anforderungen!$M:$M,$R22)) -> 0 | R22: =IFERROR(MATCH(ROWS($A$14:$A22),$T$7:$T$2000,0)+6,"") -> 15 | T22: =IF(Anforderungen!$B22="","",IF(AND(OR($B5="(alle)",Anforderungen!$K22=$B5),OR($E5="(alle)",Anforderungen!$C22=$E5),OR($H5="(alle)",Anforderungen!$E22=$H5),OR($B7="(alle)",ISNUMBER(SEARCH($B7,Anforderungen!$J22))),OR($E7="(alle)",ISNUMBER(SEARCH($E7,Anforderungen!$I22))),OR($H7="",ISNUMBER(SEARCH($H7,Anforderungen!$F22&" "&Anforderungen!$G22)))),COUNT($T$6:$T21)+1,"")) -> 16
A23: =IF($R23="","",INDEX(Anforderungen!$B:$B,$R23)) -> ANF-010 | B23: =IF($R23="","",INDEX(Anforderungen!$C:$C,$R23)) -> Betreibervertrag | C23: =IF($R23="","",INDEX(Anforderungen!$D:$D,$R23)) -> § 25 (6) | D23: =IF($R23="","",INDEX(Anforderungen!$E:$E,$R23)) -> Reservierung | E23: =IF($R23="","",INDEX(Anforderungen!$F:$F,$R23)) -> Mindestens 40% der Ladepunkte müssen reserviert werden können. | F23: =IF($R23="","",INDEX(Anforderungen!$G:$G,$R23)) -> Verstößt der Auftragnehmer gegen die Pflicht nach Absatz 1, wird für jeden Standort, an dem die Reservierung von Ladepunkten aufgrund des Verstoßes gegen die Pflicht nach Absatz 1 nicht möglich ist, eine Vertragsstrafe fällig. Die Reservierung von Ladepunkten an einem Standort gilt als nicht möglich, wenn mindestens 40 % der Ladepunkte an dem Standort nicht reserviert werden können. Die Höhe der Vertragsstrafe beträgt € 2.500,00 für jeden Kalendertag, an dem die Reservierung von Ladepunkten an einem Standort nicht möglich ist, höchstens jedoch € 40.000,00 pro Kalendermonat und pro Standort. | G23: =IF($R23="","",INDEX(Anforderungen!$I:$I,$R23)) -> eRound | H23: =IF($R23="","",INDEX(Anforderungen!$J:$J,$R23)) -> OCPI Buchungskalender | I23: =IF($R23="","",INDEX(Anforderungen!$K:$K,$R23)) -> erfasst | J23: =IF($R23="","",INDEX(Anforderungen!$L:$L,$R23)) -> 0 | K23: =IF($R23="","",INDEX(Anforderungen!$M:$M,$R23)) -> 0 | R23: =IFERROR(MATCH(ROWS($A$14:$A23),$T$7:$T$2000,0)+6,"") -> 16 | T23: =IF(Anforderungen!$B23="","",IF(AND(OR($B5="(alle)",Anforderungen!$K23=$B5),OR($E5="(alle)",Anforderungen!$C23=$E5),OR($H5="(alle)",Anforderungen!$E23=$H5),OR($B7="(alle)",ISNUMBER(SEARCH($B7,Anforderungen!$J23))),OR($E7="(alle)",ISNUMBER(SEARCH($E7,Anforderungen!$I23))),OR($H7="",ISNUMBER(SEARCH($H7,Anforderungen!$F23&" "&Anforderungen!$G23)))),COUNT($T$6:$T22)+1,"")) -> 17
A24: =IF($R24="","",INDEX(Anforderungen!$B:$B,$R24)) -> ANF-011 | B24: =IF($R24="","",INDEX(Anforderungen!$C:$C,$R24)) -> Betreibervertrag | C24: =IF($R24="","",INDEX(Anforderungen!$D:$D,$R24)) -> § 31 (1) | D24: =IF($R24="","",INDEX(Anforderungen!$E:$E,$R24)) -> Authentifizierung & Zugang | E24: =IF($R24="","",INDEX(Anforderungen!$F:$F,$R24)) -> Es muss Adhoc geladen werden können | F24: =IF($R24="","",INDEX(Anforderungen!$G:$G,$R24)) -> Der Auftragnehmer ist verpflichtet, potenziellen Endnutzern diskriminierungsfrei zu angemessenen Bedingungen ein Ad-hoc-Laden (punktuelles Aufladen i. S. d. AFIR) zu ermöglichen, soweit es ihm zumutbar ist (z. B. mit Blick auf die Bonität des Endnutzers). | G24: =IF($R24="","",INDEX(Anforderungen!$I:$I,$R24)) -> eRound / SCS | H24: =IF($R24="","",INDEX(Anforderungen!$J:$J,$R24)) -> Authentifizierungskomponente / Schrankensteuerung | I24: =IF($R24="","",INDEX(Anforderungen!$K:$K,$R24)) -> erfasst | J24: =IF($R24="","",INDEX(Anforderungen!$L:$L,$R24)) -> 0 | K24: =IF($R24="","",INDEX(Anforderungen!$M:$M,$R24)) -> 0 | R24: =IFERROR(MATCH(ROWS($A$14:$A24),$T$7:$T$2000,0)+6,"") -> 17 | T24: =IF(Anforderungen!$B24="","",IF(AND(OR($B5="(alle)",Anforderungen!$K24=$B5),OR($E5="(alle)",Anforderungen!$C24=$E5),OR($H5="(alle)",Anforderungen!$E24=$H5),OR($B7="(alle)",ISNUMBER(SEARCH($B7,Anforderungen!$J24))),OR($E7="(alle)",ISNUMBER(SEARCH($E7,Anforderungen!$I24))),OR($H7="",ISNUMBER(SEARCH($H7,Anforderungen!$F24&" "&Anforderungen!$G24)))),COUNT($T$6:$T23)+1,"")) -> 18
A25: =IF($R25="","",INDEX(Anforderungen!$B:$B,$R25)) -> ANF-012 | B25: =IF($R25="","",INDEX(Anforderungen!$C:$C,$R25)) -> Betreibervertrag | C25: =IF($R25="","",INDEX(Anforderungen!$D:$D,$R25)) -> § 38 (1) | D25: =IF($R25="","",INDEX(Anforderungen!$E:$E,$R25)) -> Nutzungszeit & Entgelte | E25: =IF($R25="","",INDEX(Anforderungen!$F:$F,$R25)) -> Blockadeentgelte und maximale Nutzungsdauer | F25: =IF($R25="","",INDEX(Anforderungen!$G:$G,$R25)) -> Start- und zeitabhängige Entgelte dürfen nicht erhoben werden. Dies gilt nicht für vertraglich vereinbarte Blockadeentgelte, die nach Ablauf einer maximalen Nutzungszeit vom Endnutzer bzw. Mobilitätsdienstleister unabhängig davon, welches der Zugangsmodelle des § 30 Abs. 2 gewählt wird, erhoben werden. Die maximale Nutzungszeit beginnt mit Beginn des Ladevorgangs und beträgt | G25: =IF($R25="","",INDEX(Anforderungen!$I:$I,$R25)) -> eRound | H25: =IF($R25="","",INDEX(Anforderungen!$J:$J,$R25)) -> OCPI Buchungskalender | I25: =IF($R25="","",INDEX(Anforderungen!$K:$K,$R25)) -> trifft nicht zu | J25: =IF($R25="","",INDEX(Anforderungen!$L:$L,$R25)) -> 0 | K25: =IF($R25="","",INDEX(Anforderungen!$M:$M,$R25)) -> Automatisch ausgewertet: Außerhalb des betrachteten Leistungsumfangs (Schranken, Kennzeichenerfassung, dynamische Anzeige). | R25: =IFERROR(MATCH(ROWS($A$14:$A25),$T$7:$T$2000,0)+6,"") -> 18 | T25: =IF(Anforderungen!$B25="","",IF(AND(OR($B5="(alle)",Anforderungen!$K25=$B5),OR($E5="(alle)",Anforderungen!$C25=$E5),OR($H5="(alle)",Anforderungen!$E25=$H5),OR($B7="(alle)",ISNUMBER(SEARCH($B7,Anforderungen!$J25))),OR($E7="(alle)",ISNUMBER(SEARCH($E7,Anforderungen!$I25))),OR($H7="",ISNUMBER(SEARCH($H7,Anforderungen!$F25&" "&Anforderungen!$G25)))),COUNT($T$6:$T24)+1,"")) -> 19
A26: =IF($R26="","",INDEX(Anforderungen!$B:$B,$R26)) -> ANF-013 | B26: =IF($R26="","",INDEX(Anforderungen!$C:$C,$R26)) -> Betreibervertrag | C26: =IF($R26="","",INDEX(Anforderungen!$D:$D,$R26)) -> § 38 (1) a | D26: =IF($R26="","",INDEX(Anforderungen!$E:$E,$R26)) -> Nutzungszeit & Entgelte | E26: =IF($R26="","",INDEX(Anforderungen!$F:$F,$R26)) -> Maximale Nutzungsdauer Zwischenladen ist 1h. | F26: =IF($R26="","",INDEX(Anforderungen!$G:$G,$R26)) -> bei MCS-Ladepunkten und CCS-Ladepunkten zum Zwischenladen 1 Stunde. | G26: =IF($R26="","",INDEX(Anforderungen!$I:$I,$R26)) -> eRound | H26: =IF($R26="","",INDEX(Anforderungen!$J:$J,$R26)) -> OCPI Buchungskalender | I26: =IF($R26="","",INDEX(Anforderungen!$K:$K,$R26)) -> trifft nicht zu | J26: =IF($R26="","",INDEX(Anforderungen!$L:$L,$R26)) -> 0 | K26: =IF($R26="","",INDEX(Anforderungen!$M:$M,$R26)) -> Automatisch ausgewertet: Außerhalb des betrachteten Leistungsumfangs (Schranken, Kennzeichenerfassung, dynamische Anzeige). | R26: =IFERROR(MATCH(ROWS($A$14:$A26),$T$7:$T$2000,0)+6,"") -> 19 | T26: =IF(Anforderungen!$B26="","",IF(AND(OR($B5="(alle)",Anforderungen!$K26=$B5),OR($E5="(alle)",Anforderungen!$C26=$E5),OR($H5="(alle)",Anforderungen!$E26=$H5),OR($B7="(alle)",ISNUMBER(SEARCH($B7,Anforderungen!$J26))),OR($E7="(alle)",ISNUMBER(SEARCH($E7,Anforderungen!$I26))),OR($H7="",ISNUMBER(SEARCH($H7,Anforderungen!$F26&" "&Anforderungen!$G26)))),COUNT($T$6:$T25)+1,"")) -> 20
A27: =IF($R27="","",INDEX(Anforderungen!$B:$B,$R27)) -> ANF-014 | B27: =IF($R27="","",INDEX(Anforderungen!$C:$C,$R27)) -> Betreibervertrag | C27: =IF($R27="","",INDEX(Anforderungen!$D:$D,$R27)) -> § 38 (1) b | D27: =IF($R27="","",INDEX(Anforderungen!$E:$E,$R27)) -> Nutzungszeit & Entgelte | E27: =IF($R27="","",INDEX(Anforderungen!$F:$F,$R27)) -> Maximale Nutzungsdauer Übernachtladen ist 12h. | F27: =IF($R27="","",INDEX(Anforderungen!$G:$G,$R27)) -> bei CCS-Ladepunkten zum Übernachtladen und MCS- oder CCS-Ladepunkte zum Zwischenladen, die zum Übernachtladen freigegeben wurden, 12 Stunden. | G27: =IF($R27="","",INDEX(Anforderungen!$I:$I,$R27)) -> eRound | H27: =IF($R27="","",INDEX(Anforderungen!$J:$J,$R27)) -> OCPI Buchungskalender | I27: =IF($R27="","",INDEX(Anforderungen!$K:$K,$R27)) -> trifft nicht zu | J27: =IF($R27="","",INDEX(Anforderungen!$L:$L,$R27)) -> 0 | K27: =IF($R27="","",INDEX(Anforderungen!$M:$M,$R27)) -> Automatisch ausgewertet: Außerhalb des betrachteten Leistungsumfangs (Schranken, Kennzeichenerfassung, dynamische Anzeige). | R27: =IFERROR(MATCH(ROWS($A$14:$A27),$T$7:$T$2000,0)+6,"") -> 20 | T27: =IF(Anforderungen!$B27="","",IF(AND(OR($B5="(alle)",Anforderungen!$K27=$B5),OR($E5="(alle)",Anforderungen!$C27=$E5),OR($H5="(alle)",Anforderungen!$E27=$H5),OR($B7="(alle)",ISNUMBER(SEARCH($B7,Anforderungen!$J27))),OR($E7="(alle)",ISNUMBER(SEARCH($E7,Anforderungen!$I27))),OR($H7="",ISNUMBER(SEARCH($H7,Anforderungen!$F27&" "&Anforderungen!$G27)))),COUNT($T$6:$T26)+1,"")) -> 21
A28: =IF($R28="","",INDEX(Anforderungen!$B:$B,$R28)) -> ANF-015 | B28: =IF($R28="","",INDEX(Anforderungen!$C:$C,$R28)) -> Betreibervertrag | C28: =IF($R28="","",INDEX(Anforderungen!$D:$D,$R28)) -> § 38 (2) | D28: =IF($R28="","",INDEX(Anforderungen!$E:$E,$R28)) -> Nutzungszeit & Entgelte | E28: =IF($R28="","",INDEX(Anforderungen!$F:$F,$R28)) -> Bei nidriger Auslastung kann die maximale Nutzungszeit vom AN verlängert werden. Bei nachfolgender Reservierung kann die maximale Nutzungszeit verkürzt werden. Bei Verkürzung zusätzliche Karenzzeit vor Blockadeentgeld von 5min. | F28: =IF($R28="","",INDEX(Anforderungen!$G:$G,$R28)) -> Der Auftragnehmer kann die maximalen Nutzungszeiten in Zeiten geringer Auslastung verlängern. Zudem kann er mit der Gestattung der Nutzung von MCS-Ladepunkten und CCS-Ladepunkten zum Zwischenladen dem Endnutzer bzw. Mobilitätsdienstleister auch ausdrücklich eine kürzere maximale Nutzungszeit einräumen, wenn wegen nachfolgender Reservierungen die maximale Nutzungszeit nach Absatz 1 lit. a nicht eingeräumt werden kann. In den Fällen des Satzes 2 ist dem Endnutzer bzw. Mobilitätsdienstleister zusätzlich eine Karenzzeit zum Verlassen des Ladeplatzes von 5 Minuten einzuräumen, nach deren Ablauf erst ein Blockadeentgelt erhoben werden darf | G28: =IF($R28="","",INDEX(Anforderungen!$I:$I,$R28)) -> eRound | H28: =IF($R28="","",INDEX(Anforderungen!$J:$J,$R28)) -> OCPI Buchungskalender | I28: =IF($R28="","",INDEX(Anforderungen!$K:$K,$R28)) -> trifft nicht zu | J28: =IF($R28="","",INDEX(Anforderungen!$L:$L,$R28)) -> 0 | K28: =IF($R28="","",INDEX(Anforderungen!$M:$M,$R28)) -> Automatisch ausgewertet: Außerhalb des betrachteten Leistungsumfangs (Schranken, Kennzeichenerfassung, dynamische Anzeige). | R28: =IFERROR(MATCH(ROWS($A$14:$A28),$T$7:$T$2000,0)+6,"") -> 21 | T28: =IF(Anforderungen!$B28="","",IF(AND(OR($B5="(alle)",Anforderungen!$K28=$B5),OR($E5="(alle)",Anforderungen!$C28=$E5),OR($H5="(alle)",Anforderungen!$E28=$H5),OR($B7="(alle)",ISNUMBER(SEARCH($B7,Anforderungen!$J28))),OR($E7="(alle)",ISNUMBER(SEARCH($E7,Anforderungen!$I28))),OR($H7="",ISNUMBER(SEARCH($H7,Anforderungen!$F28&" "&Anforderungen!$G28)))),COUNT($T$6:$T27)+1,"")) -> 22
A29: =IF($R29="","",INDEX(Anforderungen!$B:$B,$R29)) -> ANF-016 | B29: =IF($R29="","",INDEX(Anforderungen!$C:$C,$R29)) -> Betreibervertrag | C29: =IF($R29="","",INDEX(Anforderungen!$D:$D,$R29)) -> § 38 (3) | D29: =IF($R29="","",INDEX(Anforderungen!$E:$E,$R29)) -> Nutzungszeit & Entgelte | E29: =IF($R29="","",INDEX(Anforderungen!$F:$F,$R29)) -> Maximale Nutzungszeit endet mit Ablauf Reservierung. Maximale Nutzungsdauer kann vom AN verlängert werden. | F29: =IF($R29="","",INDEX(Anforderungen!$G:$G,$R29)) -> Hat ein Mobilitätsdienstleister einen Ladepunkt reserviert, so endet die maximale Nutzungszeit mit dem Ablauf des reservierten Zeitraums, auch wenn der Ladeplatz erst später belegt wurde, es sei denn, der Betreiber räumt ihm eine längere maximale Nutzungszeit ein. | G29: =IF($R29="","",INDEX(Anforderungen!$I:$I,$R29)) -> eRound | H29: =IF($R29="","",INDEX(Anforderungen!$J:$J,$R29)) -> OCPI Buchungskalender | I29: =IF($R29="","",INDEX(Anforderungen!$K:$K,$R29)) -> trifft nicht zu | J29: =IF($R29="","",INDEX(Anforderungen!$L:$L,$R29)) -> 0 | K29: =IF($R29="","",INDEX(Anforderungen!$M:$M,$R29)) -> Automatisch ausgewertet: Außerhalb des betrachteten Leistungsumfangs (Schranken, Kennzeichenerfassung, dynamische Anzeige). | R29: =IFERROR(MATCH(ROWS($A$14:$A29),$T$7:$T$2000,0)+6,"") -> 22 | T29: =IF(Anforderungen!$B29="","",IF(AND(OR($B5="(alle)",Anforderungen!$K29=$B5),OR($E5="(alle)",Anforderungen!$C29=$E5),OR($H5="(alle)",Anforderungen!$E29=$H5),OR($B7="(alle)",ISNUMBER(SEARCH($B7,Anforderungen!$J29))),OR($E7="(alle)",ISNUMBER(SEARCH($E7,Anforderungen!$I29))),OR($H7="",ISNUMBER(SEARCH($H7,Anforderungen!$F29&" "&Anforderungen!$G29)))),COUNT($T$6:$T28)+1,"")) -> 23
A30: =IF($R30="","",INDEX(Anforderungen!$B:$B,$R30)) -> ANF-017 | B30: =IF($R30="","",INDEX(Anforderungen!$C:$C,$R30)) -> Betreibervertrag | C30: =IF($R30="","",INDEX(Anforderungen!$D:$D,$R30)) -> § 38 (4) | D30: =IF($R30="","",INDEX(Anforderungen!$E:$E,$R30)) -> Nutzungszeit & Entgelte | E30: =IF($R30="","",INDEX(Anforderungen!$F:$F,$R30)) -> Ladestart 15min Wartezeit Blockadeentgeld ggf. Pönalisierung Entfall maximale Nutzungsdauer | F30: =IF($R30="","",INDEX(Anforderungen!$G:$G,$R30)) -> Wird ein Ladevorgang nicht innerhalb von 15 Minuten nach Besetzung des Stellplatzes gestartet, entfällt die maximale Nutzungszeit und es kann ein Blockadeentgelt erhoben werden. | G30: =IF($R30="","",INDEX(Anforderungen!$I:$I,$R30)) -> eRound / SCS | H30: =IF($R30="","",INDEX(Anforderungen!$J:$J,$R30)) -> OCPI Buchungskalender / Abrechnungskomponente / Belegungsdetektion / Pönalisierungssystem | I30: =IF($R30="","",INDEX(Anforderungen!$K:$K,$R30)) -> trifft nicht zu | J30: =IF($R30="","",INDEX(Anforderungen!$L:$L,$R30)) -> 0 | K30: =IF($R30="","",INDEX(Anforderungen!$M:$M,$R30)) -> Automatisch ausgewertet: Außerhalb des betrachteten Leistungsumfangs (Schranken, Kennzeichenerfassung, dynamische Anzeige). | R30: =IFERROR(MATCH(ROWS($A$14:$A30),$T$7:$T$2000,0)+6,"") -> 23 | T30: =IF(Anforderungen!$B30="","",IF(AND(OR($B5="(alle)",Anforderungen!$K30=$B5),OR($E5="(alle)",Anforderungen!$C30=$E5),OR($H5="(alle)",Anforderungen!$E30=$H5),OR($B7="(alle)",ISNUMBER(SEARCH($B7,Anforderungen!$J30))),OR($E7="(alle)",ISNUMBER(SEARCH($E7,Anforderungen!$I30))),OR($H7="",ISNUMBER(SEARCH($H7,Anforderungen!$F30&" "&Anforderungen!$G30)))),COUNT($T$6:$T29)+1,"")) -> 24
A31: =IF($R31="","",INDEX(Anforderungen!$B:$B,$R31)) -> ANF-018 | B31: =IF($R31="","",INDEX(Anforderungen!$C:$C,$R31)) -> Betreibervertrag | C31: =IF($R31="","",INDEX(Anforderungen!$D:$D,$R31)) -> § 38 (5) | D31: =IF($R31="","",INDEX(Anforderungen!$E:$E,$R31)) -> Nutzungszeit & Entgelte | E31: =IF($R31="","",INDEX(Anforderungen!$F:$F,$R31)) -> Kein Blockadeentgeld während Nachtruhezeiten, Sonn- und Feiertage der Bundesländer. | F31: =IF($R31="","",INDEX(Anforderungen!$G:$G,$R31)) -> An Sonn- und Feiertagen sowie zwischen 22 Uhr abends und 5 Uhr morgens (Nachtruhezeit) darf der Auftragnehmer für CCS-Ladepunkte zum Übernachtladen bzw. MCS- und CCS- Ladepunkten zum Zwischenladen, die zum Übernachtladen freigegeben wurden, keine Blockadeentgelte erheben. Hat der Ladevorgang bereits vor Beginn der Nachtruhezeiten begonnen und endet die maximale Nutzungszeit nach Absatz 1 während der Nachtruhezeit, so werden Blockadeentgelte mithin erst nach Ende der Nachtruhezeit berechnet. Satz 1 und 2 gelten entsprechend für Sonntage und gesetzliche Feiertage in dem Bundesland, in dem der jeweilige Standort gelegen ist. | G31: =IF($R31="","",INDEX(Anforderungen!$I:$I,$R31)) -> eRound | H31: =IF($R31="","",INDEX(Anforderungen!$J:$J,$R31)) -> OCPI Buchungskalender | I31: =IF($R31="","",INDEX(Anforderungen!$K:$K,$R31)) -> trifft nicht zu | J31: =IF($R31="","",INDEX(Anforderungen!$L:$L,$R31)) -> 0 | K31: =IF($R31="","",INDEX(Anforderungen!$M:$M,$R31)) -> Automatisch ausgewertet: Außerhalb des betrachteten Leistungsumfangs (Schranken, Kennzeichenerfassung, dynamische Anzeige). | R31: =IFERROR(MATCH(ROWS($A$14:$A31),$T$7:$T$2000,0)+6,"") -> 24 | T31: =IF(Anforderungen!$B31="","",IF(AND(OR($B5="(alle)",Anforderungen!$K31=$B5),OR($E5="(alle)",Anforderungen!$C31=$E5),OR($H5="(alle)",Anforderungen!$E31=$H5),OR($B7="(alle)",ISNUMBER(SEARCH($B7,Anforderungen!$J31))),OR($E7="(alle)",ISNUMBER(SEARCH($E7,Anforderungen!$I31))),OR($H7="",ISNUMBER(SEARCH($H7,Anforderungen!$F31&" "&Anforderungen!$G31)))),COUNT($T$6:$T30)+1,"")) -> 25
A32: =IF($R32="","",INDEX(Anforderungen!$B:$B,$R32)) -> ANF-019 | B32: =IF($R32="","",INDEX(Anforderungen!$C:$C,$R32)) -> Betreibervertrag | C32: =IF($R32="","",INDEX(Anforderungen!$D:$D,$R32)) -> § 38 (6) | D32: =IF($R32="","",INDEX(Anforderungen!$E:$E,$R32)) -> Nutzungszeit & Entgelte | E32: =IF($R32="","",INDEX(Anforderungen!$F:$F,$R32)) -> Blockadeentgeld Höhe 0,50€ / 0,15€ pro Min. | F32: =IF($R32="","",INDEX(Anforderungen!$G:$G,$R32)) -> Die Höhe des Blockadeentgelts darf bei MCS-Ladepunkten und bei CCS-Ladepunkten zum Zwischenladen maximal 0,50 €/Minute und bei CCS-Ladepunkten bzw. CCS- und MCS- Ladepunkten zum Zwischenladen, während des Zeitraums, für den sie zum Übernachtladen freigegeben wurden, maximal 0,15 €/Minute betragen. Das vereinnahmte Blockadeentgelt steht dem Auftragnehmer zu. | G32: =IF($R32="","",INDEX(Anforderungen!$I:$I,$R32)) -> eRound | H32: =IF($R32="","",INDEX(Anforderungen!$J:$J,$R32)) -> Abrechnungskomponente | I32: =IF($R32="","",INDEX(Anforderungen!$K:$K,$R32)) -> trifft nicht zu | J32: =IF($R32="","",INDEX(Anforderungen!$L:$L,$R32)) -> 0 | K32: =IF($R32="","",INDEX(Anforderungen!$M:$M,$R32)) -> Automatisch ausgewertet: Außerhalb des betrachteten Leistungsumfangs (Schranken, Kennzeichenerfassung, dynamische Anzeige). | R32: =IFERROR(MATCH(ROWS($A$14:$A32),$T$7:$T$2000,0)+6,"") -> 25 | T32: =IF(Anforderungen!$B32="","",IF(AND(OR($B5="(alle)",Anforderungen!$K32=$B5),OR($E5="(alle)",Anforderungen!$C32=$E5),OR($H5="(alle)",Anforderungen!$E32=$H5),OR($B7="(alle)",ISNUMBER(SEARCH($B7,Anforderungen!$J32))),OR($E7="(alle)",ISNUMBER(SEARCH($E7,Anforderungen!$I32))),OR($H7="",ISNUMBER(SEARCH($H7,Anforderungen!$F32&" "&Anforderungen!$G32)))),COUNT($T$6:$T31)+1,"")) -> 26
A33: =IF($R33="","",INDEX(Anforderungen!$B:$B,$R33)) -> ANF-020 | B33: =IF($R33="","",INDEX(Anforderungen!$C:$C,$R33)) -> Betreibervertrag | C33: =IF($R33="","",INDEX(Anforderungen!$D:$D,$R33)) -> § 38 (7) | D33: =IF($R33="","",INDEX(Anforderungen!$E:$E,$R33)) -> Nutzungszeit & Entgelte | E33: =IF($R33="","",INDEX(Anforderungen!$F:$F,$R33)) -> Änderungen an maximaler Nutzungsdauer, Blockadeentgelt und Sperrzeiten mit Vorlauf möglich. | F33: =IF($R33="","",INDEX(Anforderungen!$G:$G,$R33)) -> Der Auftraggeber 2 kann die maximale Höhe der Blockadeentgelte nach Absatz 6 und die maximalen Nutzungszeiten bzw. Sperrzeiten für die Erhebung eines Blockadeentgeltes nach den Absätzen 1 bis 4 während der Laufzeit des Vertrags mit einer Frist von vier Monaten auf den Beginn eines Quartals schriftlich mit Wirkung gegenüber dem Auftragnehmer anpassen. Absenkungen der Höhe oder Verlängerungen die maximalen Nutzungszeiten bzw. Sperrzeiten sind nur mit Zustimmung des Auftragnehmers zulässig. Die Zustimmung gilt als erteilt, sofern der Auftragnehmer dem Auftraggeber 2 nicht innerhalb von zwei Wochen nach Mitteilung der geplanten Absenkung in Textform widerspricht. | G33: =IF($R33="","",INDEX(Anforderungen!$I:$I,$R33)) -> eRound | H33: =IF($R33="","",INDEX(Anforderungen!$J:$J,$R33)) -> Abrechnungskomponente | I33: =IF($R33="","",INDEX(Anforderungen!$K:$K,$R33)) -> trifft nicht zu | J33: =IF($R33="","",INDEX(Anforderungen!$L:$L,$R33)) -> 0 | K33: =IF($R33="","",INDEX(Anforderungen!$M:$M,$R33)) -> Automatisch ausgewertet: Außerhalb des betrachteten Leistungsumfangs (Schranken, Kennzeichenerfassung, dynamische Anzeige). | R33: =IFERROR(MATCH(ROWS($A$14:$A33),$T$7:$T$2000,0)+6,"") -> 26 | T33: =IF(Anforderungen!$B33="","",IF(AND(OR($B5="(alle)",Anforderungen!$K33=$B5),OR($E5="(alle)",Anforderungen!$C33=$E5),OR($H5="(alle)",Anforderungen!$E33=$H5),OR($B7="(alle)",ISNUMBER(SEARCH($B7,Anforderungen!$J33))),OR($E7="(alle)",ISNUMBER(SEARCH($E7,Anforderungen!$I33))),OR($H7="",ISNUMBER(SEARCH($H7,Anforderungen!$F33&" "&Anforderungen!$G33)))),COUNT($T$6:$T32)+1,"")) -> 27
A34: =IF($R34="","",INDEX(Anforderungen!$B:$B,$R34)) -> ANF-021 | B34: =IF($R34="","",INDEX(Anforderungen!$C:$C,$R34)) -> Betreibervertrag | C34: =IF($R34="","",INDEX(Anforderungen!$D:$D,$R34)) -> § 38 (8) | D34: =IF($R34="","",INDEX(Anforderungen!$E:$E,$R34)) -> Nutzungszeit & Entgelte | E34: =IF($R34="","",INDEX(Anforderungen!$F:$F,$R34)) -> Mindestabnahmemenge und Vergütung bei Unterschreitung. | F34: =IF($R34="","",INDEX(Anforderungen!$G:$G,$R34)) -> Für jeden Übernachtladevorgang ist eine Mindestabnahmemenge von 150 kWh vorzusehen, dies gilt auch für MCS- und CCS-Ladepunkte, die nach Maßgabe dieses Vertrags zum Übernachtladen freigegeben werden. Wird die Mindestabnahmemenge nicht erreicht, so ist für die Differenz zwischen der tatsächlich abgenommenen Strommenge und der vertraglich vorgesehenen Mindestabnahmemenge vom Endnutzer bzw. Mobilitätsdienstleister eine Entschädigung in Höhe von 30 ct/kWh an den Auftragnehmer zu leisten. Die Entschädigungshöhe kann vom Auftraggeber 2 in Absprache mit dem Auftragnehmer zu einem späteren Zeitpunkt angepasst werden. | G34: =IF($R34="","",INDEX(Anforderungen!$I:$I,$R34)) -> eRound | H34: =IF($R34="","",INDEX(Anforderungen!$J:$J,$R34)) -> Abrechnungskomponente | I34: =IF($R34="","",INDEX(Anforderungen!$K:$K,$R34)) -> trifft nicht zu | J34: =IF($R34="","",INDEX(Anforderungen!$L:$L,$R34)) -> 0 | K34: =IF($R34="","",INDEX(Anforderungen!$M:$M,$R34)) -> Automatisch ausgewertet: Außerhalb des betrachteten Leistungsumfangs (Schranken, Kennzeichenerfassung, dynamische Anzeige). | R34: =IFERROR(MATCH(ROWS($A$14:$A34),$T$7:$T$2000,0)+6,"") -> 27 | T34: =IF(Anforderungen!$B34="","",IF(AND(OR($B5="(alle)",Anforderungen!$K34=$B5),OR($E5="(alle)",Anforderungen!$C34=$E5),OR($H5="(alle)",Anforderungen!$E34=$H5),OR($B7="(alle)",ISNUMBER(SEARCH($B7,Anforderungen!$J34))),OR($E7="(alle)",ISNUMBER(SEARCH($E7,Anforderungen!$I34))),OR($H7="",ISNUMBER(SEARCH($H7,Anforderungen!$F34&" "&Anforderungen!$G34)))),COUNT($T$6:$T33)+1,"")) -> 28
A35: =IF($R35="","",INDEX(Anforderungen!$B:$B,$R35)) -> ANF-022 | B35: =IF($R35="","",INDEX(Anforderungen!$C:$C,$R35)) -> Betreibervertrag | C35: =IF($R35="","",INDEX(Anforderungen!$D:$D,$R35)) -> § 38 (9) | D35: =IF($R35="","",INDEX(Anforderungen!$E:$E,$R35)) -> Nutzungszeit & Entgelte | E35: =IF($R35="","",INDEX(Anforderungen!$F:$F,$R35)) -> Warnung NutzerIn vor Blockadeentgeld | F35: =IF($R35="","",INDEX(Anforderungen!$G:$G,$R35)) -> Endnutzer sind über eine gut sichtbare Beschilderung darauf hinzuweisen, dass der Stellplatz nach Abschluss des Ladevorgangs unverzüglich freizugeben ist; der Text der Beschilderung bedarf der Zustimmung des Auftraggebers 2. Zusätzlich soll der Endnutzer über eine App oder – falls er eine solche nicht nutzt – an der Ladeeinrichtung, vor Erhebung von Blockadeentgelt oder einer Vertragsstrafe einen Hinweis erhalten, dass der Ladevorgang beendet wurde und der Ladeplatz unverzüglich zu räumen ist | G35: =IF($R35="","",INDEX(Anforderungen!$I:$I,$R35)) -> eRound | H35: =IF($R35="","",INDEX(Anforderungen!$J:$J,$R35)) -> Abrechnungskomponente / Beschilderung | I35: =IF($R35="","",INDEX(Anforderungen!$K:$K,$R35)) -> trifft nicht zu | J35: =IF($R35="","",INDEX(Anforderungen!$L:$L,$R35)) -> 46259 | K35: =IF($R35="","",INDEX(Anforderungen!$M:$M,$R35)) -> ggf. Thema für eRound ansonsten Beschilderung -> Bau GU | R35: =IFERROR(MATCH(ROWS($A$14:$A35),$T$7:$T$2000,0)+6,"") -> 28 | T35: =IF(Anforderungen!$B35="","",IF(AND(OR($B5="(alle)",Anforderungen!$K35=$B5),OR($E5="(alle)",Anforderungen!$C35=$E5),OR($H5="(alle)",Anforderungen!$E35=$H5),OR($B7="(alle)",ISNUMBER(SEARCH($B7,Anforderungen!$J35))),OR($E7="(alle)",ISNUMBER(SEARCH($E7,Anforderungen!$I35))),OR($H7="",ISNUMBER(SEARCH($H7,Anforderungen!$F35&" "&Anforderungen!$G35)))),COUNT($T$6:$T34)+1,"")) -> 29
A36: =IF($R36="","",INDEX(Anforderungen!$B:$B,$R36)) -> ANF-023 | B36: =IF($R36="","",INDEX(Anforderungen!$C:$C,$R36)) -> Betreibervertrag | C36: =IF($R36="","",INDEX(Anforderungen!$D:$D,$R36)) -> § 42 (5) | D36: =IF($R36="","",INDEX(Anforderungen!$E:$E,$R36)) -> Betrieb & Auslastung | E36: =IF($R36="","",INDEX(Anforderungen!$F:$F,$R36)) -> Updates verpflichtend. | F36: =IF($R36="","",INDEX(Anforderungen!$G:$G,$R36)) -> Der Auftragnehmer ist auf Aufforderung des Auftraggebers 2 verpflichtet, die Ladeeinrichtungen technisch und/oder mit Blick auf die Software (insbesondere Schnittstellen und Protokolle) weiterzuentwickeln und zu verbessern. Die Erstattung der tatsächlich erforderlichen Kosten (zuzüglich angemessener Zuschläge für allgemeine Geschäftskosten, Wagnis und Gewinn) erfolgt nach den Regelungen über geänderte oder zusätzliche Leistungen nach § 40. | G36: =IF($R36="","",INDEX(Anforderungen!$I:$I,$R36)) -> Alpitronic | H36: =IF($R36="","",INDEX(Anforderungen!$J:$J,$R36)) -> Ladeeinrichtung | I36: =IF($R36="","",INDEX(Anforderungen!$K:$K,$R36)) -> trifft nicht zu | J36: =IF($R36="","",INDEX(Anforderungen!$L:$L,$R36)) -> 46260 | K36: =IF($R36="","",INDEX(Anforderungen!$M:$M,$R36)) -> Betrifft LIS | R36: =IFERROR(MATCH(ROWS($A$14:$A36),$T$7:$T$2000,0)+6,"") -> 29 | T36: =IF(Anforderungen!$B36="","",IF(AND(OR($B5="(alle)",Anforderungen!$K36=$B5),OR($E5="(alle)",Anforderungen!$C36=$E5),OR($H5="(alle)",Anforderungen!$E36=$H5),OR($B7="(alle)",ISNUMBER(SEARCH($B7,Anforderungen!$J36))),OR($E7="(alle)",ISNUMBER(SEARCH($E7,Anforderungen!$I36))),OR($H7="",ISNUMBER(SEARCH($H7,Anforderungen!$F36&" "&Anforderungen!$G36)))),COUNT($T$6:$T35)+1,"")) -> 30
A37: =IF($R37="","",INDEX(Anforderungen!$B:$B,$R37)) -> ANF-024 | B37: =IF($R37="","",INDEX(Anforderungen!$C:$C,$R37)) -> Betreibervertrag | C37: =IF($R37="","",INDEX(Anforderungen!$D:$D,$R37)) -> § 22 (3) | D37: =IF($R37="","",INDEX(Anforderungen!$E:$E,$R37)) -> Betrieb & Auslastung | E37: =IF($R37="","",INDEX(Anforderungen!$F:$F,$R37)) -> Bei nidriger Auslastung: Zwischenladepunkte können zwischen 17 und 6 Uhr für Übernachtladen freigegeben werden. Aber mind. 40% Zwischenladepunkte, aber mind. 2 MCS und 1 CCS. | F37: =IF($R37="","",INDEX(Anforderungen!$G:$G,$R37)) -> CCS- und MCS-Ladepunkte zum Zwischenladen sind bei fehlender Auslastung ab 17:00 Uhr sowie an Wochenenden zum Übernachtladen freizugegeben. Es müssen jedoch auch in dieser Zeit 40 %, aber mindestens zwei MCS-Ladepunkte bzw. ein CCS-Ladepunkt, zum Zwischenladen für das Zwischenladen freigehalten werden. An Standorten, an denen nur ein MCS-Ladepunkt vorhanden ist, ist dieser für das Zwischenladen freizuhalten. Der Auftragnehmer hat sicherzustellen, dass die MCS- und CCS-Ladepunkte zum Zwischenladen ab 06:00 Uhr wieder für das Zwischenladen bereitstehen. Auftragnehmer und Auftraggeber 2 können sich je nach Auslastung der Ladepunkte auf abweichende Vorgaben zur Freigabe von Ladepunkten zum Zwischenladen einigen. | G37: =IF($R37="","",INDEX(Anforderungen!$I:$I,$R37)) -> eRound / SCS | H37: =IF($R37="","",INDEX(Anforderungen!$J:$J,$R37)) -> OCPI Buchungskalender / Dynamische Anzeige | I37: =IF($R37="","",INDEX(Anforderungen!$K:$K,$R37)) -> erfüllt | J37: =IF($R37="","",INDEX(Anforderungen!$L:$L,$R37)) -> 46259 | K37: =IF($R37="","",INDEX(Anforderungen!$M:$M,$R37)) -> eRound regelt - SCS zeigt an | R37: =IFERROR(MATCH(ROWS($A$14:$A37),$T$7:$T$2000,0)+6,"") -> 30 | T37: =IF(Anforderungen!$B37="","",IF(AND(OR($B5="(alle)",Anforderungen!$K37=$B5),OR($E5="(alle)",Anforderungen!$C37=$E5),OR($H5="(alle)",Anforderungen!$E37=$H5),OR($B7="(alle)",ISNUMBER(SEARCH($B7,Anforderungen!$J37))),OR($E7="(alle)",ISNUMBER(SEARCH($E7,Anforderungen!$I37))),OR($H7="",ISNUMBER(SEARCH($H7,Anforderungen!$F37&" "&Anforderungen!$G37)))),COUNT($T$6:$T36)+1,"")) -> 31
A38: =IF($R38="","",INDEX(Anforderungen!$B:$B,$R38)) -> ANF-025 | B38: =IF($R38="","",INDEX(Anforderungen!$C:$C,$R38)) -> Betreibervertrag | C38: =IF($R38="","",INDEX(Anforderungen!$D:$D,$R38)) -> § 4 (52) | D38: =IF($R38="","",INDEX(Anforderungen!$E:$E,$R38)) -> Reservierung | E38: =IF($R38="","",INDEX(Anforderungen!$F:$F,$R38)) -> Mindestens AN plus ein weiterer. | F38: =IF($R38="","",INDEX(Anforderungen!$G:$G,$R38)) -> "Reservierungssystem“: Ein System zur Reservierung von Ladepunkten, das Mobilitätsdienstleistern ermöglicht, Ladepunkte bei dem Auftragnehmer und mindestens einem weiteren Ladepunktbetreiber zu reservieren. | G38: =IF($R38="","",INDEX(Anforderungen!$I:$I,$R38)) -> Autostrom+ | H38: =IF($R38="","",INDEX(Anforderungen!$J:$J,$R38)) -> Anbindung | I38: =IF($R38="","",INDEX(Anforderungen!$K:$K,$R38)) -> bewertet | J38: =IF($R38="","",INDEX(Anforderungen!$L:$L,$R38)) -> 0 | K38: =IF($R38="","",INDEX(Anforderungen!$M:$M,$R38)) -> 0 | R38: =IFERROR(MATCH(ROWS($A$14:$A38),$T$7:$T$2000,0)+6,"") -> 31 | T38: =IF(Anforderungen!$B38="","",IF(AND(OR($B5="(alle)",Anforderungen!$K38=$B5),OR($E5="(alle)",Anforderungen!$C38=$E5),OR($H5="(alle)",Anforderungen!$E38=$H5),OR($B7="(alle)",ISNUMBER(SEARCH($B7,Anforderungen!$J38))),OR($E7="(alle)",ISNUMBER(SEARCH($E7,Anforderungen!$I38))),OR($H7="",ISNUMBER(SEARCH($H7,Anforderungen!$F38&" "&Anforderungen!$G38)))),COUNT($T$6:$T37)+1,"")) -> 32
A39: =IF($R39="","",INDEX(Anforderungen!$B:$B,$R39)) -> ANF-026 | B39: =IF($R39="","",INDEX(Anforderungen!$C:$C,$R39)) -> Vertragsanlage 4 | C39: =IF($R39="","",INDEX(Anforderungen!$D:$D,$R39)) -> § 3.13.2 | D39: =IF($R39="","",INDEX(Anforderungen!$E:$E,$R39)) -> Zufahrt & Schranke | E39: =IF($R39="","",INDEX(Anforderungen!$F:$F,$R39)) -> Schrankenanlage auf Schrankeninsel | F39: =IF($R39="","",INDEX(Anforderungen!$G:$G,$R39)) -> Anforderungen an Lade-, Schrankeninseln und physische Zufahrtbeschränkungen | G39: =IF($R39="","",INDEX(Anforderungen!$I:$I,$R39)) -> Schrankenhersteller | H39: =IF($R39="","",INDEX(Anforderungen!$J:$J,$R39)) -> Schrankenanlage | I39: =IF($R39="","",INDEX(Anforderungen!$K:$K,$R39)) -> erfasst | J39: =IF($R39="","",INDEX(Anforderungen!$L:$L,$R39)) -> 46259 | K39: =IF($R39="","",INDEX(Anforderungen!$M:$M,$R39)) -> Schranke auf Schrankeninsel geplant | R39: =IFERROR(MATCH(ROWS($A$14:$A39),$T$7:$T$2000,0)+6,"") -> 32 | T39: =IF(Anforderungen!$B39="","",IF(AND(OR($B5="(alle)",Anforderungen!$K39=$B5),OR($E5="(alle)",Anforderungen!$C39=$E5),OR($H5="(alle)",Anforderungen!$E39=$H5),OR($B7="(alle)",ISNUMBER(SEARCH($B7,Anforderungen!$J39))),OR($E7="(alle)",ISNUMBER(SEARCH($E7,Anforderungen!$I39))),OR($H7="",ISNUMBER(SEARCH($H7,Anforderungen!$F39&" "&Anforderungen!$G39)))),COUNT($T$6:$T38)+1,"")) -> 33
A40: =IF($R40="","",INDEX(Anforderungen!$B:$B,$R40)) -> ANF-027 | B40: =IF($R40="","",INDEX(Anforderungen!$C:$C,$R40)) -> Vertragsanlage 4 | C40: =IF($R40="","",INDEX(Anforderungen!$D:$D,$R40)) -> § 3.13.2 (1) | D40: =IF($R40="","",INDEX(Anforderungen!$E:$E,$R40)) -> Zufahrt & Schranke | E40: =IF($R40="","",INDEX(Anforderungen!$F:$F,$R40)) -> Schranke an Einfahrt Ladepunkt und Ausfahrt Ladepunkt. Bei Schrägparken Poller? | F40: =IF($R40="","",INDEX(Anforderungen!$G:$G,$R40)) -> Für den Zweck einer geordneten Zufahrt und Abfahrt sowie zur Sicherstellung der Verfügbarkeit der Ladeinfrastruktur sind Ladeinseln, Schrankeninseln sowie physische Zufahrtsbeschränkungen zu errichten. Diese dienen der Vermeidung unbefugter Inanspruchnahmen der Ladeplätze durch nichtladende Fahrzeuge aus allen Fahrtrichtungen und gewährleisten den bestimmungsgemäßen Betrieb der Ladeinfrastruktur. | G40: =IF($R40="","",INDEX(Anforderungen!$I:$I,$R40)) -> Schrankenhersteller | H40: =IF($R40="","",INDEX(Anforderungen!$J:$J,$R40)) -> Schrankenanlage | I40: =IF($R40="","",INDEX(Anforderungen!$K:$K,$R40)) -> erfüllt | J40: =IF($R40="","",INDEX(Anforderungen!$L:$L,$R40)) -> 46259 | K40: =IF($R40="","",INDEX(Anforderungen!$M:$M,$R40)) -> Schranken auf beiden Seiten gepplant | R40: =IFERROR(MATCH(ROWS($A$14:$A40),$T$7:$T$2000,0)+6,"") -> 33 | T40: =IF(Anforderungen!$B40="","",IF(AND(OR($B5="(alle)",Anforderungen!$K40=$B5),OR($E5="(alle)",Anforderungen!$C40=$E5),OR($H5="(alle)",Anforderungen!$E40=$H5),OR($B7="(alle)",ISNUMBER(SEARCH($B7,Anforderungen!$J40))),OR($E7="(alle)",ISNUMBER(SEARCH($E7,Anforderungen!$I40))),OR($H7="",ISNUMBER(SEARCH($H7,Anforderungen!$F40&" "&Anforderungen!$G40)))),COUNT($T$6:$T39)+1,"")) -> 34
A41: =IF($R41="","",INDEX(Anforderungen!$B:$B,$R41)) -> ANF-028 | B41: =IF($R41="","",INDEX(Anforderungen!$C:$C,$R41)) -> Vertragsanlage 4 | C41: =IF($R41="","",INDEX(Anforderungen!$D:$D,$R41)) -> § 3.13.4 | D41: =IF($R41="","",INDEX(Anforderungen!$E:$E,$R41)) -> Anzeige & Beschilderung | E41: =IF($R41="","",INDEX(Anforderungen!$F:$F,$R41)) -> Darstellung statischer und dynamischer Infos. | F41: =IF($R41="","",INDEX(Anforderungen!$G:$G,$R41)) -> Jeder Ladeplatz ist mit einer Kennzeichnung bzw. Anzeige mit folgenden Informationen auszurüsten: - Ladeplatznummer (Schild mit schwarzer Nummer auf weißem retroreflektierendem Hintergrund mit der Reflektionsklasse RA1 A) - Dynamische Anzeige mit - Typ des Ladeplatzes (MCS, CCS-Zwischenladen, CCS-Übernachtladen) - Leistung der Ladesäule - Status (verfügbar, reserviert ab XX:XX Uhr, belegt, außer Betrieb) - optional: Kennzeichen/Reservierungsnummer - Der Status des Ladeplatzes ist zusätzlich zur dynamischen Anzeige über eine farbcodierte Statuskennzeichnung darzustellen (Grün = verfügbar, Gelb = reserviert, Rot = belegt / außer Betrieb). Die farbcodierte Kennzeichnung dient der optischen Erkennbarkeit des Betriebszustands, insbesondere bei Ausfall der digitalen Anzeige. Die Platzierung der Kennzeichnung und Anzeigen hat bei Parkständen in Schrägaufstellung gut sichtbar auf der Schrankeninsel zu erfolgen. Die Platzierung der Kennzeichnung und Anzeigen hat bei Parkständen in Längsaufstellung gut sichtbar, dem entsprechenden Ladeplatz zugehörig im Bereich der Ladeinsel bzw. Ladesäule zu erfolgen. Weitere Anforderungen im Zusammenhang mit dynamischen Anzeigen sind der Vertragsanlage 6: Anforderungen an die Ladeinfrastruktur zu entnehmen. | G41: =IF($R41="","",INDEX(Anforderungen!$I:$I,$R41)) -> eRound / SCS | H41: =IF($R41="","",INDEX(Anforderungen!$J:$J,$R41)) -> Dynamische Anzeige | I41: =IF($R41="","",INDEX(Anforderungen!$K:$K,$R41)) -> erfüllt | J41: =IF($R41="","",INDEX(Anforderungen!$L:$L,$R41)) -> 46259 | K41: =IF($R41="","",INDEX(Anforderungen!$M:$M,$R41)) -> LIS zeigt Zustand an, Rest auf Anzeige | R41: =IFERROR(MATCH(ROWS($A$14:$A41),$T$7:$T$2000,0)+6,"") -> 34 | T41: =IF(Anforderungen!$B41="","",IF(AND(OR($B5="(alle)",Anforderungen!$K41=$B5),OR($E5="(alle)",Anforderungen!$C41=$E5),OR($H5="(alle)",Anforderungen!$E41=$H5),OR($B7="(alle)",ISNUMBER(SEARCH($B7,Anforderungen!$J41))),OR($E7="(alle)",ISNUMBER(SEARCH($E7,Anforderungen!$I41))),OR($H7="",ISNUMBER(SEARCH($H7,Anforderungen!$F41&" "&Anforderungen!$G41)))),COUNT($T$6:$T40)+1,"")) -> 35
A42: =IF($R42="","",INDEX(Anforderungen!$B:$B,$R42)) -> ANF-029 | B42: =IF($R42="","",INDEX(Anforderungen!$C:$C,$R42)) -> Vertragsanlage 4 | C42: =IF($R42="","",INDEX(Anforderungen!$D:$D,$R42)) -> § 3.13.5 | D42: =IF($R42="","",INDEX(Anforderungen!$E:$E,$R42)) -> Zufahrt & Schranke | E42: =IF($R42="","",INDEX(Anforderungen!$F:$F,$R42)) -> 0 | F42: =IF($R42="","",INDEX(Anforderungen!$G:$G,$R42)) -> Zur Gewährleistung eines sicheren und zuverlässigen Betriebs sind Schrankenanlagen und automatische Poller gemäß den folgenden technischen Anforderungen auszuführen: - robuste Witterungsbeständige und korrosionsgeschützte Ausführung für den ganzjährigen Einsatz im Außenbereich - automatisches Öffnen nach Abschluss des Ladevorgangs oder bei entsprechender Systemfreigabe - Erkennung der Fahrzeugposition sowie von Hindernissen vor dem Schließvorgang zur Vermeidung von Kollisionen - manuelle Notentriegelung durch autorisiertes Personal, um die Betriebsfähigkeit auch im Stör- oder Spannungsfall sicherzustellen - Integration in das zentrale Steuerungssystem (Backend oder lokales Steuergerät) zur Überwachung, Steuerung und Protokollierung der Schranken- und Pollerfunktionen - Schrankenbäume sind gemäß geltender Vorschriften mit rot-weißer Schraffierung zu kennzeichnen - Ausstattung von Schrankenbäumen und automatischen Pollern mit integrierter Beleuchtung zur Verbesserung der Sichtbarkeit und Betriebssicherheit; dabei sind die Vorgaben zur Blendwirkung gemäß ERS zu beachten Weitere Anforderungen für den Betrieb der Schranken sind der Vertragsanlage 6: Anforderungen an die Ladeinfrastruktur zu entnehmen. | G42: =IF($R42="","",INDEX(Anforderungen!$I:$I,$R42)) -> Schrankenhersteller / SCS / eRound | H42: =IF($R42="","",INDEX(Anforderungen!$J:$J,$R42)) -> Schrankenanlage | I42: =IF($R42="","",INDEX(Anforderungen!$K:$K,$R42)) -> erfüllt | J42: =IF($R42="","",INDEX(Anforderungen!$L:$L,$R42)) -> 46260 | K42: =IF($R42="","",INDEX(Anforderungen!$M:$M,$R42)) -> Sicherheitseinrichtung geplant LED in Schrankenbaum geplant Integration des Schrankenstatus in eRound | R42: =IFERROR(MATCH(ROWS($A$14:$A42),$T$7:$T$2000,0)+6,"") -> 35 | T42: =IF(Anforderungen!$B42="","",IF(AND(OR($B5="(alle)",Anforderungen!$K42=$B5),OR($E5="(alle)",Anforderungen!$C42=$E5),OR($H5="(alle)",Anforderungen!$E42=$H5),OR($B7="(alle)",ISNUMBER(SEARCH($B7,Anforderungen!$J42))),OR($E7="(alle)",ISNUMBER(SEARCH($E7,Anforderungen!$I42))),OR($H7="",ISNUMBER(SEARCH($H7,Anforderungen!$F42&" "&Anforderungen!$G42)))),COUNT($T$6:$T41)+1,"")) -> 36
A43: =IF($R43="","",INDEX(Anforderungen!$B:$B,$R43)) -> ANF-030 | B43: =IF($R43="","",INDEX(Anforderungen!$C:$C,$R43)) -> Vertragsanlage 4 | C43: =IF($R43="","",INDEX(Anforderungen!$D:$D,$R43)) -> § 3.13.2.2 | D43: =IF($R43="","",INDEX(Anforderungen!$E:$E,$R43)) -> Zufahrt & Schranke | E43: =IF($R43="","",INDEX(Anforderungen!$F:$F,$R43)) -> 0 | F43: =IF($R43="","",INDEX(Anforderungen!$G:$G,$R43)) -> Bei Parkständen in Längsaufstellung sind automatisch versenkbare Poller zur Zufahrtsbeschränkung vorzusehen. Pro Parkstand sind drei Poller so anzuordnen, dass Fehlbelegungen ausgeschlossen sind. Die Abstände der Poller untereinander sowie zur Fahrgasse ergeben sich aus der Referenzplanung (Anhang 1a: Referenzplanung Längs- und Schrägparken). Das Ein- und Ausfahren zum Ladeplatz muss jederzeit gewährleistet bleiben, auch wenn die benachbarten Stellplätze durch ausgefahrene Poller gesichert sind. Die Dauer der Öffnungs- und Schließvorgänge ist auf das technisch mögliche Minimum zu begrenzen, um einen unterbrechungsarmen Verkehrsfluss sicherzustellen. Die Regelbreite der Parkstände muss 4,50 m betragen, die Länge entspricht den Vorgaben gemäß ERS für Längsparker von 25,00 m. Ergeben sich aufgrund der örtlichen Bestandsituation Abweichungen von der Regelbreite, ist die Befahrbarkeit stets durch einen Schleppkurvennachweis zu belegen. Die Poller sind elektrisch oder hydraulisch versenkbar auszuführen und müssen über eine automatische Höhenverstellung verfügen. Das Absenken erfolgt im Regelbetrieb ausschließlich bei autorisiertem Zugang (Ladevorgang oder Reservierung). Nach Beendigung des Ladevorgangs und nach erfolgter Ausfahrt des Fahrzeuges müssen sich Poller automatisch wieder heben. Eine Notabsenkung bei Ausfall muss durch autorisiertes Personal jederzeit möglich sein. Die Poller müssen widerstandsfähig gegen Anprall und sonstige auf Rastplätzen zu erwartende Einwirkungen sein sowie frost- und salzbeständig ausgeführt werden. Zudem ist ein Schutz gegen Fremdsteuerung und Manipulation sicherzustellen. Die Steuerung der Poller muss in das übergeordnete Zugangskontrollsystem integrierbar sein. Die Erkennbarkeit des Hindernissesist stets sicherzustellen. Die Poller sind zu beleuchten. Die Ladesäule ist im Randbereich des Stellplatzes in einem praktikablen Abstand zum fahrzeugseitigen Ladeanschluss zu positionieren. Die Fläche um die Ladesäule ist in Betonbauweise auszuführen und mit zweckdienlichen Mitteln gegen Anprall und sonstige übliche Einwirkungen auf Rastplätzen zu sichern. Befindet sich im Randbereich bereits eine Bordanlage, ist eine zusätzliche Hochbordabsicherung der Ladesäule nicht erforderlich. In allen übrigen Fällen ist, neben einem Anprallschutz, eine ausreichend dimensionierte Ladeinsel zum Schutz der Ladeinfrastruktur vorzusehen. | G43: =IF($R43="","",INDEX(Anforderungen!$I:$I,$R43)) -> Autostrom+ | H43: =IF($R43="","",INDEX(Anforderungen!$J:$J,$R43)) -> – | I43: =IF($R43="","",INDEX(Anforderungen!$K:$K,$R43)) -> trifft nicht zu | J43: =IF($R43="","",INDEX(Anforderungen!$L:$L,$R43)) -> 45894 | K43: =IF($R43="","",INDEX(Anforderungen!$M:$M,$R43)) -> Los 2 hat keine Poller - betrifft nur längsparkplätze | R43: =IFERROR(MATCH(ROWS($A$14:$A43),$T$7:$T$2000,0)+6,"") -> 36 | T43: =IF(Anforderungen!$B43="","",IF(AND(OR($B5="(alle)",Anforderungen!$K43=$B5),OR($E5="(alle)",Anforderungen!$C43=$E5),OR($H5="(alle)",Anforderungen!$E43=$H5),OR($B7="(alle)",ISNUMBER(SEARCH($B7,Anforderungen!$J43))),OR($E7="(alle)",ISNUMBER(SEARCH($E7,Anforderungen!$I43))),OR($H7="",ISNUMBER(SEARCH($H7,Anforderungen!$F43&" "&Anforderungen!$G43)))),COUNT($T$6:$T42)+1,"")) -> 37
A44: =IF($R44="","",INDEX(Anforderungen!$B:$B,$R44)) -> ANF-031 | B44: =IF($R44="","",INDEX(Anforderungen!$C:$C,$R44)) -> Vertragsanlage 4 | C44: =IF($R44="","",INDEX(Anforderungen!$D:$D,$R44)) -> § 3.6 | D44: =IF($R44="","",INDEX(Anforderungen!$E:$E,$R44)) -> Bau & Dokumentation | E44: =IF($R44="","",INDEX(Anforderungen!$F:$F,$R44)) -> 0 | F44: =IF($R44="","",INDEX(Anforderungen!$G:$G,$R44)) -> Antrag auf Baufreigabe und Ausführungs-, Werk- und Montageplanung | G44: =IF($R44="","",INDEX(Anforderungen!$I:$I,$R44)) -> Autostrom+ | H44: =IF($R44="","",INDEX(Anforderungen!$J:$J,$R44)) -> – | I44: =IF($R44="","",INDEX(Anforderungen!$K:$K,$R44)) -> bewertet | J44: =IF($R44="","",INDEX(Anforderungen!$L:$L,$R44)) -> 0 | K44: =IF($R44="","",INDEX(Anforderungen!$M:$M,$R44)) -> 0 | R44: =IFERROR(MATCH(ROWS($A$14:$A44),$T$7:$T$2000,0)+6,"") -> 37 | T44: =IF(Anforderungen!$B44="","",IF(AND(OR($B5="(alle)",Anforderungen!$K44=$B5),OR($E5="(alle)",Anforderungen!$C44=$E5),OR($H5="(alle)",Anforderungen!$E44=$H5),OR($B7="(alle)",ISNUMBER(SEARCH($B7,Anforderungen!$J44))),OR($E7="(alle)",ISNUMBER(SEARCH($E7,Anforderungen!$I44))),OR($H7="",ISNUMBER(SEARCH($H7,Anforderungen!$F44&" "&Anforderungen!$G44)))),COUNT($T$6:$T43)+1,"")) -> 38
A45: =IF($R45="","",INDEX(Anforderungen!$B:$B,$R45)) -> ANF-032 | B45: =IF($R45="","",INDEX(Anforderungen!$C:$C,$R45)) -> Vertragsanlage 4 | C45: =IF($R45="","",INDEX(Anforderungen!$D:$D,$R45)) -> § 3.7 | D45: =IF($R45="","",INDEX(Anforderungen!$E:$E,$R45)) -> Bau & Dokumentation | E45: =IF($R45="","",INDEX(Anforderungen!$F:$F,$R45)) -> 0 | F45: =IF($R45="","",INDEX(Anforderungen!$G:$G,$R45)) -> Bestandsunterlagen (As-Built) | G45: =IF($R45="","",INDEX(Anforderungen!$I:$I,$R45)) -> Autostrom+ | H45: =IF($R45="","",INDEX(Anforderungen!$J:$J,$R45)) -> – | I45: =IF($R45="","",INDEX(Anforderungen!$K:$K,$R45)) -> bewertet | J45: =IF($R45="","",INDEX(Anforderungen!$L:$L,$R45)) -> 0 | K45: =IF($R45="","",INDEX(Anforderungen!$M:$M,$R45)) -> 0 | R45: =IFERROR(MATCH(ROWS($A$14:$A45),$T$7:$T$2000,0)+6,"") -> 38 | T45: =IF(Anforderungen!$B45="","",IF(AND(OR($B5="(alle)",Anforderungen!$K45=$B5),OR($E5="(alle)",Anforderungen!$C45=$E5),OR($H5="(alle)",Anforderungen!$E45=$H5),OR($B7="(alle)",ISNUMBER(SEARCH($B7,Anforderungen!$J45))),OR($E7="(alle)",ISNUMBER(SEARCH($E7,Anforderungen!$I45))),OR($H7="",ISNUMBER(SEARCH($H7,Anforderungen!$F45&" "&Anforderungen!$G45)))),COUNT($T$6:$T44)+1,"")) -> 39
A46: =IF($R46="","",INDEX(Anforderungen!$B:$B,$R46)) -> ANF-033 | B46: =IF($R46="","",INDEX(Anforderungen!$C:$C,$R46)) -> Vertragsanlage 6 | C46: =IF($R46="","",INDEX(Anforderungen!$D:$D,$R46)) -> § 8 | D46: =IF($R46="","",INDEX(Anforderungen!$E:$E,$R46)) -> Authentifizierung & Zugang | E46: =IF($R46="","",INDEX(Anforderungen!$F:$F,$R46)) -> Öffnung innerhalb von 45 Sekunden. | F46: =IF($R46="","",INDEX(Anforderungen!$G:$G,$R46)) -> Folgende Authentifizierungsoptionen (Anmeldung, Freischaltung der physischen Zufahrtsbeschränkungen und Start des Ladevorgangs etc.) müssen möglich sein: ▪ RFID-Token (Ladekarte etc.) von vertraglich angebundenen Mobilitätsdienstleister, ▪ App von vertraglich angebundenen Mobilitätsdienstleister, ▪ Ad hoc-Laden ohne Registrierung und ▪ ISO 15118 (nach Verfügbarkeit – s. o. Abschnitt 7.). Der Authentifizierungsvorgang zur Freigabe des Ladeplatzes muss innerhalb von maximal 45 Sekunden abgeschlossen sein und sollte so gestaltet sein, dass der Verkehrsfluss möglichst wenig beeinträchtigt wird. Die angegebene Zeitspanne umfasst alle praktische und technische Schritte der Authentifizierung bis zur Öffnung der Schranke bzw. des Pollers und gilt für alle vorgesehenen Zugangsarten | G46: =IF($R46="","",INDEX(Anforderungen!$I:$I,$R46)) -> eRound / SCS | H46: =IF($R46="","",INDEX(Anforderungen!$J:$J,$R46)) -> Authentifizierungskomponente / Schrankensteuerung | I46: =IF($R46="","",INDEX(Anforderungen!$K:$K,$R46)) -> erfasst | J46: =IF($R46="","",INDEX(Anforderungen!$L:$L,$R46)) -> 0 | K46: =IF($R46="","",INDEX(Anforderungen!$M:$M,$R46)) -> 0 | R46: =IFERROR(MATCH(ROWS($A$14:$A46),$T$7:$T$2000,0)+6,"") -> 39 | T46: =IF(Anforderungen!$B46="","",IF(AND(OR($B5="(alle)",Anforderungen!$K46=$B5),OR($E5="(alle)",Anforderungen!$C46=$E5),OR($H5="(alle)",Anforderungen!$E46=$H5),OR($B7="(alle)",ISNUMBER(SEARCH($B7,Anforderungen!$J46))),OR($E7="(alle)",ISNUMBER(SEARCH($E7,Anforderungen!$I46))),OR($H7="",ISNUMBER(SEARCH($H7,Anforderungen!$F46&" "&Anforderungen!$G46)))),COUNT($T$6:$T45)+1,"")) -> 40
A47: =IF($R47="","",INDEX(Anforderungen!$B:$B,$R47)) -> ANF-034 | B47: =IF($R47="","",INDEX(Anforderungen!$C:$C,$R47)) -> Vertragsanlage 6 | C47: =IF($R47="","",INDEX(Anforderungen!$D:$D,$R47)) -> § 9 (1) | D47: =IF($R47="","",INDEX(Anforderungen!$E:$E,$R47)) -> Belegungsdetektion | E47: =IF($R47="","",INDEX(Anforderungen!$F:$F,$R47)) -> Belegungsdetektion ist gefordert. | F47: =IF($R47="","",INDEX(Anforderungen!$G:$G,$R47)) -> Jeder MCS- / CCS-Ladepunkt muss über eine Detektion verfügen. Die MCS- / CCSLadeplatzdetektion ist so auszustatten, dass Objekte auf dem zum MCS- / CCSLadepunkt gehörigen MCS- / CCS-Ladeplatz detektiert werden können. | G47: =IF($R47="","",INDEX(Anforderungen!$I:$I,$R47)) -> Schrankenhersteller / SCS | H47: =IF($R47="","",INDEX(Anforderungen!$J:$J,$R47)) -> Belegungsdetektion | I47: =IF($R47="","",INDEX(Anforderungen!$K:$K,$R47)) -> erfüllt | J47: =IF($R47="","",INDEX(Anforderungen!$L:$L,$R47)) -> 46259 | K47: =IF($R47="","",INDEX(Anforderungen!$M:$M,$R47)) -> Radarsensor stellt Belegung der Ladesäule bereit | R47: =IFERROR(MATCH(ROWS($A$14:$A47),$T$7:$T$2000,0)+6,"") -> 40 | T47: =IF(Anforderungen!$B47="","",IF(AND(OR($B5="(alle)",Anforderungen!$K47=$B5),OR($E5="(alle)",Anforderungen!$C47=$E5),OR($H5="(alle)",Anforderungen!$E47=$H5),OR($B7="(alle)",ISNUMBER(SEARCH($B7,Anforderungen!$J47))),OR($E7="(alle)",ISNUMBER(SEARCH($E7,Anforderungen!$I47))),OR($H7="",ISNUMBER(SEARCH($H7,Anforderungen!$F47&" "&Anforderungen!$G47)))),COUNT($T$6:$T46)+1,"")) -> 41
A48: =IF($R48="","",INDEX(Anforderungen!$B:$B,$R48)) -> ANF-035 | B48: =IF($R48="","",INDEX(Anforderungen!$C:$C,$R48)) -> Vertragsanlage 6 | C48: =IF($R48="","",INDEX(Anforderungen!$D:$D,$R48)) -> § 9 (2) | D48: =IF($R48="","",INDEX(Anforderungen!$E:$E,$R48)) -> Belegungsdetektion | E48: =IF($R48="","",INDEX(Anforderungen!$F:$F,$R48)) -> Roaming-Infos müssen veröffentlicht werden Pönalisierung gefordert. Entfernung Falschparker gefordert. | F48: =IF($R48="","",INDEX(Anforderungen!$G:$G,$R48)) -> Die Information der Reservierung des MCS- / CCS-Ladepunkts muss dem IT-Backend der MCS- / CCS-Ladeeinrichtung zur Verfügung stehen und muss angebundenen Mobilitätsdienstleistern und Betreibern von Online-Plattformen zur Darstellung von Statusinformationen zur Verfügung gestellt werden. Zudem soll dem Betreiber die Pönalisierung und Entfernung von Falschparkern ermöglicht werden. | G48: =IF($R48="","",INDEX(Anforderungen!$I:$I,$R48)) -> eRound / SCS | H48: =IF($R48="","",INDEX(Anforderungen!$J:$J,$R48)) -> OCPI Buchungskalender / Kennzeichenerfassung / Pönalisierungssystem | I48: =IF($R48="","",INDEX(Anforderungen!$K:$K,$R48)) -> erfasst | J48: =IF($R48="","",INDEX(Anforderungen!$L:$L,$R48)) -> 0 | K48: =IF($R48="","",INDEX(Anforderungen!$M:$M,$R48)) -> 0 | R48: =IFERROR(MATCH(ROWS($A$14:$A48),$T$7:$T$2000,0)+6,"") -> 41 | T48: =IF(Anforderungen!$B48="","",IF(AND(OR($B5="(alle)",Anforderungen!$K48=$B5),OR($E5="(alle)",Anforderungen!$C48=$E5),OR($H5="(alle)",Anforderungen!$E48=$H5),OR($B7="(alle)",ISNUMBER(SEARCH($B7,Anforderungen!$J48))),OR($E7="(alle)",ISNUMBER(SEARCH($E7,Anforderungen!$I48))),OR($H7="",ISNUMBER(SEARCH($H7,Anforderungen!$F48&" "&Anforderungen!$G48)))),COUNT($T$6:$T47)+1,"")) -> 42
A49: =IF($R49="","",INDEX(Anforderungen!$B:$B,$R49)) -> ANF-036 | B49: =IF($R49="","",INDEX(Anforderungen!$C:$C,$R49)) -> Vertragsanlage 6 | C49: =IF($R49="","",INDEX(Anforderungen!$D:$D,$R49)) -> § 10 (1) | D49: =IF($R49="","",INDEX(Anforderungen!$E:$E,$R49)) -> Zufahrt & Schranke | E49: =IF($R49="","",INDEX(Anforderungen!$F:$F,$R49)) -> Einfahrtsschranke Ausfahrtsschranke Bei Nichtbelegung beide Schranken geschlossen. | F49: =IF($R49="","",INDEX(Anforderungen!$G:$G,$R49)) -> Jeder Ladeplatz ist mit einer Einfahrts- und einer Ausfahrtsschranke auszustatten. Die Schranken sind wie folgt zu betreiben: 1) Grundstellung: Beide Schranken sind bei Nichtbelegung des Ladeplatzes geschlossen. | G49: =IF($R49="","",INDEX(Anforderungen!$I:$I,$R49)) -> Schrankenhersteller | H49: =IF($R49="","",INDEX(Anforderungen!$J:$J,$R49)) -> Schrankensteuerung | I49: =IF($R49="","",INDEX(Anforderungen!$K:$K,$R49)) -> erfüllt | J49: =IF($R49="","",INDEX(Anforderungen!$L:$L,$R49)) -> 46259 | K49: =IF($R49="","",INDEX(Anforderungen!$M:$M,$R49)) -> Schranke wird konfiguriert, sodass diese zu ist | R49: =IFERROR(MATCH(ROWS($A$14:$A49),$T$7:$T$2000,0)+6,"") -> 42 | T49: =IF(Anforderungen!$B49="","",IF(AND(OR($B5="(alle)",Anforderungen!$K49=$B5),OR($E5="(alle)",Anforderungen!$C49=$E5),OR($H5="(alle)",Anforderungen!$E49=$H5),OR($B7="(alle)",ISNUMBER(SEARCH($B7,Anforderungen!$J49))),OR($E7="(alle)",ISNUMBER(SEARCH($E7,Anforderungen!$I49))),OR($H7="",ISNUMBER(SEARCH($H7,Anforderungen!$F49&" "&Anforderungen!$G49)))),COUNT($T$6:$T48)+1,"")) -> 43
A50: =IF($R50="","",INDEX(Anforderungen!$B:$B,$R50)) -> ANF-037 | B50: =IF($R50="","",INDEX(Anforderungen!$C:$C,$R50)) -> Vertragsanlage 6 | C50: =IF($R50="","",INDEX(Anforderungen!$D:$D,$R50)) -> § 10 (2) | D50: =IF($R50="","",INDEX(Anforderungen!$E:$E,$R50)) -> Zufahrt & Schranke | E50: =IF($R50="","",INDEX(Anforderungen!$F:$F,$R50)) -> Einfahrtsschranke öffnet nach Authentifizierung. | F50: =IF($R50="","",INDEX(Anforderungen!$G:$G,$R50)) -> 2) Einfahrt: Die Einfahrtschranke öffnet sich nach erfolgreicher Authentifizierung und gewährt Zugang zum Ladeplatz. Sie bleibt während des gesamten Ladevorgangs geöffnet. | G50: =IF($R50="","",INDEX(Anforderungen!$I:$I,$R50)) -> eRound / SCS | H50: =IF($R50="","",INDEX(Anforderungen!$J:$J,$R50)) -> Authentifizierungskomponente / Schrankensteuerung | I50: =IF($R50="","",INDEX(Anforderungen!$K:$K,$R50)) -> erfüllt | J50: =IF($R50="","",INDEX(Anforderungen!$L:$L,$R50)) -> 46259 | K50: =IF($R50="","",INDEX(Anforderungen!$M:$M,$R50)) -> Radarsensor erkennt Einfahrt bleibt geöffnet bis die Zone wieder frei ist. | R50: =IFERROR(MATCH(ROWS($A$14:$A50),$T$7:$T$2000,0)+6,"") -> 43 | T50: =IF(Anforderungen!$B50="","",IF(AND(OR($B5="(alle)",Anforderungen!$K50=$B5),OR($E5="(alle)",Anforderungen!$C50=$E5),OR($H5="(alle)",Anforderungen!$E50=$H5),OR($B7="(alle)",ISNUMBER(SEARCH($B7,Anforderungen!$J50))),OR($E7="(alle)",ISNUMBER(SEARCH($E7,Anforderungen!$I50))),OR($H7="",ISNUMBER(SEARCH($H7,Anforderungen!$F50&" "&Anforderungen!$G50)))),COUNT($T$6:$T49)+1,"")) -> 44
A51: =IF($R51="","",INDEX(Anforderungen!$B:$B,$R51)) -> ANF-038 | B51: =IF($R51="","",INDEX(Anforderungen!$C:$C,$R51)) -> Vertragsanlage 6 | C51: =IF($R51="","",INDEX(Anforderungen!$D:$D,$R51)) -> § 10 (3) | D51: =IF($R51="","",INDEX(Anforderungen!$E:$E,$R51)) -> Zufahrt & Schranke | E51: =IF($R51="","",INDEX(Anforderungen!$F:$F,$R51)) -> Ausfahrtsschranke öffnet bei Ankunft LKW. | F51: =IF($R51="","",INDEX(Anforderungen!$G:$G,$R51)) -> 3) Ausfahrtsschaltung: Sobald der Lkw seine Parkposition auf dem Ladeplatz erreicht hat, öffnet sich die Ausfahrtsschranke. | G51: =IF($R51="","",INDEX(Anforderungen!$I:$I,$R51)) -> Schrankenhersteller / SCS | H51: =IF($R51="","",INDEX(Anforderungen!$J:$J,$R51)) -> Schrankensteuerung | I51: =IF($R51="","",INDEX(Anforderungen!$K:$K,$R51)) -> erfüllt | J51: =IF($R51="","",INDEX(Anforderungen!$L:$L,$R51)) -> 46259 | K51: =IF($R51="","",INDEX(Anforderungen!$M:$M,$R51)) -> Die Schranke kann selbstständig öffnen und schließen | R51: =IFERROR(MATCH(ROWS($A$14:$A51),$T$7:$T$2000,0)+6,"") -> 44 | T51: =IF(Anforderungen!$B51="","",IF(AND(OR($B5="(alle)",Anforderungen!$K51=$B5),OR($E5="(alle)",Anforderungen!$C51=$E5),OR($H5="(alle)",Anforderungen!$E51=$H5),OR($B7="(alle)",ISNUMBER(SEARCH($B7,Anforderungen!$J51))),OR($E7="(alle)",ISNUMBER(SEARCH($E7,Anforderungen!$I51))),OR($H7="",ISNUMBER(SEARCH($H7,Anforderungen!$F51&" "&Anforderungen!$G51)))),COUNT($T$6:$T50)+1,"")) -> 45
A52: =IF($R52="","",INDEX(Anforderungen!$B:$B,$R52)) -> ANF-039 | B52: =IF($R52="","",INDEX(Anforderungen!$C:$C,$R52)) -> Vertragsanlage 6 | C52: =IF($R52="","",INDEX(Anforderungen!$D:$D,$R52)) -> § 10 (4) | D52: =IF($R52="","",INDEX(Anforderungen!$E:$E,$R52)) -> Zufahrt & Schranke | E52: =IF($R52="","",INDEX(Anforderungen!$F:$F,$R52)) -> Ausfahrtsschranke schließt nach Verlassen des LKW. Fernsteuerung der Schranken. | F52: =IF($R52="","",INDEX(Anforderungen!$G:$G,$R52)) -> 4) Verlassen des Ladeplatzes: Nach Abschluss des Ladevorgangs und dem Verlassen des Ladeplatzes schließt sich die Ausfahrtsschranke wieder. Zudem ist dafür zu sorgen, dass die Einfahrts- und Ausfahrtsschranken im Notfall geöffnet werden können | G52: =IF($R52="","",INDEX(Anforderungen!$I:$I,$R52)) -> Schrankenhersteller | H52: =IF($R52="","",INDEX(Anforderungen!$J:$J,$R52)) -> Schrankensteuerung | I52: =IF($R52="","",INDEX(Anforderungen!$K:$K,$R52)) -> erfüllt | J52: =IF($R52="","",INDEX(Anforderungen!$L:$L,$R52)) -> 46259 | K52: =IF($R52="","",INDEX(Anforderungen!$M:$M,$R52)) -> Schranke schließt von alleine | R52: =IFERROR(MATCH(ROWS($A$14:$A52),$T$7:$T$2000,0)+6,"") -> 45 | T52: =IF(Anforderungen!$B52="","",IF(AND(OR($B5="(alle)",Anforderungen!$K52=$B5),OR($E5="(alle)",Anforderungen!$C52=$E5),OR($H5="(alle)",Anforderungen!$E52=$H5),OR($B7="(alle)",ISNUMBER(SEARCH($B7,Anforderungen!$J52))),OR($E7="(alle)",ISNUMBER(SEARCH($E7,Anforderungen!$I52))),OR($H7="",ISNUMBER(SEARCH($H7,Anforderungen!$F52&" "&Anforderungen!$G52)))),COUNT($T$6:$T51)+1,"")) -> 46
A53: =IF($R53="","",INDEX(Anforderungen!$B:$B,$R53)) -> ANF-040 | B53: =IF($R53="","",INDEX(Anforderungen!$C:$C,$R53)) -> Vertragsanlage 6 | C53: =IF($R53="","",INDEX(Anforderungen!$D:$D,$R53)) -> § 4 | D53: =IF($R53="","",INDEX(Anforderungen!$E:$E,$R53)) -> Anzeige & Beschilderung | E53: =IF($R53="","",INDEX(Anforderungen!$F:$F,$R53)) -> Bezahlterminal für mehrere MCS/CCS Ladepunkte möglich. | F53: =IF($R53="","",INDEX(Anforderungen!$G:$G,$R53)) -> Display zur Anzeige von Informationen zum Ladevorgang (Ad hoc-Preis des CPO, geladene Energiemenge in kWh, Blockadeentgelt, Anweisungen zum Ablauf des Ladens). ▪ Das Display muss sowohl bei Tageslicht unter Sonneneinstrahlung als auch bei Dunkelheit gut ablesbar sein. ▪ Die Menüführung erfolgt mindestens in den Sprachen Deutsch und Englisch. ▪ RFID-Multireader zum Lesen von allen gängigen und zukünftig erwartbaren Ladekarten von Fahrstromanbietern (z.B. unter Berücksichtigung VDE-AR-E 2532-100) zum Authentifizieren und Starten von Ladevorgängen. Bezahlterminal für das Bezahlen von Ad hoc-Ladevorgängen (ohne Dauerschuldverhältnis). Dieses muss bargeldlose Zahlungen entsprechend den Vorgaben der AFIR ermöglichen. Zusätzliche Authentifizierungs- und Zahlungsmöglichkeiten können den Nutzern kostenlos eingeräumt werden. Dabei ist NFC-Technologie (Nahfeldkommunikation) und PinEingabe erforderlich. Von der Möglichkeit einer Pin-Eingabe kann abgesehen werden, wenn die Notwendigkeit der Pin-Eingabe dauerhaft bei allen relevanten Karten, insbesondere bei Präsentation einer physischen Karte zum Bezahlen von Fahrstrom entfällt. ▪ Ein Bezahlterminal kann auch zur Bezahlung von Ladevorgängen mehrerer MCS- bzw. CCS-Ladeeinrichtungen bzw. -Ladepunkten dienen | G53: =IF($R53="","",INDEX(Anforderungen!$I:$I,$R53)) -> eRound | H53: =IF($R53="","",INDEX(Anforderungen!$J:$J,$R53)) -> Authentifizierungskomponente | I53: =IF($R53="","",INDEX(Anforderungen!$K:$K,$R53)) -> erfüllt | J53: =IF($R53="","",INDEX(Anforderungen!$L:$L,$R53)) -> 46259 | K53: =IF($R53="","",INDEX(Anforderungen!$M:$M,$R53)) -> Jede LIS hat ein Display, rest in KANN-Anforderung | R53: =IFERROR(MATCH(ROWS($A$14:$A53),$T$7:$T$2000,0)+6,"") -> 46 | T53: =IF(Anforderungen!$B53="","",IF(AND(OR($B5="(alle)",Anforderungen!$K53=$B5),OR($E5="(alle)",Anforderungen!$C53=$E5),OR($H5="(alle)",Anforderungen!$E53=$H5),OR($B7="(alle)",ISNUMBER(SEARCH($B7,Anforderungen!$J53))),OR($E7="(alle)",ISNUMBER(SEARCH($E7,Anforderungen!$I53))),OR($H7="",ISNUMBER(SEARCH($H7,Anforderungen!$F53&" "&Anforderungen!$G53)))),COUNT($T$6:$T52)+1,"")) -> 47
A54: =IF($R54="","",INDEX(Anforderungen!$B:$B,$R54)) -> ANF-041 | B54: =IF($R54="","",INDEX(Anforderungen!$C:$C,$R54)) -> Vertragsanlage 10 | C54: =IF($R54="","",INDEX(Anforderungen!$D:$D,$R54)) -> § 3.1 | D54: =IF($R54="","",INDEX(Anforderungen!$E:$E,$R54)) -> Monitoring & Reporting | E54: =IF($R54="","",INDEX(Anforderungen!$F:$F,$R54)) -> Benennung Datenpunkte zu Reservierungen im Monatsbericht. | F54: =IF($R54="","",INDEX(Anforderungen!$G:$G,$R54)) -> ab_total_reservations Anzahl Reservierungen je Ladepunkt ab_total_reservations_cancelled Anzahl stornierter Reservierungen je Ladepunkt ab_reservations_no-show Anzahl nicht eingehaltener Reservierungen je Ladepunkt | G54: =IF($R54="","",INDEX(Anforderungen!$I:$I,$R54)) -> eRound | H54: =IF($R54="","",INDEX(Anforderungen!$J:$J,$R54)) -> Monitoring | I54: =IF($R54="","",INDEX(Anforderungen!$K:$K,$R54)) -> trifft nicht zu | J54: =IF($R54="","",INDEX(Anforderungen!$L:$L,$R54)) -> 0 | K54: =IF($R54="","",INDEX(Anforderungen!$M:$M,$R54)) -> Automatisch ausgewertet: Außerhalb des betrachteten Leistungsumfangs (Schranken, Kennzeichenerfassung, dynamische Anzeige). | R54: =IFERROR(MATCH(ROWS($A$14:$A54),$T$7:$T$2000,0)+6,"") -> 47 | T54: =IF(Anforderungen!$B54="","",IF(AND(OR($B5="(alle)",Anforderungen!$K54=$B5),OR($E5="(alle)",Anforderungen!$C54=$E5),OR($H5="(alle)",Anforderungen!$E54=$H5),OR($B7="(alle)",ISNUMBER(SEARCH($B7,Anforderungen!$J54))),OR($E7="(alle)",ISNUMBER(SEARCH($E7,Anforderungen!$I54))),OR($H7="",ISNUMBER(SEARCH($H7,Anforderungen!$F54&" "&Anforderungen!$G54)))),COUNT($T$6:$T53)+1,"")) -> 48
A55: =IF($R55="","",INDEX(Anforderungen!$B:$B,$R55)) -> ANF-042 | B55: =IF($R55="","",INDEX(Anforderungen!$C:$C,$R55)) -> Vertragsanlage 10 | C55: =IF($R55="","",INDEX(Anforderungen!$D:$D,$R55)) -> § 5 (d) | D55: =IF($R55="","",INDEX(Anforderungen!$E:$E,$R55)) -> Monitoring & Reporting | E55: =IF($R55="","",INDEX(Anforderungen!$F:$F,$R55)) -> Benennung Datenpunkte zu Reservierungen im Monatsbericht. | F55: =IF($R55="","",INDEX(Anforderungen!$G:$G,$R55)) -> total_reservation_cost Gesamtsumme aller Kosten im Zusammenhang mit der Reservierung eines Ladepunkts, einschließlich Festpreisbestandteilen (€) | G55: =IF($R55="","",INDEX(Anforderungen!$I:$I,$R55)) -> eRound | H55: =IF($R55="","",INDEX(Anforderungen!$J:$J,$R55)) -> Monitoring | I55: =IF($R55="","",INDEX(Anforderungen!$K:$K,$R55)) -> trifft nicht zu | J55: =IF($R55="","",INDEX(Anforderungen!$L:$L,$R55)) -> 0 | K55: =IF($R55="","",INDEX(Anforderungen!$M:$M,$R55)) -> Automatisch ausgewertet: Außerhalb des betrachteten Leistungsumfangs (Schranken, Kennzeichenerfassung, dynamische Anzeige). | R55: =IFERROR(MATCH(ROWS($A$14:$A55),$T$7:$T$2000,0)+6,"") -> 48 | T55: =IF(Anforderungen!$B55="","",IF(AND(OR($B5="(alle)",Anforderungen!$K55=$B5),OR($E5="(alle)",Anforderungen!$C55=$E5),OR($H5="(alle)",Anforderungen!$E55=$H5),OR($B7="(alle)",ISNUMBER(SEARCH($B7,Anforderungen!$J55))),OR($E7="(alle)",ISNUMBER(SEARCH($E7,Anforderungen!$I55))),OR($H7="",ISNUMBER(SEARCH($H7,Anforderungen!$F55&" "&Anforderungen!$G55)))),COUNT($T$6:$T54)+1,"")) -> 49
A56: =IF($R56="","",INDEX(Anforderungen!$B:$B,$R56)) -> ANF-043 | B56: =IF($R56="","",INDEX(Anforderungen!$C:$C,$R56)) -> Vertragsanlage 13 | C56: =IF($R56="","",INDEX(Anforderungen!$D:$D,$R56)) -> § 8 (1) | D56: =IF($R56="","",INDEX(Anforderungen!$E:$E,$R56)) -> Reservierung | E56: =IF($R56="","",INDEX(Anforderungen!$F:$F,$R56)) -> Mehrfachbuchungen unterbinden | F56: =IF($R56="","",INDEX(Anforderungen!$G:$G,$R56)) -> Grundsätzlich möchte der Auftraggeber den Nutzern eine gewisse Flexibilität ermöglichen, da die Inanspruchnahme einer Reservierung z.B. aufgrund kurzfristiger Staus auch ohne Verschulden ggf. nicht wahrgenommen werden kann. Ein missbräuchliches Verhalten durch Nutzer, z.B. durch mehrfache Reservierungsbuchungen am gleichen Standort und am gleichen Tag, ist nicht im Interesse des Auftraggebers. Sollte sich ein solches Verhalten einstellen, besteht vor dem Hintergrund eines abweichenden Marktstandards nach §23 Abs. 3 des Betreibervertrags die Möglichkeit, die definierten Mindestvoraussetzungen an Reservierungsplattformen zu ändern. | G56: =IF($R56="","",INDEX(Anforderungen!$I:$I,$R56)) -> eRound | H56: =IF($R56="","",INDEX(Anforderungen!$J:$J,$R56)) -> OCPI Buchungskalender | I56: =IF($R56="","",INDEX(Anforderungen!$K:$K,$R56)) -> trifft nicht zu | J56: =IF($R56="","",INDEX(Anforderungen!$L:$L,$R56)) -> 0 | K56: =IF($R56="","",INDEX(Anforderungen!$M:$M,$R56)) -> Automatisch ausgewertet: Außerhalb des betrachteten Leistungsumfangs (Schranken, Kennzeichenerfassung, dynamische Anzeige). | R56: =IFERROR(MATCH(ROWS($A$14:$A56),$T$7:$T$2000,0)+6,"") -> 49 | T56: =IF(Anforderungen!$B56="","",IF(AND(OR($B5="(alle)",Anforderungen!$K56=$B5),OR($E5="(alle)",Anforderungen!$C56=$E5),OR($H5="(alle)",Anforderungen!$E56=$H5),OR($B7="(alle)",ISNUMBER(SEARCH($B7,Anforderungen!$J56))),OR($E7="(alle)",ISNUMBER(SEARCH($E7,Anforderungen!$I56))),OR($H7="",ISNUMBER(SEARCH($H7,Anforderungen!$F56&" "&Anforderungen!$G56)))),COUNT($T$6:$T55)+1,"")) -> 50
A57: =IF($R57="","",INDEX(Anforderungen!$B:$B,$R57)) -> ANF-044 | B57: =IF($R57="","",INDEX(Anforderungen!$C:$C,$R57)) -> Bieterfragenkatalog | C57: =IF($R57="","",INDEX(Anforderungen!$D:$D,$R57)) -> § 351 | D57: =IF($R57="","",INDEX(Anforderungen!$E:$E,$R57)) -> Belegungsdetektion | E57: =IF($R57="","",INDEX(Anforderungen!$F:$F,$R57)) -> Belegungsdetektion ist gefordert. | F57: =IF($R57="","",INDEX(Anforderungen!$G:$G,$R57)) -> Nein, auch bei installierten Zufahrtsbeschränkungen sind Sensoren als Redundanz zum Zweck der Detektion des Belegungsstatus des Ladeplatzes vorzusehen. | G57: =IF($R57="","",INDEX(Anforderungen!$I:$I,$R57)) -> SCS | H57: =IF($R57="","",INDEX(Anforderungen!$J:$J,$R57)) -> Belegungsdetektion | I57: =IF($R57="","",INDEX(Anforderungen!$K:$K,$R57)) -> erfasst | J57: =IF($R57="","",INDEX(Anforderungen!$L:$L,$R57)) -> 0 | K57: =IF($R57="","",INDEX(Anforderungen!$M:$M,$R57)) -> 0 | R57: =IFERROR(MATCH(ROWS($A$14:$A57),$T$7:$T$2000,0)+6,"") -> 50 | T57: =IF(Anforderungen!$B57="","",IF(AND(OR($B5="(alle)",Anforderungen!$K57=$B5),OR($E5="(alle)",Anforderungen!$C57=$E5),OR($H5="(alle)",Anforderungen!$E57=$H5),OR($B7="(alle)",ISNUMBER(SEARCH($B7,Anforderungen!$J57))),OR($E7="(alle)",ISNUMBER(SEARCH($E7,Anforderungen!$I57))),OR($H7="",ISNUMBER(SEARCH($H7,Anforderungen!$F57&" "&Anforderungen!$G57)))),COUNT($T$6:$T56)+1,"")) -> 51
A58: =IF($R58="","",INDEX(Anforderungen!$B:$B,$R58)) -> ANF-045 | B58: =IF($R58="","",INDEX(Anforderungen!$C:$C,$R58)) -> Bieterfragenkatalog | C58: =IF($R58="","",INDEX(Anforderungen!$D:$D,$R58)) -> § 373 | D58: =IF($R58="","",INDEX(Anforderungen!$E:$E,$R58)) -> Reservierung | E58: =IF($R58="","",INDEX(Anforderungen!$F:$F,$R58)) -> OCPI Schnittstelle für Reservierungen ist gefordert. | F58: =IF($R58="","",INDEX(Anforderungen!$G:$G,$R58)) -> Frage: Laut Ziff. 3.4 im 4. Verfahrensbrief soll es nur ein zentrales Reservierungssystem geben. zugleich ist in § 23 Abs. 1 des Betreibervertrags von Reservierungsplattformen (Mehrzahl) die Rede. Wie passt dies zusammen? Antwort: Die überarbeitete Regelung im Betreibervertrag (§ 24) sieht vor, dass der Auftragnehmer eine Anbindung von Reservierungsplattformen über eine OCPI basierte Schnittstelle sicherstellt und Reservierungsplattformen über diese Schnittstelle ermöglicht, wenn sie die im Vertrag genannten Mindestvoraussetzungen erfüllt. | G58: =IF($R58="","",INDEX(Anforderungen!$I:$I,$R58)) -> eRound | H58: =IF($R58="","",INDEX(Anforderungen!$J:$J,$R58)) -> OCPI Buchungskalender | I58: =IF($R58="","",INDEX(Anforderungen!$K:$K,$R58)) -> trifft nicht zu | J58: =IF($R58="","",INDEX(Anforderungen!$L:$L,$R58)) -> 0 | K58: =IF($R58="","",INDEX(Anforderungen!$M:$M,$R58)) -> Automatisch ausgewertet: Außerhalb des betrachteten Leistungsumfangs (Schranken, Kennzeichenerfassung, dynamische Anzeige). | R58: =IFERROR(MATCH(ROWS($A$14:$A58),$T$7:$T$2000,0)+6,"") -> 51 | T58: =IF(Anforderungen!$B58="","",IF(AND(OR($B5="(alle)",Anforderungen!$K58=$B5),OR($E5="(alle)",Anforderungen!$C58=$E5),OR($H5="(alle)",Anforderungen!$E58=$H5),OR($B7="(alle)",ISNUMBER(SEARCH($B7,Anforderungen!$J58))),OR($E7="(alle)",ISNUMBER(SEARCH($E7,Anforderungen!$I58))),OR($H7="",ISNUMBER(SEARCH($H7,Anforderungen!$F58&" "&Anforderungen!$G58)))),COUNT($T$6:$T57)+1,"")) -> 52
A59: =IF($R59="","",INDEX(Anforderungen!$B:$B,$R59)) -> ANF-046 | B59: =IF($R59="","",INDEX(Anforderungen!$C:$C,$R59)) -> Bieterfragenkatalog | C59: =IF($R59="","",INDEX(Anforderungen!$D:$D,$R59)) -> § 374 | D59: =IF($R59="","",INDEX(Anforderungen!$E:$E,$R59)) -> Reservierung | E59: =IF($R59="","",INDEX(Anforderungen!$F:$F,$R59)) -> Anbindung muss deutschlandweit sichergestellt sein. | F59: =IF($R59="","",INDEX(Anforderungen!$G:$G,$R59)) -> Frage: Bei einer Reservierungsplattform handelt es sich um Software, die damit grundsätzlich weltweit verfügbar ist. Wie ist der Passus zu verstehen, dass die Plattform im gesamten Gebiet der Bundesrepublik Deutschland Reservierungen ermöglichen soll? Antwort: Es muss sichergestellt sein, dass die Reservierung für alle Rastanlagen mit Ladeinfrastruktur für E-LKW auf Bundesautobahnen möglich ist | G59: =IF($R59="","",INDEX(Anforderungen!$I:$I,$R59)) -> Reservierungsplattform | H59: =IF($R59="","",INDEX(Anforderungen!$J:$J,$R59)) -> Anbindung | I59: =IF($R59="","",INDEX(Anforderungen!$K:$K,$R59)) -> trifft nicht zu | J59: =IF($R59="","",INDEX(Anforderungen!$L:$L,$R59)) -> 0 | K59: =IF($R59="","",INDEX(Anforderungen!$M:$M,$R59)) -> Automatisch ausgewertet: Außerhalb des betrachteten Leistungsumfangs (Schranken, Kennzeichenerfassung, dynamische Anzeige). | R59: =IFERROR(MATCH(ROWS($A$14:$A59),$T$7:$T$2000,0)+6,"") -> 52 | T59: =IF(Anforderungen!$B59="","",IF(AND(OR($B5="(alle)",Anforderungen!$K59=$B5),OR($E5="(alle)",Anforderungen!$C59=$E5),OR($H5="(alle)",Anforderungen!$E59=$H5),OR($B7="(alle)",ISNUMBER(SEARCH($B7,Anforderungen!$J59))),OR($E7="(alle)",ISNUMBER(SEARCH($E7,Anforderungen!$I59))),OR($H7="",ISNUMBER(SEARCH($H7,Anforderungen!$F59&" "&Anforderungen!$G59)))),COUNT($T$6:$T58)+1,"")) -> 53
A60: =IF($R60="","",INDEX(Anforderungen!$B:$B,$R60)) -> ANF-047 | B60: =IF($R60="","",INDEX(Anforderungen!$C:$C,$R60)) -> Bieterfragenkatalog | C60: =IF($R60="","",INDEX(Anforderungen!$D:$D,$R60)) -> § 375 | D60: =IF($R60="","",INDEX(Anforderungen!$E:$E,$R60)) -> Nutzungszeit & Entgelte | E60: =IF($R60="","",INDEX(Anforderungen!$F:$F,$R60)) -> 0 | F60: =IF($R60="","",INDEX(Anforderungen!$G:$G,$R60)) -> Es ist in Verbindung mit §36 das Erheben eines Blockadeentgeltes möglich, welches (bei Erscheinen) erst nach 75 min greift. Gehen wir recht in der Annahme, dass der CPO mit einer Belegung durch einen Reservierungsvorgang von 75 min rechnen muss, bevor er die Ladestation erneut als verfügbar meldet? | G60: =IF($R60="","",INDEX(Anforderungen!$I:$I,$R60)) -> offen | H60: =IF($R60="","",INDEX(Anforderungen!$J:$J,$R60)) -> – | I60: =IF($R60="","",INDEX(Anforderungen!$K:$K,$R60)) -> trifft nicht zu | J60: =IF($R60="","",INDEX(Anforderungen!$L:$L,$R60)) -> 0 | K60: =IF($R60="","",INDEX(Anforderungen!$M:$M,$R60)) -> Automatisch ausgewertet: Außerhalb des betrachteten Leistungsumfangs (Schranken, Kennzeichenerfassung, dynamische Anzeige). | R60: =IFERROR(MATCH(ROWS($A$14:$A60),$T$7:$T$2000,0)+6,"") -> 53 | T60: =IF(Anforderungen!$B60="","",IF(AND(OR($B5="(alle)",Anforderungen!$K60=$B5),OR($E5="(alle)",Anforderungen!$C60=$E5),OR($H5="(alle)",Anforderungen!$E60=$H5),OR($B7="(alle)",ISNUMBER(SEARCH($B7,Anforderungen!$J60))),OR($E7="(alle)",ISNUMBER(SEARCH($E7,Anforderungen!$I60))),OR($H7="",ISNUMBER(SEARCH($H7,Anforderungen!$F60&" "&Anforderungen!$G60)))),COUNT($T$6:$T59)+1,"")) -> 54
A61: =IF($R61="","",INDEX(Anforderungen!$B:$B,$R61)) -> ANF-048 | B61: =IF($R61="","",INDEX(Anforderungen!$C:$C,$R61)) -> Bieterfragenkatalog | C61: =IF($R61="","",INDEX(Anforderungen!$D:$D,$R61)) -> § 376 | D61: =IF($R61="","",INDEX(Anforderungen!$E:$E,$R61)) -> Nutzungszeit & Entgelte | E61: =IF($R61="","",INDEX(Anforderungen!$F:$F,$R61)) -> 0 | F61: =IF($R61="","",INDEX(Anforderungen!$G:$G,$R61)) -> Frage: Der Vertrag sieht eine spätere mögliche Anpassung der Höhe des Blockadeentgeltes vor, aber keine Anpassungsoption hinsichtlich der Wartezeit. Gehen wir richtig in der Annahme, dass der AG nicht beabsichtigt, mögliche Optimierungspotenziale durch kürzere Wartezeiten während der Vertragslaufzeit zu realisieren? Antwort: Der Betreibervertrag wird mit der Aufforderung der Abgabe verbindlicher Angebote aktualisiert. | G61: =IF($R61="","",INDEX(Anforderungen!$I:$I,$R61)) -> offen | H61: =IF($R61="","",INDEX(Anforderungen!$J:$J,$R61)) -> – | I61: =IF($R61="","",INDEX(Anforderungen!$K:$K,$R61)) -> trifft nicht zu | J61: =IF($R61="","",INDEX(Anforderungen!$L:$L,$R61)) -> 0 | K61: =IF($R61="","",INDEX(Anforderungen!$M:$M,$R61)) -> Automatisch ausgewertet: Außerhalb des betrachteten Leistungsumfangs (Schranken, Kennzeichenerfassung, dynamische Anzeige). | R61: =IFERROR(MATCH(ROWS($A$14:$A61),$T$7:$T$2000,0)+6,"") -> 54 | T61: =IF(Anforderungen!$B61="","",IF(AND(OR($B5="(alle)",Anforderungen!$K61=$B5),OR($E5="(alle)",Anforderungen!$C61=$E5),OR($H5="(alle)",Anforderungen!$E61=$H5),OR($B7="(alle)",ISNUMBER(SEARCH($B7,Anforderungen!$J61))),OR($E7="(alle)",ISNUMBER(SEARCH($E7,Anforderungen!$I61))),OR($H7="",ISNUMBER(SEARCH($H7,Anforderungen!$F61&" "&Anforderungen!$G61)))),COUNT($T$6:$T60)+1,"")) -> 55
A62: =IF($R62="","",INDEX(Anforderungen!$B:$B,$R62)) -> ANF-049 | B62: =IF($R62="","",INDEX(Anforderungen!$C:$C,$R62)) -> Bieterfragenkatalog | C62: =IF($R62="","",INDEX(Anforderungen!$D:$D,$R62)) -> § 377 | D62: =IF($R62="","",INDEX(Anforderungen!$E:$E,$R62)) -> Reservierung | E62: =IF($R62="","",INDEX(Anforderungen!$F:$F,$R62)) -> 0 | F62: =IF($R62="","",INDEX(Anforderungen!$G:$G,$R62)) -> Im In § 23 Abs. 4 BV heißt es, dass der Auftragnehmer verpflichtet ist, Endnutzern bzw. anderen Mobilitätsdienstleistern die Nutzung von MCS- oder CCS auch ohne vorherige Reservierung zu ermöglichen. Gehen wir recht in der Annahme, dass mit CCS nur Ladepunkte zum Zwischenladen gemeint sind und keine Ladepunkte zum Übernachtladen? Gehen wir weiter recht in der Annahme, dass sich dies auf die Ladepunkte eines Standortes bezieht und nicht auf jeden einzelnen Ladepunkt? Falls nein, heißt dies, dass es zulässig ist, ab weniger als 1h vor dem nächsten reservierten Lade Slot, keinen neuen Ladevorgang an dem betreffenden Ladepunkt mehr zuzulassen, da eine Blockiergebühr erst nach 60 min zulässig ist? Inwiefern sieht es die Vergabestelle als zulässig an, dass der adhoc-Nutzer einen spätesten Abfahrtzeitpunkt bestätigen muss, bei dessen Überschreiten eine Blockiergebühr erhoben werden darf? | G62: =IF($R62="","",INDEX(Anforderungen!$I:$I,$R62)) -> offen | H62: =IF($R62="","",INDEX(Anforderungen!$J:$J,$R62)) -> – | I62: =IF($R62="","",INDEX(Anforderungen!$K:$K,$R62)) -> trifft nicht zu | J62: =IF($R62="","",INDEX(Anforderungen!$L:$L,$R62)) -> 0 | K62: =IF($R62="","",INDEX(Anforderungen!$M:$M,$R62)) -> Automatisch ausgewertet: Außerhalb des betrachteten Leistungsumfangs (Schranken, Kennzeichenerfassung, dynamische Anzeige). | R62: =IFERROR(MATCH(ROWS($A$14:$A62),$T$7:$T$2000,0)+6,"") -> 55 | T62: =IF(Anforderungen!$B62="","",IF(AND(OR($B5="(alle)",Anforderungen!$K62=$B5),OR($E5="(alle)",Anforderungen!$C62=$E5),OR($H5="(alle)",Anforderungen!$E62=$H5),OR($B7="(alle)",ISNUMBER(SEARCH($B7,Anforderungen!$J62))),OR($E7="(alle)",ISNUMBER(SEARCH($E7,Anforderungen!$I62))),OR($H7="",ISNUMBER(SEARCH($H7,Anforderungen!$F62&" "&Anforderungen!$G62)))),COUNT($T$6:$T61)+1,"")) -> 56
A63: =IF($R63="","",INDEX(Anforderungen!$B:$B,$R63)) -> ANF-050 | B63: =IF($R63="","",INDEX(Anforderungen!$C:$C,$R63)) -> Bieterfragenkatalog | C63: =IF($R63="","",INDEX(Anforderungen!$D:$D,$R63)) -> § 378 | D63: =IF($R63="","",INDEX(Anforderungen!$E:$E,$R63)) -> Reservierung | E63: =IF($R63="","",INDEX(Anforderungen!$F:$F,$R63)) -> Anpassung möglich, bei ungewolltem Nutzerverhalten. | F63: =IF($R63="","",INDEX(Anforderungen!$G:$G,$R63)) -> Frage: Aus Sicht eines Kunden liegt es nahe, ggf. mehr als einen Standort zu reservieren, solange eine Buchung kostenlos storniert werden kann. Eine Stornierung und damit Freigabe eines Ladepunkts 30 Minuten vor dem geplanten Nutzungsbeginn führt jedoch dazu, dass die Wahrscheinlichkeit einer tatsächlichen Nutzung des zuvor reservierten Ladepunkts deutlich sinkt. Welche Maßnahmen sieht der AG vor, um ein derartiges Verhalten der Nutzer zu verhindern? Antwort: Grundsätzlich möchte der Auftraggeber den Nutzern eine gewisse Flexibilität ermöglichen, da die Inanspruchnahme einer Reservierung z.B. aufgrund kurzfristiger Staus auch ohne Verschulden ggf. nicht wahrgenommen werden kann. Ein missbräuchliches Verhalten durch Nutzer, z.B. durch mehrfache Reservierungsbuchungen am gleichen Standort und am gleichen Tag, ist nicht im Interesse des Auftraggebers. Sollte sich ein solches Verhalten einstellen, besteht vor dem Hintergrund eines abweichenden Marktstandards nach §23 Abs. 3 des Betreibervertrags die Möglichkeit, die definierten Mindestvoraussetzungen an Reservierungsplattformen zu ändern. | G63: =IF($R63="","",INDEX(Anforderungen!$I:$I,$R63)) -> eRound | H63: =IF($R63="","",INDEX(Anforderungen!$J:$J,$R63)) -> OCPI Buchungskalender | I63: =IF($R63="","",INDEX(Anforderungen!$K:$K,$R63)) -> trifft nicht zu | J63: =IF($R63="","",INDEX(Anforderungen!$L:$L,$R63)) -> 0 | K63: =IF($R63="","",INDEX(Anforderungen!$M:$M,$R63)) -> Automatisch ausgewertet: Außerhalb des betrachteten Leistungsumfangs (Schranken, Kennzeichenerfassung, dynamische Anzeige). | R63: =IFERROR(MATCH(ROWS($A$14:$A63),$T$7:$T$2000,0)+6,"") -> 56 | T63: =IF(Anforderungen!$B63="","",IF(AND(OR($B5="(alle)",Anforderungen!$K63=$B5),OR($E5="(alle)",Anforderungen!$C63=$E5),OR($H5="(alle)",Anforderungen!$E63=$H5),OR($B7="(alle)",ISNUMBER(SEARCH($B7,Anforderungen!$J63))),OR($E7="(alle)",ISNUMBER(SEARCH($E7,Anforderungen!$I63))),OR($H7="",ISNUMBER(SEARCH($H7,Anforderungen!$F63&" "&Anforderungen!$G63)))),COUNT($T$6:$T62)+1,"")) -> 57
A64: =IF($R64="","",INDEX(Anforderungen!$B:$B,$R64)) -> ANF-051 | B64: =IF($R64="","",INDEX(Anforderungen!$C:$C,$R64)) -> Bieterfragenkatalog | C64: =IF($R64="","",INDEX(Anforderungen!$D:$D,$R64)) -> § 455 | D64: =IF($R64="","",INDEX(Anforderungen!$E:$E,$R64)) -> Reservierung | E64: =IF($R64="","",INDEX(Anforderungen!$F:$F,$R64)) -> Reservierungsplattform ist nicht Teil der Ausschreibung. | F64: =IF($R64="","",INDEX(Anforderungen!$G:$G,$R64)) -> Frage: Im vierten Verfahrensbrief findet sich folgende Aussage unter 3.4.: „Die Vorgaben zum Reservierungssystem wurden dahingehend angepasst, dass es nunmehr ein zentrales Reservierungssystem geben wird.“ Im Betreibervertrag unter § 23, 2. Lesen wir allerdings: „Der Auftragnehmer ist verpflichtet, jeder Reservierungsplattform die Anbindung über die in Absatz 1 genannte Schnittstelle kostenfrei zu ermöglichen, soweit die Reservierungsplattform die folgenden Mindestvoraussetzungen erfüllt: (…)“ Dies stellt aus unserer Sicht ggf. einen Widerspruch dar. Wir bitten darum, die geplante Architektur des Reservierungsökosystems einmal zu erläutern. Antwort: Der Vertrag gilt. Sobald Reservierungsplattformen die im Vertrag genannten Mindestvoraussetzungen erfüllen, werden sie als anbindungsfähig und als zentral angesehen. In diesem Fall hat der Auftragnehmer auf Wunsch der externen Reservierungsplattformen eine Anbindung über eine OCPI-basierte Schnittstelle zu gewährleisten. Ein durch den Auftraggeber (z.B. per Vergabeverfahren) organisiertes, zentrales Reservierungssystem ist nicht in Planung. | G64: =IF($R64="","",INDEX(Anforderungen!$I:$I,$R64)) -> Reservierungsplattform | H64: =IF($R64="","",INDEX(Anforderungen!$J:$J,$R64)) -> Reservierungsplattform | I64: =IF($R64="","",INDEX(Anforderungen!$K:$K,$R64)) -> trifft nicht zu | J64: =IF($R64="","",INDEX(Anforderungen!$L:$L,$R64)) -> 0 | K64: =IF($R64="","",INDEX(Anforderungen!$M:$M,$R64)) -> Automatisch ausgewertet: Außerhalb des betrachteten Leistungsumfangs (Schranken, Kennzeichenerfassung, dynamische Anzeige). | R64: =IFERROR(MATCH(ROWS($A$14:$A64),$T$7:$T$2000,0)+6,"") -> 57 | T64: =IF(Anforderungen!$B64="","",IF(AND(OR($B5="(alle)",Anforderungen!$K64=$B5),OR($E5="(alle)",Anforderungen!$C64=$E5),OR($H5="(alle)",Anforderungen!$E64=$H5),OR($B7="(alle)",ISNUMBER(SEARCH($B7,Anforderungen!$J64))),OR($E7="(alle)",ISNUMBER(SEARCH($E7,Anforderungen!$I64))),OR($H7="",ISNUMBER(SEARCH($H7,Anforderungen!$F64&" "&Anforderungen!$G64)))),COUNT($T$6:$T63)+1,"")) -> 58
A65: =IF($R65="","",INDEX(Anforderungen!$B:$B,$R65)) -> ANF-052 | B65: =IF($R65="","",INDEX(Anforderungen!$C:$C,$R65)) -> Bieterfragenkatalog | C65: =IF($R65="","",INDEX(Anforderungen!$D:$D,$R65)) -> § 370 | D65: =IF($R65="","",INDEX(Anforderungen!$E:$E,$R65)) -> Reservierung | E65: =IF($R65="","",INDEX(Anforderungen!$F:$F,$R65)) -> Sämtliche Infos via gängigen Roamingprotokoll / Marktstandard zur verfügung stellen. | F65: =IF($R65="","",INDEX(Anforderungen!$G:$G,$R65)) -> Frage: Welche Informationen der Reservierung sollen MSP und sonstigen bereitgestellt werden? Antwort: Es ist vom AN sicherzustellen, dass sämtliche Statusinformationen der Reservierungen bereitgestellt werden, die mittels der gängigen Roamingprotokolle übermittelt werden können und dem gängigen Marktstandard entsprechen. | G65: =IF($R65="","",INDEX(Anforderungen!$I:$I,$R65)) -> eRound | H65: =IF($R65="","",INDEX(Anforderungen!$J:$J,$R65)) -> OCPI Buchungskalender | I65: =IF($R65="","",INDEX(Anforderungen!$K:$K,$R65)) -> trifft nicht zu | J65: =IF($R65="","",INDEX(Anforderungen!$L:$L,$R65)) -> 0 | K65: =IF($R65="","",INDEX(Anforderungen!$M:$M,$R65)) -> Automatisch ausgewertet: Außerhalb des betrachteten Leistungsumfangs (Schranken, Kennzeichenerfassung, dynamische Anzeige). | R65: =IFERROR(MATCH(ROWS($A$14:$A65),$T$7:$T$2000,0)+6,"") -> 58 | T65: =IF(Anforderungen!$B65="","",IF(AND(OR($B5="(alle)",Anforderungen!$K65=$B5),OR($E5="(alle)",Anforderungen!$C65=$E5),OR($H5="(alle)",Anforderungen!$E65=$H5),OR($B7="(alle)",ISNUMBER(SEARCH($B7,Anforderungen!$J65))),OR($E7="(alle)",ISNUMBER(SEARCH($E7,Anforderungen!$I65))),OR($H7="",ISNUMBER(SEARCH($H7,Anforderungen!$F65&" "&Anforderungen!$G65)))),COUNT($T$6:$T64)+1,"")) -> 59
A66: =IF($R66="","",INDEX(Anforderungen!$B:$B,$R66)) -> ANF-053 | B66: =IF($R66="","",INDEX(Anforderungen!$C:$C,$R66)) -> Bieterfragenkatalog | C66: =IF($R66="","",INDEX(Anforderungen!$D:$D,$R66)) -> Nr. 1 / S. 1 | D66: =IF($R66="","",INDEX(Anforderungen!$E:$E,$R66)) -> Vergabeverfahren & Angebot | E66: =IF($R66="","",INDEX(Anforderungen!$F:$F,$R66)) -> Klarstellung: Der Zuschlag wird nicht bereits auf die Erstangebote erteilt. Eine auf die Erstangebote bezogene Bindefrist ist daher gegenstandslos. | F66: =IF($R66="","",INDEX(Anforderungen!$G:$G,$R66)) -> Erster Verfahrensbrief, Formblatt A1, Fragenkatalog Nr. 61: In der Antwort auf Bieterfrage 61 ist ausgeführt, dass die Erstangebote indikativ sein werden und erst die Folgeangebote verbindlich. Unter Ziffer 3.1 des Ersten Verfahrensbriefs zum Verhandlungsverfahren heißt es entsprechend, dass der Auftraggeber den Zuschlag nicht auf das jeweils wirtschaftlichste Erstangebot erteilen wird. Unter Ziffer 4.6 des Ersten Verfahrensbriefs zum Verhandlungsverfahren heißt es allerdings, dass das Erstangebot zuschlagsfähig sein muss. Zudem soll der Bieter im Formblatt A1 – Angebotsschreiben erklären, sich bis zum Ablauf der Bindefrist an sein Erstangebot gebunden zu halten. Vor diesem Hintergrund bitten wir um Klarstellung: Ist unser Verständnis richtig, dass die Erstangebote rein indikativer Natur sind, also vom Auftraggeber unter keinen Umständen bezuschlagt werden können? Wie ist die Bindefrist zu verstehen? | G66: =IF($R66="","",INDEX(Anforderungen!$I:$I,$R66)) -> Autostrom+ | H66: =IF($R66="","",INDEX(Anforderungen!$J:$J,$R66)) -> – | I66: =IF($R66="","",INDEX(Anforderungen!$K:$K,$R66)) -> trifft nicht zu | J66: =IF($R66="","",INDEX(Anforderungen!$L:$L,$R66)) -> 0 | K66: =IF($R66="","",INDEX(Anforderungen!$M:$M,$R66)) -> 0 | R66: =IFERROR(MATCH(ROWS($A$14:$A66),$T$7:$T$2000,0)+6,"") -> 59 | T66: =IF(Anforderungen!$B66="","",IF(AND(OR($B5="(alle)",Anforderungen!$K66=$B5),OR($E5="(alle)",Anforderungen!$C66=$E5),OR($H5="(alle)",Anforderungen!$E66=$H5),OR($B7="(alle)",ISNUMBER(SEARCH($B7,Anforderungen!$J66))),OR($E7="(alle)",ISNUMBER(SEARCH($E7,Anforderungen!$I66))),OR($H7="",ISNUMBER(SEARCH($H7,Anforderungen!$F66&" "&Anforderungen!$G66)))),COUNT($T$6:$T65)+1,"")) -> 60
A67: =IF($R67="","",INDEX(Anforderungen!$B:$B,$R67)) -> ANF-054 | B67: =IF($R67="","",INDEX(Anforderungen!$C:$C,$R67)) -> Bieterfragenkatalog | C67: =IF($R67="","",INDEX(Anforderungen!$D:$D,$R67)) -> Nr. 2 / S. 1 | D67: =IF($R67="","",INDEX(Anforderungen!$E:$E,$R67)) -> Anzeige & Beschilderung | E67: =IF($R67="","",INDEX(Anforderungen!$F:$F,$R67)) -> Zusage / Ankündigung: Der AG beabsichtigt, die Unterlagen im weiteren Vergabeverfahren zur Verfügung zu stellen. | F67: =IF($R67="","",INDEX(Anforderungen!$G:$G,$R67)) -> Wann werden Anlage 04 Anhang 2 (Regelschnitt und Details für die Gestaltung der LKW- Ladeinfrastruktur) und Anlage 04 Anhang 3 (Markierungs- und Beschilderungsplan) zur Verfügung gestellt? | G67: =IF($R67="","",INDEX(Anforderungen!$I:$I,$R67)) -> tbd | H67: =IF($R67="","",INDEX(Anforderungen!$J:$J,$R67)) -> Beschilderung | I67: =IF($R67="","",INDEX(Anforderungen!$K:$K,$R67)) -> trifft nicht zu | J67: =IF($R67="","",INDEX(Anforderungen!$L:$L,$R67)) -> 0 | K67: =IF($R67="","",INDEX(Anforderungen!$M:$M,$R67)) -> Automatisch ausgewertet: Außerhalb des betrachteten Leistungsumfangs (Schranken, Kennzeichenerfassung, dynamische Anzeige). | R67: =IFERROR(MATCH(ROWS($A$14:$A67),$T$7:$T$2000,0)+6,"") -> 60 | T67: =IF(Anforderungen!$B67="","",IF(AND(OR($B5="(alle)",Anforderungen!$K67=$B5),OR($E5="(alle)",Anforderungen!$C67=$E5),OR($H5="(alle)",Anforderungen!$E67=$H5),OR($B7="(alle)",ISNUMBER(SEARCH($B7,Anforderungen!$J67))),OR($E7="(alle)",ISNUMBER(SEARCH($E7,Anforderungen!$I67))),OR($H7="",ISNUMBER(SEARCH($H7,Anforderungen!$F67&" "&Anforderungen!$G67)))),COUNT($T$6:$T66)+1,"")) -> 61
A68: =IF($R68="","",INDEX(Anforderungen!$B:$B,$R68)) -> ANF-055 | B68: =IF($R68="","",INDEX(Anforderungen!$C:$C,$R68)) -> Bieterfragenkatalog | C68: =IF($R68="","",INDEX(Anforderungen!$D:$D,$R68)) -> Nr. 3 / S. 1 | D68: =IF($R68="","",INDEX(Anforderungen!$E:$E,$R68)) -> Vertrag & Recht | E68: =IF($R68="","",INDEX(Anforderungen!$F:$F,$R68)) -> Klarstellung: Eine entsprechende Vertragsfassung wird allen für das Verhandlungsverfahren ausgewählten Bewerbern und Bewerbergemeinschaften mit Beantwortung zur Verfügung gestellt. | F68: =IF($R68="","",INDEX(Anforderungen!$G:$G,$R68)) -> Wir bitte zur besseren Nachverfolgung der Unterlagenfortschreibung um Zusendung einer ChangeVersion, um nachzuvollziehen in welchen Punkte das Vertragswerk angepasst wurde. | G68: =IF($R68="","",INDEX(Anforderungen!$I:$I,$R68)) -> offen | H68: =IF($R68="","",INDEX(Anforderungen!$J:$J,$R68)) -> – | I68: =IF($R68="","",INDEX(Anforderungen!$K:$K,$R68)) -> trifft nicht zu | J68: =IF($R68="","",INDEX(Anforderungen!$L:$L,$R68)) -> 0 | K68: =IF($R68="","",INDEX(Anforderungen!$M:$M,$R68)) -> Automatisch ausgewertet: Außerhalb des betrachteten Leistungsumfangs (Schranken, Kennzeichenerfassung, dynamische Anzeige). | R68: =IFERROR(MATCH(ROWS($A$14:$A68),$T$7:$T$2000,0)+6,"") -> 61 | T68: =IF(Anforderungen!$B68="","",IF(AND(OR($B5="(alle)",Anforderungen!$K68=$B5),OR($E5="(alle)",Anforderungen!$C68=$E5),OR($H5="(alle)",Anforderungen!$E68=$H5),OR($B7="(alle)",ISNUMBER(SEARCH($B7,Anforderungen!$J68))),OR($E7="(alle)",ISNUMBER(SEARCH($E7,Anforderungen!$I68))),OR($H7="",ISNUMBER(SEARCH($H7,Anforderungen!$F68&" "&Anforderungen!$G68)))),COUNT($T$6:$T67)+1,"")) -> 62
A69: =IF($R69="","",INDEX(Anforderungen!$B:$B,$R69)) -> ANF-056 | B69: =IF($R69="","",INDEX(Anforderungen!$C:$C,$R69)) -> Bieterfragenkatalog | C69: =IF($R69="","",INDEX(Anforderungen!$D:$D,$R69)) -> Nr. 4 / S. 1 | D69: =IF($R69="","",INDEX(Anforderungen!$E:$E,$R69)) -> Vertrag & Recht | E69: =IF($R69="","",INDEX(Anforderungen!$F:$F,$R69)) -> Zusage / Ankündigung: Anlage 9 zum Vertrag wird dem AN nach Vertragsschluss zu Verfügung gestellt (vgl. Vertragsanlage 4 LB Errichtung, S.13). | F69: =IF($R69="","",INDEX(Anforderungen!$G:$G,$R69)) -> Die für die zweite Phase der Ausschreibung geteilten Unterlagen enthalten NICHT die Vertragsanlagen 7 ("Logos") und 9 ("Ansprechpartner (losspezifisch)"). Wenn diese bewusst nicht geteilt werden - wann kann mit diesen gerechnet werden? | G69: =IF($R69="","",INDEX(Anforderungen!$I:$I,$R69)) -> offen | H69: =IF($R69="","",INDEX(Anforderungen!$J:$J,$R69)) -> – | I69: =IF($R69="","",INDEX(Anforderungen!$K:$K,$R69)) -> trifft nicht zu | J69: =IF($R69="","",INDEX(Anforderungen!$L:$L,$R69)) -> 0 | K69: =IF($R69="","",INDEX(Anforderungen!$M:$M,$R69)) -> Automatisch ausgewertet: Außerhalb des betrachteten Leistungsumfangs (Schranken, Kennzeichenerfassung, dynamische Anzeige). | R69: =IFERROR(MATCH(ROWS($A$14:$A69),$T$7:$T$2000,0)+6,"") -> 62 | T69: =IF(Anforderungen!$B69="","",IF(AND(OR($B5="(alle)",Anforderungen!$K69=$B5),OR($E5="(alle)",Anforderungen!$C69=$E5),OR($H5="(alle)",Anforderungen!$E69=$H5),OR($B7="(alle)",ISNUMBER(SEARCH($B7,Anforderungen!$J69))),OR($E7="(alle)",ISNUMBER(SEARCH($E7,Anforderungen!$I69))),OR($H7="",ISNUMBER(SEARCH($H7,Anforderungen!$F69&" "&Anforderungen!$G69)))),COUNT($T$6:$T68)+1,"")) -> 63
