Workbook

Sheet Cockpit
A1: Cockpit – Anforderungen Autostrom / LKW-Laden
A2: Status, Erfüllung und Dokumentationsqualität auf einen Blick
A3: Alle Kennzahlen rechnen direkt aus den Registern „Anforderungen“ und „Komponenten“ – inklusive des vollständigen Bieterfragenkatalogs.
A5: Kennzahl | B5: Wert
A6: Anforderungen gesamt | B6: =COUNTA(Anforderungen!$B$7:$B$2000) -> 1382
A7: Erfasst | B7: =COUNTIF(Anforderungen!$K$7:$K$2000,"erfasst") -> 1211
A8: Bewertet | B8: =COUNTIF(Anforderungen!$K$7:$K$2000,"bewertet") -> 3
A9: Erfüllt | B9: =COUNTIF(Anforderungen!$K$7:$K$2000,"erfüllt") -> 10
A10: davon vollständig dokumentiert | B10: =COUNTIFS(Anforderungen!$K$7:$K$2000,"erfüllt",Anforderungen!$L$7:$L$2000,"<>",Anforderungen!$M$7:$M$2000,"<>") -> 10
A11: Trifft nicht zu | B11: =COUNTIF(Anforderungen!$K$7:$K$2000,"trifft nicht zu") -> 158
A12: Erfüllt ohne Datum | B12: =COUNTIFS(Anforderungen!$K$7:$K$2000,"erfüllt",Anforderungen!$L$7:$L$2000,"") -> 0
A13: Erfüllt ohne Nachweis / Notiz | B13: =COUNTIFS(Anforderungen!$K$7:$K$2000,"erfüllt",Anforderungen!$M$7:$M$2000,"") -> 0
A14: Trifft nicht zu ohne Begründung | B14: =COUNTIFS(Anforderungen!$K$7:$K$2000,"trifft nicht zu",Anforderungen!$M$7:$M$2000,"") -> 2
A15: Erfüllungsgrad | B15: =IFERROR(COUNTIF(Anforderungen!$K$7:$K$2000,"erfüllt")/(COUNTA(Anforderungen!$B$7:$B$2000)-COUNTIF(Anforderungen!$K$7:$K$2000,"trifft nicht zu")),0) -> 0.0081699346
A16: Dokumentationsgrad erfüllt | B16: =IFERROR(COUNTIFS(Anforderungen!$K$7:$K$2000,"erfüllt",Anforderungen!$L$7:$L$2000,"<>",Anforderungen!$M$7:$M$2000,"<>")/COUNTIF(Anforderungen!$K$7:$K$2000,"erfüllt"),0) -> 1
A17: Komponenten/Schnittstellen erfüllt | B17: =COUNTIF(Komponenten!$J$6:$J$29,"erfüllt") -> 0
A18: Bieterfragen im Register | B18: =COUNTIF(Anforderungen!$C$7:$C$2000,"Bieterfragenkatalog") -> 663
A19: Offene Zuordnungen (Komponente/Partner) | B19: =COUNTIF(Anforderungen!$J$7:$J$2000,"Zuordnung prüfen")+COUNTIF(Anforderungen!$I$7:$I$2000,"Zuordnung prüfen") -> 460
A20: Anforderungen im betrachteten Umfang | B20: =COUNTIF(Anforderungen!$N$7:$N$2000,"im Umfang") -> 62

Sheet Anforderungen
A1: Anforderungen – Autostrom / LKW-Laden
A2: Zentrales Anforderungsregister: Der Block „Erfüllung / Nachweis“ verbindet Status, tatsächliches Erfüllungsdatum und Dokumentation.
A3: Logik: erfasst → bewertet → erfüllt. Bei „erfüllt“ sind Datum und Nachweis/Notiz erforderlich, bei „trifft nicht zu“ eine Begründung. Gelb markierte Zuordnungen (Partner/Komponente) sind fachlich zu prüfen.
B5: Anforderung & Zuordnung | K5: Erfüllung / Nachweis (Konzept)
B6: ID | C6: Dokument | D6: Fundstelle | E6: Themenfeld | F6: Kernaussage | G6: Anforderung / Frage (Originaltext) | H6: Bemerkung | I6: Partner | J6: Komponente(n) | K6: Status | L6: Erfüllt am | M6: Nachweis / Notiz | N6: Umfang | O6: Filter-Rang
B7: ANF-001 | C7: Betreibervertrag | D7: § 25 (1) | E7: Reservierung | F7: OCPI Schnittstelle | G7: Der Auftragnehmer stellt sicher, dass die Reservierung von Ladepunkten über Reservierungsplattformen während der Laufzeit dieses Vertrags möglich ist. Hierzu hält der Auftragnehmer eine auf OCPI (Open Charge Point Interface) basierende Schnittstelle vor, über die sich Reservierungsplattformen nach Maßgabe der folgenden Absätze anbinden können. | I7: eRound | J7: OCPI Buchungskalender | K7: erfasst | N7: außerhalb | O7: =IF($B7="",0,IF(AND(OR(Filter!$B$5="(alle)",$N7=Filter!$B$5),OR(Filter!$E$5="(alle)",$K7=Filter!$E$5),OR(Filter!$H$5="(alle)",$C7=Filter!$H$5),OR(Filter!$B$7="(alle)",$E7=Filter!$B$7),OR(Filter!$E$7="(alle)",ISNUMBER(SEARCH(Filter!$E$7,$J7))),OR(Filter!$H$7="(alle)",ISNUMBER(SEARCH(Filter!$H$7,$I7))),OR(Filter!$B$9="",ISNUMBER(SEARCH(Filter!$B$9,$F7&" "&$G7)))),COUNTIF($O$6:$O6,">0")+1,0)) -> 1
B8: ANF-002 | C8: Betreibervertrag | D8: § 25 (2) | E8: Reservierung | F8: OCPI Kostenfrei | G8: Der Auftragnehmer ist verpflichtet, jeder Reservierungsplattform die Anbindung über die in Absatz 1 genannte Schnittstelle kostenfrei zu ermöglichen, soweit die Reservierungsplattform die folgenden Mindestvoraussetzungen erfüllt: | I8: eRound | J8: OCPI Buchungskalender | K8: erfasst | N8: außerhalb | O8: =IF($B8="",0,IF(AND(OR(Filter!$B$5="(alle)",$N8=Filter!$B$5),OR(Filter!$E$5="(alle)",$K8=Filter!$E$5),OR(Filter!$H$5="(alle)",$C8=Filter!$H$5),OR(Filter!$B$7="(alle)",$E8=Filter!$B$7),OR(Filter!$E$7="(alle)",ISNUMBER(SEARCH(Filter!$E$7,$J8))),OR(Filter!$H$7="(alle)",ISNUMBER(SEARCH(Filter!$H$7,$I8))),OR(Filter!$B$9="",ISNUMBER(SEARCH(Filter!$B$9,$F8&" "&$G8)))),COUNTIF($O$6:$O7,">0")+1,0)) -> 2
B9: ANF-003 | C9: Betreibervertrag | D9: § 25 (2) a | E9: Reservierung | F9: OCPI Kostenfrei | G9: Die Reservierungsplattform stellt dem Auftragnehmer für die Anbindung der Reservierungsplattform keine Anbindungskosten in Rechnung | I9: eRound | J9: Anbindung | K9: erfasst | N9: außerhalb | O9: =IF($B9="",0,IF(AND(OR(Filter!$B$5="(alle)",$N9=Filter!$B$5),OR(Filter!$E$5="(alle)",$K9=Filter!$E$5),OR(Filter!$H$5="(alle)",$C9=Filter!$H$5),OR(Filter!$B$7="(alle)",$E9=Filter!$B$7),OR(Filter!$E$7="(alle)",ISNUMBER(SEARCH(Filter!$E$7,$J9))),OR(Filter!$H$7="(alle)",ISNUMBER(SEARCH(Filter!$H$7,$I9))),OR(Filter!$B$9="",ISNUMBER(SEARCH(Filter!$B$9,$F9&" "&$G9)))),COUNTIF($O$6:$O8,">0")+1,0)) -> 3
B10: ANF-004 | C10: Betreibervertrag | D10: § 25 (2) b | E10: Reservierung | F10: Anbindung verpflichtend, wenn alle AN angebunden werden oder AG2 auffordert | G10: Die Reservierungsplattform ermöglicht Endnutzern und Mobilitätsdienstleistern die Reservierung von Ladepunkten im gesamten Gebiet der Bundesrepublik Deutschland gegen ein angemessenes Entgelt. Ermöglicht eine Reservierungsplattform eine Reservierung von Ladepunkten nur in Teilen des Gebiets der Bundesrepublik Deutschland, ist der Auftragnehmer zur Anbindung nur verpflichtet, wenn der Auftraggeber 2 den Auftragnehmer hierzu auffordert. | I10: eRound | J10: OCPI Buchungskalender | K10: erfasst | N10: außerhalb | O10: =IF($B10="",0,IF(AND(OR(Filter!$B$5="(alle)",$N10=Filter!$B$5),OR(Filter!$E$5="(alle)",$K10=Filter!$E$5),OR(Filter!$H$5="(alle)",$C10=Filter!$H$5),OR(Filter!$B$7="(alle)",$E10=Filter!$B$7),OR(Filter!$E$7="(alle)",ISNUMBER(SEARCH(Filter!$E$7,$J10))),OR(Filter!$H$7="(alle)",ISNUMBER(SEARCH(Filter!$H$7,$I10))),OR(Filter!$B$9="",ISNUMBER(SEARCH(Filter!$B$9,$F10&" "&$G10)))),COUNTIF($O$6:$O9,">0")+1,0)) -> 4
B11: ANF-005 | C11: Betreibervertrag | D11: § 25 (2) c | E11: Reservierung | F11: Reservierung mit Vorlauf von max. 7 Tagen und min. 15 min. Kostenfreie Stornierung und Änderung bis 30min vorher. Kennzeichenabgleich zur Unterbindung von Doppelbuchungen. | G11: Die Reservierungsplattform ermöglicht eine Reservierung von Ladepunkten mit einer Vorlaufzeit von maximal 7 Kalendertagen und mindestens 15 Minuten. Eine kostenfreie Stornierung oder Änderung der Reservierung über die Reservierungsplattform muss, soweit möglich, bis zu 30 Minuten vor Beginn des in der Reservierung angegebenen Startzeitpunkts möglich sein. Die Reservierungsplattform stellt durch geeignete Vorkehrungen (z. B. durch einen Kennzeichenabgleich) sicher, dass für einen E-LKW in einem Zeitintervall nur ein Ladepunkt reserviert wird. | I11: eRound | J11: OCPI Buchungskalender | K11: erfasst | N11: im Umfang | O11: =IF($B11="",0,IF(AND(OR(Filter!$B$5="(alle)",$N11=Filter!$B$5),OR(Filter!$E$5="(alle)",$K11=Filter!$E$5),OR(Filter!$H$5="(alle)",$C11=Filter!$H$5),OR(Filter!$B$7="(alle)",$E11=Filter!$B$7),OR(Filter!$E$7="(alle)",ISNUMBER(SEARCH(Filter!$E$7,$J11))),OR(Filter!$H$7="(alle)",ISNUMBER(SEARCH(Filter!$H$7,$I11))),OR(Filter!$B$9="",ISNUMBER(SEARCH(Filter!$B$9,$F11&" "&$G11)))),COUNTIF($O$6:$O10,">0")+1,0)) -> 5
B12: ANF-006 | C12: Betreibervertrag | D12: § 25 (2) d | E12: Reservierung | F12: Entschädigung an AN von der Reservierungsplattform i.H.v. mind. 30€ nach 15/30 min Wartezeit bei No-Show. | G12: Die Reservierungsplattform entschädigt den Auftragnehmer in angemessener Höhe, wenn an der reservierten Ladeeinrichtung ab dem in der Reservierung angegebenen Startzeitpunkt und Ablauf einer Wartezeit von 15 Minuten bei Ladepunkten zum Zwischenladen, bzw. 30 Minuten bei Ladepunkten zum Übernachtladen (sog. „no-show“) kein Start eines Ladevorgangs erfolgt. Die Entschädigung des Auftragnehmers ist angemessen, wenn der Auftragnehmer im Fall eines „no-show“ mindestens € 30,00 erhält. | I12: eRound | J12: Abrechnungskomponente | K12: erfasst | N12: außerhalb | O12: =IF($B12="",0,IF(AND(OR(Filter!$B$5="(alle)",$N12=Filter!$B$5),OR(Filter!$E$5="(alle)",$K12=Filter!$E$5),OR(Filter!$H$5="(alle)",$C12=Filter!$H$5),OR(Filter!$B$7="(alle)",$E12=Filter!$B$7),OR(Filter!$E$7="(alle)",ISNUMBER(SEARCH(Filter!$E$7,$J12))),OR(Filter!$H$7="(alle)",ISNUMBER(SEARCH(Filter!$H$7,$I12))),OR(Filter!$B$9="",ISNUMBER(SEARCH(Filter!$B$9,$F12&" "&$G12)))),COUNTIF($O$6:$O11,">0")+1,0)) -> 6
B13: ANF-007 | C13: Betreibervertrag | D13: § 25 (3) | E13: Reservierung | F13: Anpassung an Marktstandards mit 2 Monaten Vorlauf. | G13: Der Auftraggeber 2 ist berechtigt, die in Absatz 2 definierten Mindestvoraussetzungen im Fall abweichender Marktstandards mit einer Vorlaufzeit von zwei Monaten anzupassen | I13: eRound | J13: OCPI Buchungskalender | K13: erfasst | N13: außerhalb | O13: =IF($B13="",0,IF(AND(OR(Filter!$B$5="(alle)",$N13=Filter!$B$5),OR(Filter!$E$5="(alle)",$K13=Filter!$E$5),OR(Filter!$H$5="(alle)",$C13=Filter!$H$5),OR(Filter!$B$7="(alle)",$E13=Filter!$B$7),OR(Filter!$E$7="(alle)",ISNUMBER(SEARCH(Filter!$E$7,$J13))),OR(Filter!$H$7="(alle)",ISNUMBER(SEARCH(Filter!$H$7,$I13))),OR(Filter!$B$9="",ISNUMBER(SEARCH(Filter!$B$9,$F13&" "&$G13)))),COUNTIF($O$6:$O12,">0")+1,0)) -> 7
B14: ANF-008 | C14: Betreibervertrag | D14: § 25 (4) | E14: Reservierung | F14: Ladepunkte an einem Standort können von der Reservierung ausgenommen werden. | G14: Der Auftragnehmer kann CCS- und MCS-Ladepunkten an einem Standort von der Reservierungsmöglichkeit ausnehmen. | I14: eRound | J14: OCPI Buchungskalender | K14: erfasst | N14: außerhalb | O14: =IF($B14="",0,IF(AND(OR(Filter!$B$5="(alle)",$N14=Filter!$B$5),OR(Filter!$E$5="(alle)",$K14=Filter!$E$5),OR(Filter!$H$5="(alle)",$C14=Filter!$H$5),OR(Filter!$B$7="(alle)",$E14=Filter!$B$7),OR(Filter!$E$7="(alle)",ISNUMBER(SEARCH(Filter!$E$7,$J14))),OR(Filter!$H$7="(alle)",ISNUMBER(SEARCH(Filter!$H$7,$I14))),OR(Filter!$B$9="",ISNUMBER(SEARCH(Filter!$B$9,$F14&" "&$G14)))),COUNTIF($O$6:$O13,">0")+1,0)) -> 8
B15: ANF-009 | C15: Betreibervertrag | D15: § 25 (5) | E15: Zufahrt & Schranke | F15: Bauliche Maßnahme zur Reservierung an jedem Ladepunkt. | G15: Der Auftragnehmer hat geeignete Vorkehrungen, insbesondere die in Vertragsanlage 4: Leistungsbeschreibung Errichtung vorgesehenen baulichen Maßnahmen, zu treffen, um ein anderweitiges Laden an dem Ladepunkt der Ladeeinrichtung während des reservierten Zeitraums zu verhindern. | H15: Schrankensteuerung | I15: Schrankenhersteller | J15: Schrankenanlage | K15: erfasst | N15: im Umfang | O15: =IF($B15="",0,IF(AND(OR(Filter!$B$5="(alle)",$N15=Filter!$B$5),OR(Filter!$E$5="(alle)",$K15=Filter!$E$5),OR(Filter!$H$5="(alle)",$C15=Filter!$H$5),OR(Filter!$B$7="(alle)",$E15=Filter!$B$7),OR(Filter!$E$7="(alle)",ISNUMBER(SEARCH(Filter!$E$7,$J15))),OR(Filter!$H$7="(alle)",ISNUMBER(SEARCH(Filter!$H$7,$I15))),OR(Filter!$B$9="",ISNUMBER(SEARCH(Filter!$B$9,$F15&" "&$G15)))),COUNTIF($O$6:$O14,">0")+1,0)) -> 9
B16: ANF-010 | C16: Betreibervertrag | D16: § 25 (6) | E16: Reservierung | F16: Mindestens 40% der Ladepunkte müssen reserviert werden können. | G16: Verstößt der Auftragnehmer gegen die Pflicht nach Absatz 1, wird für jeden Standort, an dem die Reservierung von Ladepunkten aufgrund des Verstoßes gegen die Pflicht nach Absatz 1 nicht möglich ist, eine Vertragsstrafe fällig. Die Reservierung von Ladepunkten an einem Standort gilt als nicht möglich, wenn mindestens 40 % der Ladepunkte an dem Standort nicht reserviert werden können. Die Höhe der Vertragsstrafe beträgt € 2.500,00 für jeden Kalendertag, an dem die Reservierung von Ladepunkten an einem Standort nicht möglich ist, höchstens jedoch € 40.000,00 pro Kalendermonat und pro Standort. | H16: 40% der Schranken offen lassen? | I16: eRound | J16: OCPI Buchungskalender | K16: erfasst | N16: im Umfang | O16: =IF($B16="",0,IF(AND(OR(Filter!$B$5="(alle)",$N16=Filter!$B$5),OR(Filter!$E$5="(alle)",$K16=Filter!$E$5),OR(Filter!$H$5="(alle)",$C16=Filter!$H$5),OR(Filter!$B$7="(alle)",$E16=Filter!$B$7),OR(Filter!$E$7="(alle)",ISNUMBER(SEARCH(Filter!$E$7,$J16))),OR(Filter!$H$7="(alle)",ISNUMBER(SEARCH(Filter!$H$7,$I16))),OR(Filter!$B$9="",ISNUMBER(SEARCH(Filter!$B$9,$F16&" "&$G16)))),COUNTIF($O$6:$O15,">0")+1,0)) -> 10
B17: ANF-011 | C17: Betreibervertrag | D17: § 31 (1) | E17: Authentifizierung & Zugang | F17: Es muss Adhoc geladen werden können | G17: Der Auftragnehmer ist verpflichtet, potenziellen Endnutzern diskriminierungsfrei zu angemessenen Bedingungen ein Ad-hoc-Laden (punktuelles Aufladen i. S. d. AFIR) zu ermöglichen, soweit es ihm zumutbar ist (z. B. mit Blick auf die Bonität des Endnutzers). | H17: Adhoc muss möglich sein -> Schranke -> wie? | I17: eRound / SCS | J17: Authentifizierungskomponente / Schrankensteuerung | K17: erfasst | N17: im Umfang | O17: =IF($B17="",0,IF(AND(OR(Filter!$B$5="(alle)",$N17=Filter!$B$5),OR(Filter!$E$5="(alle)",$K17=Filter!$E$5),OR(Filter!$H$5="(alle)",$C17=Filter!$H$5),OR(Filter!$B$7="(alle)",$E17=Filter!$B$7),OR(Filter!$E$7="(alle)",ISNUMBER(SEARCH(Filter!$E$7,$J17))),OR(Filter!$H$7="(alle)",ISNUMBER(SEARCH(Filter!$H$7,$I17))),OR(Filter!$B$9="",ISNUMBER(SEARCH(Filter!$B$9,$F17&" "&$G17)))),COUNTIF($O$6:$O16,">0")+1,0)) -> 11
B18: ANF-012 | C18: Betreibervertrag | D18: § 38 (1) | E18: Nutzungszeit & Entgelte | F18: Blockadeentgelte und maximale Nutzungsdauer | G18: Start- und zeitabhängige Entgelte dürfen nicht erhoben werden. Dies gilt nicht für vertraglich vereinbarte Blockadeentgelte, die nach Ablauf einer maximalen Nutzungszeit vom Endnutzer bzw. Mobilitätsdienstleister unabhängig davon, welches der Zugangsmodelle des § 30 Abs. 2 gewählt wird, erhoben werden. Die maximale Nutzungszeit beginnt mit Beginn des Ladevorgangs und beträgt | H18: Schnittstelle Nutzungszeit | I18: eRound | J18: OCPI Buchungskalender | K18: erfasst | N18: außerhalb | O18: =IF($B18="",0,IF(AND(OR(Filter!$B$5="(alle)",$N18=Filter!$B$5),OR(Filter!$E$5="(alle)",$K18=Filter!$E$5),OR(Filter!$H$5="(alle)",$C18=Filter!$H$5),OR(Filter!$B$7="(alle)",$E18=Filter!$B$7),OR(Filter!$E$7="(alle)",ISNUMBER(SEARCH(Filter!$E$7,$J18))),OR(Filter!$H$7="(alle)",ISNUMBER(SEARCH(Filter!$H$7,$I18))),OR(Filter!$B$9="",ISNUMBER(SEARCH(Filter!$B$9,$F18&" "&$G18)))),COUNTIF($O$6:$O17,">0")+1,0)) -> 12
B19: ANF-013 | C19: Betreibervertrag | D19: § 38 (1) a | E19: Nutzungszeit & Entgelte | F19: Maximale Nutzungsdauer Zwischenladen ist 1h. | G19: bei MCS-Ladepunkten und CCS-Ladepunkten zum Zwischenladen 1 Stunde. | H19: Schnittstelle Nutzungszeit | I19: eRound | J19: OCPI Buchungskalender | K19: erfasst | N19: außerhalb | O19: =IF($B19="",0,IF(AND(OR(Filter!$B$5="(alle)",$N19=Filter!$B$5),OR(Filter!$E$5="(alle)",$K19=Filter!$E$5),OR(Filter!$H$5="(alle)",$C19=Filter!$H$5),OR(Filter!$B$7="(alle)",$E19=Filter!$B$7),OR(Filter!$E$7="(alle)",ISNUMBER(SEARCH(Filter!$E$7,$J19))),OR(Filter!$H$7="(alle)",ISNUMBER(SEARCH(Filter!$H$7,$I19))),OR(Filter!$B$9="",ISNUMBER(SEARCH(Filter!$B$9,$F19&" "&$G19)))),COUNTIF($O$6:$O18,">0")+1,0)) -> 13
B20: ANF-014 | C20: Betreibervertrag | D20: § 38 (1) b | E20: Nutzungszeit & Entgelte | F20: Maximale Nutzungsdauer Übernachtladen ist 12h. | G20: bei CCS-Ladepunkten zum Übernachtladen und MCS- oder CCS-Ladepunkte zum Zwischenladen, die zum Übernachtladen freigegeben wurden, 12 Stunden. | H20: Schnittstelle Nutzungszeit | I20: eRound | J20: OCPI Buchungskalender | K20: erfasst | N20: außerhalb | O20: =IF($B20="",0,IF(AND(OR(Filter!$B$5="(alle)",$N20=Filter!$B$5),OR(Filter!$E$5="(alle)",$K20=Filter!$E$5),OR(Filter!$H$5="(alle)",$C20=Filter!$H$5),OR(Filter!$B$7="(alle)",$E20=Filter!$B$7),OR(Filter!$E$7="(alle)",ISNUMBER(SEARCH(Filter!$E$7,$J20))),OR(Filter!$H$7="(alle)",ISNUMBER(SEARCH(Filter!$H$7,$I20))),OR(Filter!$B$9="",ISNUMBER(SEARCH(Filter!$B$9,$F20&" "&$G20)))),COUNTIF($O$6:$O19,">0")+1,0)) -> 14
B21: ANF-015 | C21: Betreibervertrag | D21: § 38 (2) | E21: Nutzungszeit & Entgelte | F21: Bei nidriger Auslastung kann die maximale Nutzungszeit vom AN verlängert werden. Bei nachfolgender Reservierung kann die maximale Nutzungszeit verkürzt werden. Bei Verkürzung zusätzliche Karenzzeit vor Blockadeentgeld von 5min. | G21: Der Auftragnehmer kann die maximalen Nutzungszeiten in Zeiten geringer Auslastung verlängern. Zudem kann er mit der Gestattung der Nutzung von MCS-Ladepunkten und CCS-Ladepunkten zum Zwischenladen dem Endnutzer bzw. Mobilitätsdienstleister auch ausdrücklich eine kürzere maximale Nutzungszeit einräumen, wenn wegen nachfolgender Reservierungen die maximale Nutzungszeit nach Absatz 1 lit. a nicht eingeräumt werden kann. In den Fällen des Satzes 2 ist dem Endnutzer bzw. Mobilitätsdienstleister zusätzlich eine Karenzzeit zum Verlassen des Ladeplatzes von 5 Minuten einzuräumen, nach deren Ablauf erst ein Blockadeentgelt erhoben werden darf | H21: SCS: Reaktionszeit System | I21: eRound | J21: OCPI Buchungskalender | K21: erfasst | N21: außerhalb | O21: =IF($B21="",0,IF(AND(OR(Filter!$B$5="(alle)",$N21=Filter!$B$5),OR(Filter!$E$5="(alle)",$K21=Filter!$E$5),OR(Filter!$H$5="(alle)",$C21=Filter!$H$5),OR(Filter!$B$7="(alle)",$E21=Filter!$B$7),OR(Filter!$E$7="(alle)",ISNUMBER(SEARCH(Filter!$E$7,$J21))),OR(Filter!$H$7="(alle)",ISNUMBER(SEARCH(Filter!$H$7,$I21))),OR(Filter!$B$9="",ISNUMBER(SEARCH(Filter!$B$9,$F21&" "&$G21)))),COUNTIF($O$6:$O20,">0")+1,0)) -> 15
B22: ANF-016 | C22: Betreibervertrag | D22: § 38 (3) | E22: Nutzungszeit & Entgelte | F22: Maximale Nutzungszeit endet mit Ablauf Reservierung. Maximale Nutzungsdauer kann vom AN verlängert werden. | G22: Hat ein Mobilitätsdienstleister einen Ladepunkt reserviert, so endet die maximale Nutzungszeit mit dem Ablauf des reservierten Zeitraums, auch wenn der Ladeplatz erst später belegt wurde, es sei denn, der Betreiber räumt ihm eine längere maximale Nutzungszeit ein. | I22: eRound | J22: OCPI Buchungskalender | K22: erfasst | N22: außerhalb | O22: =IF($B22="",0,IF(AND(OR(Filter!$B$5="(alle)",$N22=Filter!$B$5),OR(Filter!$E$5="(alle)",$K22=Filter!$E$5),OR(Filter!$H$5="(alle)",$C22=Filter!$H$5),OR(Filter!$B$7="(alle)",$E22=Filter!$B$7),OR(Filter!$E$7="(alle)",ISNUMBER(SEARCH(Filter!$E$7,$J22))),OR(Filter!$H$7="(alle)",ISNUMBER(SEARCH(Filter!$H$7,$I22))),OR(Filter!$B$9="",ISNUMBER(SEARCH(Filter!$B$9,$F22&" "&$G22)))),COUNTIF($O$6:$O21,">0")+1,0)) -> 16
B23: ANF-017 | C23: Betreibervertrag | D23: § 38 (4) | E23: Nutzungszeit & Entgelte | F23: Ladestart 15min Wartezeit Blockadeentgeld ggf. Pönalisierung Entfall maximale Nutzungsdauer | G23: Wird ein Ladevorgang nicht innerhalb von 15 Minuten nach Besetzung des Stellplatzes gestartet, entfällt die maximale Nutzungszeit und es kann ein Blockadeentgelt erhoben werden. | I23: eRound / SCS | J23: OCPI Buchungskalender / Abrechnungskomponente / Belegungsdetektion / Pönalisierungssystem | K23: erfasst | N23: außerhalb | O23: =IF($B23="",0,IF(AND(OR(Filter!$B$5="(alle)",$N23=Filter!$B$5),OR(Filter!$E$5="(alle)",$K23=Filter!$E$5),OR(Filter!$H$5="(alle)",$C23=Filter!$H$5),OR(Filter!$B$7="(alle)",$E23=Filter!$B$7),OR(Filter!$E$7="(alle)",ISNUMBER(SEARCH(Filter!$E$7,$J23))),OR(Filter!$H$7="(alle)",ISNUMBER(SEARCH(Filter!$H$7,$I23))),OR(Filter!$B$9="",ISNUMBER(SEARCH(Filter!$B$9,$F23&" "&$G23)))),COUNTIF($O$6:$O22,">0")+1,0)) -> 17
B24: ANF-018 | C24: Betreibervertrag | D24: § 38 (5) | E24: Nutzungszeit & Entgelte | F24: Kein Blockadeentgeld während Nachtruhezeiten, Sonn- und Feiertage der Bundesländer. | G24: An Sonn- und Feiertagen sowie zwischen 22 Uhr abends und 5 Uhr morgens (Nachtruhezeit) darf der Auftragnehmer für CCS-Ladepunkte zum Übernachtladen bzw. MCS- und CCS- Ladepunkten zum Zwischenladen, die zum Übernachtladen freigegeben wurden, keine Blockadeentgelte erheben. Hat der Ladevorgang bereits vor Beginn der Nachtruhezeiten begonnen und endet die maximale Nutzungszeit nach Absatz 1 während der Nachtruhezeit, so werden Blockadeentgelte mithin erst nach Ende der Nachtruhezeit berechnet. Satz 1 und 2 gelten entsprechend für Sonntage und gesetzliche Feiertage in dem Bundesland, in dem der jeweilige Standort gelegen ist. | H24: Einfluss auf Reservierung? | I24: eRound | J24: OCPI Buchungskalender | K24: erfasst | N24: außerhalb | O24: =IF($B24="",0,IF(AND(OR(Filter!$B$5="(alle)",$N24=Filter!$B$5),OR(Filter!$E$5="(alle)",$K24=Filter!$E$5),OR(Filter!$H$5="(alle)",$C24=Filter!$H$5),OR(Filter!$B$7="(alle)",$E24=Filter!$B$7),OR(Filter!$E$7="(alle)",ISNUMBER(SEARCH(Filter!$E$7,$J24))),OR(Filter!$H$7="(alle)",ISNUMBER(SEARCH(Filter!$H$7,$I24))),OR(Filter!$B$9="",ISNUMBER(SEARCH(Filter!$B$9,$F24&" "&$G24)))),COUNTIF($O$6:$O23,">0")+1,0)) -> 18
B25: ANF-019 | C25: Betreibervertrag | D25: § 38 (6) | E25: Nutzungszeit & Entgelte | F25: Blockadeentgeld Höhe 0,50€ / 0,15€ pro Min. | G25: Die Höhe des Blockadeentgelts darf bei MCS-Ladepunkten und bei CCS-Ladepunkten zum Zwischenladen maximal 0,50 €/Minute und bei CCS-Ladepunkten bzw. CCS- und MCS- Ladepunkten zum Zwischenladen, während des Zeitraums, für den sie zum Übernachtladen freigegeben wurden, maximal 0,15 €/Minute betragen. Das vereinnahmte Blockadeentgelt steht dem Auftragnehmer zu. | I25: eRound | J25: Abrechnungskomponente | K25: erfasst | N25: außerhalb | O25: =IF($B25="",0,IF(AND(OR(Filter!$B$5="(alle)",$N25=Filter!$B$5),OR(Filter!$E$5="(alle)",$K25=Filter!$E$5),OR(Filter!$H$5="(alle)",$C25=Filter!$H$5),OR(Filter!$B$7="(alle)",$E25=Filter!$B$7),OR(Filter!$E$7="(alle)",ISNUMBER(SEARCH(Filter!$E$7,$J25))),OR(Filter!$H$7="(alle)",ISNUMBER(SEARCH(Filter!$H$7,$I25))),OR(Filter!$B$9="",ISNUMBER(SEARCH(Filter!$B$9,$F25&" "&$G25)))),COUNTIF($O$6:$O24,">0")+1,0)) -> 19
B26: ANF-020 | C26: Betreibervertrag | D26: § 38 (7) | E26: Nutzungszeit & Entgelte | F26: Änderungen an maximaler Nutzungsdauer, Blockadeentgelt und Sperrzeiten mit Vorlauf möglich. | G26: Der Auftraggeber 2 kann die maximale Höhe der Blockadeentgelte nach Absatz 6 und die maximalen Nutzungszeiten bzw. Sperrzeiten für die Erhebung eines Blockadeentgeltes nach den Absätzen 1 bis 4 während der Laufzeit des Vertrags mit einer Frist von vier Monaten auf den Beginn eines Quartals schriftlich mit Wirkung gegenüber dem Auftragnehmer anpassen. Absenkungen der Höhe oder Verlängerungen die maximalen Nutzungszeiten bzw. Sperrzeiten sind nur mit Zustimmung des Auftragnehmers zulässig. Die Zustimmung gilt als erteilt, sofern der Auftragnehmer dem Auftraggeber 2 nicht innerhalb von zwei Wochen nach Mitteilung der geplanten Absenkung in Textform widerspricht. | I26: eRound | J26: Abrechnungskomponente | K26: erfasst | N26: außerhalb | O26: =IF($B26="",0,IF(AND(OR(Filter!$B$5="(alle)",$N26=Filter!$B$5),OR(Filter!$E$5="(alle)",$K26=Filter!$E$5),OR(Filter!$H$5="(alle)",$C26=Filter!$H$5),OR(Filter!$B$7="(alle)",$E26=Filter!$B$7),OR(Filter!$E$7="(alle)",ISNUMBER(SEARCH(Filter!$E$7,$J26))),OR(Filter!$H$7="(alle)",ISNUMBER(SEARCH(Filter!$H$7,$I26))),OR(Filter!$B$9="",ISNUMBER(SEARCH(Filter!$B$9,$F26&" "&$G26)))),COUNTIF($O$6:$O25,">0")+1,0)) -> 20
B27: ANF-021 | C27: Betreibervertrag | D27: § 38 (8) | E27: Nutzungszeit & Entgelte | F27: Mindestabnahmemenge und Vergütung bei Unterschreitung. | G27: Für jeden Übernachtladevorgang ist eine Mindestabnahmemenge von 150 kWh vorzusehen, dies gilt auch für MCS- und CCS-Ladepunkte, die nach Maßgabe dieses Vertrags zum Übernachtladen freigegeben werden. Wird die Mindestabnahmemenge nicht erreicht, so ist für die Differenz zwischen der tatsächlich abgenommenen Strommenge und der vertraglich vorgesehenen Mindestabnahmemenge vom Endnutzer bzw. Mobilitätsdienstleister eine Entschädigung in Höhe von 30 ct/kWh an den Auftragnehmer zu leisten. Die Entschädigungshöhe kann vom Auftraggeber 2 in Absprache mit dem Auftragnehmer zu einem späteren Zeitpunkt angepasst werden. | I27: eRound | J27: Abrechnungskomponente | K27: erfasst | N27: außerhalb | O27: =IF($B27="",0,IF(AND(OR(Filter!$B$5="(alle)",$N27=Filter!$B$5),OR(Filter!$E$5="(alle)",$K27=Filter!$E$5),OR(Filter!$H$5="(alle)",$C27=Filter!$H$5),OR(Filter!$B$7="(alle)",$E27=Filter!$B$7),OR(Filter!$E$7="(alle)",ISNUMBER(SEARCH(Filter!$E$7,$J27))),OR(Filter!$H$7="(alle)",ISNUMBER(SEARCH(Filter!$H$7,$I27))),OR(Filter!$B$9="",ISNUMBER(SEARCH(Filter!$B$9,$F27&" "&$G27)))),COUNTIF($O$6:$O26,">0")+1,0)) -> 21
B28: ANF-022 | C28: Betreibervertrag | D28: § 38 (9) | E28: Nutzungszeit & Entgelte | F28: Warnung NutzerIn vor Blockadeentgeld | G28: Endnutzer sind über eine gut sichtbare Beschilderung darauf hinzuweisen, dass der Stellplatz nach Abschluss des Ladevorgangs unverzüglich freizugeben ist; der Text der Beschilderung bedarf der Zustimmung des Auftraggebers 2. Zusätzlich soll der Endnutzer über eine App oder – falls er eine solche nicht nutzt – an der Ladeeinrichtung, vor Erhebung von Blockadeentgelt oder einer Vertragsstrafe einen Hinweis erhalten, dass der Ladevorgang beendet wurde und der Ladeplatz unverzüglich zu räumen ist | H28: ggf. Mitteilung? | I28: eRound | J28: Abrechnungskomponente / Beschilderung | K28: trifft nicht zu | L28: 46259 | M28: ggf. Thema für eRound ansonsten Beschilderung -> Bau GU | N28: außerhalb | O28: =IF($B28="",0,IF(AND(OR(Filter!$B$5="(alle)",$N28=Filter!$B$5),OR(Filter!$E$5="(alle)",$K28=Filter!$E$5),OR(Filter!$H$5="(alle)",$C28=Filter!$H$5),OR(Filter!$B$7="(alle)",$E28=Filter!$B$7),OR(Filter!$E$7="(alle)",ISNUMBER(SEARCH(Filter!$E$7,$J28))),OR(Filter!$H$7="(alle)",ISNUMBER(SEARCH(Filter!$H$7,$I28))),OR(Filter!$B$9="",ISNUMBER(SEARCH(Filter!$B$9,$F28&" "&$G28)))),COUNTIF($O$6:$O27,">0")+1,0)) -> 22
B29: ANF-023 | C29: Betreibervertrag | D29: § 42 (5) | E29: Betrieb & Auslastung | F29: Updates verpflichtend. | G29: Der Auftragnehmer ist auf Aufforderung des Auftraggebers 2 verpflichtet, die Ladeeinrichtungen technisch und/oder mit Blick auf die Software (insbesondere Schnittstellen und Protokolle) weiterzuentwickeln und zu verbessern. Die Erstattung der tatsächlich erforderlichen Kosten (zuzüglich angemessener Zuschläge für allgemeine Geschäftskosten, Wagnis und Gewinn) erfolgt nach den Regelungen über geänderte oder zusätzliche Leistungen nach § 40. | I29: Alpitronic | J29: Ladeeinrichtung | K29: trifft nicht zu | L29: 46260 | M29: Betrifft LIS | N29: außerhalb | O29: =IF($B29="",0,IF(AND(OR(Filter!$B$5="(alle)",$N29=Filter!$B$5),OR(Filter!$E$5="(alle)",$K29=Filter!$E$5),OR(Filter!$H$5="(alle)",$C29=Filter!$H$5),OR(Filter!$B$7="(alle)",$E29=Filter!$B$7),OR(Filter!$E$7="(alle)",ISNUMBER(SEARCH(Filter!$E$7,$J29))),OR(Filter!$H$7="(alle)",ISNUMBER(SEARCH(Filter!$H$7,$I29))),OR(Filter!$B$9="",ISNUMBER(SEARCH(Filter!$B$9,$F29&" "&$G29)))),COUNTIF($O$6:$O28,">0")+1,0)) -> 23
B30: ANF-024 | C30: Betreibervertrag | D30: § 22 (3) | E30: Betrieb & Auslastung | F30: Bei nidriger Auslastung: Zwischenladepunkte können zwischen 17 und 6 Uhr für Übernachtladen freigegeben werden. Aber mind. 40% Zwischenladepunkte, aber mind. 2 MCS und 1 CCS. | G30: CCS- und MCS-Ladepunkte zum Zwischenladen sind bei fehlender Auslastung ab 17:00 Uhr sowie an Wochenenden zum Übernachtladen freizugegeben. Es müssen jedoch auch in dieser Zeit 40 %, aber mindestens zwei MCS-Ladepunkte bzw. ein CCS-Ladepunkt, zum Zwischenladen für das Zwischenladen freigehalten werden. An Standorten, an denen nur ein MCS-Ladepunkt vorhanden ist, ist dieser für das Zwischenladen freizuhalten. Der Auftragnehmer hat sicherzustellen, dass die MCS- und CCS-Ladepunkte zum Zwischenladen ab 06:00 Uhr wieder für das Zwischenladen bereitstehen. Auftragnehmer und Auftraggeber 2 können sich je nach Auslastung der Ladepunkte auf abweichende Vorgaben zur Freigabe von Ladepunkten zum Zwischenladen einigen. | H30: 40% Zwischenladen | I30: eRound / SCS | J30: OCPI Buchungskalender / Dynamische Anzeige | K30: erfüllt | L30: 46259 | M30: eRound regelt - SCS zeigt an | N30: im Umfang | O30: =IF($B30="",0,IF(AND(OR(Filter!$B$5="(alle)",$N30=Filter!$B$5),OR(Filter!$E$5="(alle)",$K30=Filter!$E$5),OR(Filter!$H$5="(alle)",$C30=Filter!$H$5),OR(Filter!$B$7="(alle)",$E30=Filter!$B$7),OR(Filter!$E$7="(alle)",ISNUMBER(SEARCH(Filter!$E$7,$J30))),OR(Filter!$H$7="(alle)",ISNUMBER(SEARCH(Filter!$H$7,$I30))),OR(Filter!$B$9="",ISNUMBER(SEARCH(Filter!$B$9,$F30&" "&$G30)))),COUNTIF($O$6:$O29,">0")+1,0)) -> 24
B31: ANF-025 | C31: Betreibervertrag | D31: § 4 (52) | E31: Reservierung | F31: Mindestens AN plus ein weiterer. | G31: "Reservierungssystem“: Ein System zur Reservierung von Ladepunkten, das Mobilitätsdienstleistern ermöglicht, Ladepunkte bei dem Auftragnehmer und mindestens einem weiteren Ladepunktbetreiber zu reservieren. | H31: Mehr als 1 Anbieter | I31: Autostrom+ | J31: Anbindung | K31: bewertet | N31: außerhalb | O31: =IF($B31="",0,IF(AND(OR(Filter!$B$5="(alle)",$N31=Filter!$B$5),OR(Filter!$E$5="(alle)",$K31=Filter!$E$5),OR(Filter!$H$5="(alle)",$C31=Filter!$H$5),OR(Filter!$B$7="(alle)",$E31=Filter!$B$7),OR(Filter!$E$7="(alle)",ISNUMBER(SEARCH(Filter!$E$7,$J31))),OR(Filter!$H$7="(alle)",ISNUMBER(SEARCH(Filter!$H$7,$I31))),OR(Filter!$B$9="",ISNUMBER(SEARCH(Filter!$B$9,$F31&" "&$G31)))),COUNTIF($O$6:$O30,">0")+1,0)) -> 25
B32: ANF-026 | C32: Vertragsanlage 4 | D32: § 3.13.2 | E32: Zufahrt & Schranke | F32: Schrankenanlage auf Schrankeninsel | G32: Anforderungen an Lade-, Schrankeninseln und physische Zufahrtbeschränkungen | I32: Schrankenhersteller | J32: Schrankenanlage | K32: erfasst | L32: 46259 | M32: Schranke auf Schrankeninsel geplant | N32: im Umfang | O32: =IF($B32="",0,IF(AND(OR(Filter!$B$5="(alle)",$N32=Filter!$B$5),OR(Filter!$E$5="(alle)",$K32=Filter!$E$5),OR(Filter!$H$5="(alle)",$C32=Filter!$H$5),OR(Filter!$B$7="(alle)",$E32=Filter!$B$7),OR(Filter!$E$7="(alle)",ISNUMBER(SEARCH(Filter!$E$7,$J32))),OR(Filter!$H$7="(alle)",ISNUMBER(SEARCH(Filter!$H$7,$I32))),OR(Filter!$B$9="",ISNUMBER(SEARCH(Filter!$B$9,$F32&" "&$G32)))),COUNTIF($O$6:$O31,">0")+1,0)) -> 26
B33: ANF-027 | C33: Vertragsanlage 4 | D33: § 3.13.2 (1) | E33: Zufahrt & Schranke | F33: Schranke an Einfahrt Ladepunkt und Ausfahrt Ladepunkt. Bei Schrägparken Poller? | G33: Für den Zweck einer geordneten Zufahrt und Abfahrt sowie zur Sicherstellung der Verfügbarkeit der Ladeinfrastruktur sind Ladeinseln, Schrankeninseln sowie physische Zufahrtsbeschränkungen zu errichten. Diese dienen der Vermeidung unbefugter Inanspruchnahmen der Ladeplätze durch nichtladende Fahrzeuge aus allen Fahrtrichtungen und gewährleisten den bestimmungsgemäßen Betrieb der Ladeinfrastruktur. | H33: Schranke gefordert aus allen Richtungen | I33: Schrankenhersteller | J33: Schrankenanlage | K33: erfüllt | L33: 46259 | M33: Schranken auf beiden Seiten gepplant | N33: im Umfang | O33: =IF($B33="",0,IF(AND(OR(Filter!$B$5="(alle)",$N33=Filter!$B$5),OR(Filter!$E$5="(alle)",$K33=Filter!$E$5),OR(Filter!$H$5="(alle)",$C33=Filter!$H$5),OR(Filter!$B$7="(alle)",$E33=Filter!$B$7),OR(Filter!$E$7="(alle)",ISNUMBER(SEARCH(Filter!$E$7,$J33))),OR(Filter!$H$7="(alle)",ISNUMBER(SEARCH(Filter!$H$7,$I33))),OR(Filter!$B$9="",ISNUMBER(SEARCH(Filter!$B$9,$F33&" "&$G33)))),COUNTIF($O$6:$O32,">0")+1,0)) -> 27
B34: ANF-028 | C34: Vertragsanlage 4 | D34: § 3.13.4 | E34: Anzeige & Beschilderung | F34: Darstellung statischer und dynamischer Infos. | G34: Jeder Ladeplatz ist mit einer Kennzeichnung bzw. Anzeige mit folgenden Informationen auszurüsten: - Ladeplatznummer (Schild mit schwarzer Nummer auf weißem retroreflektierendem Hintergrund mit der Reflektionsklasse RA1 A) - Dynamische Anzeige mit - Typ des Ladeplatzes (MCS, CCS-Zwischenladen, CCS-Übernachtladen) - Leistung der Ladesäule - Status (verfügbar, reserviert ab XX:XX Uhr, belegt, außer Betrieb) - optional: Kennzeichen/Reservierungsnummer - Der Status des Ladeplatzes ist zusätzlich zur dynamischen Anzeige über eine farbcodierte Statuskennzeichnung darzustellen (Grün = verfügbar, Gelb = reserviert, Rot = belegt / außer Betrieb). Die farbcodierte Kennzeichnung dient der optischen Erkennbarkeit des Betriebszustands, insbesondere bei Ausfall der digitalen Anzeige. Die Platzierung der Kennzeichnung und Anzeigen hat bei Parkständen in Schrägaufstellung gut sichtbar auf der Schrankeninsel zu erfolgen. Die Platzierung der Kennzeichnung und Anzeigen hat bei Parkständen in Längsaufstellung gut sichtbar, dem entsprechenden Ladeplatz zugehörig im Bereich der Ladeinsel bzw. Ladesäule zu erfolgen. Weitere Anforderungen im Zusammenhang mit dynamischen Anzeigen sind der Vertragsanlage 6: Anforderungen an die Ladeinfrastruktur zu entnehmen. | H34: LED Anzeigen | I34: eRound / SCS | J34: Dynamische Anzeige | K34: erfüllt | L34: 46259 | M34: LIS zeigt Zustand an, Rest auf Anzeige | N34: im Umfang | O34: =IF($B34="",0,IF(AND(OR(Filter!$B$5="(alle)",$N34=Filter!$B$5),OR(Filter!$E$5="(alle)",$K34=Filter!$E$5),OR(Filter!$H$5="(alle)",$C34=Filter!$H$5),OR(Filter!$B$7="(alle)",$E34=Filter!$B$7),OR(Filter!$E$7="(alle)",ISNUMBER(SEARCH(Filter!$E$7,$J34))),OR(Filter!$H$7="(alle)",ISNUMBER(SEARCH(Filter!$H$7,$I34))),OR(Filter!$B$9="",ISNUMBER(SEARCH(Filter!$B$9,$F34&" "&$G34)))),COUNTIF($O$6:$O33,">0")+1,0)) -> 28
B35: ANF-029 | C35: Vertragsanlage 4 | D35: § 3.13.5 | E35: Zufahrt & Schranke | G35: Zur Gewährleistung eines sicheren und zuverlässigen Betriebs sind Schrankenanlagen und automatische Poller gemäß den folgenden technischen Anforderungen auszuführen: - robuste Witterungsbeständige und korrosionsgeschützte Ausführung für den ganzjährigen Einsatz im Außenbereich - automatisches Öffnen nach Abschluss des Ladevorgangs oder bei entsprechender Systemfreigabe - Erkennung der Fahrzeugposition sowie von Hindernissen vor dem Schließvorgang zur Vermeidung von Kollisionen - manuelle Notentriegelung durch autorisiertes Personal, um die Betriebsfähigkeit auch im Stör- oder Spannungsfall sicherzustellen - Integration in das zentrale Steuerungssystem (Backend oder lokales Steuergerät) zur Überwachung, Steuerung und Protokollierung der Schranken- und Pollerfunktionen - Schrankenbäume sind gemäß geltender Vorschriften mit rot-weißer Schraffierung zu kennzeichnen - Ausstattung von Schrankenbäumen und automatischen Pollern mit integrierter Beleuchtung zur Verbesserung der Sichtbarkeit und Betriebssicherheit; dabei sind die Vorgaben zur Blendwirkung gemäß ERS zu beachten Weitere Anforderungen für den Betrieb der Schranken sind der Vertragsanlage 6: Anforderungen an die Ladeinfrastruktur zu entnehmen. | H35: Öffnen bei Ladevorgangs-Ende wiederspricht sich mit Vertragsanlage 6 §10 Abs 2 Und funktioniert für Poller nicht -> da LKW darüber steht. Einheitliche Ansteuerung reduziert komplexität Bei Partnern | I35: Schrankenhersteller / SCS / eRound | J35: Schrankenanlage | K35: erfüllt | L35: 46260 | M35: Sicherheitseinrichtung geplant LED in Schrankenbaum geplant Integration des Schrankenstatus in eRound | N35: im Umfang | O35: =IF($B35="",0,IF(AND(OR(Filter!$B$5="(alle)",$N35=Filter!$B$5),OR(Filter!$E$5="(alle)",$K35=Filter!$E$5),OR(Filter!$H$5="(alle)",$C35=Filter!$H$5),OR(Filter!$B$7="(alle)",$E35=Filter!$B$7),OR(Filter!$E$7="(alle)",ISNUMBER(SEARCH(Filter!$E$7,$J35))),OR(Filter!$H$7="(alle)",ISNUMBER(SEARCH(Filter!$H$7,$I35))),OR(Filter!$B$9="",ISNUMBER(SEARCH(Filter!$B$9,$F35&" "&$G35)))),COUNTIF($O$6:$O34,">0")+1,0)) -> 29
B36: ANF-030 | C36: Vertragsanlage 4 | D36: § 3.13.2.2 | E36: Zufahrt & Schranke | G36: Bei Parkständen in Längsaufstellung sind automatisch versenkbare Poller zur Zufahrtsbeschränkung vorzusehen. Pro Parkstand sind drei Poller so anzuordnen, dass Fehlbelegungen ausgeschlossen sind. Die Abstände der Poller untereinander sowie zur Fahrgasse ergeben sich aus der Referenzplanung (Anhang 1a: Referenzplanung Längs- und Schrägparken). Das Ein- und Ausfahren zum Ladeplatz muss jederzeit gewährleistet bleiben, auch wenn die benachbarten Stellplätze durch ausgefahrene Poller gesichert sind. Die Dauer der Öffnungs- und Schließvorgänge ist auf das technisch mögliche Minimum zu begrenzen, um einen unterbrechungsarmen Verkehrsfluss sicherzustellen. Die Regelbreite der Parkstände muss 4,50 m betragen, die Länge entspricht den Vorgaben gemäß ERS für Längsparker von 25,00 m. Ergeben sich aufgrund der örtlichen Bestandsituation Abweichungen von der Regelbreite, ist die Befahrbarkeit stets durch einen Schleppkurvennachweis zu belegen. Die Poller sind elektrisch oder hydraulisch versenkbar auszuführen und müssen über eine automatische Höhenverstellung verfügen. Das Absenken erfolgt im Regelbetrieb ausschließlich bei autorisiertem Zugang (Ladevorgang oder Reservierung). Nach Beendigung des Ladevorgangs und nach erfolgter Ausfahrt des Fahrzeuges müssen sich Poller automatisch wieder heben. Eine Notabsenkung bei Ausfall muss durch autorisiertes Personal jederzeit möglich sein. Die Poller müssen widerstandsfähig gegen Anprall und sonstige auf Rastplätzen zu erwartende Einwirkungen sein sowie frost- und salzbeständig ausgeführt werden. Zudem ist ein Schutz gegen Fremdsteuerung und Manipulation sicherzustellen. Die Steuerung der Poller muss in das übergeordnete Zugangskontrollsystem integrierbar sein. Die Erkennbarkeit des Hindernissesist stets sicherzustellen. Die Poller sind zu beleuchten. Die Ladesäule ist im Randbereich des Stellplatzes in einem praktikablen Abstand zum fahrzeugseitigen Ladeanschluss zu positionieren. Die Fläche um die Ladesäule ist in Betonbauweise auszuführen und mit zweckdienlichen Mitteln gegen Anprall und sonstige übliche Einwirkungen auf Rastplätzen zu sichern. Befindet sich im Randbereich bereits eine Bordanlage, ist eine zusätzliche Hochbordabsicherung der Ladesäule nicht erforderlich. In allen übrigen Fällen ist, neben einem Anprallschutz, eine ausreichend dimensionierte Ladeinsel zum Schutz der Ladeinfrastruktur vorzusehen. | H36: Längsparken | I36: Autostrom+ | J36: – | K36: trifft nicht zu | L36: 45894 | M36: Los 2 hat keine Poller - betrifft nur längsparkplätze | N36: im Umfang | O36: =IF($B36="",0,IF(AND(OR(Filter!$B$5="(alle)",$N36=Filter!$B$5),OR(Filter!$E$5="(alle)",$K36=Filter!$E$5),OR(Filter!$H$5="(alle)",$C36=Filter!$H$5),OR(Filter!$B$7="(alle)",$E36=Filter!$B$7),OR(Filter!$E$7="(alle)",ISNUMBER(SEARCH(Filter!$E$7,$J36))),OR(Filter!$H$7="(alle)",ISNUMBER(SEARCH(Filter!$H$7,$I36))),OR(Filter!$B$9="",ISNUMBER(SEARCH(Filter!$B$9,$F36&" "&$G36)))),COUNTIF($O$6:$O35,">0")+1,0)) -> 30
B37: ANF-031 | C37: Vertragsanlage 4 | D37: § 3.6 | E37: Bau & Dokumentation | G37: Antrag auf Baufreigabe und Ausführungs-, Werk- und Montageplanung | H37: Mitwirkung an Planung und Freigabe | I37: Autostrom+ | J37: – | K37: bewertet | N37: außerhalb | O37: =IF($B37="",0,IF(AND(OR(Filter!$B$5="(alle)",$N37=Filter!$B$5),OR(Filter!$E$5="(alle)",$K37=Filter!$E$5),OR(Filter!$H$5="(alle)",$C37=Filter!$H$5),OR(Filter!$B$7="(alle)",$E37=Filter!$B$7),OR(Filter!$E$7="(alle)",ISNUMBER(SEARCH(Filter!$E$7,$J37))),OR(Filter!$H$7="(alle)",ISNUMBER(SEARCH(Filter!$H$7,$I37))),OR(Filter!$B$9="",ISNUMBER(SEARCH(Filter!$B$9,$F37&" "&$G37)))),COUNTIF($O$6:$O36,">0")+1,0)) -> 31
B38: ANF-032 | C38: Vertragsanlage 4 | D38: § 3.7 | E38: Bau & Dokumentation | G38: Bestandsunterlagen (As-Built) | H38: Verantwortlich für Dokumentation und Erstellung Unterlagen | I38: Autostrom+ | J38: – | K38: bewertet | N38: außerhalb | O38: =IF($B38="",0,IF(AND(OR(Filter!$B$5="(alle)",$N38=Filter!$B$5),OR(Filter!$E$5="(alle)",$K38=Filter!$E$5),OR(Filter!$H$5="(alle)",$C38=Filter!$H$5),OR(Filter!$B$7="(alle)",$E38=Filter!$B$7),OR(Filter!$E$7="(alle)",ISNUMBER(SEARCH(Filter!$E$7,$J38))),OR(Filter!$H$7="(alle)",ISNUMBER(SEARCH(Filter!$H$7,$I38))),OR(Filter!$B$9="",ISNUMBER(SEARCH(Filter!$B$9,$F38&" "&$G38)))),COUNTIF($O$6:$O37,">0")+1,0)) -> 32
B39: ANF-033 | C39: Vertragsanlage 6 | D39: § 8 | E39: Authentifizierung & Zugang | F39: Öffnung innerhalb von 45 Sekunden. | G39: Folgende Authentifizierungsoptionen (Anmeldung, Freischaltung der physischen Zufahrtsbeschränkungen und Start des Ladevorgangs etc.) müssen möglich sein: ▪ RFID-Token (Ladekarte etc.) von vertraglich angebundenen Mobilitätsdienstleister, ▪ App von vertraglich angebundenen Mobilitätsdienstleister, ▪ Ad hoc-Laden ohne Registrierung und ▪ ISO 15118 (nach Verfügbarkeit – s. o. Abschnitt 7.). Der Authentifizierungsvorgang zur Freigabe des Ladeplatzes muss innerhalb von maximal 45 Sekunden abgeschlossen sein und sollte so gestaltet sein, dass der Verkehrsfluss möglichst wenig beeinträchtigt wird. Die angegebene Zeitspanne umfasst alle praktische und technische Schritte der Authentifizierung bis zur Öffnung der Schranke bzw. des Pollers und gilt für alle vorgesehenen Zugangsarten | H39: 45 Sekunden (!) Wie (wer) Erfüllt das? Bieterfrage 441 nach Bezahlterminal ? | I39: eRound / SCS | J39: Authentifizierungskomponente / Schrankensteuerung | K39: erfasst | N39: im Umfang | O39: =IF($B39="",0,IF(AND(OR(Filter!$B$5="(alle)",$N39=Filter!$B$5),OR(Filter!$E$5="(alle)",$K39=Filter!$E$5),OR(Filter!$H$5="(alle)",$C39=Filter!$H$5),OR(Filter!$B$7="(alle)",$E39=Filter!$B$7),OR(Filter!$E$7="(alle)",ISNUMBER(SEARCH(Filter!$E$7,$J39))),OR(Filter!$H$7="(alle)",ISNUMBER(SEARCH(Filter!$H$7,$I39))),OR(Filter!$B$9="",ISNUMBER(SEARCH(Filter!$B$9,$F39&" "&$G39)))),COUNTIF($O$6:$O38,">0")+1,0)) -> 33
B40: ANF-034 | C40: Vertragsanlage 6 | D40: § 9 (1) | E40: Belegungsdetektion | F40: Belegungsdetektion ist gefordert. | G40: Jeder MCS- / CCS-Ladepunkt muss über eine Detektion verfügen. Die MCS- / CCSLadeplatzdetektion ist so auszustatten, dass Objekte auf dem zum MCS- / CCSLadepunkt gehörigen MCS- / CCS-Ladeplatz detektiert werden können. | H40: Deckensensoren Pönalisierung / Falschparker | I40: Schrankenhersteller / SCS | J40: Belegungsdetektion | K40: erfüllt | L40: 46259 | M40: Radarsensor stellt Belegung der Ladesäule bereit | N40: außerhalb | O40: =IF($B40="",0,IF(AND(OR(Filter!$B$5="(alle)",$N40=Filter!$B$5),OR(Filter!$E$5="(alle)",$K40=Filter!$E$5),OR(Filter!$H$5="(alle)",$C40=Filter!$H$5),OR(Filter!$B$7="(alle)",$E40=Filter!$B$7),OR(Filter!$E$7="(alle)",ISNUMBER(SEARCH(Filter!$E$7,$J40))),OR(Filter!$H$7="(alle)",ISNUMBER(SEARCH(Filter!$H$7,$I40))),OR(Filter!$B$9="",ISNUMBER(SEARCH(Filter!$B$9,$F40&" "&$G40)))),COUNTIF($O$6:$O39,">0")+1,0)) -> 34
B41: ANF-035 | C41: Vertragsanlage 6 | D41: § 9 (2) | E41: Belegungsdetektion | F41: Roaming-Infos müssen veröffentlicht werden Pönalisierung gefordert. Entfernung Falschparker gefordert. | G41: Die Information der Reservierung des MCS- / CCS-Ladepunkts muss dem IT-Backend der MCS- / CCS-Ladeeinrichtung zur Verfügung stehen und muss angebundenen Mobilitätsdienstleistern und Betreibern von Online-Plattformen zur Darstellung von Statusinformationen zur Verfügung gestellt werden. Zudem soll dem Betreiber die Pönalisierung und Entfernung von Falschparkern ermöglicht werden. | H41: Pönalisierung / Falschparker | I41: eRound / SCS | J41: OCPI Buchungskalender / Kennzeichenerfassung / Pönalisierungssystem | K41: erfasst | N41: im Umfang | O41: =IF($B41="",0,IF(AND(OR(Filter!$B$5="(alle)",$N41=Filter!$B$5),OR(Filter!$E$5="(alle)",$K41=Filter!$E$5),OR(Filter!$H$5="(alle)",$C41=Filter!$H$5),OR(Filter!$B$7="(alle)",$E41=Filter!$B$7),OR(Filter!$E$7="(alle)",ISNUMBER(SEARCH(Filter!$E$7,$J41))),OR(Filter!$H$7="(alle)",ISNUMBER(SEARCH(Filter!$H$7,$I41))),OR(Filter!$B$9="",ISNUMBER(SEARCH(Filter!$B$9,$F41&" "&$G41)))),COUNTIF($O$6:$O40,">0")+1,0)) -> 35
B42: ANF-036 | C42: Vertragsanlage 6 | D42: § 10 (1) | E42: Zufahrt & Schranke | F42: Einfahrtsschranke Ausfahrtsschranke Bei Nichtbelegung beide Schranken geschlossen. | G42: Jeder Ladeplatz ist mit einer Einfahrts- und einer Ausfahrtsschranke auszustatten. Die Schranken sind wie folgt zu betreiben: 1) Grundstellung: Beide Schranken sind bei Nichtbelegung des Ladeplatzes geschlossen. | I42: Schrankenhersteller | J42: Schrankensteuerung | K42: erfüllt | L42: 46259 | M42: Schranke wird konfiguriert, sodass diese zu ist | N42: im Umfang | O42: =IF($B42="",0,IF(AND(OR(Filter!$B$5="(alle)",$N42=Filter!$B$5),OR(Filter!$E$5="(alle)",$K42=Filter!$E$5),OR(Filter!$H$5="(alle)",$C42=Filter!$H$5),OR(Filter!$B$7="(alle)",$E42=Filter!$B$7),OR(Filter!$E$7="(alle)",ISNUMBER(SEARCH(Filter!$E$7,$J42))),OR(Filter!$H$7="(alle)",ISNUMBER(SEARCH(Filter!$H$7,$I42))),OR(Filter!$B$9="",ISNUMBER(SEARCH(Filter!$B$9,$F42&" "&$G42)))),COUNTIF($O$6:$O41,">0")+1,0)) -> 36
B43: ANF-037 | C43: Vertragsanlage 6 | D43: § 10 (2) | E43: Zufahrt & Schranke | F43: Einfahrtsschranke öffnet nach Authentifizierung. | G43: 2) Einfahrt: Die Einfahrtschranke öffnet sich nach erfolgreicher Authentifizierung und gewährt Zugang zum Ladeplatz. Sie bleibt während des gesamten Ladevorgangs geöffnet. | H43: Schnittstelle notwendig: Öffnen direkt nach Authentifizierung Schließen bei Ende Ladevorgang | I43: eRound / SCS | J43: Authentifizierungskomponente / Schrankensteuerung | K43: erfüllt | L43: 46259 | M43: Radarsensor erkennt Einfahrt bleibt geöffnet bis die Zone wieder frei ist. | N43: im Umfang | O43: =IF($B43="",0,IF(AND(OR(Filter!$B$5="(alle)",$N43=Filter!$B$5),OR(Filter!$E$5="(alle)",$K43=Filter!$E$5),OR(Filter!$H$5="(alle)",$C43=Filter!$H$5),OR(Filter!$B$7="(alle)",$E43=Filter!$B$7),OR(Filter!$E$7="(alle)",ISNUMBER(SEARCH(Filter!$E$7,$J43))),OR(Filter!$H$7="(alle)",ISNUMBER(SEARCH(Filter!$H$7,$I43))),OR(Filter!$B$9="",ISNUMBER(SEARCH(Filter!$B$9,$F43&" "&$G43)))),COUNTIF($O$6:$O42,">0")+1,0)) -> 37
B44: ANF-038 | C44: Vertragsanlage 6 | D44: § 10 (3) | E44: Zufahrt & Schranke | F44: Ausfahrtsschranke öffnet bei Ankunft LKW. | G44: 3) Ausfahrtsschaltung: Sobald der Lkw seine Parkposition auf dem Ladeplatz erreicht hat, öffnet sich die Ausfahrtsschranke. | H44: Ausfahrtsschranke also recht dumm -> komplett durch SCS möglich? | I44: Schrankenhersteller / SCS | J44: Schrankensteuerung | K44: erfüllt | L44: 46259 | M44: Die Schranke kann selbstständig öffnen und schließen | N44: im Umfang | O44: =IF($B44="",0,IF(AND(OR(Filter!$B$5="(alle)",$N44=Filter!$B$5),OR(Filter!$E$5="(alle)",$K44=Filter!$E$5),OR(Filter!$H$5="(alle)",$C44=Filter!$H$5),OR(Filter!$B$7="(alle)",$E44=Filter!$B$7),OR(Filter!$E$7="(alle)",ISNUMBER(SEARCH(Filter!$E$7,$J44))),OR(Filter!$H$7="(alle)",ISNUMBER(SEARCH(Filter!$H$7,$I44))),OR(Filter!$B$9="",ISNUMBER(SEARCH(Filter!$B$9,$F44&" "&$G44)))),COUNTIF($O$6:$O43,">0")+1,0)) -> 38
B45: ANF-039 | C45: Vertragsanlage 6 | D45: § 10 (4) | E45: Zufahrt & Schranke | F45: Ausfahrtsschranke schließt nach Verlassen des LKW. Fernsteuerung der Schranken. | G45: 4) Verlassen des Ladeplatzes: Nach Abschluss des Ladevorgangs und dem Verlassen des Ladeplatzes schließt sich die Ausfahrtsschranke wieder. Zudem ist dafür zu sorgen, dass die Einfahrts- und Ausfahrtsschranken im Notfall geöffnet werden können | H45: Schließen nach Ausfahrt -> Schranke selbst | I45: Schrankenhersteller | J45: Schrankensteuerung | K45: erfüllt | L45: 46259 | M45: Schranke schließt von alleine | N45: im Umfang | O45: =IF($B45="",0,IF(AND(OR(Filter!$B$5="(alle)",$N45=Filter!$B$5),OR(Filter!$E$5="(alle)",$K45=Filter!$E$5),OR(Filter!$H$5="(alle)",$C45=Filter!$H$5),OR(Filter!$B$7="(alle)",$E45=Filter!$B$7),OR(Filter!$E$7="(alle)",ISNUMBER(SEARCH(Filter!$E$7,$J45))),OR(Filter!$H$7="(alle)",ISNUMBER(SEARCH(Filter!$H$7,$I45))),OR(Filter!$B$9="",ISNUMBER(SEARCH(Filter!$B$9,$F45&" "&$G45)))),COUNTIF($O$6:$O44,">0")+1,0)) -> 39
B46: ANF-040 | C46: Vertragsanlage 6 | D46: § 4 | E46: Anzeige & Beschilderung | F46: Bezahlterminal für mehrere MCS/CCS Ladepunkte möglich. | G46: Display zur Anzeige von Informationen zum Ladevorgang (Ad hoc-Preis des CPO, geladene Energiemenge in kWh, Blockadeentgelt, Anweisungen zum Ablauf des Ladens). ▪ Das Display muss sowohl bei Tageslicht unter Sonneneinstrahlung als auch bei Dunkelheit gut ablesbar sein. ▪ Die Menüführung erfolgt mindestens in den Sprachen Deutsch und Englisch. ▪ RFID-Multireader zum Lesen von allen gängigen und zukünftig erwartbaren Ladekarten von Fahrstromanbietern (z.B. unter Berücksichtigung VDE-AR-E 2532-100) zum Authentifizieren und Starten von Ladevorgängen. Bezahlterminal für das Bezahlen von Ad hoc-Ladevorgängen (ohne Dauerschuldverhältnis). Dieses muss bargeldlose Zahlungen entsprechend den Vorgaben der AFIR ermöglichen. Zusätzliche Authentifizierungs- und Zahlungsmöglichkeiten können den Nutzern kostenlos eingeräumt werden. Dabei ist NFC-Technologie (Nahfeldkommunikation) und PinEingabe erforderlich. Von der Möglichkeit einer Pin-Eingabe kann abgesehen werden, wenn die Notwendigkeit der Pin-Eingabe dauerhaft bei allen relevanten Karten, insbesondere bei Präsentation einer physischen Karte zum Bezahlen von Fahrstrom entfällt. ▪ Ein Bezahlterminal kann auch zur Bezahlung von Ladevorgängen mehrerer MCS- bzw. CCS-Ladeeinrichtungen bzw. -Ladepunkten dienen | H46: Bezahlterminal kann für mehrere MCS / CCS genutzt werden | I46: eRound | J46: Authentifizierungskomponente | K46: erfüllt | L46: 46259 | M46: Jede LIS hat ein Display, rest in KANN-Anforderung | N46: im Umfang | O46: =IF($B46="",0,IF(AND(OR(Filter!$B$5="(alle)",$N46=Filter!$B$5),OR(Filter!$E$5="(alle)",$K46=Filter!$E$5),OR(Filter!$H$5="(alle)",$C46=Filter!$H$5),OR(Filter!$B$7="(alle)",$E46=Filter!$B$7),OR(Filter!$E$7="(alle)",ISNUMBER(SEARCH(Filter!$E$7,$J46))),OR(Filter!$H$7="(alle)",ISNUMBER(SEARCH(Filter!$H$7,$I46))),OR(Filter!$B$9="",ISNUMBER(SEARCH(Filter!$B$9,$F46&" "&$G46)))),COUNTIF($O$6:$O45,">0")+1,0)) -> 40
B47: ANF-041 | C47: Vertragsanlage 10 | D47: § 3.1 | E47: Monitoring & Reporting | F47: Benennung Datenpunkte zu Reservierungen im Monatsbericht. | G47: ab_total_reservations Anzahl Reservierungen je Ladepunkt ab_total_reservations_cancelled Anzahl stornierter Reservierungen je Ladepunkt ab_reservations_no-show Anzahl nicht eingehaltener Reservierungen je Ladepunkt | H47: Datentabelle Monatsbericht Verfügbarkeit | I47: eRound | J47: Monitoring | K47: erfasst | N47: außerhalb | O47: =IF($B47="",0,IF(AND(OR(Filter!$B$5="(alle)",$N47=Filter!$B$5),OR(Filter!$E$5="(alle)",$K47=Filter!$E$5),OR(Filter!$H$5="(alle)",$C47=Filter!$H$5),OR(Filter!$B$7="(alle)",$E47=Filter!$B$7),OR(Filter!$E$7="(alle)",ISNUMBER(SEARCH(Filter!$E$7,$J47))),OR(Filter!$H$7="(alle)",ISNUMBER(SEARCH(Filter!$H$7,$I47))),OR(Filter!$B$9="",ISNUMBER(SEARCH(Filter!$B$9,$F47&" "&$G47)))),COUNTIF($O$6:$O46,">0")+1,0)) -> 41
B48: ANF-042 | C48: Vertragsanlage 10 | D48: § 5 (d) | E48: Monitoring & Reporting | F48: Benennung Datenpunkte zu Reservierungen im Monatsbericht. | G48: total_reservation_cost Gesamtsumme aller Kosten im Zusammenhang mit der Reservierung eines Ladepunkts, einschließlich Festpreisbestandteilen (€) | H48: Datentabelle Reservierungskosten | I48: eRound | J48: Monitoring | K48: erfasst | N48: außerhalb | O48: =IF($B48="",0,IF(AND(OR(Filter!$B$5="(alle)",$N48=Filter!$B$5),OR(Filter!$E$5="(alle)",$K48=Filter!$E$5),OR(Filter!$H$5="(alle)",$C48=Filter!$H$5),OR(Filter!$B$7="(alle)",$E48=Filter!$B$7),OR(Filter!$E$7="(alle)",ISNUMBER(SEARCH(Filter!$E$7,$J48))),OR(Filter!$H$7="(alle)",ISNUMBER(SEARCH(Filter!$H$7,$I48))),OR(Filter!$B$9="",ISNUMBER(SEARCH(Filter!$B$9,$F48&" "&$G48)))),COUNTIF($O$6:$O47,">0")+1,0)) -> 42
B49: ANF-043 | C49: Vertragsanlage 13 | D49: § 8 (1) | E49: Reservierung | F49: Mehrfachbuchungen unterbinden | G49: Grundsätzlich möchte der Auftraggeber den Nutzern eine gewisse Flexibilität ermöglichen, da die Inanspruchnahme einer Reservierung z.B. aufgrund kurzfristiger Staus auch ohne Verschulden ggf. nicht wahrgenommen werden kann. Ein missbräuchliches Verhalten durch Nutzer, z.B. durch mehrfache Reservierungsbuchungen am gleichen Standort und am gleichen Tag, ist nicht im Interesse des Auftraggebers. Sollte sich ein solches Verhalten einstellen, besteht vor dem Hintergrund eines abweichenden Marktstandards nach §23 Abs. 3 des Betreibervertrags die Möglichkeit, die definierten Mindestvoraussetzungen an Reservierungsplattformen zu ändern. | H49: identisch zu Paragraph 38 - 1 | I49: eRound | J49: OCPI Buchungskalender | K49: erfasst | N49: außerhalb | O49: =IF($B49="",0,IF(AND(OR(Filter!$B$5="(alle)",$N49=Filter!$B$5),OR(Filter!$E$5="(alle)",$K49=Filter!$E$5),OR(Filter!$H$5="(alle)",$C49=Filter!$H$5),OR(Filter!$B$7="(alle)",$E49=Filter!$B$7),OR(Filter!$E$7="(alle)",ISNUMBER(SEARCH(Filter!$E$7,$J49))),OR(Filter!$H$7="(alle)",ISNUMBER(SEARCH(Filter!$H$7,$I49))),OR(Filter!$B$9="",ISNUMBER(SEARCH(Filter!$B$9,$F49&" "&$G49)))),COUNTIF($O$6:$O48,">0")+1,0)) -> 43
B50: ANF-044 | C50: Bieterfragenkatalog | D50: § 351 | E50: Belegungsdetektion | F50: Belegungsdetektion ist gefordert. | G50: Nein, auch bei installierten Zufahrtsbeschränkungen sind Sensoren als Redundanz zum Zweck der Detektion des Belegungsstatus des Ladeplatzes vorzusehen. | H50: // Antwort: Nein, auch bei installierten Zufahrtsbeschränkungen sind Sensoren als Redundanz zum Zweck der Detektion des Belegungsstatus des Ladeplatzes vorzusehen. | I50: SCS | J50: Belegungsdetektion | K50: erfasst | N50: im Umfang | O50: =IF($B50="",0,IF(AND(OR(Filter!$B$5="(alle)",$N50=Filter!$B$5),OR(Filter!$E$5="(alle)",$K50=Filter!$E$5),OR(Filter!$H$5="(alle)",$C50=Filter!$H$5),OR(Filter!$B$7="(alle)",$E50=Filter!$B$7),OR(Filter!$E$7="(alle)",ISNUMBER(SEARCH(Filter!$E$7,$J50))),OR(Filter!$H$7="(alle)",ISNUMBER(SEARCH(Filter!$H$7,$I50))),OR(Filter!$B$9="",ISNUMBER(SEARCH(Filter!$B$9,$F50&" "&$G50)))),COUNTIF($O$6:$O49,">0")+1,0)) -> 44
B51: ANF-045 | C51: Bieterfragenkatalog | D51: § 373 | E51: Reservierung | F51: OCPI Schnittstelle für Reservierungen ist gefordert. | G51: Frage: Laut Ziff. 3.4 im 4. Verfahrensbrief soll es nur ein zentrales Reservierungssystem geben. zugleich ist in § 23 Abs. 1 des Betreibervertrags von Reservierungsplattformen (Mehrzahl) die Rede. Wie passt dies zusammen? Antwort: Die überarbeitete Regelung im Betreibervertrag (§ 24) sieht vor, dass der Auftragnehmer eine Anbindung von Reservierungsplattformen über eine OCPI basierte Schnittstelle sicherstellt und Reservierungsplattformen über diese Schnittstelle ermöglicht, wenn sie die im Vertrag genannten Mindestvoraussetzungen erfüllt. | H51: OCPI Schnittstelle // Antwort: Die überarbeitete Regelung im Betreibervertrag (§ 24) sieht vor, dass der Auftragnehmer eine Anbindung von Reservierungsplattformen über eine OCPI basierte Schnittstelle sicherstellt und Reservierungsplattformen über diese Schnittstelle ermöglicht, wenn sie die im Vertrag genannten Mindestvoraussetzungen erfüllt. | I51: eRound | J51: OCPI Buchungskalender | K51: erfasst | N51: außerhalb | O51: =IF($B51="",0,IF(AND(OR(Filter!$B$5="(alle)",$N51=Filter!$B$5),OR(Filter!$E$5="(alle)",$K51=Filter!$E$5),OR(Filter!$H$5="(alle)",$C51=Filter!$H$5),OR(Filter!$B$7="(alle)",$E51=Filter!$B$7),OR(Filter!$E$7="(alle)",ISNUMBER(SEARCH(Filter!$E$7,$J51))),OR(Filter!$H$7="(alle)",ISNUMBER(SEARCH(Filter!$H$7,$I51))),OR(Filter!$B$9="",ISNUMBER(SEARCH(Filter!$B$9,$F51&" "&$G51)))),COUNTIF($O$6:$O50,">0")+1,0)) -> 45
B52: ANF-046 | C52: Bieterfragenkatalog | D52: § 374 | E52: Reservierung | F52: Anbindung muss deutschlandweit sichergestellt sein. | G52: Frage: Bei einer Reservierungsplattform handelt es sich um Software, die damit grundsätzlich weltweit verfügbar ist. Wie ist der Passus zu verstehen, dass die Plattform im gesamten Gebiet der Bundesrepublik Deutschland Reservierungen ermöglichen soll? Antwort: Es muss sichergestellt sein, dass die Reservierung für alle Rastanlagen mit Ladeinfrastruktur für E-LKW auf Bundesautobahnen möglich ist | H52: // Antwort: Es muss sichergestellt sein, dass die Reservierung für alle Rastanlagen mit Ladeinfrastruktur für E-LKW auf Bundesautobahnen möglich ist. | I52: Reservierungsplattform | J52: Anbindung | K52: erfasst | N52: außerhalb | O52: =IF($B52="",0,IF(AND(OR(Filter!$B$5="(alle)",$N52=Filter!$B$5),OR(Filter!$E$5="(alle)",$K52=Filter!$E$5),OR(Filter!$H$5="(alle)",$C52=Filter!$H$5),OR(Filter!$B$7="(alle)",$E52=Filter!$B$7),OR(Filter!$E$7="(alle)",ISNUMBER(SEARCH(Filter!$E$7,$J52))),OR(Filter!$H$7="(alle)",ISNUMBER(SEARCH(Filter!$H$7,$I52))),OR(Filter!$B$9="",ISNUMBER(SEARCH(Filter!$B$9,$F52&" "&$G52)))),COUNTIF($O$6:$O51,">0")+1,0)) -> 46
B53: ANF-047 | C53: Bieterfragenkatalog | D53: § 375 | E53: Nutzungszeit & Entgelte | G53: Es ist in Verbindung mit §36 das Erheben eines Blockadeentgeltes möglich, welches (bei Erscheinen) erst nach 75 min greift. Gehen wir recht in der Annahme, dass der CPO mit einer Belegung durch einen Reservierungsvorgang von 75 min rechnen muss, bevor er die Ladestation erneut als verfügbar meldet? | H53: leer 10.12.2025 // Antwort: Der Auftragnehmer muss nicht mit einer Belegung durch einen Reservierungsvorgang von 75min (beim Zwischenladen) rechnen. Der entsprechende Paragraph (jetzt §38) wurde im Betreibervertrag mit der Aufforderung zur Angebotsabge (Dezember 2025) überarbeitet. Die zuvor vorgesehene Wartezeit von 15 Minuten ist entfallen. Nach der neuen Regelung des § 38 Abs. 3 kann ein Blockadeentgelt im Fall einer Reservierung nach Ablauf des reservierten Zeitraums (ohne Wartezeit) erhoben werden. | I53: offen | J53: – | K53: erfasst | N53: außerhalb | O53: =IF($B53="",0,IF(AND(OR(Filter!$B$5="(alle)",$N53=Filter!$B$5),OR(Filter!$E$5="(alle)",$K53=Filter!$E$5),OR(Filter!$H$5="(alle)",$C53=Filter!$H$5),OR(Filter!$B$7="(alle)",$E53=Filter!$B$7),OR(Filter!$E$7="(alle)",ISNUMBER(SEARCH(Filter!$E$7,$J53))),OR(Filter!$H$7="(alle)",ISNUMBER(SEARCH(Filter!$H$7,$I53))),OR(Filter!$B$9="",ISNUMBER(SEARCH(Filter!$B$9,$F53&" "&$G53)))),COUNTIF($O$6:$O52,">0")+1,0)) -> 47
B54: ANF-048 | C54: Bieterfragenkatalog | D54: § 376 | E54: Nutzungszeit & Entgelte | G54: Frage: Der Vertrag sieht eine spätere mögliche Anpassung der Höhe des Blockadeentgeltes vor, aber keine Anpassungsoption hinsichtlich der Wartezeit. Gehen wir richtig in der Annahme, dass der AG nicht beabsichtigt, mögliche Optimierungspotenziale durch kürzere Wartezeiten während der Vertragslaufzeit zu realisieren? Antwort: Der Betreibervertrag wird mit der Aufforderung der Abgabe verbindlicher Angebote aktualisiert. | H54: Verweis Ausschreibungsunterlagen // Antwort: Der Betreibervertrag wird mit der Aufforderung der Abgabe verbindlicher Angebote aktualisiert. | I54: offen | J54: – | K54: erfasst | N54: außerhalb | O54: =IF($B54="",0,IF(AND(OR(Filter!$B$5="(alle)",$N54=Filter!$B$5),OR(Filter!$E$5="(alle)",$K54=Filter!$E$5),OR(Filter!$H$5="(alle)",$C54=Filter!$H$5),OR(Filter!$B$7="(alle)",$E54=Filter!$B$7),OR(Filter!$E$7="(alle)",ISNUMBER(SEARCH(Filter!$E$7,$J54))),OR(Filter!$H$7="(alle)",ISNUMBER(SEARCH(Filter!$H$7,$I54))),OR(Filter!$B$9="",ISNUMBER(SEARCH(Filter!$B$9,$F54&" "&$G54)))),COUNTIF($O$6:$O53,">0")+1,0)) -> 48
B55: ANF-049 | C55: Bieterfragenkatalog | D55: § 377 | E55: Reservierung | G55: Im In § 23 Abs. 4 BV heißt es, dass der Auftragnehmer verpflichtet ist, Endnutzern bzw. anderen Mobilitätsdienstleistern die Nutzung von MCS- oder CCS auch ohne vorherige Reservierung zu ermöglichen. Gehen wir recht in der Annahme, dass mit CCS nur Ladepunkte zum Zwischenladen gemeint sind und keine Ladepunkte zum Übernachtladen? Gehen wir weiter recht in der Annahme, dass sich dies auf die Ladepunkte eines Standortes bezieht und nicht auf jeden einzelnen Ladepunkt? Falls nein, heißt dies, dass es zulässig ist, ab weniger als 1h vor dem nächsten reservierten Lade Slot, keinen neuen Ladevorgang an dem betreffenden Ladepunkt mehr zuzulassen, da eine Blockiergebühr erst nach 60 min zulässig ist? Inwiefern sieht es die Vergabestelle als zulässig an, dass der adhoc-Nutzer einen spätesten Abfahrtzeitpunkt bestätigen muss, bei dessen Überschreiten eine Blockiergebühr erhoben werden darf? | H55: Verweis Ausschreibungsunterlagen // Antwort: Der Betreibervertrag wird mit der Aufforderung der Abgabe verbindlicher Angebote aktualisiert. | I55: offen | J55: – | K55: erfasst | N55: außerhalb | O55: =IF($B55="",0,IF(AND(OR(Filter!$B$5="(alle)",$N55=Filter!$B$5),OR(Filter!$E$5="(alle)",$K55=Filter!$E$5),OR(Filter!$H$5="(alle)",$C55=Filter!$H$5),OR(Filter!$B$7="(alle)",$E55=Filter!$B$7),OR(Filter!$E$7="(alle)",ISNUMBER(SEARCH(Filter!$E$7,$J55))),OR(Filter!$H$7="(alle)",ISNUMBER(SEARCH(Filter!$H$7,$I55))),OR(Filter!$B$9="",ISNUMBER(SEARCH(Filter!$B$9,$F55&" "&$G55)))),COUNTIF($O$6:$O54,">0")+1,0)) -> 49
B56: ANF-050 | C56: Bieterfragenkatalog | D56: § 378 | E56: Reservierung | F56: Anpassung möglich, bei ungewolltem Nutzerverhalten. | G56: Frage: Aus Sicht eines Kunden liegt es nahe, ggf. mehr als einen Standort zu reservieren, solange eine Buchung kostenlos storniert werden kann. Eine Stornierung und damit Freigabe eines Ladepunkts 30 Minuten vor dem geplanten Nutzungsbeginn führt jedoch dazu, dass die Wahrscheinlichkeit einer tatsächlichen Nutzung des zuvor reservierten Ladepunkts deutlich sinkt. Welche Maßnahmen sieht der AG vor, um ein derartiges Verhalten der Nutzer zu verhindern? Antwort: Grundsätzlich möchte der Auftraggeber den Nutzern eine gewisse Flexibilität ermöglichen, da die Inanspruchnahme einer Reservierung z.B. aufgrund kurzfristiger Staus auch ohne Verschulden ggf. nicht wahrgenommen werden kann. Ein missbräuchliches Verhalten durch Nutzer, z.B. durch mehrfache Reservierungsbuchungen am gleichen Standort und am gleichen Tag, ist nicht im Interesse des Auftraggebers. Sollte sich ein solches Verhalten einstellen, besteht vor dem Hintergrund eines abweichenden Marktstandards nach §23 Abs. 3 des Betreibervertrags die Möglichkeit, die definierten Mindestvoraussetzungen an Reservierungsplattformen zu ändern. | H56: // Antwort: Grundsätzlich möchte der Auftraggeber den Nutzern eine gewisse Flexibilität ermöglichen, da die Inanspruchnahme einer Reservierung z.B. aufgrund kurzfristiger Staus auch ohne Verschulden ggf. nicht wahrgenommen werden kann. Ein missbräuchliches Verhalten durch Nutzer, z.B. durch mehrfache Reservierungsbuchungen am gleichen Standort und am gleichen Tag, ist nicht im Interesse des Auftraggebers. Sollte sich ein solches Verhalten einstellen, besteht vor dem Hintergrund eines abweichenden Marktstandards nach §23 Abs. 3 des Betreibervertrags die Möglichkeit, die definierten Mindestvoraussetzungen an Reservierungsplattformen zu ändern. | I56: eRound | J56: OCPI Buchungskalender | K56: erfasst | N56: außerhalb | O56: =IF($B56="",0,IF(AND(OR(Filter!$B$5="(alle)",$N56=Filter!$B$5),OR(Filter!$E$5="(alle)",$K56=Filter!$E$5),OR(Filter!$H$5="(alle)",$C56=Filter!$H$5),OR(Filter!$B$7="(alle)",$E56=Filter!$B$7),OR(Filter!$E$7="(alle)",ISNUMBER(SEARCH(Filter!$E$7,$J56))),OR(Filter!$H$7="(alle)",ISNUMBER(SEARCH(Filter!$H$7,$I56))),OR(Filter!$B$9="",ISNUMBER(SEARCH(Filter!$B$9,$F56&" "&$G56)))),COUNTIF($O$6:$O55,">0")+1,0)) -> 50
B57: ANF-051 | C57: Bieterfragenkatalog | D57: § 455 | E57: Reservierung | F57: Reservierungsplattform ist nicht Teil der Ausschreibung. | G57: Frage: Im vierten Verfahrensbrief findet sich folgende Aussage unter 3.4.: „Die Vorgaben zum Reservierungssystem wurden dahingehend angepasst, dass es nunmehr ein zentrales Reservierungssystem geben wird.“ Im Betreibervertrag unter § 23, 2. Lesen wir allerdings: „Der Auftragnehmer ist verpflichtet, jeder Reservierungsplattform die Anbindung über die in Absatz 1 genannte Schnittstelle kostenfrei zu ermöglichen, soweit die Reservierungsplattform die folgenden Mindestvoraussetzungen erfüllt: (…)“ Dies stellt aus unserer Sicht ggf. einen Widerspruch dar. Wir bitten darum, die geplante Architektur des Reservierungsökosystems einmal zu erläutern. Antwort: Der Vertrag gilt. Sobald Reservierungsplattformen die im Vertrag genannten Mindestvoraussetzungen erfüllen, werden sie als anbindungsfähig und als zentral angesehen. In diesem Fall hat der Auftragnehmer auf Wunsch der externen Reservierungsplattformen eine Anbindung über eine OCPI-basierte Schnittstelle zu gewährleisten. Ein durch den Auftraggeber (z.B. per Vergabeverfahren) organisiertes, zentrales Reservierungssystem ist nicht in Planung. | H57: Zentrales Reservierungssystem // Antwort: Der Vertrag gilt. Sobald Reservierungsplattformen die im Vertrag genannten Mindestvoraussetzungen erfüllen, werden sie als anbindungsfähig und als zentral angesehen. In diesem Fall hat der Auftragnehmer auf Wunsch der externen Reservierungsplattformen eine Anbindung über eine OCPI-basierte Schnittstelle zu gewährleisten. Ein durch den Auftraggeber (z.B. per Vergabeverfahren) organisiertes, zentrales Reservierungssystem ist nicht in Planung. | I57: Reservierungsplattform | J57: Reservierungsplattform | K57: erfasst | N57: außerhalb | O57: =IF($B57="",0,IF(AND(OR(Filter!$B$5="(alle)",$N57=Filter!$B$5),OR(Filter!$E$5="(alle)",$K57=Filter!$E$5),OR(Filter!$H$5="(alle)",$C57=Filter!$H$5),OR(Filter!$B$7="(alle)",$E57=Filter!$B$7),OR(Filter!$E$7="(alle)",ISNUMBER(SEARCH(Filter!$E$7,$J57))),OR(Filter!$H$7="(alle)",ISNUMBER(SEARCH(Filter!$H$7,$I57))),OR(Filter!$B$9="",ISNUMBER(SEARCH(Filter!$B$9,$F57&" "&$G57)))),COUNTIF($O$6:$O56,">0")+1,0)) -> 51
B58: ANF-052 | C58: Bieterfragenkatalog | D58: § 370 | E58: Reservierung | F58: Sämtliche Infos via gängigen Roamingprotokoll / Marktstandard zur verfügung stellen. | G58: Frage: Welche Informationen der Reservierung sollen MSP und sonstigen bereitgestellt werden? Antwort: Es ist vom AN sicherzustellen, dass sämtliche Statusinformationen der Reservierungen bereitgestellt werden, die mittels der gängigen Roamingprotokolle übermittelt werden können und dem gängigen Marktstandard entsprechen. | H58: // Antwort: Es ist vom AN sicherzustellen, dass sämtliche Statusinformationen der Reservierungen bereitgestellt werden, die mittels der gängigen Roamingprotokolle übermittelt werden können und dem gängigen Marktstandard entsprechen. | I58: eRound | J58: OCPI Buchungskalender | K58: erfasst | N58: außerhalb | O58: =IF($B58="",0,IF(AND(OR(Filter!$B$5="(alle)",$N58=Filter!$B$5),OR(Filter!$E$5="(alle)",$K58=Filter!$E$5),OR(Filter!$H$5="(alle)",$C58=Filter!$H$5),OR(Filter!$B$7="(alle)",$E58=Filter!$B$7),OR(Filter!$E$7="(alle)",ISNUMBER(SEARCH(Filter!$E$7,$J58))),OR(Filter!$H$7="(alle)",ISNUMBER(SEARCH(Filter!$H$7,$I58))),OR(Filter!$B$9="",ISNUMBER(SEARCH(Filter!$B$9,$F58&" "&$G58)))),COUNTIF($O$6:$O57,">0")+1,0)) -> 52
B59: ANF-053 | C59: Bieterfragenkatalog | D59: Nr. 1 / S. 1 | E59: Vergabeverfahren & Angebot | F59: Klarstellung: Der Zuschlag wird nicht bereits auf die Erstangebote erteilt. Eine auf die Erstangebote bezogene Bindefrist ist daher gegenstandslos. | G59: Erster Verfahrensbrief, Formblatt A1, Fragenkatalog Nr. 61: In der Antwort auf Bieterfrage 61 ist ausgeführt, dass die Erstangebote indikativ sein werden und erst die Folgeangebote verbindlich. Unter Ziffer 3.1 des Ersten Verfahrensbriefs zum Verhandlungsverfahren heißt es entsprechend, dass der Auftraggeber den Zuschlag nicht auf das jeweils wirtschaftlichste Erstangebot erteilen wird. Unter Ziffer 4.6 des Ersten Verfahrensbriefs zum Verhandlungsverfahren heißt es allerdings, dass das Erstangebot zuschlagsfähig sein muss. Zudem soll der Bieter im Formblatt A1 – Angebotsschreiben erklären, sich bis zum Ablauf der Bindefrist an sein Erstangebot gebunden zu halten. Vor diesem Hintergrund bitten wir um Klarstellung: Ist unser Verständnis richtig, dass die Erstangebote rein indikativer Natur sind, also vom Auftraggeber unter keinen Umständen bezuschlagt werden können? Wie ist die Bindefrist zu verstehen? | H59: Bezug lt. Katalog: Erster Verfahrensvrief Katalogdatum: 08.01.2025 // Antwort: Der Zuschlag wird nicht bereits auf die Erstangeboite erteilt. Eine auf die Erstangebote bezogene Bindefrist ist daher gegenstandslos. | I59: Autostrom+ | J59: – | K59: trifft nicht zu | N59: außerhalb | O59: =IF($B59="",0,IF(AND(OR(Filter!$B$5="(alle)",$N59=Filter!$B$5),OR(Filter!$E$5="(alle)",$K59=Filter!$E$5),OR(Filter!$H$5="(alle)",$C59=Filter!$H$5),OR(Filter!$B$7="(alle)",$E59=Filter!$B$7),OR(Filter!$E$7="(alle)",ISNUMBER(SEARCH(Filter!$E$7,$J59))),OR(Filter!$H$7="(alle)",ISNUMBER(SEARCH(Filter!$H$7,$I59))),OR(Filter!$B$9="",ISNUMBER(SEARCH(Filter!$B$9,$F59&" "&$G59)))),COUNTIF($O$6:$O58,">0")+1,0)) -> 53
B60: ANF-054 | C60: Bieterfragenkatalog | D60: Nr. 2 / S. 1 | E60: Anzeige & Beschilderung | F60: Zusage / Ankündigung: Der AG beabsichtigt, die Unterlagen im weiteren Vergabeverfahren zur Verfügung zu stellen. | G60: Wann werden Anlage 04 Anhang 2 (Regelschnitt und Details für die Gestaltung der LKW- Ladeinfrastruktur) und Anlage 04 Anhang 3 (Markierungs- und Beschilderungsplan) zur Verfügung gestellt? | H60: Bezug lt. Katalog: LB Errichtung Katalogdatum: 08.01.2025 // Antwort: Der AG beabsichtigt, die Unterlagen im weiteren Vergabeverfahren zur Verfügung zu stellen. Die Erstellung eines Erstangebotes ist unabhängig davon auch ohne die genannten Unterlagen möglich. | I60: tbd | J60: Beschilderung | K60: erfasst | N60: außerhalb | O60: =IF($B60="",0,IF(AND(OR(Filter!$B$5="(alle)",$N60=Filter!$B$5),OR(Filter!$E$5="(alle)",$K60=Filter!$E$5),OR(Filter!$H$5="(alle)",$C60=Filter!$H$5),OR(Filter!$B$7="(alle)",$E60=Filter!$B$7),OR(Filter!$E$7="(alle)",ISNUMBER(SEARCH(Filter!$E$7,$J60))),OR(Filter!$H$7="(alle)",ISNUMBER(SEARCH(Filter!$H$7,$I60))),OR(Filter!$B$9="",ISNUMBER(SEARCH(Filter!$B$9,$F60&" "&$G60)))),COUNTIF($O$6:$O59,">0")+1,0)) -> 54
B61: ANF-055 | C61: Bieterfragenkatalog | D61: Nr. 3 / S. 1 | E61: Vertrag & Recht | F61: Klarstellung: Eine entsprechende Vertragsfassung wird allen für das Verhandlungsverfahren ausgewählten Bewerbern und Bewerbergemeinschaften mit Beantwortung zur Verfügung gestellt. | G61: Wir bitte zur besseren Nachverfolgung der Unterlagenfortschreibung um Zusendung einer ChangeVersion, um nachzuvollziehen in welchen Punkte das Vertragswerk angepasst wurde. | H61: Bezug lt. Katalog: Vertrag Katalogdatum: 09.01.2025 // Antwort: Eine entsprechende Vertragsfassung wird allen für das Verhandlungsverfahren ausgewählten Bewerbern und Bewerbergemeinschaften mit Beantwortung zur Verfügung gestellt. | I61: offen | J61: – | K61: erfasst | N61: außerhalb | O61: =IF($B61="",0,IF(AND(OR(Filter!$B$5="(alle)",$N61=Filter!$B$5),OR(Filter!$E$5="(alle)",$K61=Filter!$E$5),OR(Filter!$H$5="(alle)",$C61=Filter!$H$5),OR(Filter!$B$7="(alle)",$E61=Filter!$B$7),OR(Filter!$E$7="(alle)",ISNUMBER(SEARCH(Filter!$E$7,$J61))),OR(Filter!$H$7="(alle)",ISNUMBER(SEARCH(Filter!$H$7,$I61))),OR(Filter!$B$9="",ISNUMBER(SEARCH(Filter!$B$9,$F61&" "&$G61)))),COUNTIF($O$6:$O60,">0")+1,0)) -> 55
B62: ANF-056 | C62: Bieterfragenkatalog | D62: Nr. 4 / S. 1 | E62: Vertrag & Recht | F62: Zusage / Ankündigung: Anlage 9 zum Vertrag wird dem AN nach Vertragsschluss zu Verfügung gestellt (vgl. Vertragsanlage 4 LB Errichtung, S.13). | G62: Die für die zweite Phase der Ausschreibung geteilten Unterlagen enthalten NICHT die Vertragsanlagen 7 ("Logos") und 9 ("Ansprechpartner (losspezifisch)"). Wenn diese bewusst nicht geteilt werden - wann kann mit diesen gerechnet werden? | H62: Bezug lt. Katalog: Vertrag Katalogdatum: 09.01.2025 // Antwort: Anlage 9 zum Vertrag wird dem AN nach Vertragsschluss zu Verfügung gestellt (vgl. Vertragsanlage 4 LB Errichtung, S.13). Der AG beabsichtigt, die Anlage 7 im weiteren Vergabeverfahren zur Verfügung zu stellen. Die Erstellung eines Erstangebotes ist unabhängig davon auch ohne die genannten Unterlagen möglich. | I62: offen | J62: – | K62: erfasst | N62: außerhalb | O62: =IF($B62="",0,IF(AND(OR(Filter!$B$5="(alle)",$N62=Filter!$B$5),OR(Filter!$E$5="(alle)",$K62=Filter!$E$5),OR(Filter!$H$5="(alle)",$C62=Filter!$H$5),OR(Filter!$B$7="(alle)",$E62=Filter!$B$7),OR(Filter!$E$7="(alle)",ISNUMBER(SEARCH(Filter!$E$7,$J62))),OR(Filter!$H$7="(alle)",ISNUMBER(SEARCH(Filter!$H$7,$I62))),OR(Filter!$B$9="",ISNUMBER(SEARCH(Filter!$B$9,$F62&" "&$G62)))),COUNTIF($O$6:$O61,">0")+1,0)) -> 56
B63: ANF-057 | C63: Bieterfragenkatalog | D63: Nr. 5 / S. 1 | E63: Flächen & Genehmigungen | F63: Klarstellung: Die Unterlagen Vertragsanlage 2 ("Standortübersicht (losspezifisch)") und Anlage 2 zum Verfahrensbrief ("Gesamtübersicht über die Lose") wurden entsprechend aktualisiert und stehen Ihnen in der überarbeiteten Version zur … | G63: wir bitten um Klärung der folgenden Frage betreffend Anlage 2 zum Verfahrensbrief, Vertragsanlage 2_Standortübersicht und Vertragsanlage 3. In diesen Dokumenten ergeben sich teilweise Inkonsistenzen hinsichtlich der Anzahl der Ladepunkte je Standort. Könnten Sie diese bitte erläutern? Beispiel: Los 1, Standort Schwalenberg Ost: - laut Vertragsanlage 2_Standortübersicht, Los 1 und laut Anlage 2 zum Ersten Verfahrensbrief sollen an dem Standort 1 MCS-Ladepunkt, 1 CCS (Zwischenladepunkt) aufgebaut werden - laut Anlage 3 Los 1 (Vorplanungsdokument) sollen an dem Standort 6 MCS-Ladepunkte und 30 CCS Ladepunkt aufgebaut werden (keine Unterscheidung von Zwischenladen und Übernachtladen) | H63: Bezug lt. Katalog: Anlage 2/3 Katalogdatum: 09.01.2025 // Antwort: Die Unterlagen Vertragsanlage 2 ("Standortübersicht (losspezifisch)") und Anlage 2 zum Verfahrensbrief ("Gesamtübersicht über die Lose") wurden entsprechend aktualisiert und stehen Ihnen in der überarbeiteten Version zur Verfügung. Diese aktualisierten Dokumente sind dem Erstangebot zu Grunde zu legen. In den unverbindlichen Vorplanungen (Vertragsanlage 3 "Angaben und Informationen zu den Standorten (losspezifisch)") wird nicht zwischen CCS 400 und CCS 100 Ladepunkten unterschieden, da von gleichen baulichen Anforderungen auszugehen ist. Etwaige Unterschiede bei z. B. Kabelquerschnitten und anderen Komponenten sind zu berücksichtigen. | I63: offen | J63: – | K63: erfasst | N63: außerhalb | O63: =IF($B63="",0,IF(AND(OR(Filter!$B$5="(alle)",$N63=Filter!$B$5),OR(Filter!$E$5="(alle)",$K63=Filter!$E$5),OR(Filter!$H$5="(alle)",$C63=Filter!$H$5),OR(Filter!$B$7="(alle)",$E63=Filter!$B$7),OR(Filter!$E$7="(alle)",ISNUMBER(SEARCH(Filter!$E$7,$J63))),OR(Filter!$H$7="(alle)",ISNUMBER(SEARCH(Filter!$H$7,$I63))),OR(Filter!$B$9="",ISNUMBER(SEARCH(Filter!$B$9,$F63&" "&$G63)))),COUNTIF($O$6:$O62,">0")+1,0)) -> 57
B64: ANF-058 | C64: Bieterfragenkatalog | D64: Nr. 6 / S. 1 | E64: Netzanschluss & Energie | F64: Klarstellung: Die Unterlagen Vertragsanlage 2 ("Standortübersicht (losspezifish)") und Anlage 2 zum Verfahrensbrief ("Gesamtübersicht über die Lose") wurden entsprechend aktualisiert und stehen Ihnen in der überarbeiteten Version zur Verfügung. | G64: Es ist aufgefallen, dass in den Standortübersichten sowie in der Gesamtübersicht über die Lose (Anlagen 02) die Angaben in den Spalten "Nr. BAB" sowie "Geogr. Länge" und "Geogr. Breite" in weiten Teilen nicht mit der jeweiligen Kennung und Bezeichnung der Rastanlage (PWC-Anlage) zusammenpassen. Wir bitten um Überprüfung. Darüber hinaus unterscheiden sich die Angaben zur jeweiligen Anzahl der Ladepunkte in den Dokumenten der Vertragsanlagen 02 und der Vertragsanlage 05. Wir bitten um Überprüfung dieses Widerspruchs. Des Weiteren bitten wir um Überprüfung der Unterlagen in "Vertragsanlage 3 - Angaben und Informationen zu den einzelnen Standorten (losspezifisch)", da die dort enthaltenen Angaben teilweise nicht mit den vorgenannten Dokumenten aus "Anlage 2" übereinstimmen. Außerdem scheint in "Anlage 3" bei der "lfd. Nr." 74 die Angabe der "Nr. BAB" fehlerhaft zu sein. | H64: Bezug lt. Katalog: Vertragsanlage 02 Standortübersicht (losspezifisch) - Stand 06.01.2025 / Anlage 02_zum Verfahrensbrief_Gesamtübersich t über die Lose - Stand 06.01.2025 / Vertragsanlage 3 - Angaben und Informationen zu den einzelnen Standorten (losspezifisch) - Stand 06.01.2025 / Vertragsanlage 5 - Details zum Netzanschluss - Stand 06.01.25 Katalogdatum: 10.01.2025 // Antwort: Die Unterlagen Vertragsanlage 2 ("Standortübersicht (losspezifish)") und Anlage 2 zum Verfahrensbrief ("Gesamtübersicht über die Lose") wurden entsprechend aktualisiert und stehen Ihnen in der überarbeiteten Version zur Verfügung. Diese aktualisierten Dokumente sind dem Erstangebot zu Grunde zu legen. Die Angaben der Vertragsanlage 05 (Stand 06.01.2025) sind korrekt. | I64: offen | J64: – | K64: erfasst | N64: außerhalb | O64: =IF($B64="",0,IF(AND(OR(Filter!$B$5="(alle)",$N64=Filter!$B$5),OR(Filter!$E$5="(alle)",$K64=Filter!$E$5),OR(Filter!$H$5="(alle)",$C64=Filter!$H$5),OR(Filter!$B$7="(alle)",$E64=Filter!$B$7),OR(Filter!$E$7="(alle)",ISNUMBER(SEARCH(Filter!$E$7,$J64))),OR(Filter!$H$7="(alle)",ISNUMBER(SEARCH(Filter!$H$7,$I64))),OR(Filter!$B$9="",ISNUMBER(SEARCH(Filter!$B$9,$F64&" "&$G64)))),COUNTIF($O$6:$O63,">0")+1,0)) -> 58
B65: ANF-059 | C65: Bieterfragenkatalog | D65: Nr. 7 / S. 2 | E65: Vergabeverfahren & Angebot | F65: Klarstellung: Die Unterlagen Anlage 5 zum Verfahrensbrief wurden entsprechend aktualisiert und stehen Ihnen in der überarbeiteten Version zur Verfügung. | G65: Es ist aufgefallen, dass die Karte der Standorte fälschlicherweise als "Anlage 4 zum Verfahrensbrief" betitelt ist, während die Dateibezeichnung "Anlage 05..." ist. Wir bitten um Überprüfung. Des Weiteren bitten wir um Überprüfung der dargestellten Standorte, da mindestens 3 Standorte aus Los 4 nicht dargestellt sind. | H65: Bezug lt. Katalog: Anlage 05 zum Verfahrensbrief - Karte zur Losaufteilung - Stand 06.01.2025 Katalogdatum: 10.01.2025 // Antwort: Die Unterlagen Anlage 5 zum Verfahrensbrief wurden entsprechend aktualisiert und stehen Ihnen in der überarbeiteten Version zur Verfügung. Diese aktualisierte Dokumente ist dem Erstangebot zu Grunde zu legen. | I65: offen | J65: – | K65: trifft nicht zu | M65: Automatisch ausgewertet: Betrifft das Vergabeverfahren (Angebot, Wertung, Unterlagen), nicht die zu erbringende Leistung. Keiner Komponente zugeordnet. | N65: außerhalb | O65: =IF($B65="",0,IF(AND(OR(Filter!$B$5="(alle)",$N65=Filter!$B$5),OR(Filter!$E$5="(alle)",$K65=Filter!$E$5),OR(Filter!$H$5="(alle)",$C65=Filter!$H$5),OR(Filter!$B$7="(alle)",$E65=Filter!$B$7),OR(Filter!$E$7="(alle)",ISNUMBER(SEARCH(Filter!$E$7,$J65))),OR(Filter!$H$7="(alle)",ISNUMBER(SEARCH(Filter!$H$7,$I65))),OR(Filter!$B$9="",ISNUMBER(SEARCH(Filter!$B$9,$F65&" "&$G65)))),COUNTIF($O$6:$O64,">0")+1,0)) -> 59
B66: ANF-060 | C66: Bieterfragenkatalog | D66: Nr. 8 / S. 2 | E66: Vergabeverfahren & Angebot | F66: Zusage / Ankündigung: Siehe die Antwort auf Frage 1. Die Bieter sind dennoch aufgefordert ein zuschlagsfähiges Erstangebot abzugeben. | G66: Bindung an Erstangebot: Im ersten Verfahrensbrief ist in 4.6 von der Abgabe eines "zuschlagsfähigen" Erstangebots die Rede. Wird somit in der Verhandlungsphase nur das verhandelt, was als "Verhandlungsbedarf" im Formblatt A6 explizit angemeldet wird und der Rest ist bereits bindend im Falle eines Zuschlags? | H66: Bezug lt. Katalog: Verfahrensbrief in 4.6 Katalogdatum: 14.01.2025 // Antwort: Siehe die Antwort auf Frage 1. Die Bieter sind dennoch aufgefordert ein zuschlagsfähiges Erstangebot abzugeben. In den Verhandlungen wird der von den Bietern im Formblatt A6 addressierte Verhandlungsbedarf behandelt. Im Anschluss an die Verhandlungen werden den Bietern entsprechend der Ergebnisse der Verhandlungen überarbeitete Vergabeunterlagen zur Verfügung gestellt. Auf der Grundlage dieser überarbeiteten Vergabeunterlagen werden die Bieter aufgefordert werden ein verbindliches Angbeot abzugeben. Dieses verbindliche Angbeot, auf das der AG beabsichtigt den Zuschlag zu erteilen, wird vollständig neu einzureichen sein und nicht auf Bestandteile des Erstangebots bezunehmen. | I66: offen | J66: – | K66: trifft nicht zu | M66: Automatisch ausgewertet: Betrifft das Vergabeverfahren (Angebot, Wertung, Unterlagen), nicht die zu erbringende Leistung. Keiner Komponente zugeordnet. | N66: außerhalb | O66: =IF($B66="",0,IF(AND(OR(Filter!$B$5="(alle)",$N66=Filter!$B$5),OR(Filter!$E$5="(alle)",$K66=Filter!$E$5),OR(Filter!$H$5="(alle)",$C66=Filter!$H$5),OR(Filter!$B$7="(alle)",$E66=Filter!$B$7),OR(Filter!$E$7="(alle)",ISNUMBER(SEARCH(Filter!$E$7,$J66))),OR(Filter!$H$7="(alle)",ISNUMBER(SEARCH(Filter!$H$7,$I66))),OR(Filter!$B$9="",ISNUMBER(SEARCH(Filter!$B$9,$F66&" "&$G66)))),COUNTIF($O$6:$O65,">0")+1,0)) -> 60
B67: ANF-061 | C67: Bieterfragenkatalog | D67: Nr. 9 / S. 2 | E67: Netzanschluss & Energie | F67: Klarstellung: Die Pflicht, mit allen Mobilitätsdienstleistern diskriminierungsfrei Verträge zu schließen ist in §27(1) des Hauptvertrags geregelt. | G67: Müssen die Teilnehmer einen Vertrag mit jedem möglichen Mobilitätsdienstleister für das Durchleitungsmodell abschließen oder kann dies von einem einzelnen Akteur aggregiert werden? Vergleichbar mit einer Roaming-Plattform im MSP-Geschäft. | H67: Bezug lt. Katalog: BYOP Katalogdatum: 14.01.2025 // Antwort: Die Pflicht, mit allen Mobilitätsdienstleistern diskriminierungsfrei Verträge zu schließen ist in §27(1) des Hauptvertrags geregelt. Der Mobilitätsdienstleister kann dabei optional das Durchleitungsmodell wählen und den Strom bilanziell bereitstellen (§28 des Hauptvertrags). Erforderlich ist auch bei Wahl des Durchleitungsmodells der Abschluss einer Vereinbarung zwischen Ladepunktbetreiber und Mobilitätsdienstleister (vgl. Anlage 14 ). Es entstehen also bilaterale Verträge zur Durchleitung. Eine vertragliche Plattform-Lösung ist nicht zwingend vorgesehen, aber denkbar. | I67: eRound | J67: OCPI Buchungskalender | K67: erfasst | N67: außerhalb | O67: =IF($B67="",0,IF(AND(OR(Filter!$B$5="(alle)",$N67=Filter!$B$5),OR(Filter!$E$5="(alle)",$K67=Filter!$E$5),OR(Filter!$H$5="(alle)",$C67=Filter!$H$5),OR(Filter!$B$7="(alle)",$E67=Filter!$B$7),OR(Filter!$E$7="(alle)",ISNUMBER(SEARCH(Filter!$E$7,$J67))),OR(Filter!$H$7="(alle)",ISNUMBER(SEARCH(Filter!$H$7,$I67))),OR(Filter!$B$9="",ISNUMBER(SEARCH(Filter!$B$9,$F67&" "&$G67)))),COUNTIF($O$6:$O66,">0")+1,0)) -> 61
B68: ANF-062 | C68: Bieterfragenkatalog | D68: Nr. 10 / S. 2 | E68: Vergabeverfahren & Angebot | F68: Bestätigt: der Rastplatz mit der Kennung DE-ST-001249 ist "Brockenblick Ost". | G68: Bezieht sich "Parkplatz Brockenblick Ost" (DE-ST-001249) tatsächlich auf "Parkplatz Brocken Nord"? | H68: Bezug lt. Katalog: Standortbezeichnung Katalogdatum: 14.01.2025 // Antwort: Ja, der Rastplatz mit der Kennung DE-ST-001249 ist "Brockenblick Ost". Für die Indentifikation der Standorte sind die angegebene Kennung und die in Anlage 2 zum Verfahrensbrief "Gesamtübersicht über die Lose" genannten Geokoordinaten maßgebend. Rastanalagenbezeichungen können in unterschiedlichen Kartensystemen (insb. von Drittanbietern) abweichen bzw. sind nicht immer aktuell. | I68: offen | J68: – | K68: trifft nicht zu | M68: Automatisch ausgewertet: Betrifft das Vergabeverfahren (Angebot, Wertung, Unterlagen), nicht die zu erbringende Leistung. Keiner Komponente zugeordnet. | N68: außerhalb | O68: =IF($B68="",0,IF(AND(OR(Filter!$B$5="(alle)",$N68=Filter!$B$5),OR(Filter!$E$5="(alle)",$K68=Filter!$E$5),OR(Filter!$H$5="(alle)",$C68=Filter!$H$5),OR(Filter!$B$7="(alle)",$E68=Filter!$B$7),OR(Filter!$E$7="(alle)",ISNUMBER(SEARCH(Filter!$E$7,$J68))),OR(Filter!$H$7="(alle)",ISNUMBER(SEARCH(Filter!$H$7,$I68))),OR(Filter!$B$9="",ISNUMBER(SEARCH(Filter!$B$9,$F68&" "&$G68)))),COUNTIF($O$6:$O67,">0")+1,0)) -> 62
B69: ANF-063 | C69: Bieterfragenkatalog | D69: Nr. 11 / S. 2 | E69: Netzanschluss & Energie | F69: Verweis des Auftraggebers auf die Antwort zu Bieterfrage 6. | G69: Die zur Verfügung gestellten standortspezifischen Dokumente bieten keine kongruenten Informationen. Die Anzahl der CCS/MCS-Ladepunkte pro Standort ist in den Unterlagen nicht konsistent: - 20250106_Vertragsanlage 02_Standortübersicht (losspezifisch) - 20250106_Vertragsanlage 05_Details zum Netzanschluss Bitte bestätigen Sie, welche Version korrekt ist und passen Sie die Dokumente entsprechend an. | H69: Bezug lt. Katalog: Ladeinfrastruktur je Standort Katalogdatum: 14.01.2025 // Antwort: siehe die Antwort auf Frage 6 | I69: offen | J69: – | K69: trifft nicht zu | M69: Automatisch ausgewertet: Die Antwort des Auftraggebers verweist ausschließlich auf Bieterfrage 6. Keine eigenständige Anforderung – der Inhalt ist unter der dort erfassten Zeile nachzuhalten. | N69: außerhalb | O69: =IF($B69="",0,IF(AND(OR(Filter!$B$5="(alle)",$N69=Filter!$B$5),OR(Filter!$E$5="(alle)",$K69=Filter!$E$5),OR(Filter!$H$5="(alle)",$C69=Filter!$H$5),OR(Filter!$B$7="(alle)",$E69=Filter!$B$7),OR(Filter!$E$7="(alle)",ISNUMBER(SEARCH(Filter!$E$7,$J69))),OR(Filter!$H$7="(alle)",ISNUMBER(SEARCH(Filter!$H$7,$I69))),OR(Filter!$B$9="",ISNUMBER(SEARCH(Filter!$B$9,$F69&" "&$G69)))),COUNTIF($O$6:$O68,">0")+1,0)) -> 63
B70: ANF-064 | C70: Bieterfragenkatalog | D70: Nr. 12 / S. 2 | E70: Bau & Dokumentation | F70: Klarstellung: Siehe Anlage 1 zum Verfahrensbrief - Betreibervertrag, §39 Abs. 3: "Das Errichtungsentgelt für den betreffenden Standort wird, sofern die jeweils nachfolgenden Zahlungsvoraussetzungen vorliegen, [...] gezahlt, […]." | G70: Sie schreiben: "Der Abschluss der Errichtungsphase wird mit der Verkehrsfreigabe des letzten Standortes im Los erreicht." Werden erst im Anschluss daran die ersten 50% der Errichtungskosten aller Standorte überwiesen, oder kann man nach jeder einzelnen Errichtung bereits 50% der Errichtungskosten anfordern? | H70: Bezug lt. Katalog: - Katalogdatum: 15.01.2024 // Antwort: Siehe Anlage 1 zum Verfahrensbrief - Betreibervertrag, §39 Abs. 3: "Das Errichtungsentgelt für den betreffenden Standort wird, sofern die jeweils nachfolgenden Zahlungsvoraussetzungen vorliegen, [...] gezahlt, […]." | I70: offen | J70: – | K70: erfasst | N70: außerhalb | O70: =IF($B70="",0,IF(AND(OR(Filter!$B$5="(alle)",$N70=Filter!$B$5),OR(Filter!$E$5="(alle)",$K70=Filter!$E$5),OR(Filter!$H$5="(alle)",$C70=Filter!$H$5),OR(Filter!$B$7="(alle)",$E70=Filter!$B$7),OR(Filter!$E$7="(alle)",ISNUMBER(SEARCH(Filter!$E$7,$J70))),OR(Filter!$H$7="(alle)",ISNUMBER(SEARCH(Filter!$H$7,$I70))),OR(Filter!$B$9="",ISNUMBER(SEARCH(Filter!$B$9,$F70&" "&$G70)))),COUNTIF($O$6:$O69,">0")+1,0)) -> 64
B71: ANF-065 | C71: Bieterfragenkatalog | D71: Nr. 13 / S. 2 | E71: Vergabeverfahren & Angebot | F71: Verweis des Auftraggebers auf die Antwort zu Bieterfrage 1. | G71: Nach Ablauf der Angebotsfrist bleibt der Bieter bis zum Ablauf der vom öffentlichen Auftraggeber festgelegten Bindefrist an sein Angebot gebunden." Inwiefern ist damit das Erstangebot bindend? | H71: Bezug lt. Katalog: - Katalogdatum: 15.01.2024 // Antwort: siehe die Antwort auf Frage 1 | I71: offen | J71: – | K71: trifft nicht zu | M71: Automatisch ausgewertet: Die Antwort des Auftraggebers verweist ausschließlich auf Bieterfrage 1. Keine eigenständige Anforderung – der Inhalt ist unter der dort erfassten Zeile nachzuhalten. | N71: außerhalb | O71: =IF($B71="",0,IF(AND(OR(Filter!$B$5="(alle)",$N71=Filter!$B$5),OR(Filter!$E$5="(alle)",$K71=Filter!$E$5),OR(Filter!$H$5="(alle)",$C71=Filter!$H$5),OR(Filter!$B$7="(alle)",$E71=Filter!$B$7),OR(Filter!$E$7="(alle)",ISNUMBER(SEARCH(Filter!$E$7,$J71))),OR(Filter!$H$7="(alle)",ISNUMBER(SEARCH(Filter!$H$7,$I71))),OR(Filter!$B$9="",ISNUMBER(SEARCH(Filter!$B$9,$F71&" "&$G71)))),COUNTIF($O$6:$O70,">0")+1,0)) -> 65
B72: ANF-066 | C72: Bieterfragenkatalog | D72: Nr. 14 / S. 2 | E72: Reservierung | F72: Klarstellung: Etwaige IT Entwicklungskosten sind im Betreiberentgelt kalkulieren. Soweit das Vorgehen als unzweckmäßig erachtet wird, kann dies im Rahmen des Verhanldungsbedarfs (Formblatt A6) an den AG addressiert werden. | G72: In welcher Kostenposition Ihrer Vorlage werden IT Entwicklungskosten für die Entwicklung von bspw. Reservierungstool und Durchleitungsmodell hinterlegt? | H72: Bezug lt. Katalog: - Katalogdatum: 15.01.2024 // Antwort: Etwaige IT Entwicklungskosten sind im Betreiberentgelt kalkulieren. Soweit das Vorgehen als unzweckmäßig erachtet wird, kann dies im Rahmen des Verhanldungsbedarfs (Formblatt A6) an den AG addressiert werden. | I72: eRound | J72: OCPI Buchungskalender | K72: erfasst | N72: außerhalb | O72: =IF($B72="",0,IF(AND(OR(Filter!$B$5="(alle)",$N72=Filter!$B$5),OR(Filter!$E$5="(alle)",$K72=Filter!$E$5),OR(Filter!$H$5="(alle)",$C72=Filter!$H$5),OR(Filter!$B$7="(alle)",$E72=Filter!$B$7),OR(Filter!$E$7="(alle)",ISNUMBER(SEARCH(Filter!$E$7,$J72))),OR(Filter!$H$7="(alle)",ISNUMBER(SEARCH(Filter!$H$7,$I72))),OR(Filter!$B$9="",ISNUMBER(SEARCH(Filter!$B$9,$F72&" "&$G72)))),COUNTIF($O$6:$O71,">0")+1,0)) -> 66
B73: ANF-067 | C73: Bieterfragenkatalog | D73: Nr. 15 / S. 2 | E73: Netzanschluss & Energie | F73: Klarstellung: Die Verlustenergie wäre nach den aktuellen vertraglichen Regelungen im Angebot in das Betreiberentgelt einzupreisen. | G73: In welchem Kostenposten wird die im Durchleitungsmodell auftretende Verlustenergie hinterlegt? Derzeit schätzen wir die Kosten dafür auf 2-stellige Millionenbeträge pro Jahr. | H73: Bezug lt. Katalog: - Katalogdatum: 15.01.2024 // Antwort: Die Verlustenergie wäre nach den aktuellen vertraglichen Regelungen im Angebot in das Betreiberentgelt einzupreisen. Einzelheiten können in den Bietergesprächen thematisiert werden. | I73: offen | J73: – | K73: erfasst | N73: außerhalb | O73: =IF($B73="",0,IF(AND(OR(Filter!$B$5="(alle)",$N73=Filter!$B$5),OR(Filter!$E$5="(alle)",$K73=Filter!$E$5),OR(Filter!$H$5="(alle)",$C73=Filter!$H$5),OR(Filter!$B$7="(alle)",$E73=Filter!$B$7),OR(Filter!$E$7="(alle)",ISNUMBER(SEARCH(Filter!$E$7,$J73))),OR(Filter!$H$7="(alle)",ISNUMBER(SEARCH(Filter!$H$7,$I73))),OR(Filter!$B$9="",ISNUMBER(SEARCH(Filter!$B$9,$F73&" "&$G73)))),COUNTIF($O$6:$O72,">0")+1,0)) -> 67
B74: ANF-068 | C74: Bieterfragenkatalog | D74: Nr. 16 / S. 2 | E74: Netzanschluss & Energie | F74: Klarstellung: Die bilanzielle Zuordnung der Energie im Durchleitungsmodell erfolgt über eine Zuordnungsermächtigung des EMP/MSP zu einem Bilanzkreis. | G74: In welchem Kostenposten werden Risikopositionen zu Lieferantenausfällen beim Durchleitungsmodell hinterlegt? Diese sind auslastungsabhängig und somit nicht prognostizierbar. | H74: Bezug lt. Katalog: - Katalogdatum: 15.01.2024 // Antwort: Die bilanzielle Zuordnung der Energie im Durchleitungsmodell erfolgt über eine Zuordnungsermächtigung des EMP/MSP zu einem Bilanzkreis. Diese Zuordnungsermächtigung kann solange durch den Betreiber genutzt werden, bis der Bilanzkreis, auf den sich die Zuordnungsermächtigung bezieht, gekündigt wurde. Der Betreiber muss - entsprechend einem normalen Netzbetreiber - also sicherstellen, dass nach Kündigung des Bilanzkreises (Veröffentlichung der ÜNB) keine Ladevorgänge mehr im Rahmen des Durchleitungsmodells erfolgen. "Lieferantenausfälle" führen beim Betreiber daher grundsätzlich nicht zu Kosten bezogen auf die im Rahmen des Durchleitungsmodells entnommenen Strommengen. | I74: offen | J74: – | K74: erfasst | N74: außerhalb | O74: =IF($B74="",0,IF(AND(OR(Filter!$B$5="(alle)",$N74=Filter!$B$5),OR(Filter!$E$5="(alle)",$K74=Filter!$E$5),OR(Filter!$H$5="(alle)",$C74=Filter!$H$5),OR(Filter!$B$7="(alle)",$E74=Filter!$B$7),OR(Filter!$E$7="(alle)",ISNUMBER(SEARCH(Filter!$E$7,$J74))),OR(Filter!$H$7="(alle)",ISNUMBER(SEARCH(Filter!$H$7,$I74))),OR(Filter!$B$9="",ISNUMBER(SEARCH(Filter!$B$9,$F74&" "&$G74)))),COUNTIF($O$6:$O73,">0")+1,0)) -> 68
B75: ANF-069 | C75: Bieterfragenkatalog | D75: Nr. 17 / S. 2 | E75: Netzanschluss & Energie | F75: Klarstellung: Alle Standorte sind mit der ausgeschriebenen Anzahl an Ladepunkten zu errichten. Soweit die Netzanschlusskapazität an einzelnen Standorten nicht (rechtzeitig) vorliegt, kann der AG an diesen Standorten einen die … | G75: Sollen die Standorte mit dem Komplettsetup errichtet werden, ohne dass der endgültige Netzanschluss vorliegt? In diesem Fall können die Leistungsvorgaben der Ausschreibung nicht erfüllt werden. | H75: Bezug lt. Katalog: - Katalogdatum: 15.01.2024 // Antwort: Alle Standorte sind mit der ausgeschriebenen Anzahl an Ladepunkten zu errichten. Soweit die Netzanschlusskapazität an einzelnen Standorten nicht (rechtzeitig) vorliegt, kann der AG an diesen Standorten einen die Anschlusskapazität teilweise ersetzenden Speicher aufstellen (Anlage 1 zum Verfahrensbrief - Betreibervertrag, §44). | I75: offen | J75: – | K75: trifft nicht zu | N75: außerhalb | O75: =IF($B75="",0,IF(AND(OR(Filter!$B$5="(alle)",$N75=Filter!$B$5),OR(Filter!$E$5="(alle)",$K75=Filter!$E$5),OR(Filter!$H$5="(alle)",$C75=Filter!$H$5),OR(Filter!$B$7="(alle)",$E75=Filter!$B$7),OR(Filter!$E$7="(alle)",ISNUMBER(SEARCH(Filter!$E$7,$J75))),OR(Filter!$H$7="(alle)",ISNUMBER(SEARCH(Filter!$H$7,$I75))),OR(Filter!$B$9="",ISNUMBER(SEARCH(Filter!$B$9,$F75&" "&$G75)))),COUNTIF($O$6:$O74,">0")+1,0)) -> 69
B76: ANF-070 | C76: Bieterfragenkatalog | D76: Nr. 18 / S. 2 | E76: Nutzungszeit & Entgelte | F76: Klarstellung: Der Betreiber kann diese Kosten bei der Kalkulation seines EMP-Entgelts bzw. seines Ad hoc - Ladetarifs berücksichtigten. | G76: Wie wird im Zusammenhang mit Verlustenergien mit nicht absehbaren Veränderungen und damit einhergehenden regulatorischen Änderungen umgegangen (z.B. dynamische Netzentgelte oder neue Strompreiszonen)? Sollen diese Risiken im Angebot berücksichtigt werden oder können hier steigende Kosten auch im Laufe des Betriebes an den Bund weitergereicht werden? | H76: Bezug lt. Katalog: - Katalogdatum: 15.01.2024 // Antwort: Der Betreiber kann diese Kosten bei der Kalkulation seines EMP-Entgelts bzw. seines Ad hoc - Ladetarifs berücksichtigten. Beim Durchleitungsmodell können die Kosten der Netznutzung ebenfalls berücksichtigt werden. | I76: eRound | J76: Abrechnungskomponente | K76: erfasst | N76: außerhalb | O76: =IF($B76="",0,IF(AND(OR(Filter!$B$5="(alle)",$N76=Filter!$B$5),OR(Filter!$E$5="(alle)",$K76=Filter!$E$5),OR(Filter!$H$5="(alle)",$C76=Filter!$H$5),OR(Filter!$B$7="(alle)",$E76=Filter!$B$7),OR(Filter!$E$7="(alle)",ISNUMBER(SEARCH(Filter!$E$7,$J76))),OR(Filter!$H$7="(alle)",ISNUMBER(SEARCH(Filter!$H$7,$I76))),OR(Filter!$B$9="",ISNUMBER(SEARCH(Filter!$B$9,$F76&" "&$G76)))),COUNTIF($O$6:$O75,">0")+1,0)) -> 70
B77: ANF-071 | C77: Bieterfragenkatalog | D77: Nr. 19 / S. 2 | E77: Vertrag & Recht | F77: Klarstellung: Eine Anpassung des Beginns der Vertragslaufzeit auf Zeitpunkt der Inbetriebnahme der Standorte ist nicht vorgesehen. | G77: Die Laufzeit beträgt weiterhin 8 Jahre ab Loszuschlag, also voraussichtlich bis 2033? Ein großteil der Standorte muss erst 2029 und 2030 gebaut werden. Die tatsächliche Laufzeit würde für diese Standorte nur 3-4 Jahre betragen. Erwägen Sie die Option, dass die Vertragslaufzeit ab Inbetriebnahme der Standorte startet? | H77: Bezug lt. Katalog: - Katalogdatum: 15.01.2024 // Antwort: Eine Anpassung des Beginns der Vertragslaufzeit auf Zeitpunkt der Inbetriebnahme der Standorte ist nicht vorgesehen. Der tatsächliche Zeitpunkt der Inbetriebnahme der einzelnen Standorte obliegt auch der Planung des AN (Vertragsanlage 4 - Kapitel 2.2.1). | I77: offen | J77: – | K77: erfasst | N77: außerhalb | O77: =IF($B77="",0,IF(AND(OR(Filter!$B$5="(alle)",$N77=Filter!$B$5),OR(Filter!$E$5="(alle)",$K77=Filter!$E$5),OR(Filter!$H$5="(alle)",$C77=Filter!$H$5),OR(Filter!$B$7="(alle)",$E77=Filter!$B$7),OR(Filter!$E$7="(alle)",ISNUMBER(SEARCH(Filter!$E$7,$J77))),OR(Filter!$H$7="(alle)",ISNUMBER(SEARCH(Filter!$H$7,$I77))),OR(Filter!$B$9="",ISNUMBER(SEARCH(Filter!$B$9,$F77&" "&$G77)))),COUNTIF($O$6:$O76,">0")+1,0)) -> 71
B78: ANF-072 | C78: Bieterfragenkatalog | D78: Nr. 20 / S. 2 | E78: Vertrag & Recht | F78: Verweis des Auftraggebers auf die Antwort zu Bieterfrage 5. | G78: Viele der Geokoordinaten in Vertragsanlage 2 und Anlage 2 zum Verfahrensbrief stimmen nicht mit den Rastplätzen überein. Wir bitten Sie, zu spezifizieren welche Angabe massgeblich ist und die unzutreffenden Angaben zu korrigieren. | H78: Bezug lt. Katalog: – Katalogdatum: 15.01.2025 // Antwort: Siehe Antwort auf Frage 5 | I78: offen | J78: – | K78: trifft nicht zu | M78: Automatisch ausgewertet: Die Antwort des Auftraggebers verweist ausschließlich auf Bieterfrage 5. Keine eigenständige Anforderung – der Inhalt ist unter der dort erfassten Zeile nachzuhalten. | N78: außerhalb | O78: =IF($B78="",0,IF(AND(OR(Filter!$B$5="(alle)",$N78=Filter!$B$5),OR(Filter!$E$5="(alle)",$K78=Filter!$E$5),OR(Filter!$H$5="(alle)",$C78=Filter!$H$5),OR(Filter!$B$7="(alle)",$E78=Filter!$B$7),OR(Filter!$E$7="(alle)",ISNUMBER(SEARCH(Filter!$E$7,$J78))),OR(Filter!$H$7="(alle)",ISNUMBER(SEARCH(Filter!$H$7,$I78))),OR(Filter!$B$9="",ISNUMBER(SEARCH(Filter!$B$9,$F78&" "&$G78)))),COUNTIF($O$6:$O77,">0")+1,0)) -> 72
B79: ANF-073 | C79: Bieterfragenkatalog | D79: Nr. 21 / S. 2 | E79: Vertrag & Recht | F79: Klarstellung: Die Angaben der Vertragsanlage 03 sind im Fall des Rastplatzes DE-BW-006550 Eichhäuser Hof nicht korrekt. | G79: In Vertragsanlage 3 steht bei DE-BW-006550 Rastplatz Eichhäuser Hof, dass kein WC vorhanden ist. Jedoch sieht es in einschlägigen Karten-/Bewertungsdiensten danach aus, dass ein WC vorhanden und benutzbar ist. Liegt hier ein Fehler vor? Bitte spezifizieren Sie welche Information richtig ist. | H79: Bezug lt. Katalog: – Katalogdatum: 15.01.2025 // Antwort: Die Angaben der Vertragsanlage 03 sind im Fall des Rastplatzes DE-BW-006550 Eichhäuser Hof nicht korrekt. Es ist korrekt, dass auf der Anlage mittlerweile ein WC vorhanen ist. | I79: offen | J79: – | K79: erfasst | N79: außerhalb | O79: =IF($B79="",0,IF(AND(OR(Filter!$B$5="(alle)",$N79=Filter!$B$5),OR(Filter!$E$5="(alle)",$K79=Filter!$E$5),OR(Filter!$H$5="(alle)",$C79=Filter!$H$5),OR(Filter!$B$7="(alle)",$E79=Filter!$B$7),OR(Filter!$E$7="(alle)",ISNUMBER(SEARCH(Filter!$E$7,$J79))),OR(Filter!$H$7="(alle)",ISNUMBER(SEARCH(Filter!$H$7,$I79))),OR(Filter!$B$9="",ISNUMBER(SEARCH(Filter!$B$9,$F79&" "&$G79)))),COUNTIF($O$6:$O78,">0")+1,0)) -> 73
B80: ANF-074 | C80: Bieterfragenkatalog | D80: Nr. 22 / S. 3 | E80: Bau & Dokumentation | F80: Klarstellung: Eine Freigabe aller Standorte soll bis zum 31.12.2030 erfolgen. Ein Unterschied zwischen der Inbetriebnahme und der Verkehrsfreigabe besteht nicht. | G80: In der aktuellsten Vertragsfassung vom 06.01. ist in §11.4 von einer vorgesehenen spätesten Inbetriebnahme zum 31.12.2028 die Rede. In Vertragsanlage 04 (Leistungsbeschreibung Errichtung) unter Punkt 2.2.1 ist dagegen von einer Verkehrsfreigabe von 100% der Standorte spätestens zum 31.12.2030 die Rede. Könnten Sie spezifizieren, welche Angabe korrekt ist? Könnten Sie darüber hinaus spezifizieren, ob zwischen Betriebs- und Verkehrsfreigabe ein Unterschied besteht? | H80: Bezug lt. Katalog: – Katalogdatum: 15.01.2025 // Antwort: Eine Freigabe aller Standorte soll bis zum 31.12.2030 erfolgen. Ein Unterschied zwischen der Inbetriebnahme und der Verkehrsfreigabe besteht nicht. Die Regelungen im Vertrag und der Vertragsanlage 4 werden vor Aufforderung zur Abgabe verbindlicher Angebote noch aufeinander abgestimmt. | I80: offen | J80: – | K80: erfasst | N80: außerhalb | O80: =IF($B80="",0,IF(AND(OR(Filter!$B$5="(alle)",$N80=Filter!$B$5),OR(Filter!$E$5="(alle)",$K80=Filter!$E$5),OR(Filter!$H$5="(alle)",$C80=Filter!$H$5),OR(Filter!$B$7="(alle)",$E80=Filter!$B$7),OR(Filter!$E$7="(alle)",ISNUMBER(SEARCH(Filter!$E$7,$J80))),OR(Filter!$H$7="(alle)",ISNUMBER(SEARCH(Filter!$H$7,$I80))),OR(Filter!$B$9="",ISNUMBER(SEARCH(Filter!$B$9,$F80&" "&$G80)))),COUNTIF($O$6:$O79,">0")+1,0)) -> 74
B81: ANF-075 | C81: Bieterfragenkatalog | D81: Nr. 23 / S. 3 | E81: Flächen & Genehmigungen | F81: Klarstellung: Zu etwaigen weiteren Ausschreibungen können keine Angaben gemacht werden. | G81: Kann es basierend auf dem Ausgang dieser Ausschreibung Einschränkungen bei der Losvergabe der kommenden Ausschreibung (bemannte Rastanlagen) geben? Z.B. zur Vermeidung lokaler Monopole? | H81: Bezug lt. Katalog: – Katalogdatum: 15.01.2025 // Antwort: Zu etwaigen weiteren Ausschreibungen können keine Angaben gemacht werden. | I81: offen | J81: – | K81: erfasst | N81: außerhalb | O81: =IF($B81="",0,IF(AND(OR(Filter!$B$5="(alle)",$N81=Filter!$B$5),OR(Filter!$E$5="(alle)",$K81=Filter!$E$5),OR(Filter!$H$5="(alle)",$C81=Filter!$H$5),OR(Filter!$B$7="(alle)",$E81=Filter!$B$7),OR(Filter!$E$7="(alle)",ISNUMBER(SEARCH(Filter!$E$7,$J81))),OR(Filter!$H$7="(alle)",ISNUMBER(SEARCH(Filter!$H$7,$I81))),OR(Filter!$B$9="",ISNUMBER(SEARCH(Filter!$B$9,$F81&" "&$G81)))),COUNTIF($O$6:$O80,">0")+1,0)) -> 75
B82: ANF-076 | C82: Bieterfragenkatalog | D82: Nr. 24 / S. 3 | E82: Vertrag & Recht | F82: Klarstellung: Das Betreiberentgelt als Vergütungsbestandteil richtet sich nach §40 des Vertrags (Anlage 01 zum Verfahrensbrief). | G82: Was ist im Detail unter dem "Betreiberentgelt" zu verstehen und aus welchen Bestandteilen setzt sich diese zusammen? | H82: Bezug lt. Katalog: Hauptvertrag Katalogdatum: 17.01.2025 // Antwort: Das Betreiberentgelt als Vergütungsbestandteil richtet sich nach §40 des Vertrags (Anlage 01 zum Verfahrensbrief). Es bezieht sich grundsätzlich auf den Betrieb der Ladeinfrastruktur. Die Kalkulation des Betreiberentgelts unterliegt der Kalkulationsfreiheit der Bieter. Der AG behält sich vor, sich von den Bietern eine Aufschlüsselung der Bestandteile des kalkulierten Betreiberentgelts mit Abgabe der verbindlichen Angabeote einreichen zu lassen. | I82: offen | J82: – | K82: erfasst | N82: außerhalb | O82: =IF($B82="",0,IF(AND(OR(Filter!$B$5="(alle)",$N82=Filter!$B$5),OR(Filter!$E$5="(alle)",$K82=Filter!$E$5),OR(Filter!$H$5="(alle)",$C82=Filter!$H$5),OR(Filter!$B$7="(alle)",$E82=Filter!$B$7),OR(Filter!$E$7="(alle)",ISNUMBER(SEARCH(Filter!$E$7,$J82))),OR(Filter!$H$7="(alle)",ISNUMBER(SEARCH(Filter!$H$7,$I82))),OR(Filter!$B$9="",ISNUMBER(SEARCH(Filter!$B$9,$F82&" "&$G82)))),COUNTIF($O$6:$O81,">0")+1,0)) -> 76
B83: ANF-077 | C83: Bieterfragenkatalog | D83: Nr. 25 / S. 3 | E83: Reservierung | F83: Verneint: das Ad-hoc Entgelt soll nicht gemindert werden. § 19 Abs. | G83: § 19: Ist es gewollt, dass bei Nutzung des Reservierungssystems und Ad-hoc Ladung die Erlöse für den AN gemindert werden? | H83: Bezug lt. Katalog: Hauptvertrag Katalogdatum: 17.01.2025 // Antwort: Nein, das Ad-hoc Entgelt soll nicht gemindert werden. § 19 Abs. 6 sieht lediglich eine Anrechnung eines gzahlten Reservierungsentgelts vor. | I83: eRound / Reservierungsplattform | J83: Authentifizierungskomponente / OCPI Buchungskalender / Reservierungsplattform | K83: erfasst | N83: außerhalb | O83: =IF($B83="",0,IF(AND(OR(Filter!$B$5="(alle)",$N83=Filter!$B$5),OR(Filter!$E$5="(alle)",$K83=Filter!$E$5),OR(Filter!$H$5="(alle)",$C83=Filter!$H$5),OR(Filter!$B$7="(alle)",$E83=Filter!$B$7),OR(Filter!$E$7="(alle)",ISNUMBER(SEARCH(Filter!$E$7,$J83))),OR(Filter!$H$7="(alle)",ISNUMBER(SEARCH(Filter!$H$7,$I83))),OR(Filter!$B$9="",ISNUMBER(SEARCH(Filter!$B$9,$F83&" "&$G83)))),COUNTIF($O$6:$O82,">0")+1,0)) -> 77
B84: ANF-078 | C84: Bieterfragenkatalog | D84: Nr. 26 / S. 3 | E84: Vergabeverfahren & Angebot | F84: Klarstellung: Die Angebotsfrist ist angemessen und auskömmlich. Eine Fristverlängerung erfolgt nicht. | G84: Es ist eine Abgabefrist des Erstangebots bis zum 27.02.2025, 12 Uhr vorgesehen. Die Klärung der Fragen als Basis für die Angebotskalkulation und Erstellung der Konzepte sowie die danach erforderlichen Prüfungs-, Freigabe und insbesondere hochrangigen Gremienbeteiligungen mit anschließender Finalisierung der Angebote sind bis zum 27.02.2025 ist terminlich nicht möglich. Wir bitten daher um Verlängerung der Abgabefrist für das Erstangebot bis zum 20.03.2025. | H84: Bezug lt. Katalog: Frist für Abgabe Erstangebote Katalogdatum: 17.01.2025 // Antwort: Die Angebotsfrist ist angemessen und auskömmlich. Eine Fristverlängerung erfolgt nicht. | I84: offen | J84: – | K84: trifft nicht zu | M84: Automatisch ausgewertet: Betrifft das Vergabeverfahren (Angebot, Wertung, Unterlagen), nicht die zu erbringende Leistung. Keiner Komponente zugeordnet. | N84: außerhalb | O84: =IF($B84="",0,IF(AND(OR(Filter!$B$5="(alle)",$N84=Filter!$B$5),OR(Filter!$E$5="(alle)",$K84=Filter!$E$5),OR(Filter!$H$5="(alle)",$C84=Filter!$H$5),OR(Filter!$B$7="(alle)",$E84=Filter!$B$7),OR(Filter!$E$7="(alle)",ISNUMBER(SEARCH(Filter!$E$7,$J84))),OR(Filter!$H$7="(alle)",ISNUMBER(SEARCH(Filter!$H$7,$I84))),OR(Filter!$B$9="",ISNUMBER(SEARCH(Filter!$B$9,$F84&" "&$G84)))),COUNTIF($O$6:$O83,">0")+1,0)) -> 78
B85: ANF-079 | C85: Bieterfragenkatalog | D85: Nr. 27 / S. 3 | E85: Flächen & Genehmigungen | F85: Klarstellung: Die ladeplatzbezogene Beleuchtung ist an die Niederspannungsanalage der Ladeinfrastruktur anzuschließen. | G85: In diesem Kapitel wird beschrieben, dass der Anschluss und die Abrechnung der Mastbeleuchtung über das Energienetz der Rastanlage erfolgt. Gleichzeitig soll die Beleuchtungsanlage an die Niederspannungsanlage der E-Mobilität angeschlossen werden. Wir bitten um Prüfung, welche der beiden Vorgaben tatsächlich zutrifft. | H85: Bezug lt. Katalog: LB Errichtung, Kapitl 3.10.1 Katalogdatum: 17.01.2025 Zuordnung prüfen (Komponente/Partner nicht eindeutig) // Antwort: Die ladeplatzbezogene Beleuchtung ist an die Niederspannungsanalage der Ladeinfrastruktur anzuschließen. | I85: Zuordnung prüfen | J85: Zuordnung prüfen | K85: erfasst | N85: außerhalb | O85: =IF($B85="",0,IF(AND(OR(Filter!$B$5="(alle)",$N85=Filter!$B$5),OR(Filter!$E$5="(alle)",$K85=Filter!$E$5),OR(Filter!$H$5="(alle)",$C85=Filter!$H$5),OR(Filter!$B$7="(alle)",$E85=Filter!$B$7),OR(Filter!$E$7="(alle)",ISNUMBER(SEARCH(Filter!$E$7,$J85))),OR(Filter!$H$7="(alle)",ISNUMBER(SEARCH(Filter!$H$7,$I85))),OR(Filter!$B$9="",ISNUMBER(SEARCH(Filter!$B$9,$F85&" "&$G85)))),COUNTIF($O$6:$O84,">0")+1,0)) -> 79
B86: ANF-080 | C86: Bieterfragenkatalog | D86: Nr. 28 / S. 3 | E86: Netzanschluss & Energie | F86: Klarstellung: Die Endausbauleistung für jeden Standort finden Sie in der Vertragsanlage 5 "Details zum Netzanschluss" in der Spalte "beantragte Leistung 2035". | G86: Sämtliche Kabelführungen sind auf die Endausbauleistung im Jahr 2035 zu bemessen.Wir bitten um Angabe der Endausbauleistung für jeden Standort. | H86: Bezug lt. Katalog: LB Errichtung, Kapitel 4.11.6 Katalogdatum: 17.01.2025 // Antwort: Die Endausbauleistung für jeden Standort finden Sie in der Vertragsanlage 5 "Details zum Netzanschluss" in der Spalte "beantragte Leistung 2035". | I86: offen | J86: – | K86: erfasst | N86: außerhalb | O86: =IF($B86="",0,IF(AND(OR(Filter!$B$5="(alle)",$N86=Filter!$B$5),OR(Filter!$E$5="(alle)",$K86=Filter!$E$5),OR(Filter!$H$5="(alle)",$C86=Filter!$H$5),OR(Filter!$B$7="(alle)",$E86=Filter!$B$7),OR(Filter!$E$7="(alle)",ISNUMBER(SEARCH(Filter!$E$7,$J86))),OR(Filter!$H$7="(alle)",ISNUMBER(SEARCH(Filter!$H$7,$I86))),OR(Filter!$B$9="",ISNUMBER(SEARCH(Filter!$B$9,$F86&" "&$G86)))),COUNTIF($O$6:$O85,">0")+1,0)) -> 80
B87: ANF-081 | C87: Bieterfragenkatalog | D87: Nr. 29 / S. 3 | E87: Vertrag & Recht | F87: Klarstellung: Es ist vorgesehen, dass das Infrastrukturentgelt über alle Standorte berechnet wird. | G87: Wird das Infrastrukturentgelt standortbezogen, losbezogen (und damit anbieterbezogen) oder über alle Standorte berechnet? | H87: Bezug lt. Katalog: Infrastrukturentgelt Katalogdatum: 17.01.2025 // Antwort: Es ist vorgesehen, dass das Infrastrukturentgelt über alle Standorte berechnet wird. | I87: offen | J87: – | K87: erfasst | N87: außerhalb | O87: =IF($B87="",0,IF(AND(OR(Filter!$B$5="(alle)",$N87=Filter!$B$5),OR(Filter!$E$5="(alle)",$K87=Filter!$E$5),OR(Filter!$H$5="(alle)",$C87=Filter!$H$5),OR(Filter!$B$7="(alle)",$E87=Filter!$B$7),OR(Filter!$E$7="(alle)",ISNUMBER(SEARCH(Filter!$E$7,$J87))),OR(Filter!$H$7="(alle)",ISNUMBER(SEARCH(Filter!$H$7,$I87))),OR(Filter!$B$9="",ISNUMBER(SEARCH(Filter!$B$9,$F87&" "&$G87)))),COUNTIF($O$6:$O86,">0")+1,0)) -> 81
B88: ANF-082 | C88: Bieterfragenkatalog | D88: Nr. 30 / S. 3 | E88: Netzanschluss & Energie | F88: Klarstellung: An der MS-Unterstation können Komponenten wie Ladetechnik, Schaltanlage und Versorgungstransformator angeschlossen sein. | G88: In allen Unterlagen im Ordner Vorplanung ist neben der MS-Station, auch eine MS-Unterstation. Welche Funktion hat die MS-Unterstation? | H88: Bezug lt. Katalog: Dokument: Vorplanung Katalogdatum: 17.01.2025 // Antwort: An der MS-Unterstation können Komponenten wie Ladetechnik, Schaltanlage und Versorgungstransformator angeschlossen sein. MS-Übergabestation und MS- Unterstation können auch örtlich voneinander getrennt aufgestellt sein. | I88: offen | J88: – | K88: erfasst | N88: außerhalb | O88: =IF($B88="",0,IF(AND(OR(Filter!$B$5="(alle)",$N88=Filter!$B$5),OR(Filter!$E$5="(alle)",$K88=Filter!$E$5),OR(Filter!$H$5="(alle)",$C88=Filter!$H$5),OR(Filter!$B$7="(alle)",$E88=Filter!$B$7),OR(Filter!$E$7="(alle)",ISNUMBER(SEARCH(Filter!$E$7,$J88))),OR(Filter!$H$7="(alle)",ISNUMBER(SEARCH(Filter!$H$7,$I88))),OR(Filter!$B$9="",ISNUMBER(SEARCH(Filter!$B$9,$F88&" "&$G88)))),COUNTIF($O$6:$O87,">0")+1,0)) -> 82
B89: ANF-083 | C89: Bieterfragenkatalog | D89: Nr. 31 / S. 3 | E89: Flächen & Genehmigungen | F89: Klarstellung: Die in Vertragsanlage 4, Kapitel 3.10.1 aufgeführten Anforderungen an die Beleuchtung sind zu erfüllen. | G89: In den Vorplanungen einzelner Standorte wird Beleuchtung wie folgt benötigt (Beschreibung rauskopiert): e 6 LKW-Stellplätze ist ein 10,00m hoher Lichtmast vorzusehen. Alternativ ist pro 8 LKW-Stellplätze ein 12,00m hoher Lichtmast vorzusehen. Frage: Entfällt die Anforderung, wenn jeder Stellplatz eine eigene Beleuchtung (Lichtmast) erhält? Und sind die Anforderungen dann wie in Anlage 4 "Leistungsbeschreibung Errichtung" zu erfüllen? | H89: Bezug lt. Katalog: Dokument: Vorplanung Katalogdatum: 17.01.2025 Zuordnung prüfen (Komponente/Partner nicht eindeutig) // Antwort: Die in Vertragsanlage 4, Kapitel 3.10.1 aufgeführten Anforderungen an die Beleuchtung sind zu erfüllen. Dazu kann auf eine der beiden in der Vorplanung (Vertragsanlage 3 - Vorplanung) genannten Varianten zurückgegriffen werden. Sofern der Bieter eine andere Variante vorsieht, hat er die Einhaltung der in Vertragsanlage 4, Kapitel 3.10.1 aufgeführten Anforderungen an die Beleuchtung nachzuweisen. | I89: Zuordnung prüfen | J89: Zuordnung prüfen | K89: erfasst | N89: außerhalb | O89: =IF($B89="",0,IF(AND(OR(Filter!$B$5="(alle)",$N89=Filter!$B$5),OR(Filter!$E$5="(alle)",$K89=Filter!$E$5),OR(Filter!$H$5="(alle)",$C89=Filter!$H$5),OR(Filter!$B$7="(alle)",$E89=Filter!$B$7),OR(Filter!$E$7="(alle)",ISNUMBER(SEARCH(Filter!$E$7,$J89))),OR(Filter!$H$7="(alle)",ISNUMBER(SEARCH(Filter!$H$7,$I89))),OR(Filter!$B$9="",ISNUMBER(SEARCH(Filter!$B$9,$F89&" "&$G89)))),COUNTIF($O$6:$O88,">0")+1,0)) -> 83
B90: ANF-084 | C90: Bieterfragenkatalog | D90: Nr. 32 / S. 3 | E90: Netzanschluss & Energie | F90: Klarstellung: Die Installationsaktivitäten sind in den jeweiligen Kostengruppen mitzuberücksichtigen. | G90: Dokument: "20250106_Anlage 06_zum Verfahrensbrief_Aufschlüssel_Preise Errichtung" --> Sind alle Installationsaktivitäten (Ladehardware, CCTV, Trafo, Unterstation etc.) in Position 3.9 (Zeile 26) und Position 3.10 (Zeile 27) aufzuführen oder wird der gesamte Kostenpunkt "Installation" an anderer Stelle aufgeführt? | H90: Bezug lt. Katalog: Preise Errichtung Katalogdatum: 17.01.2025 // Antwort: Die Installationsaktivitäten sind in den jeweiligen Kostengruppen mitzuberücksichtigen. | I90: Alpitronic | J90: Ladeeinrichtung | K90: erfasst | N90: außerhalb | O90: =IF($B90="",0,IF(AND(OR(Filter!$B$5="(alle)",$N90=Filter!$B$5),OR(Filter!$E$5="(alle)",$K90=Filter!$E$5),OR(Filter!$H$5="(alle)",$C90=Filter!$H$5),OR(Filter!$B$7="(alle)",$E90=Filter!$B$7),OR(Filter!$E$7="(alle)",ISNUMBER(SEARCH(Filter!$E$7,$J90))),OR(Filter!$H$7="(alle)",ISNUMBER(SEARCH(Filter!$H$7,$I90))),OR(Filter!$B$9="",ISNUMBER(SEARCH(Filter!$B$9,$F90&" "&$G90)))),COUNTIF($O$6:$O89,">0")+1,0)) -> 84
B91: ANF-085 | C91: Bieterfragenkatalog | D91: Nr. 33 / S. 3 | E91: Reservierung | F91: Zusage / Ankündigung: Die Möglichkeiten und Rahmenbedingungen der Reservierung werden Teil der Bieterverhandlungen sein, hierbei wird insbesondere auch zu erörtern sein, inwieweit die Reservierung von Energiemengen bzw. die Angabe des benötigten … | G91: Im Betriebskonzept ist es erforderlich, dass etwaiges Falschparken durch z.B. Diesel LKW nicht passieren kann. Müssen die Stellplätze eine Schranke aufweisen, also muss das Standortlayout Schranken integriert haben oder kann man in dem Betriebskonzept und Layout auch andere Lösungen aufzeigen? | H91: Bezug lt. Katalog: Betriebskonzept Katalogdatum: 17.01.2025 // Antwort: Die Möglichkeiten und Rahmenbedingungen der Reservierung werden Teil der Bieterverhandlungen sein, hierbei wird insbesondere auch zu erörtern sein, inwieweit die Reservierung von Energiemengen bzw. die Angabe des benötigten Energiebedarfs im Rahmen des Reservierungsprozesses möglich sein soll bzw. sinnvoll ist und wie ein Freihalten eines reservierten Ladepunktes sichergestellt werden kann. Für die Angebotsabgabe ist davon auszugehen, dass eine Reservierung von Ladepunkten und Ahndung von Falschparkern möglich ist. (vgl. Fußnote 3 zu §19 des Vertrags) Dementsprechend können im Betriebskonzept zum Erstangebot auch andere Lösungen aufgezeigt werden. Für die verbindlichen Angebote wird der AG einheitliche Rahmenbedingungen vorgeben. | I91: eRound / SCS | J91: Schrankensteuerung / OCPI Buchungskalender / Pönalisierungssystem | K91: erfasst | N91: im Umfang | O91: =IF($B91="",0,IF(AND(OR(Filter!$B$5="(alle)",$N91=Filter!$B$5),OR(Filter!$E$5="(alle)",$K91=Filter!$E$5),OR(Filter!$H$5="(alle)",$C91=Filter!$H$5),OR(Filter!$B$7="(alle)",$E91=Filter!$B$7),OR(Filter!$E$7="(alle)",ISNUMBER(SEARCH(Filter!$E$7,$J91))),OR(Filter!$H$7="(alle)",ISNUMBER(SEARCH(Filter!$H$7,$I91))),OR(Filter!$B$9="",ISNUMBER(SEARCH(Filter!$B$9,$F91&" "&$G91)))),COUNTIF($O$6:$O90,">0")+1,0)) -> 85
B92: ANF-086 | C92: Bieterfragenkatalog | D92: Nr. 34 / S. 3 | E92: Flächen & Genehmigungen | F92: Klarstellung: Sofern sich Ihre Frage auf die Dokumente Anlage 2 zum Verfahrensbrief "Gesamtübersicht über die Lose", Vertragsanlage 2 "Standortübersicht (losspezifisch)" und Anlage 5 zum Verfahrensbrief "Karte zur Losaufteilung" bezieht wurden … | G92: Aus der Bereitstellung der neuen Unterlagen am 17.01. geht nicht hervor, welche Änderungen im Vergleich zu den Originalversionen vorgenommen wurden. Kann das bitte kenntlich gemacht werden? | H92: Bezug lt. Katalog: Change Log Katalogdatum: 17.01.2025 // Antwort: Sofern sich Ihre Frage auf die Dokumente Anlage 2 zum Verfahrensbrief "Gesamtübersicht über die Lose", Vertragsanlage 2 "Standortübersicht (losspezifisch)" und Anlage 5 zum Verfahrensbrief "Karte zur Losaufteilung" bezieht wurden folgende Informationen aktualisert: Anlage 2 zum Verfahrensbrief "Gesamtübersicht über die Lose": Die Anzahl der Ladepunkte, die BAB-Nr., die Geogr. Länge und Breite sowie die Anzahl der Ladepunkte wurden korrigiert. Vertragsanlage 2 "Standortübersicht (losspezifisch)": Die Anzahl der Ladepunkte, die BAB-Nr., die Geogr. Länge und Breite, die Anzahl der Ladepunkte sowie die zusammenfassende Tabelle wurden korrigiert. Anlage 5 zum Verfahrensbrief "Karte zur Losaufteilung": Fehlende Standorte wurden ergänzt. | I92: offen | J92: – | K92: erfasst | N92: außerhalb | O92: =IF($B92="",0,IF(AND(OR(Filter!$B$5="(alle)",$N92=Filter!$B$5),OR(Filter!$E$5="(alle)",$K92=Filter!$E$5),OR(Filter!$H$5="(alle)",$C92=Filter!$H$5),OR(Filter!$B$7="(alle)",$E92=Filter!$B$7),OR(Filter!$E$7="(alle)",ISNUMBER(SEARCH(Filter!$E$7,$J92))),OR(Filter!$H$7="(alle)",ISNUMBER(SEARCH(Filter!$H$7,$I92))),OR(Filter!$B$9="",ISNUMBER(SEARCH(Filter!$B$9,$F92&" "&$G92)))),COUNTIF($O$6:$O91,">0")+1,0)) -> 86
B93: ANF-087 | C93: Bieterfragenkatalog | D93: Nr. 35 / S. 3 | E93: Netzanschluss & Energie | F93: Verneint: es wurde - wie sich aus den §§ 27 ff. ergibt - nicht gestrichen. | G93: Ist das Durchleitungsmodell nicht mehr Grundvoraussetzung für ein Angebot? In den neuen Vertragsunterlagen wurde es unter §3 gestrichen. | H93: Bezug lt. Katalog: Vertrag Katalogdatum: 20.01.2025 // Antwort: Nein, es wurde - wie sich aus den §§ 27 ff. ergibt - nicht gestrichen. Mit der Streichung in § 3 des Vertrages wurde nur verdeutlicht, dass es sich beim Durchleitungsmodell um eine besondere Form des "EMP-Ladens", nämlich die Gewährung von Zugang ohne bilanzielle Bereitstellung von Strom, handelt. | I93: offen | J93: – | K93: erfasst | N93: außerhalb | O93: =IF($B93="",0,IF(AND(OR(Filter!$B$5="(alle)",$N93=Filter!$B$5),OR(Filter!$E$5="(alle)",$K93=Filter!$E$5),OR(Filter!$H$5="(alle)",$C93=Filter!$H$5),OR(Filter!$B$7="(alle)",$E93=Filter!$B$7),OR(Filter!$E$7="(alle)",ISNUMBER(SEARCH(Filter!$E$7,$J93))),OR(Filter!$H$7="(alle)",ISNUMBER(SEARCH(Filter!$H$7,$I93))),OR(Filter!$B$9="",ISNUMBER(SEARCH(Filter!$B$9,$F93&" "&$G93)))),COUNTIF($O$6:$O92,">0")+1,0)) -> 87
B94: ANF-088 | C94: Bieterfragenkatalog | D94: Nr. 36 / S. 3 | E94: Flächen & Genehmigungen | F94: Vorgaben bleiben unverändert: Soweit nicht ausdrücklich etwas anderes geregelt wird, sind die Bieter an die Vorgaben der Vertragsanlage 4 (Leistungsbeschreibung Errichtung) gebunden. | G94: Warum sind gemäß Vorplanungen die MCS-Aufstellflächen 4 Meter breit und die CCS Aufstellflächen nur 3 Meter breit? Sind wir daran gebunden so zu bauen? | H94: Bezug lt. Katalog: Leistungsbeschreibung Katalogdatum: 20.01.2025 // Antwort: Soweit nicht ausdrücklich etwas anderes geregelt wird, sind die Bieter an die Vorgaben der Vertragsanlage 4 (Leistungsbeschreibung Errichtung) gebunden. Den Bietern steht es frei, anderweitige Aufstellflächen als Verhandlungsbedarf mit dem Erstangebot einzureichen. | I94: offen | J94: – | K94: erfasst | N94: außerhalb | O94: =IF($B94="",0,IF(AND(OR(Filter!$B$5="(alle)",$N94=Filter!$B$5),OR(Filter!$E$5="(alle)",$K94=Filter!$E$5),OR(Filter!$H$5="(alle)",$C94=Filter!$H$5),OR(Filter!$B$7="(alle)",$E94=Filter!$B$7),OR(Filter!$E$7="(alle)",ISNUMBER(SEARCH(Filter!$E$7,$J94))),OR(Filter!$H$7="(alle)",ISNUMBER(SEARCH(Filter!$H$7,$I94))),OR(Filter!$B$9="",ISNUMBER(SEARCH(Filter!$B$9,$F94&" "&$G94)))),COUNTIF($O$6:$O93,">0")+1,0)) -> 88
B95: ANF-089 | C95: Bieterfragenkatalog | D95: Nr. 37 / S. 4 | E95: Vergabeverfahren & Angebot | F95: Klarstellung: Ein entsprechendes Vorgehen ist aktuell nicht vorgesehen. Gegenstand dieses Vergabeverfahrens ist ausschließlich LKW Ladeinfrastruktur. | G95: Ist es beabsichtigt, im weiteren Verlauf des Verfahrens den Bietern Zusagen darüber zu machen, dass an ausgewählten Standorten mit erfolgtem Zuschlag in der Zukunft per geplanter Erweiterung die Errichtung von zusätzlicher PKW-Ladeinfrastruktur gestattet werden wird, soweit dies technisch umsetzbar ist und bislang noch nicht durch vergangene Ausschreibungen des Bundes abgedeckt wurde bzw. könnte dies Gegenstand der Verhandlungen sein? | H95: Bezug lt. Katalog: – Katalogdatum: 20.01.2025 // Antwort: Ein entsprechendes Vorgehen ist aktuell nicht vorgesehen. Gegenstand dieses Vergabeverfahrens ist ausschließlich LKW Ladeinfrastruktur. | I95: offen | J95: – | K95: trifft nicht zu | M95: Automatisch ausgewertet: Betrifft das Vergabeverfahren (Angebot, Wertung, Unterlagen), nicht die zu erbringende Leistung. Keiner Komponente zugeordnet. | N95: außerhalb | O95: =IF($B95="",0,IF(AND(OR(Filter!$B$5="(alle)",$N95=Filter!$B$5),OR(Filter!$E$5="(alle)",$K95=Filter!$E$5),OR(Filter!$H$5="(alle)",$C95=Filter!$H$5),OR(Filter!$B$7="(alle)",$E95=Filter!$B$7),OR(Filter!$E$7="(alle)",ISNUMBER(SEARCH(Filter!$E$7,$J95))),OR(Filter!$H$7="(alle)",ISNUMBER(SEARCH(Filter!$H$7,$I95))),OR(Filter!$B$9="",ISNUMBER(SEARCH(Filter!$B$9,$F95&" "&$G95)))),COUNTIF($O$6:$O94,">0")+1,0)) -> 89
B96: ANF-090 | C96: Bieterfragenkatalog | D96: Nr. 38 / S. 4 | E96: Vergabeverfahren & Angebot | F96: Klarstellung: Da es sich bei der Angabe um Mindestmengen handelt, können die Mengengrudnsätzlich auch in den jeweiligen Jahren vorgezogen werden. | G96: Der Bau verteilt sich auf 2026 bis 2030, wobei hier die Mindestmenge angegeben wird. Können die Mengen in den jeweiligen Jahren vorgezogen werden? Wenn ja, bis zu welchem Maße? | H96: Bezug lt. Katalog: Leistungsbeschreibung Errichtung Katalogdatum: 20.01.2025 // Antwort: Da es sich bei der Angabe um Mindestmengen handelt, können die Mengengrudnsätzlich auch in den jeweiligen Jahren vorgezogen werden. Einzelheiten können zum Gegenstand der Bieterverhandlungen gemacht werden. | I96: offen | J96: – | K96: trifft nicht zu | M96: Automatisch ausgewertet: Betrifft das Vergabeverfahren (Angebot, Wertung, Unterlagen), nicht die zu erbringende Leistung. Keiner Komponente zugeordnet. | N96: außerhalb | O96: =IF($B96="",0,IF(AND(OR(Filter!$B$5="(alle)",$N96=Filter!$B$5),OR(Filter!$E$5="(alle)",$K96=Filter!$E$5),OR(Filter!$H$5="(alle)",$C96=Filter!$H$5),OR(Filter!$B$7="(alle)",$E96=Filter!$B$7),OR(Filter!$E$7="(alle)",ISNUMBER(SEARCH(Filter!$E$7,$J96))),OR(Filter!$H$7="(alle)",ISNUMBER(SEARCH(Filter!$H$7,$I96))),OR(Filter!$B$9="",ISNUMBER(SEARCH(Filter!$B$9,$F96&" "&$G96)))),COUNTIF($O$6:$O95,">0")+1,0)) -> 90
B97: ANF-091 | C97: Bieterfragenkatalog | D97: Nr. 39 / S. 4 | E97: Netzanschluss & Energie | F97: Klarstellung: Die entsprechenden Informationen werden den Bietern im weiteren Vergabeverfahren mitgeteilt, sobald sie dem AG von dem jeweilgien Netzbetreiber vorliegen. | G97: Wie und wann erhält man Info zur MSP-Ebene, 10/20 oder 30 kV macht einen großen Preisunterschied und ist für die Kalkulation wesentlich. | H97: Bezug lt. Katalog: – Katalogdatum: 20.01.2025 // Antwort: Die entsprechenden Informationen werden den Bietern im weiteren Vergabeverfahren mitgeteilt, sobald sie dem AG von dem jeweilgien Netzbetreiber vorliegen. | I97: offen | J97: – | K97: erfasst | N97: außerhalb | O97: =IF($B97="",0,IF(AND(OR(Filter!$B$5="(alle)",$N97=Filter!$B$5),OR(Filter!$E$5="(alle)",$K97=Filter!$E$5),OR(Filter!$H$5="(alle)",$C97=Filter!$H$5),OR(Filter!$B$7="(alle)",$E97=Filter!$B$7),OR(Filter!$E$7="(alle)",ISNUMBER(SEARCH(Filter!$E$7,$J97))),OR(Filter!$H$7="(alle)",ISNUMBER(SEARCH(Filter!$H$7,$I97))),OR(Filter!$B$9="",ISNUMBER(SEARCH(Filter!$B$9,$F97&" "&$G97)))),COUNTIF($O$6:$O96,">0")+1,0)) -> 91
B98: ANF-092 | C98: Bieterfragenkatalog | D98: Nr. 40 / S. 4 | E98: Nutzungszeit & Entgelte | F98: Klarstellung: Es wird auf §24 Abs. 3 des Vertrages sowie Ziffer 10 der Vertragsanlage 06 "Anforderungen an die Ladeeinrichtung" verwiesen. | G98: An jedem Ladepunkt sollen CEE Steckdosen für die Trailer vorhanden sein, muss die Abrechnung eichrechtskonform erfolgen? Zu welchen Konditionen sind die Stromerlöse zwischen AG und AN zu kalkulieren? Sind festgelegte Preise vorgesehen? | H98: Bezug lt. Katalog: Vertragsanlage 06 Katalogdatum: 20.01.2025 // Antwort: Es wird auf §24 Abs. 3 des Vertrages sowie Ziffer 10 der Vertragsanlage 06 "Anforderungen an die Ladeeinrichtung" verwiesen. Einzelheiten können zum Gegenstand der Bieterverhandlungen gemacht werden. | I98: Alpitronic / eRound | J98: Abrechnungskomponente / Ladeeinrichtung | K98: erfasst | N98: außerhalb | O98: =IF($B98="",0,IF(AND(OR(Filter!$B$5="(alle)",$N98=Filter!$B$5),OR(Filter!$E$5="(alle)",$K98=Filter!$E$5),OR(Filter!$H$5="(alle)",$C98=Filter!$H$5),OR(Filter!$B$7="(alle)",$E98=Filter!$B$7),OR(Filter!$E$7="(alle)",ISNUMBER(SEARCH(Filter!$E$7,$J98))),OR(Filter!$H$7="(alle)",ISNUMBER(SEARCH(Filter!$H$7,$I98))),OR(Filter!$B$9="",ISNUMBER(SEARCH(Filter!$B$9,$F98&" "&$G98)))),COUNTIF($O$6:$O97,">0")+1,0)) -> 92
B99: ANF-093 | C99: Bieterfragenkatalog | D99: Nr. 41 / S. 4 | E99: Sonstiges / Zuordnung prüfen | F99: Klarstellung: Der AG wird die Unterlagen im weiteren Vergabeverfahren zur Verfügung stellen. | G99: Kap. 3.1: Lt. Seite 16 ist die Tabelle von Seite 15 nur beispielhaft. Eine vollständige Liste der zu erstellenden und einzureichenden Unterlagen kann dem Anhang 8 entnommenen werden. Diese fehlt in den Ausschreibungsunterlagen. Bitte um Verteilung des Anhangs 8. | H99: Bezug lt. Katalog: Leistungsbeschreibung Errichtung Katalogdatum: 20.01.2025 Zuordnung prüfen (Komponente/Partner nicht eindeutig) // Antwort: Der AG wird die Unterlagen im weiteren Vergabeverfahren zur Verfügung stellen. | I99: Zuordnung prüfen | J99: Zuordnung prüfen | K99: erfasst | N99: außerhalb | O99: =IF($B99="",0,IF(AND(OR(Filter!$B$5="(alle)",$N99=Filter!$B$5),OR(Filter!$E$5="(alle)",$K99=Filter!$E$5),OR(Filter!$H$5="(alle)",$C99=Filter!$H$5),OR(Filter!$B$7="(alle)",$E99=Filter!$B$7),OR(Filter!$E$7="(alle)",ISNUMBER(SEARCH(Filter!$E$7,$J99))),OR(Filter!$H$7="(alle)",ISNUMBER(SEARCH(Filter!$H$7,$I99))),OR(Filter!$B$9="",ISNUMBER(SEARCH(Filter!$B$9,$F99&" "&$G99)))),COUNTIF($O$6:$O98,">0")+1,0)) -> 93
B100: ANF-094 | C100: Bieterfragenkatalog | D100: Nr. 42 / S. 4 | E100: Bau & Dokumentation | F100: Klarstellung: Es ist nicht klar, was mit Sicherheitsaudits gemeint ist. Sofern Verkehrssicherheitsaudits gemeint sind, haben diese einmalig im Rahmen der Baufreigabefreigabe zu erfolgen. | G100: Sind Sicherheitsaudits durchzuführen? Wenn ja, sind die Leistungen vom AN zu erbringen und wie oft durchzuführen? | H100: Bezug lt. Katalog: Sicherheitsaudits Katalogdatum: 20.01.2025 // Antwort: Es ist nicht klar, was mit Sicherheitsaudits gemeint ist. Sofern Verkehrssicherheitsaudits gemeint sind, haben diese einmalig im Rahmen der Baufreigabefreigabe zu erfolgen. | I100: offen | J100: – | K100: erfasst | N100: außerhalb | O100: =IF($B100="",0,IF(AND(OR(Filter!$B$5="(alle)",$N100=Filter!$B$5),OR(Filter!$E$5="(alle)",$K100=Filter!$E$5),OR(Filter!$H$5="(alle)",$C100=Filter!$H$5),OR(Filter!$B$7="(alle)",$E100=Filter!$B$7),OR(Filter!$E$7="(alle)",ISNUMBER(SEARCH(Filter!$E$7,$J100))),OR(Filter!$H$7="(alle)",ISNUMBER(SEARCH(Filter!$H$7,$I100))),OR(Filter!$B$9="",ISNUMBER(SEARCH(Filter!$B$9,$F100&" "&$G100)))),COUNTIF($O$6:$O99,">0")+1,0)) -> 94
B101: ANF-095 | C101: Bieterfragenkatalog | D101: Nr. 43 / S. 4 | E101: Flächen & Genehmigungen | F101: Klarstellung: Eine Kanalnetzberechnung ist erforderlich, sofern das Regenwassernetz angepasst/ verändert wird. | G101: Kap. 3.8.2: Den vorliegenden Unterlagen ist nicht zu entnehmen, ob eine Kanalnetzberechnung der gesamten Rastanlage erforderlich ist. Bitte um Präzisierung der erforderlichen Leistungen. | H101: Bezug lt. Katalog: – Katalogdatum: 20.01.2025 // Antwort: Eine Kanalnetzberechnung ist erforderlich, sofern das Regenwassernetz angepasst/ verändert wird. | I101: offen | J101: – | K101: erfasst | N101: außerhalb | O101: =IF($B101="",0,IF(AND(OR(Filter!$B$5="(alle)",$N101=Filter!$B$5),OR(Filter!$E$5="(alle)",$K101=Filter!$E$5),OR(Filter!$H$5="(alle)",$C101=Filter!$H$5),OR(Filter!$B$7="(alle)",$E101=Filter!$B$7),OR(Filter!$E$7="(alle)",ISNUMBER(SEARCH(Filter!$E$7,$J101))),OR(Filter!$H$7="(alle)",ISNUMBER(SEARCH(Filter!$H$7,$I101))),OR(Filter!$B$9="",ISNUMBER(SEARCH(Filter!$B$9,$F101&" "&$G101)))),COUNTIF($O$6:$O100,">0")+1,0)) -> 95
...

Sheet Filter
A1: Filter – Anforderungen gezielt anzeigen | V1: Auswahllisten (Grundlage der Dropdowns)
A2: Auswahl in den gelben Feldern treffen; die Liste unten aktualisiert sich sofort. „(alle)“ lässt das Feld unberücksichtigt. Komponente und Partner suchen als Teiltext, finden also auch Mehrfachzuordnungen. Gepflegt wird weiterhin nur im Register „Anforderungen“. | U2: (alle) | V2: (alle) | W2: (alle) | X2: (alle) | Y2: (alle) | Z2: (alle)
U3: außerhalb | V3: bewertet | W3: Betreibervertrag | X3: Anzeige & Beschilderung | Y3: Abrechnungskomponente | Z3: Alpitronic
B4: Umfang | E4: Status | H4: Dokument | U4: im Umfang | V4: erfasst | W4: Bieterfragenkatalog | X4: Authentifizierung & Zugang | Y4: Anbindung | Z4: Autostrom+
B5: (alle) | E5: (alle) | H5: (alle) | V5: erfüllt | W5: Vertragsanlage 10 | X5: Bau & Dokumentation | Y5: Authentifizierungskomponente | Z5: Reservierungsplattform
B6: Themenfeld | E6: Komponente | H6: Partner | V6: trifft nicht zu | W6: Vertragsanlage 13 | X6: Belegungsdetektion | Y6: Belegungsdetektion | Z6: SCS
B7: (alle) | E7: (alle) | H7: (alle) | W7: Vertragsanlage 4 | X7: Betrieb & Auslastung | Y7: Beschilderung | Z7: Schrankenhersteller
B8: Suchbegriff | W8: Vertragsanlage 6 | X8: Flächen & Genehmigungen | Y8: Dynamische Anzeige | Z8: Schrankenhersteller / SCS
X9: Monitoring & Reporting | Y9: Kennzeichenerfassung | Z9: Schrankenhersteller / SCS / eRound
A10: Der Suchbegriff wirkt auf Kernaussage und Originaltext. „(alle)“ lässt ein Feld unberücksichtigt; Komponente und Partner suchen als Teiltext. | X10: Netzanschluss & Energie | Y10: Ladeeinrichtung | Z10: WWL
X11: Nutzungszeit & Entgelte | Y11: Monitoring | Z11: Zuordnung prüfen
A12: Treffer | B12: =COUNTIF(Anforderungen!$O$7:$O$2000,">0") -> 1382 | D12: erfasst | E12: =SUMPRODUCT((Anforderungen!$O$7:$O$2000>0)*(Anforderungen!$K$7:$K$2000="erfasst")) -> 1211 | F12: bewertet | G12: =SUMPRODUCT((Anforderungen!$O$7:$O$2000>0)*(Anforderungen!$K$7:$K$2000="bewertet")) -> 3 | H12: erfüllt | I12: =SUMPRODUCT((Anforderungen!$O$7:$O$2000>0)*(Anforderungen!$K$7:$K$2000="erfüllt")) -> 10 | J12: trifft nicht zu | K12: =SUMPRODUCT((Anforderungen!$O$7:$O$2000>0)*(Anforderungen!$K$7:$K$2000="trifft nicht zu")) -> 158 | X12: Reservierung | Y12: OCPI Buchungskalender | Z12: eRound
A13: Angezeigt werden die ersten 300 Treffer. Bei mehr Treffern die Auswahl weiter eingrenzen. | X13: Sonstiges / Zuordnung prüfen | Y13: Pönalisierungssystem | Z13: eRound / SCS
X14: Technik Ladeinfrastruktur | Y14: Reservierungsplattform | Z14: offen
A15: ID | B15: Dokument | C15: Fundstelle | D15: Themenfeld | E15: Kernaussage | F15: Originaltext | G15: Partner | H15: Komponente(n) | I15: Status | J15: Erfüllt am | K15: Nachweis / Notiz | X15: Vergabeverfahren & Angebot | Y15: Schrankenanlage | Z15: tbd
A16: =IF($R16="","",INDEX(Anforderungen!$B:$B,$R16)) -> ANF-001 | B16: =IF($R16="","",INDEX(Anforderungen!$C:$C,$R16)) -> Betreibervertrag | C16: =IF($R16="","",INDEX(Anforderungen!$D:$D,$R16)) -> § 25 (1) | D16: =IF($R16="","",INDEX(Anforderungen!$E:$E,$R16)) -> Reservierung | E16: =IF($R16="","",INDEX(Anforderungen!$F:$F,$R16)) -> OCPI Schnittstelle | F16: =IF($R16="","",INDEX(Anforderungen!$G:$G,$R16)) -> Der Auftragnehmer stellt sicher, dass die Reservierung von Ladepunkten über Reservierungsplattformen während der Laufzeit dieses Vertrags möglich ist. Hierzu hält der Auftragnehmer eine auf OCPI (Open Charge Point Interface) basierende Schnittstelle vor, über die sich Reservierungsplattformen nach Maßgabe der folgenden Absätze anbinden können. | G16: =IF($R16="","",INDEX(Anforderungen!$I:$I,$R16)) -> eRound | H16: =IF($R16="","",INDEX(Anforderungen!$J:$J,$R16)) -> OCPI Buchungskalender | I16: =IF($R16="","",INDEX(Anforderungen!$K:$K,$R16)) -> erfasst | J16: =IF($R16="","",INDEX(Anforderungen!$L:$L,$R16)) -> 0 | K16: =IF($R16="","",INDEX(Anforderungen!$M:$M,$R16)) -> 0 | R16: =IFERROR(MATCH(ROWS($A$16:$A16),Anforderungen!$O$7:$O$2000,0)+6,"") -> 7 | X16: Vertrag & Recht | Y16: Schrankensteuerung
A17: =IF($R17="","",INDEX(Anforderungen!$B:$B,$R17)) -> ANF-002 | B17: =IF($R17="","",INDEX(Anforderungen!$C:$C,$R17)) -> Betreibervertrag | C17: =IF($R17="","",INDEX(Anforderungen!$D:$D,$R17)) -> § 25 (2) | D17: =IF($R17="","",INDEX(Anforderungen!$E:$E,$R17)) -> Reservierung | E17: =IF($R17="","",INDEX(Anforderungen!$F:$F,$R17)) -> OCPI Kostenfrei | F17: =IF($R17="","",INDEX(Anforderungen!$G:$G,$R17)) -> Der Auftragnehmer ist verpflichtet, jeder Reservierungsplattform die Anbindung über die in Absatz 1 genannte Schnittstelle kostenfrei zu ermöglichen, soweit die Reservierungsplattform die folgenden Mindestvoraussetzungen erfüllt: | G17: =IF($R17="","",INDEX(Anforderungen!$I:$I,$R17)) -> eRound | H17: =IF($R17="","",INDEX(Anforderungen!$J:$J,$R17)) -> OCPI Buchungskalender | I17: =IF($R17="","",INDEX(Anforderungen!$K:$K,$R17)) -> erfasst | J17: =IF($R17="","",INDEX(Anforderungen!$L:$L,$R17)) -> 0 | K17: =IF($R17="","",INDEX(Anforderungen!$M:$M,$R17)) -> 0 | R17: =IFERROR(MATCH(ROWS($A$16:$A17),Anforderungen!$O$7:$O$2000,0)+6,"") -> 8 | X17: Zufahrt & Schranke | Y17: Zuordnung prüfen
A18: =IF($R18="","",INDEX(Anforderungen!$B:$B,$R18)) -> ANF-003 | B18: =IF($R18="","",INDEX(Anforderungen!$C:$C,$R18)) -> Betreibervertrag | C18: =IF($R18="","",INDEX(Anforderungen!$D:$D,$R18)) -> § 25 (2) a | D18: =IF($R18="","",INDEX(Anforderungen!$E:$E,$R18)) -> Reservierung | E18: =IF($R18="","",INDEX(Anforderungen!$F:$F,$R18)) -> OCPI Kostenfrei | F18: =IF($R18="","",INDEX(Anforderungen!$G:$G,$R18)) -> Die Reservierungsplattform stellt dem Auftragnehmer für die Anbindung der Reservierungsplattform keine Anbindungskosten in Rechnung | G18: =IF($R18="","",INDEX(Anforderungen!$I:$I,$R18)) -> eRound | H18: =IF($R18="","",INDEX(Anforderungen!$J:$J,$R18)) -> Anbindung | I18: =IF($R18="","",INDEX(Anforderungen!$K:$K,$R18)) -> erfasst | J18: =IF($R18="","",INDEX(Anforderungen!$L:$L,$R18)) -> 0 | K18: =IF($R18="","",INDEX(Anforderungen!$M:$M,$R18)) -> 0 | R18: =IFERROR(MATCH(ROWS($A$16:$A18),Anforderungen!$O$7:$O$2000,0)+6,"") -> 9 | Y18: –
A19: =IF($R19="","",INDEX(Anforderungen!$B:$B,$R19)) -> ANF-004 | B19: =IF($R19="","",INDEX(Anforderungen!$C:$C,$R19)) -> Betreibervertrag | C19: =IF($R19="","",INDEX(Anforderungen!$D:$D,$R19)) -> § 25 (2) b | D19: =IF($R19="","",INDEX(Anforderungen!$E:$E,$R19)) -> Reservierung | E19: =IF($R19="","",INDEX(Anforderungen!$F:$F,$R19)) -> Anbindung verpflichtend, wenn alle AN angebunden werden oder AG2 auffordert | F19: =IF($R19="","",INDEX(Anforderungen!$G:$G,$R19)) -> Die Reservierungsplattform ermöglicht Endnutzern und Mobilitätsdienstleistern die Reservierung von Ladepunkten im gesamten Gebiet der Bundesrepublik Deutschland gegen ein angemessenes Entgelt. Ermöglicht eine Reservierungsplattform eine Reservierung von Ladepunkten nur in Teilen des Gebiets der Bundesrepublik Deutschland, ist der Auftragnehmer zur Anbindung nur verpflichtet, wenn der Auftraggeber 2 den Auftragnehmer hierzu auffordert. | G19: =IF($R19="","",INDEX(Anforderungen!$I:$I,$R19)) -> eRound | H19: =IF($R19="","",INDEX(Anforderungen!$J:$J,$R19)) -> OCPI Buchungskalender | I19: =IF($R19="","",INDEX(Anforderungen!$K:$K,$R19)) -> erfasst | J19: =IF($R19="","",INDEX(Anforderungen!$L:$L,$R19)) -> 0 | K19: =IF($R19="","",INDEX(Anforderungen!$M:$M,$R19)) -> 0 | R19: =IFERROR(MATCH(ROWS($A$16:$A19),Anforderungen!$O$7:$O$2000,0)+6,"") -> 10
A20: =IF($R20="","",INDEX(Anforderungen!$B:$B,$R20)) -> ANF-005 | B20: =IF($R20="","",INDEX(Anforderungen!$C:$C,$R20)) -> Betreibervertrag | C20: =IF($R20="","",INDEX(Anforderungen!$D:$D,$R20)) -> § 25 (2) c | D20: =IF($R20="","",INDEX(Anforderungen!$E:$E,$R20)) -> Reservierung | E20: =IF($R20="","",INDEX(Anforderungen!$F:$F,$R20)) -> Reservierung mit Vorlauf von max. 7 Tagen und min. 15 min. Kostenfreie Stornierung und Änderung bis 30min vorher. Kennzeichenabgleich zur Unterbindung von Doppelbuchungen. | F20: =IF($R20="","",INDEX(Anforderungen!$G:$G,$R20)) -> Die Reservierungsplattform ermöglicht eine Reservierung von Ladepunkten mit einer Vorlaufzeit von maximal 7 Kalendertagen und mindestens 15 Minuten. Eine kostenfreie Stornierung oder Änderung der Reservierung über die Reservierungsplattform muss, soweit möglich, bis zu 30 Minuten vor Beginn des in der Reservierung angegebenen Startzeitpunkts möglich sein. Die Reservierungsplattform stellt durch geeignete Vorkehrungen (z. B. durch einen Kennzeichenabgleich) sicher, dass für einen E-LKW in einem Zeitintervall nur ein Ladepunkt reserviert wird. | G20: =IF($R20="","",INDEX(Anforderungen!$I:$I,$R20)) -> eRound | H20: =IF($R20="","",INDEX(Anforderungen!$J:$J,$R20)) -> OCPI Buchungskalender | I20: =IF($R20="","",INDEX(Anforderungen!$K:$K,$R20)) -> erfasst | J20: =IF($R20="","",INDEX(Anforderungen!$L:$L,$R20)) -> 0 | K20: =IF($R20="","",INDEX(Anforderungen!$M:$M,$R20)) -> 0 | R20: =IFERROR(MATCH(ROWS($A$16:$A20),Anforderungen!$O$7:$O$2000,0)+6,"") -> 11
A21: =IF($R21="","",INDEX(Anforderungen!$B:$B,$R21)) -> ANF-006 | B21: =IF($R21="","",INDEX(Anforderungen!$C:$C,$R21)) -> Betreibervertrag | C21: =IF($R21="","",INDEX(Anforderungen!$D:$D,$R21)) -> § 25 (2) d | D21: =IF($R21="","",INDEX(Anforderungen!$E:$E,$R21)) -> Reservierung | E21: =IF($R21="","",INDEX(Anforderungen!$F:$F,$R21)) -> Entschädigung an AN von der Reservierungsplattform i.H.v. mind. 30€ nach 15/30 min Wartezeit bei No-Show. | F21: =IF($R21="","",INDEX(Anforderungen!$G:$G,$R21)) -> Die Reservierungsplattform entschädigt den Auftragnehmer in angemessener Höhe, wenn an der reservierten Ladeeinrichtung ab dem in der Reservierung angegebenen Startzeitpunkt und Ablauf einer Wartezeit von 15 Minuten bei Ladepunkten zum Zwischenladen, bzw. 30 Minuten bei Ladepunkten zum Übernachtladen (sog. „no-show“) kein Start eines Ladevorgangs erfolgt. Die Entschädigung des Auftragnehmers ist angemessen, wenn der Auftragnehmer im Fall eines „no-show“ mindestens € 30,00 erhält. | G21: =IF($R21="","",INDEX(Anforderungen!$I:$I,$R21)) -> eRound | H21: =IF($R21="","",INDEX(Anforderungen!$J:$J,$R21)) -> Abrechnungskomponente | I21: =IF($R21="","",INDEX(Anforderungen!$K:$K,$R21)) -> erfasst | J21: =IF($R21="","",INDEX(Anforderungen!$L:$L,$R21)) -> 0 | K21: =IF($R21="","",INDEX(Anforderungen!$M:$M,$R21)) -> 0 | R21: =IFERROR(MATCH(ROWS($A$16:$A21),Anforderungen!$O$7:$O$2000,0)+6,"") -> 12
A22: =IF($R22="","",INDEX(Anforderungen!$B:$B,$R22)) -> ANF-007 | B22: =IF($R22="","",INDEX(Anforderungen!$C:$C,$R22)) -> Betreibervertrag | C22: =IF($R22="","",INDEX(Anforderungen!$D:$D,$R22)) -> § 25 (3) | D22: =IF($R22="","",INDEX(Anforderungen!$E:$E,$R22)) -> Reservierung | E22: =IF($R22="","",INDEX(Anforderungen!$F:$F,$R22)) -> Anpassung an Marktstandards mit 2 Monaten Vorlauf. | F22: =IF($R22="","",INDEX(Anforderungen!$G:$G,$R22)) -> Der Auftraggeber 2 ist berechtigt, die in Absatz 2 definierten Mindestvoraussetzungen im Fall abweichender Marktstandards mit einer Vorlaufzeit von zwei Monaten anzupassen | G22: =IF($R22="","",INDEX(Anforderungen!$I:$I,$R22)) -> eRound | H22: =IF($R22="","",INDEX(Anforderungen!$J:$J,$R22)) -> OCPI Buchungskalender | I22: =IF($R22="","",INDEX(Anforderungen!$K:$K,$R22)) -> erfasst | J22: =IF($R22="","",INDEX(Anforderungen!$L:$L,$R22)) -> 0 | K22: =IF($R22="","",INDEX(Anforderungen!$M:$M,$R22)) -> 0 | R22: =IFERROR(MATCH(ROWS($A$16:$A22),Anforderungen!$O$7:$O$2000,0)+6,"") -> 13
A23: =IF($R23="","",INDEX(Anforderungen!$B:$B,$R23)) -> ANF-008 | B23: =IF($R23="","",INDEX(Anforderungen!$C:$C,$R23)) -> Betreibervertrag | C23: =IF($R23="","",INDEX(Anforderungen!$D:$D,$R23)) -> § 25 (4) | D23: =IF($R23="","",INDEX(Anforderungen!$E:$E,$R23)) -> Reservierung | E23: =IF($R23="","",INDEX(Anforderungen!$F:$F,$R23)) -> Ladepunkte an einem Standort können von der Reservierung ausgenommen werden. | F23: =IF($R23="","",INDEX(Anforderungen!$G:$G,$R23)) -> Der Auftragnehmer kann CCS- und MCS-Ladepunkten an einem Standort von der Reservierungsmöglichkeit ausnehmen. | G23: =IF($R23="","",INDEX(Anforderungen!$I:$I,$R23)) -> eRound | H23: =IF($R23="","",INDEX(Anforderungen!$J:$J,$R23)) -> OCPI Buchungskalender | I23: =IF($R23="","",INDEX(Anforderungen!$K:$K,$R23)) -> erfasst | J23: =IF($R23="","",INDEX(Anforderungen!$L:$L,$R23)) -> 0 | K23: =IF($R23="","",INDEX(Anforderungen!$M:$M,$R23)) -> 0 | R23: =IFERROR(MATCH(ROWS($A$16:$A23),Anforderungen!$O$7:$O$2000,0)+6,"") -> 14
A24: =IF($R24="","",INDEX(Anforderungen!$B:$B,$R24)) -> ANF-009 | B24: =IF($R24="","",INDEX(Anforderungen!$C:$C,$R24)) -> Betreibervertrag | C24: =IF($R24="","",INDEX(Anforderungen!$D:$D,$R24)) -> § 25 (5) | D24: =IF($R24="","",INDEX(Anforderungen!$E:$E,$R24)) -> Zufahrt & Schranke | E24: =IF($R24="","",INDEX(Anforderungen!$F:$F,$R24)) -> Bauliche Maßnahme zur Reservierung an jedem Ladepunkt. | F24: =IF($R24="","",INDEX(Anforderungen!$G:$G,$R24)) -> Der Auftragnehmer hat geeignete Vorkehrungen, insbesondere die in Vertragsanlage 4: Leistungsbeschreibung Errichtung vorgesehenen baulichen Maßnahmen, zu treffen, um ein anderweitiges Laden an dem Ladepunkt der Ladeeinrichtung während des reservierten Zeitraums zu verhindern. | G24: =IF($R24="","",INDEX(Anforderungen!$I:$I,$R24)) -> Schrankenhersteller | H24: =IF($R24="","",INDEX(Anforderungen!$J:$J,$R24)) -> Schrankenanlage | I24: =IF($R24="","",INDEX(Anforderungen!$K:$K,$R24)) -> erfasst | J24: =IF($R24="","",INDEX(Anforderungen!$L:$L,$R24)) -> 0 | K24: =IF($R24="","",INDEX(Anforderungen!$M:$M,$R24)) -> 0 | R24: =IFERROR(MATCH(ROWS($A$16:$A24),Anforderungen!$O$7:$O$2000,0)+6,"") -> 15
A25: =IF($R25="","",INDEX(Anforderungen!$B:$B,$R25)) -> ANF-010 | B25: =IF($R25="","",INDEX(Anforderungen!$C:$C,$R25)) -> Betreibervertrag | C25: =IF($R25="","",INDEX(Anforderungen!$D:$D,$R25)) -> § 25 (6) | D25: =IF($R25="","",INDEX(Anforderungen!$E:$E,$R25)) -> Reservierung | E25: =IF($R25="","",INDEX(Anforderungen!$F:$F,$R25)) -> Mindestens 40% der Ladepunkte müssen reserviert werden können. | F25: =IF($R25="","",INDEX(Anforderungen!$G:$G,$R25)) -> Verstößt der Auftragnehmer gegen die Pflicht nach Absatz 1, wird für jeden Standort, an dem die Reservierung von Ladepunkten aufgrund des Verstoßes gegen die Pflicht nach Absatz 1 nicht möglich ist, eine Vertragsstrafe fällig. Die Reservierung von Ladepunkten an einem Standort gilt als nicht möglich, wenn mindestens 40 % der Ladepunkte an dem Standort nicht reserviert werden können. Die Höhe der Vertragsstrafe beträgt € 2.500,00 für jeden Kalendertag, an dem die Reservierung von Ladepunkten an einem Standort nicht möglich ist, höchstens jedoch € 40.000,00 pro Kalendermonat und pro Standort. | G25: =IF($R25="","",INDEX(Anforderungen!$I:$I,$R25)) -> eRound | H25: =IF($R25="","",INDEX(Anforderungen!$J:$J,$R25)) -> OCPI Buchungskalender | I25: =IF($R25="","",INDEX(Anforderungen!$K:$K,$R25)) -> erfasst | J25: =IF($R25="","",INDEX(Anforderungen!$L:$L,$R25)) -> 0 | K25: =IF($R25="","",INDEX(Anforderungen!$M:$M,$R25)) -> 0 | R25: =IFERROR(MATCH(ROWS($A$16:$A25),Anforderungen!$O$7:$O$2000,0)+6,"") -> 16
A26: =IF($R26="","",INDEX(Anforderungen!$B:$B,$R26)) -> ANF-011 | B26: =IF($R26="","",INDEX(Anforderungen!$C:$C,$R26)) -> Betreibervertrag | C26: =IF($R26="","",INDEX(Anforderungen!$D:$D,$R26)) -> § 31 (1) | D26: =IF($R26="","",INDEX(Anforderungen!$E:$E,$R26)) -> Authentifizierung & Zugang | E26: =IF($R26="","",INDEX(Anforderungen!$F:$F,$R26)) -> Es muss Adhoc geladen werden können | F26: =IF($R26="","",INDEX(Anforderungen!$G:$G,$R26)) -> Der Auftragnehmer ist verpflichtet, potenziellen Endnutzern diskriminierungsfrei zu angemessenen Bedingungen ein Ad-hoc-Laden (punktuelles Aufladen i. S. d. AFIR) zu ermöglichen, soweit es ihm zumutbar ist (z. B. mit Blick auf die Bonität des Endnutzers). | G26: =IF($R26="","",INDEX(Anforderungen!$I:$I,$R26)) -> eRound / SCS | H26: =IF($R26="","",INDEX(Anforderungen!$J:$J,$R26)) -> Authentifizierungskomponente / Schrankensteuerung | I26: =IF($R26="","",INDEX(Anforderungen!$K:$K,$R26)) -> erfasst | J26: =IF($R26="","",INDEX(Anforderungen!$L:$L,$R26)) -> 0 | K26: =IF($R26="","",INDEX(Anforderungen!$M:$M,$R26)) -> 0 | R26: =IFERROR(MATCH(ROWS($A$16:$A26),Anforderungen!$O$7:$O$2000,0)+6,"") -> 17
A27: =IF($R27="","",INDEX(Anforderungen!$B:$B,$R27)) -> ANF-012 | B27: =IF($R27="","",INDEX(Anforderungen!$C:$C,$R27)) -> Betreibervertrag | C27: =IF($R27="","",INDEX(Anforderungen!$D:$D,$R27)) -> § 38 (1) | D27: =IF($R27="","",INDEX(Anforderungen!$E:$E,$R27)) -> Nutzungszeit & Entgelte | E27: =IF($R27="","",INDEX(Anforderungen!$F:$F,$R27)) -> Blockadeentgelte und maximale Nutzungsdauer | F27: =IF($R27="","",INDEX(Anforderungen!$G:$G,$R27)) -> Start- und zeitabhängige Entgelte dürfen nicht erhoben werden. Dies gilt nicht für vertraglich vereinbarte Blockadeentgelte, die nach Ablauf einer maximalen Nutzungszeit vom Endnutzer bzw. Mobilitätsdienstleister unabhängig davon, welches der Zugangsmodelle des § 30 Abs. 2 gewählt wird, erhoben werden. Die maximale Nutzungszeit beginnt mit Beginn des Ladevorgangs und beträgt | G27: =IF($R27="","",INDEX(Anforderungen!$I:$I,$R27)) -> eRound | H27: =IF($R27="","",INDEX(Anforderungen!$J:$J,$R27)) -> OCPI Buchungskalender | I27: =IF($R27="","",INDEX(Anforderungen!$K:$K,$R27)) -> erfasst | J27: =IF($R27="","",INDEX(Anforderungen!$L:$L,$R27)) -> 0 | K27: =IF($R27="","",INDEX(Anforderungen!$M:$M,$R27)) -> 0 | R27: =IFERROR(MATCH(ROWS($A$16:$A27),Anforderungen!$O$7:$O$2000,0)+6,"") -> 18
A28: =IF($R28="","",INDEX(Anforderungen!$B:$B,$R28)) -> ANF-013 | B28: =IF($R28="","",INDEX(Anforderungen!$C:$C,$R28)) -> Betreibervertrag | C28: =IF($R28="","",INDEX(Anforderungen!$D:$D,$R28)) -> § 38 (1) a | D28: =IF($R28="","",INDEX(Anforderungen!$E:$E,$R28)) -> Nutzungszeit & Entgelte | E28: =IF($R28="","",INDEX(Anforderungen!$F:$F,$R28)) -> Maximale Nutzungsdauer Zwischenladen ist 1h. | F28: =IF($R28="","",INDEX(Anforderungen!$G:$G,$R28)) -> bei MCS-Ladepunkten und CCS-Ladepunkten zum Zwischenladen 1 Stunde. | G28: =IF($R28="","",INDEX(Anforderungen!$I:$I,$R28)) -> eRound | H28: =IF($R28="","",INDEX(Anforderungen!$J:$J,$R28)) -> OCPI Buchungskalender | I28: =IF($R28="","",INDEX(Anforderungen!$K:$K,$R28)) -> erfasst | J28: =IF($R28="","",INDEX(Anforderungen!$L:$L,$R28)) -> 0 | K28: =IF($R28="","",INDEX(Anforderungen!$M:$M,$R28)) -> 0 | R28: =IFERROR(MATCH(ROWS($A$16:$A28),Anforderungen!$O$7:$O$2000,0)+6,"") -> 19
A29: =IF($R29="","",INDEX(Anforderungen!$B:$B,$R29)) -> ANF-014 | B29: =IF($R29="","",INDEX(Anforderungen!$C:$C,$R29)) -> Betreibervertrag | C29: =IF($R29="","",INDEX(Anforderungen!$D:$D,$R29)) -> § 38 (1) b | D29: =IF($R29="","",INDEX(Anforderungen!$E:$E,$R29)) -> Nutzungszeit & Entgelte | E29: =IF($R29="","",INDEX(Anforderungen!$F:$F,$R29)) -> Maximale Nutzungsdauer Übernachtladen ist 12h. | F29: =IF($R29="","",INDEX(Anforderungen!$G:$G,$R29)) -> bei CCS-Ladepunkten zum Übernachtladen und MCS- oder CCS-Ladepunkte zum Zwischenladen, die zum Übernachtladen freigegeben wurden, 12 Stunden. | G29: =IF($R29="","",INDEX(Anforderungen!$I:$I,$R29)) -> eRound | H29: =IF($R29="","",INDEX(Anforderungen!$J:$J,$R29)) -> OCPI Buchungskalender | I29: =IF($R29="","",INDEX(Anforderungen!$K:$K,$R29)) -> erfasst | J29: =IF($R29="","",INDEX(Anforderungen!$L:$L,$R29)) -> 0 | K29: =IF($R29="","",INDEX(Anforderungen!$M:$M,$R29)) -> 0 | R29: =IFERROR(MATCH(ROWS($A$16:$A29),Anforderungen!$O$7:$O$2000,0)+6,"") -> 20
A30: =IF($R30="","",INDEX(Anforderungen!$B:$B,$R30)) -> ANF-015 | B30: =IF($R30="","",INDEX(Anforderungen!$C:$C,$R30)) -> Betreibervertrag | C30: =IF($R30="","",INDEX(Anforderungen!$D:$D,$R30)) -> § 38 (2) | D30: =IF($R30="","",INDEX(Anforderungen!$E:$E,$R30)) -> Nutzungszeit & Entgelte | E30: =IF($R30="","",INDEX(Anforderungen!$F:$F,$R30)) -> Bei nidriger Auslastung kann die maximale Nutzungszeit vom AN verlängert werden. Bei nachfolgender Reservierung kann die maximale Nutzungszeit verkürzt werden. Bei Verkürzung zusätzliche Karenzzeit vor Blockadeentgeld von 5min. | F30: =IF($R30="","",INDEX(Anforderungen!$G:$G,$R30)) -> Der Auftragnehmer kann die maximalen Nutzungszeiten in Zeiten geringer Auslastung verlängern. Zudem kann er mit der Gestattung der Nutzung von MCS-Ladepunkten und CCS-Ladepunkten zum Zwischenladen dem Endnutzer bzw. Mobilitätsdienstleister auch ausdrücklich eine kürzere maximale Nutzungszeit einräumen, wenn wegen nachfolgender Reservierungen die maximale Nutzungszeit nach Absatz 1 lit. a nicht eingeräumt werden kann. In den Fällen des Satzes 2 ist dem Endnutzer bzw. Mobilitätsdienstleister zusätzlich eine Karenzzeit zum Verlassen des Ladeplatzes von 5 Minuten einzuräumen, nach deren Ablauf erst ein Blockadeentgelt erhoben werden darf | G30: =IF($R30="","",INDEX(Anforderungen!$I:$I,$R30)) -> eRound | H30: =IF($R30="","",INDEX(Anforderungen!$J:$J,$R30)) -> OCPI Buchungskalender | I30: =IF($R30="","",INDEX(Anforderungen!$K:$K,$R30)) -> erfasst | J30: =IF($R30="","",INDEX(Anforderungen!$L:$L,$R30)) -> 0 | K30: =IF($R30="","",INDEX(Anforderungen!$M:$M,$R30)) -> 0 | R30: =IFERROR(MATCH(ROWS($A$16:$A30),Anforderungen!$O$7:$O$2000,0)+6,"") -> 21
... A315: =IF($R315="","",INDEX(Anforderungen!$B:$B,$R315)) -> ANF-300 | B315: =IF($R315="","",INDEX(Anforderungen!$C:$C,$R315)) -> Bieterfragenkatalog | C315: =IF($R315="","",INDEX(Anforderungen!$D:$D,$R315)) -> Nr. 247 / S. 22 | D315: =IF($R315="","",INDEX(Anforderungen!$E:$E,$R315)) -> Flächen & Genehmigungen | E315: =IF($R315="","",INDEX(Anforderungen!$F:$F,$R315)) -> Klarstellung: Die baulichen Vorgaben ergeben sich aus der Vertragsanlage 4 und insbesondere aus dem Anhang 1a „Referenzplanung“. | F315: =IF($R315="","",INDEX(Anforderungen!$G:$G,$R315)) -> Gibt es bauliche Vorgaben für die Anreichung der Ladestecker, welche den Einsatz von Überkopflösungen in Stahlbauweise betreffen? Überkopflösungen haben hinsichtlich des Baus und der optimalen Flächennutzung erhebliche Vorteile. | G315: =IF($R315="","",INDEX(Anforderungen!$I:$I,$R315)) -> Alpitronic | H315: =IF($R315="","",INDEX(Anforderungen!$J:$J,$R315)) -> Ladeeinrichtung | I315: =IF($R315="","",INDEX(Anforderungen!$K:$K,$R315)) -> erfasst | J315: =IF($R315="","",INDEX(Anforderungen!$L:$L,$R315)) -> 0 | K315: =IF($R315="","",INDEX(Anforderungen!$M:$M,$R315)) -> 0 | R315: =IFERROR(MATCH(ROWS($A$16:$A315),Anforderungen!$O$7:$O$2000,0)+6,"") -> 306

Sheet Auswertung
A1: Auswertung – Anforderungen
A2: Automatische Auswertung des Statusprozesses erfasst → bewertet → erfüllt bzw. trifft nicht zu – inklusive Bieterfragenkatalog.
A3: Erfüllungsgrad = erfüllte Anforderungen / anwendbare Anforderungen (Status „trifft nicht zu“ wird aus dem Nenner ausgeschlossen).
A5: 1 Nach Themenfeld
A6: Merkmal | B6: Gesamt | C6: Erfasst | D6: Bewertet | E6: Erfüllt | F6: Trifft nicht zu | G6: Erfüllungsgrad
A7: Anzeige & Beschilderung | B7: =COUNTIF(Anforderungen!$E$7:$E$2000,$A7) -> 14 | C7: =COUNTIFS(Anforderungen!$E$7:$E$2000,$A7,Anforderungen!$K$7:$K$2000,"erfasst") -> 11 | D7: =COUNTIFS(Anforderungen!$E$7:$E$2000,$A7,Anforderungen!$K$7:$K$2000,"bewertet") -> 0 | E7: =COUNTIFS(Anforderungen!$E$7:$E$2000,$A7,Anforderungen!$K$7:$K$2000,"erfüllt") -> 2 | F7: =COUNTIFS(Anforderungen!$E$7:$E$2000,$A7,Anforderungen!$K$7:$K$2000,"trifft nicht zu") -> 1 | G7: =IFERROR(E7/(B7-F7),0) -> 0.15384615
A8: Authentifizierung & Zugang | B8: =COUNTIF(Anforderungen!$E$7:$E$2000,$A8) -> 51 | C8: =COUNTIFS(Anforderungen!$E$7:$E$2000,$A8,Anforderungen!$K$7:$K$2000,"erfasst") -> 47 | D8: =COUNTIFS(Anforderungen!$E$7:$E$2000,$A8,Anforderungen!$K$7:$K$2000,"bewertet") -> 0 | E8: =COUNTIFS(Anforderungen!$E$7:$E$2000,$A8,Anforderungen!$K$7:$K$2000,"erfüllt") -> 0 | F8: =COUNTIFS(Anforderungen!$E$7:$E$2000,$A8,Anforderungen!$K$7:$K$2000,"trifft nicht zu") -> 4 | G8: =IFERROR(E8/(B8-F8),0) -> 0
A9: Bau & Dokumentation | B9: =COUNTIF(Anforderungen!$E$7:$E$2000,$A9) -> 98 | C9: =COUNTIFS(Anforderungen!$E$7:$E$2000,$A9,Anforderungen!$K$7:$K$2000,"erfasst") -> 90 | D9: =COUNTIFS(Anforderungen!$E$7:$E$2000,$A9,Anforderungen!$K$7:$K$2000,"bewertet") -> 2 | E9: =COUNTIFS(Anforderungen!$E$7:$E$2000,$A9,Anforderungen!$K$7:$K$2000,"erfüllt") -> 0 | F9: =COUNTIFS(Anforderungen!$E$7:$E$2000,$A9,Anforderungen!$K$7:$K$2000,"trifft nicht zu") -> 6 | G9: =IFERROR(E9/(B9-F9),0) -> 0
A10: Belegungsdetektion | B10: =COUNTIF(Anforderungen!$E$7:$E$2000,$A10) -> 4 | C10: =COUNTIFS(Anforderungen!$E$7:$E$2000,$A10,Anforderungen!$K$7:$K$2000,"erfasst") -> 3 | D10: =COUNTIFS(Anforderungen!$E$7:$E$2000,$A10,Anforderungen!$K$7:$K$2000,"bewertet") -> 0 | E10: =COUNTIFS(Anforderungen!$E$7:$E$2000,$A10,Anforderungen!$K$7:$K$2000,"erfüllt") -> 1 | F10: =COUNTIFS(Anforderungen!$E$7:$E$2000,$A10,Anforderungen!$K$7:$K$2000,"trifft nicht zu") -> 0 | G10: =IFERROR(E10/(B10-F10),0) -> 0.25
A11: Betrieb & Auslastung | B11: =COUNTIF(Anforderungen!$E$7:$E$2000,$A11) -> 76 | C11: =COUNTIFS(Anforderungen!$E$7:$E$2000,$A11,Anforderungen!$K$7:$K$2000,"erfasst") -> 71 | D11: =COUNTIFS(Anforderungen!$E$7:$E$2000,$A11,Anforderungen!$K$7:$K$2000,"bewertet") -> 0 | E11: =COUNTIFS(Anforderungen!$E$7:$E$2000,$A11,Anforderungen!$K$7:$K$2000,"erfüllt") -> 1 | F11: =COUNTIFS(Anforderungen!$E$7:$E$2000,$A11,Anforderungen!$K$7:$K$2000,"trifft nicht zu") -> 4 | G11: =IFERROR(E11/(B11-F11),0) -> 0.013888889
A12: Flächen & Genehmigungen | B12: =COUNTIF(Anforderungen!$E$7:$E$2000,$A12) -> 94 | C12: =COUNTIFS(Anforderungen!$E$7:$E$2000,$A12,Anforderungen!$K$7:$K$2000,"erfasst") -> 88 | D12: =COUNTIFS(Anforderungen!$E$7:$E$2000,$A12,Anforderungen!$K$7:$K$2000,"bewertet") -> 0 | E12: =COUNTIFS(Anforderungen!$E$7:$E$2000,$A12,Anforderungen!$K$7:$K$2000,"erfüllt") -> 0 | F12: =COUNTIFS(Anforderungen!$E$7:$E$2000,$A12,Anforderungen!$K$7:$K$2000,"trifft nicht zu") -> 6 | G12: =IFERROR(E12/(B12-F12),0) -> 0
A13: Monitoring & Reporting | B13: =COUNTIF(Anforderungen!$E$7:$E$2000,$A13) -> 34 | C13: =COUNTIFS(Anforderungen!$E$7:$E$2000,$A13,Anforderungen!$K$7:$K$2000,"erfasst") -> 34 | D13: =COUNTIFS(Anforderungen!$E$7:$E$2000,$A13,Anforderungen!$K$7:$K$2000,"bewertet") -> 0 | E13: =COUNTIFS(Anforderungen!$E$7:$E$2000,$A13,Anforderungen!$K$7:$K$2000,"erfüllt") -> 0 | F13: =COUNTIFS(Anforderungen!$E$7:$E$2000,$A13,Anforderungen!$K$7:$K$2000,"trifft nicht zu") -> 0 | G13: =IFERROR(E13/(B13-F13),0) -> 0
A14: Netzanschluss & Energie | B14: =COUNTIF(Anforderungen!$E$7:$E$2000,$A14) -> 228 | C14: =COUNTIFS(Anforderungen!$E$7:$E$2000,$A14,Anforderungen!$K$7:$K$2000,"erfasst") -> 210 | D14: =COUNTIFS(Anforderungen!$E$7:$E$2000,$A14,Anforderungen!$K$7:$K$2000,"bewertet") -> 0 | E14: =COUNTIFS(Anforderungen!$E$7:$E$2000,$A14,Anforderungen!$K$7:$K$2000,"erfüllt") -> 0 | F14: =COUNTIFS(Anforderungen!$E$7:$E$2000,$A14,Anforderungen!$K$7:$K$2000,"trifft nicht zu") -> 18 | G14: =IFERROR(E14/(B14-F14),0) -> 0
A15: Nutzungszeit & Entgelte | B15: =COUNTIF(Anforderungen!$E$7:$E$2000,$A15) -> 44 | C15: =COUNTIFS(Anforderungen!$E$7:$E$2000,$A15,Anforderungen!$K$7:$K$2000,"erfasst") -> 42 | D15: =COUNTIFS(Anforderungen!$E$7:$E$2000,$A15,Anforderungen!$K$7:$K$2000,"bewertet") -> 0 | E15: =COUNTIFS(Anforderungen!$E$7:$E$2000,$A15,Anforderungen!$K$7:$K$2000,"erfüllt") -> 0 | F15: =COUNTIFS(Anforderungen!$E$7:$E$2000,$A15,Anforderungen!$K$7:$K$2000,"trifft nicht zu") -> 2 | G15: =IFERROR(E15/(B15-F15),0) -> 0
A16: Reservierung | B16: =COUNTIF(Anforderungen!$E$7:$E$2000,$A16) -> 74 | C16: =COUNTIFS(Anforderungen!$E$7:$E$2000,$A16,Anforderungen!$K$7:$K$2000,"erfasst") -> 71 | D16: =COUNTIFS(Anforderungen!$E$7:$E$2000,$A16,Anforderungen!$K$7:$K$2000,"bewertet") -> 1 | E16: =COUNTIFS(Anforderungen!$E$7:$E$2000,$A16,Anforderungen!$K$7:$K$2000,"erfüllt") -> 0 | F16: =COUNTIFS(Anforderungen!$E$7:$E$2000,$A16,Anforderungen!$K$7:$K$2000,"trifft nicht zu") -> 2 | G16: =IFERROR(E16/(B16-F16),0) -> 0
A17: Sonstiges / Zuordnung prüfen | B17: =COUNTIF(Anforderungen!$E$7:$E$2000,$A17) -> 98 | C17: =COUNTIFS(Anforderungen!$E$7:$E$2000,$A17,Anforderungen!$K$7:$K$2000,"erfasst") -> 85 | D17: =COUNTIFS(Anforderungen!$E$7:$E$2000,$A17,Anforderungen!$K$7:$K$2000,"bewertet") -> 0 | E17: =COUNTIFS(Anforderungen!$E$7:$E$2000,$A17,Anforderungen!$K$7:$K$2000,"erfüllt") -> 0 | F17: =COUNTIFS(Anforderungen!$E$7:$E$2000,$A17,Anforderungen!$K$7:$K$2000,"trifft nicht zu") -> 13 | G17: =IFERROR(E17/(B17-F17),0) -> 0
A18: Technik Ladeinfrastruktur | B18: =COUNTIF(Anforderungen!$E$7:$E$2000,$A18) -> 153 | C18: =COUNTIFS(Anforderungen!$E$7:$E$2000,$A18,Anforderungen!$K$7:$K$2000,"erfasst") -> 136 | D18: =COUNTIFS(Anforderungen!$E$7:$E$2000,$A18,Anforderungen!$K$7:$K$2000,"bewertet") -> 0 | E18: =COUNTIFS(Anforderungen!$E$7:$E$2000,$A18,Anforderungen!$K$7:$K$2000,"erfüllt") -> 0 | F18: =COUNTIFS(Anforderungen!$E$7:$E$2000,$A18,Anforderungen!$K$7:$K$2000,"trifft nicht zu") -> 17 | G18: =IFERROR(E18/(B18-F18),0) -> 0
... A21: Zufahrt & Schranke | B21: =COUNTIF(Anforderungen!$E$7:$E$2000,$A21) -> 30 | C21: =COUNTIFS(Anforderungen!$E$7:$E$2000,$A21,Anforderungen!$K$7:$K$2000,"erfasst") -> 22 | D21: =COUNTIFS(Anforderungen!$E$7:$E$2000,$A21,Anforderungen!$K$7:$K$2000,"bewertet") -> 0 | E21: =COUNTIFS(Anforderungen!$E$7:$E$2000,$A21,Anforderungen!$K$7:$K$2000,"erfüllt") -> 6 | F21: =COUNTIFS(Anforderungen!$E$7:$E$2000,$A21,Anforderungen!$K$7:$K$2000,"trifft nicht zu") -> 2 | G21: =IFERROR(E21/(B21-F21),0) -> 0.21428571
A24: 2 Nach Partner
A25: Merkmal | B25: Gesamt | C25: Erfasst | D25: Bewertet | E25: Erfüllt | F25: Trifft nicht zu | G25: Erfüllungsgrad
A26: Aplitronic | B26: =SUMPRODUCT(ISNUMBER(SEARCH($A26,Anforderungen!$I$7:$I$2000))*(Anforderungen!$B$7:$B$2000<>"")) -> 104 | C26: =SUMPRODUCT(ISNUMBER(SEARCH($A26,Anforderungen!$I$7:$I$2000))*(Anforderungen!$K$7:$K$2000="erfasst")) -> 90 | D26: =SUMPRODUCT(ISNUMBER(SEARCH($A26,Anforderungen!$I$7:$I$2000))*(Anforderungen!$K$7:$K$2000="bewertet")) -> 0 | E26: =SUMPRODUCT(ISNUMBER(SEARCH($A26,Anforderungen!$I$7:$I$2000))*(Anforderungen!$K$7:$K$2000="erfüllt")) -> 0 | F26: =SUMPRODUCT(ISNUMBER(SEARCH($A26,Anforderungen!$I$7:$I$2000))*(Anforderungen!$K$7:$K$2000="trifft nicht zu")) -> 14 | G26: =IFERROR(E26/(B26-F26),0) -> 0
A27: eRound | B27: =SUMPRODUCT(ISNUMBER(SEARCH($A27,Anforderungen!$I$7:$I$2000))*(Anforderungen!$B$7:$B$2000<>"")) -> 225 | C27: =SUMPRODUCT(ISNUMBER(SEARCH($A27,Anforderungen!$I$7:$I$2000))*(Anforderungen!$K$7:$K$2000="erfasst")) -> 211 | D27: =SUMPRODUCT(ISNUMBER(SEARCH($A27,Anforderungen!$I$7:$I$2000))*(Anforderungen!$K$7:$K$2000="bewertet")) -> 0 | E27: =SUMPRODUCT(ISNUMBER(SEARCH($A27,Anforderungen!$I$7:$I$2000))*(Anforderungen!$K$7:$K$2000="erfüllt")) -> 5 | F27: =SUMPRODUCT(ISNUMBER(SEARCH($A27,Anforderungen!$I$7:$I$2000))*(Anforderungen!$K$7:$K$2000="trifft nicht zu")) -> 9 | G27: =IFERROR(E27/(B27-F27),0) -> 0.023148148
A28: SCS | B28: =SUMPRODUCT(ISNUMBER(SEARCH($A28,Anforderungen!$I$7:$I$2000))*(Anforderungen!$B$7:$B$2000<>"")) -> 76 | C28: =SUMPRODUCT(ISNUMBER(SEARCH($A28,Anforderungen!$I$7:$I$2000))*(Anforderungen!$K$7:$K$2000="erfasst")) -> 68 | D28: =SUMPRODUCT(ISNUMBER(SEARCH($A28,Anforderungen!$I$7:$I$2000))*(Anforderungen!$K$7:$K$2000="bewertet")) -> 0 | E28: =SUMPRODUCT(ISNUMBER(SEARCH($A28,Anforderungen!$I$7:$I$2000))*(Anforderungen!$K$7:$K$2000="erfüllt")) -> 6 | F28: =SUMPRODUCT(ISNUMBER(SEARCH($A28,Anforderungen!$I$7:$I$2000))*(Anforderungen!$K$7:$K$2000="trifft nicht zu")) -> 2 | G28: =IFERROR(E28/(B28-F28),0) -> 0.081081081
A29: Reservierungsplattform | B29: =SUMPRODUCT(ISNUMBER(SEARCH($A29,Anforderungen!$I$7:$I$2000))*(Anforderungen!$B$7:$B$2000<>"")) -> 13 | C29: =SUMPRODUCT(ISNUMBER(SEARCH($A29,Anforderungen!$I$7:$I$2000))*(Anforderungen!$K$7:$K$2000="erfasst")) -> 13 | D29: =SUMPRODUCT(ISNUMBER(SEARCH($A29,Anforderungen!$I$7:$I$2000))*(Anforderungen!$K$7:$K$2000="bewertet")) -> 0 | E29: =SUMPRODUCT(ISNUMBER(SEARCH($A29,Anforderungen!$I$7:$I$2000))*(Anforderungen!$K$7:$K$2000="erfüllt")) -> 0 | F29: =SUMPRODUCT(ISNUMBER(SEARCH($A29,Anforderungen!$I$7:$I$2000))*(Anforderungen!$K$7:$K$2000="trifft nicht zu")) -> 0 | G29: =IFERROR(E29/(B29-F29),0) -> 0
A30: tbd | B30: =SUMPRODUCT(ISNUMBER(SEARCH($A30,Anforderungen!$I$7:$I$2000))*(Anforderungen!$B$7:$B$2000<>"")) -> 29 | C30: =SUMPRODUCT(ISNUMBER(SEARCH($A30,Anforderungen!$I$7:$I$2000))*(Anforderungen!$K$7:$K$2000="erfasst")) -> 27 | D30: =SUMPRODUCT(ISNUMBER(SEARCH($A30,Anforderungen!$I$7:$I$2000))*(Anforderungen!$K$7:$K$2000="bewertet")) -> 0 | E30: =SUMPRODUCT(ISNUMBER(SEARCH($A30,Anforderungen!$I$7:$I$2000))*(Anforderungen!$K$7:$K$2000="erfüllt")) -> 0 | F30: =SUMPRODUCT(ISNUMBER(SEARCH($A30,Anforderungen!$I$7:$I$2000))*(Anforderungen!$K$7:$K$2000="trifft nicht zu")) -> 2 | G30: =IFERROR(E30/(B30-F30),0) -> 0
A31: offen | B31: =SUMPRODUCT(ISNUMBER(SEARCH($A31,Anforderungen!$I$7:$I$2000))*(Anforderungen!$B$7:$B$2000<>"")) -> 731 | C31: =SUMPRODUCT(ISNUMBER(SEARCH($A31,Anforderungen!$I$7:$I$2000))*(Anforderungen!$K$7:$K$2000="erfasst")) -> 626 | D31: =SUMPRODUCT(ISNUMBER(SEARCH($A31,Anforderungen!$I$7:$I$2000))*(Anforderungen!$K$7:$K$2000="bewertet")) -> 0 | E31: =SUMPRODUCT(ISNUMBER(SEARCH($A31,Anforderungen!$I$7:$I$2000))*(Anforderungen!$K$7:$K$2000="erfüllt")) -> 0 | F31: =SUMPRODUCT(ISNUMBER(SEARCH($A31,Anforderungen!$I$7:$I$2000))*(Anforderungen!$K$7:$K$2000="trifft nicht zu")) -> 105 | G31: =IFERROR(E31/(B31-F31),0) -> 0
A32: Zuordnung prüfen | B32: =SUMPRODUCT(ISNUMBER(SEARCH($A32,Anforderungen!$I$7:$I$2000))*(Anforderungen!$B$7:$B$2000<>"")) -> 230 | C32: =SUMPRODUCT(ISNUMBER(SEARCH($A32,Anforderungen!$I$7:$I$2000))*(Anforderungen!$K$7:$K$2000="erfasst")) -> 208 | D32: =SUMPRODUCT(ISNUMBER(SEARCH($A32,Anforderungen!$I$7:$I$2000))*(Anforderungen!$K$7:$K$2000="bewertet")) -> 0 | E32: =SUMPRODUCT(ISNUMBER(SEARCH($A32,Anforderungen!$I$7:$I$2000))*(Anforderungen!$K$7:$K$2000="erfüllt")) -> 0 | F32: =SUMPRODUCT(ISNUMBER(SEARCH($A32,Anforderungen!$I$7:$I$2000))*(Anforderungen!$K$7:$K$2000="trifft nicht zu")) -> 22 | G32: =IFERROR(E32/(B32-F32),0) -> 0
A35: 3 Nach Komponente
A36: Merkmal | B36: Gesamt | C36: Erfasst | D36: Bewertet | E36: Erfüllt | F36: Trifft nicht zu | G36: Erfüllungsgrad
A37: Ladeeinrichtung | B37: =SUMPRODUCT(ISNUMBER(SEARCH($A37,Anforderungen!$J$7:$J$2000))*(Anforderungen!$B$7:$B$2000<>"")) -> 171 | C37: =SUMPRODUCT(ISNUMBER(SEARCH($A37,Anforderungen!$J$7:$J$2000))*(Anforderungen!$K$7:$K$2000="erfasst")) -> 153 | D37: =SUMPRODUCT(ISNUMBER(SEARCH($A37,Anforderungen!$J$7:$J$2000))*(Anforderungen!$K$7:$K$2000="bewertet")) -> 0 | E37: =SUMPRODUCT(ISNUMBER(SEARCH($A37,Anforderungen!$J$7:$J$2000))*(Anforderungen!$K$7:$K$2000="erfüllt")) -> 0 | F37: =SUMPRODUCT(ISNUMBER(SEARCH($A37,Anforderungen!$J$7:$J$2000))*(Anforderungen!$K$7:$K$2000="trifft nicht zu")) -> 18 | G37: =IFERROR(E37/(B37-F37),0) -> 0
A38: Abrechnungskomponente | B38: =SUMPRODUCT(ISNUMBER(SEARCH($A38,Anforderungen!$J$7:$J$2000))*(Anforderungen!$B$7:$B$2000<>"")) -> 50 | C38: =SUMPRODUCT(ISNUMBER(SEARCH($A38,Anforderungen!$J$7:$J$2000))*(Anforderungen!$K$7:$K$2000="erfasst")) -> 48 | D38: =SUMPRODUCT(ISNUMBER(SEARCH($A38,Anforderungen!$J$7:$J$2000))*(Anforderungen!$K$7:$K$2000="bewertet")) -> 0 | E38: =SUMPRODUCT(ISNUMBER(SEARCH($A38,Anforderungen!$J$7:$J$2000))*(Anforderungen!$K$7:$K$2000="erfüllt")) -> 0 | F38: =SUMPRODUCT(ISNUMBER(SEARCH($A38,Anforderungen!$J$7:$J$2000))*(Anforderungen!$K$7:$K$2000="trifft nicht zu")) -> 2 | G38: =IFERROR(E38/(B38-F38),0) -> 0
A39: Authentifizierungskomponente | B39: =SUMPRODUCT(ISNUMBER(SEARCH($A39,Anforderungen!$J$7:$J$2000))*(Anforderungen!$B$7:$B$2000<>"")) -> 66 | C39: =SUMPRODUCT(ISNUMBER(SEARCH($A39,Anforderungen!$J$7:$J$2000))*(Anforderungen!$K$7:$K$2000="erfasst")) -> 60 | D39: =SUMPRODUCT(ISNUMBER(SEARCH($A39,Anforderungen!$J$7:$J$2000))*(Anforderungen!$K$7:$K$2000="bewertet")) -> 0 | E39: =SUMPRODUCT(ISNUMBER(SEARCH($A39,Anforderungen!$J$7:$J$2000))*(Anforderungen!$K$7:$K$2000="erfüllt")) -> 2 | F39: =SUMPRODUCT(ISNUMBER(SEARCH($A39,Anforderungen!$J$7:$J$2000))*(Anforderungen!$K$7:$K$2000="trifft nicht zu")) -> 4 | G39: =IFERROR(E39/(B39-F39),0) -> 0.032258065
A40: Monitoring | B40: =SUMPRODUCT(ISNUMBER(SEARCH($A40,Anforderungen!$J$7:$J$2000))*(Anforderungen!$B$7:$B$2000<>"")) -> 44 | C40: =SUMPRODUCT(ISNUMBER(SEARCH($A40,Anforderungen!$J$7:$J$2000))*(Anforderungen!$K$7:$K$2000="erfasst")) -> 44 | D40: =SUMPRODUCT(ISNUMBER(SEARCH($A40,Anforderungen!$J$7:$J$2000))*(Anforderungen!$K$7:$K$2000="bewertet")) -> 0 | E40: =SUMPRODUCT(ISNUMBER(SEARCH($A40,Anforderungen!$J$7:$J$2000))*(Anforderungen!$K$7:$K$2000="erfüllt")) -> 0 | F40: =SUMPRODUCT(ISNUMBER(SEARCH($A40,Anforderungen!$J$7:$J$2000))*(Anforderungen!$K$7:$K$2000="trifft nicht zu")) -> 0 | G40: =IFERROR(E40/(B40-F40),0) -> 0
A41: OCPI Buchungskalender | B41: =SUMPRODUCT(ISNUMBER(SEARCH($A41,Anforderungen!$J$7:$J$2000))*(Anforderungen!$B$7:$B$2000<>"")) -> 102 | C41: =SUMPRODUCT(ISNUMBER(SEARCH($A41,Anforderungen!$J$7:$J$2000))*(Anforderungen!$K$7:$K$2000="erfasst")) -> 98 | D41: =SUMPRODUCT(ISNUMBER(SEARCH($A41,Anforderungen!$J$7:$J$2000))*(Anforderungen!$K$7:$K$2000="bewertet")) -> 0 | E41: =SUMPRODUCT(ISNUMBER(SEARCH($A41,Anforderungen!$J$7:$J$2000))*(Anforderungen!$K$7:$K$2000="erfüllt")) -> 1 | F41: =SUMPRODUCT(ISNUMBER(SEARCH($A41,Anforderungen!$J$7:$J$2000))*(Anforderungen!$K$7:$K$2000="trifft nicht zu")) -> 3 | G41: =IFERROR(E41/(B41-F41),0) -> 0.01010101
A42: Anbindung | B42: =SUMPRODUCT(ISNUMBER(SEARCH($A42,Anforderungen!$J$7:$J$2000))*(Anforderungen!$B$7:$B$2000<>"")) -> 3 | C42: =SUMPRODUCT(ISNUMBER(SEARCH($A42,Anforderungen!$J$7:$J$2000))*(Anforderungen!$K$7:$K$2000="erfasst")) -> 2 | D42: =SUMPRODUCT(ISNUMBER(SEARCH($A42,Anforderungen!$J$7:$J$2000))*(Anforderungen!$K$7:$K$2000="bewertet")) -> 1 | E42: =SUMPRODUCT(ISNUMBER(SEARCH($A42,Anforderungen!$J$7:$J$2000))*(Anforderungen!$K$7:$K$2000="erfüllt")) -> 0 | F42: =SUMPRODUCT(ISNUMBER(SEARCH($A42,Anforderungen!$J$7:$J$2000))*(Anforderungen!$K$7:$K$2000="trifft nicht zu")) -> 0 | G42: =IFERROR(E42/(B42-F42),0) -> 0
A43: Reservierungsplattform | B43: =SUMPRODUCT(ISNUMBER(SEARCH($A43,Anforderungen!$J$7:$J$2000))*(Anforderungen!$B$7:$B$2000<>"")) -> 12 | C43: =SUMPRODUCT(ISNUMBER(SEARCH($A43,Anforderungen!$J$7:$J$2000))*(Anforderungen!$K$7:$K$2000="erfasst")) -> 12 | D43: =SUMPRODUCT(ISNUMBER(SEARCH($A43,Anforderungen!$J$7:$J$2000))*(Anforderungen!$K$7:$K$2000="bewertet")) -> 0 | E43: =SUMPRODUCT(ISNUMBER(SEARCH($A43,Anforderungen!$J$7:$J$2000))*(Anforderungen!$K$7:$K$2000="erfüllt")) -> 0 | F43: =SUMPRODUCT(ISNUMBER(SEARCH($A43,Anforderungen!$J$7:$J$2000))*(Anforderungen!$K$7:$K$2000="trifft nicht zu")) -> 0 | G43: =IFERROR(E43/(B43-F43),0) -> 0
A44: Belegungsdetektion | B44: =SUMPRODUCT(ISNUMBER(SEARCH($A44,Anforderungen!$J$7:$J$2000))*(Anforderungen!$B$7:$B$2000<>"")) -> 5 | C44: =SUMPRODUCT(ISNUMBER(SEARCH($A44,Anforderungen!$J$7:$J$2000))*(Anforderungen!$K$7:$K$2000="erfasst")) -> 4 | D44: =SUMPRODUCT(ISNUMBER(SEARCH($A44,Anforderungen!$J$7:$J$2000))*(Anforderungen!$K$7:$K$2000="bewertet")) -> 0 | E44: =SUMPRODUCT(ISNUMBER(SEARCH($A44,Anforderungen!$J$7:$J$2000))*(Anforderungen!$K$7:$K$2000="erfüllt")) -> 1 | F44: =SUMPRODUCT(ISNUMBER(SEARCH($A44,Anforderungen!$J$7:$J$2000))*(Anforderungen!$K$7:$K$2000="trifft nicht zu")) -> 0 | G44: =IFERROR(E44/(B44-F44),0) -> 0.2
A45: Dynamische Anzeige | B45: =SUMPRODUCT(ISNUMBER(SEARCH($A45,Anforderungen!$J$7:$J$2000))*(Anforderungen!$B$7:$B$2000<>"")) -> 12 | C45: =SUMPRODUCT(ISNUMBER(SEARCH($A45,Anforderungen!$J$7:$J$2000))*(Anforderungen!$K$7:$K$2000="erfasst")) -> 10 | D45: =SUMPRODUCT(ISNUMBER(SEARCH($A45,Anforderungen!$J$7:$J$2000))*(Anforderungen!$K$7:$K$2000="bewertet")) -> 0 | E45: =SUMPRODUCT(ISNUMBER(SEARCH($A45,Anforderungen!$J$7:$J$2000))*(Anforderungen!$K$7:$K$2000="erfüllt")) -> 2 | F45: =SUMPRODUCT(ISNUMBER(SEARCH($A45,Anforderungen!$J$7:$J$2000))*(Anforderungen!$K$7:$K$2000="trifft nicht zu")) -> 0 | G45: =IFERROR(E45/(B45-F45),0) -> 0.16666667
A46: Kennzeichenerfassung | B46: =SUMPRODUCT(ISNUMBER(SEARCH($A46,Anforderungen!$J$7:$J$2000))*(Anforderungen!$B$7:$B$2000<>"")) -> 8 | C46: =SUMPRODUCT(ISNUMBER(SEARCH($A46,Anforderungen!$J$7:$J$2000))*(Anforderungen!$K$7:$K$2000="erfasst")) -> 7 | D46: =SUMPRODUCT(ISNUMBER(SEARCH($A46,Anforderungen!$J$7:$J$2000))*(Anforderungen!$K$7:$K$2000="bewertet")) -> 0 | E46: =SUMPRODUCT(ISNUMBER(SEARCH($A46,Anforderungen!$J$7:$J$2000))*(Anforderungen!$K$7:$K$2000="erfüllt")) -> 0 | F46: =SUMPRODUCT(ISNUMBER(SEARCH($A46,Anforderungen!$J$7:$J$2000))*(Anforderungen!$K$7:$K$2000="trifft nicht zu")) -> 1 | G46: =IFERROR(E46/(B46-F46),0) -> 0
A47: Pönalisierungssystem | B47: =SUMPRODUCT(ISNUMBER(SEARCH($A47,Anforderungen!$J$7:$J$2000))*(Anforderungen!$B$7:$B$2000<>"")) -> 35 | C47: =SUMPRODUCT(ISNUMBER(SEARCH($A47,Anforderungen!$J$7:$J$2000))*(Anforderungen!$K$7:$K$2000="erfasst")) -> 34 | D47: =SUMPRODUCT(ISNUMBER(SEARCH($A47,Anforderungen!$J$7:$J$2000))*(Anforderungen!$K$7:$K$2000="bewertet")) -> 0 | E47: =SUMPRODUCT(ISNUMBER(SEARCH($A47,Anforderungen!$J$7:$J$2000))*(Anforderungen!$K$7:$K$2000="erfüllt")) -> 0 | F47: =SUMPRODUCT(ISNUMBER(SEARCH($A47,Anforderungen!$J$7:$J$2000))*(Anforderungen!$K$7:$K$2000="trifft nicht zu")) -> 1 | G47: =IFERROR(E47/(B47-F47),0) -> 0
A48: Schrankensteuerung | B48: =SUMPRODUCT(ISNUMBER(SEARCH($A48,Anforderungen!$J$7:$J$2000))*(Anforderungen!$B$7:$B$2000<>"")) -> 25 | C48: =SUMPRODUCT(ISNUMBER(SEARCH($A48,Anforderungen!$J$7:$J$2000))*(Anforderungen!$K$7:$K$2000="erfasst")) -> 20 | D48: =SUMPRODUCT(ISNUMBER(SEARCH($A48,Anforderungen!$J$7:$J$2000))*(Anforderungen!$K$7:$K$2000="bewertet")) -> 0 | E48: =SUMPRODUCT(ISNUMBER(SEARCH($A48,Anforderungen!$J$7:$J$2000))*(Anforderungen!$K$7:$K$2000="erfüllt")) -> 4 | F48: =SUMPRODUCT(ISNUMBER(SEARCH($A48,Anforderungen!$J$7:$J$2000))*(Anforderungen!$K$7:$K$2000="trifft nicht zu")) -> 1 | G48: =IFERROR(E48/(B48-F48),0) -> 0.16666667
... A51: Zuordnung prüfen | B51: =SUMPRODUCT(ISNUMBER(SEARCH($A51,Anforderungen!$J$7:$J$2000))*(Anforderungen!$B$7:$B$2000<>"")) -> 230 | C51: =SUMPRODUCT(ISNUMBER(SEARCH($A51,Anforderungen!$J$7:$J$2000))*(Anforderungen!$K$7:$K$2000="erfasst")) -> 208 | D51: =SUMPRODUCT(ISNUMBER(SEARCH($A51,Anforderungen!$J$7:$J$2000))*(Anforderungen!$K$7:$K$2000="bewertet")) -> 0 | E51: =SUMPRODUCT(ISNUMBER(SEARCH($A51,Anforderungen!$J$7:$J$2000))*(Anforderungen!$K$7:$K$2000="erfüllt")) -> 0 | F51: =SUMPRODUCT(ISNUMBER(SEARCH($A51,Anforderungen!$J$7:$J$2000))*(Anforderungen!$K$7:$K$2000="trifft nicht zu")) -> 22 | G51: =IFERROR(E51/(B51-F51),0) -> 0
A54: 4 Nach Dokument
A55: Merkmal | B55: Gesamt | C55: Erfasst | D55: Bewertet | E55: Erfüllt | F55: Trifft nicht zu | G55: Erfüllungsgrad
A56: Vertragsanlage 13 | B56: =COUNTIF(Anforderungen!$C$7:$C$2000,$A56) -> 52 | C56: =COUNTIFS(Anforderungen!$C$7:$C$2000,$A56,Anforderungen!$K$7:$K$2000,"erfasst") -> 52 | D56: =COUNTIFS(Anforderungen!$C$7:$C$2000,$A56,Anforderungen!$K$7:$K$2000,"bewertet") -> 0 | E56: =COUNTIFS(Anforderungen!$C$7:$C$2000,$A56,Anforderungen!$K$7:$K$2000,"erfüllt") -> 0 | F56: =COUNTIFS(Anforderungen!$C$7:$C$2000,$A56,Anforderungen!$K$7:$K$2000,"trifft nicht zu") -> 0 | G56: =IFERROR(E56/(B56-F56),0) -> 0
A57: Betreibervertrag | B57: =COUNTIF(Anforderungen!$C$7:$C$2000,$A57) -> 471 | C57: =COUNTIFS(Anforderungen!$C$7:$C$2000,$A57,Anforderungen!$K$7:$K$2000,"erfasst") -> 413 | D57: =COUNTIFS(Anforderungen!$C$7:$C$2000,$A57,Anforderungen!$K$7:$K$2000,"bewertet") -> 1 | E57: =COUNTIFS(Anforderungen!$C$7:$C$2000,$A57,Anforderungen!$K$7:$K$2000,"erfüllt") -> 1 | F57: =COUNTIFS(Anforderungen!$C$7:$C$2000,$A57,Anforderungen!$K$7:$K$2000,"trifft nicht zu") -> 56 | G57: =IFERROR(E57/(B57-F57),0) -> 0.0024096386
A58: Bieterfragenkatalog | B58: =COUNTIF(Anforderungen!$C$7:$C$2000,$A58) -> 663 | C58: =COUNTIFS(Anforderungen!$C$7:$C$2000,$A58,Anforderungen!$K$7:$K$2000,"erfasst") -> 562 | D58: =COUNTIFS(Anforderungen!$C$7:$C$2000,$A58,Anforderungen!$K$7:$K$2000,"bewertet") -> 0 | E58: =COUNTIFS(Anforderungen!$C$7:$C$2000,$A58,Anforderungen!$K$7:$K$2000,"erfüllt") -> 0 | F58: =COUNTIFS(Anforderungen!$C$7:$C$2000,$A58,Anforderungen!$K$7:$K$2000,"trifft nicht zu") -> 101 | G58: =IFERROR(E58/(B58-F58),0) -> 0
A59: Vertragsanlage 10 | B59: =COUNTIF(Anforderungen!$C$7:$C$2000,$A59) -> 107 | C59: =COUNTIFS(Anforderungen!$C$7:$C$2000,$A59,Anforderungen!$K$7:$K$2000,"erfasst") -> 107 | D59: =COUNTIFS(Anforderungen!$C$7:$C$2000,$A59,Anforderungen!$K$7:$K$2000,"bewertet") -> 0 | E59: =COUNTIFS(Anforderungen!$C$7:$C$2000,$A59,Anforderungen!$K$7:$K$2000,"erfüllt") -> 0 | F59: =COUNTIFS(Anforderungen!$C$7:$C$2000,$A59,Anforderungen!$K$7:$K$2000,"trifft nicht zu") -> 0 | G59: =IFERROR(E59/(B59-F59),0) -> 0
A60: Vertragsanlage 4 | B60: =COUNTIF(Anforderungen!$C$7:$C$2000,$A60) -> 7 | C60: =COUNTIFS(Anforderungen!$C$7:$C$2000,$A60,Anforderungen!$K$7:$K$2000,"erfasst") -> 1 | D60: =COUNTIFS(Anforderungen!$C$7:$C$2000,$A60,Anforderungen!$K$7:$K$2000,"bewertet") -> 2 | E60: =COUNTIFS(Anforderungen!$C$7:$C$2000,$A60,Anforderungen!$K$7:$K$2000,"erfüllt") -> 3 | F60: =COUNTIFS(Anforderungen!$C$7:$C$2000,$A60,Anforderungen!$K$7:$K$2000,"trifft nicht zu") -> 1 | G60: =IFERROR(E60/(B60-F60),0) -> 0.5
A61: Vertragsanlage 6 | B61: =COUNTIF(Anforderungen!$C$7:$C$2000,$A61) -> 82 | C61: =COUNTIFS(Anforderungen!$C$7:$C$2000,$A61,Anforderungen!$K$7:$K$2000,"erfasst") -> 76 | D61: =COUNTIFS(Anforderungen!$C$7:$C$2000,$A61,Anforderungen!$K$7:$K$2000,"bewertet") -> 0 | E61: =COUNTIFS(Anforderungen!$C$7:$C$2000,$A61,Anforderungen!$K$7:$K$2000,"erfüllt") -> 6 | F61: =COUNTIFS(Anforderungen!$C$7:$C$2000,$A61,Anforderungen!$K$7:$K$2000,"trifft nicht zu") -> 0 | G61: =IFERROR(E61/(B61-F61),0) -> 0.073170732
A64: 5 Gesamtstatus
A65: Status | B65: Anforderungen | C65: Anteil
A66: erfasst | B66: =COUNTIF(Anforderungen!$K$7:$K$2000,A66) -> 1211 | C66: =IFERROR(B66/COUNTA(Anforderungen!$B$7:$B$2000),0) -> 0.87626628
A67: bewertet | B67: =COUNTIF(Anforderungen!$K$7:$K$2000,A67) -> 3 | C67: =IFERROR(B67/COUNTA(Anforderungen!$B$7:$B$2000),0) -> 0.002170767
A68: erfüllt | B68: =COUNTIF(Anforderungen!$K$7:$K$2000,A68) -> 10 | C68: =IFERROR(B68/COUNTA(Anforderungen!$B$7:$B$2000),0) -> 0.00723589
A69: trifft nicht zu | B69: =COUNTIF(Anforderungen!$K$7:$K$2000,A69) -> 158 | C69: =IFERROR(B69/COUNTA(Anforderungen!$B$7:$B$2000),0) -> 0.11432706
A71: 6 Vollständigkeit Erfüllung / Nachweis
A72: Prüfung | B72: Anforderungen | C72: Hinweis
A73: Erfüllt + Datum + Nachweis | B73: =COUNTIFS(Anforderungen!$K$7:$K$2000,"erfüllt",Anforderungen!$L$7:$L$2000,"<>",Anforderungen!$M$7:$M$2000,"<>") -> 10 | C73: vollständig dokumentiert
A74: Erfüllt ohne Datum | B74: =COUNTIFS(Anforderungen!$K$7:$K$2000,"erfüllt",Anforderungen!$L$7:$L$2000,"") -> 0 | C74: Datum in „Erfüllt am“ ergänzen
A75: Erfüllt ohne Nachweis / Notiz | B75: =COUNTIFS(Anforderungen!$K$7:$K$2000,"erfüllt",Anforderungen!$M$7:$M$2000,"") -> 0 | C75: Nachweis oder kurze Notiz ergänzen
A76: Trifft nicht zu ohne Begründung | B76: =COUNTIFS(Anforderungen!$K$7:$K$2000,"trifft nicht zu",Anforderungen!$M$7:$M$2000,"") -> 2 | C76: Begründung in „Nachweis / Notiz“ ergänzen
A77: Anwendbare Anforderungen | B77: =COUNTA(Anforderungen!$B$7:$B$2000)-COUNTIF(Anforderungen!$K$7:$K$2000,"trifft nicht zu") -> 1224 | C77: Gesamt abzüglich „trifft nicht zu“
A78: Offene Zuordnung Komponente | B78: =COUNTIF(Anforderungen!$J$7:$J$2000,"Zuordnung prüfen") -> 230 | C78: Komponente fachlich zuordnen
A79: Offene Zuordnung Partner | B79: =COUNTIF(Anforderungen!$I$7:$I$2000,"Zuordnung prüfen") -> 230 | C79: Partner fachlich zuordnen

Sheet Komponenten
A1: Komponenten & Schnittstellen
A2: Struktur Vergabeeinheit → Partner → Art → Komponente. Anzahl und Status der Anforderungen werden automatisch aus dem Register „Anforderungen“ abgeleitet.
A3: Statuslogik: erfasst hat Vorrang vor bewertet; erst wenn keine offenen Vorstufen mehr vorhanden sind, wird erfüllt bzw. trifft nicht zu angezeigt. Nur die Felder Vergabeeinheit, Partner, Art, Komponente und Bemerkung werden gepflegt – alles Übrige rechnet sich selbst.
A5: Vergabeeinheit | B5: Partner | C5: Art | D5: Komponente | E5: Anforderungen | F5: erfasst | G5: bewertet | H5: erfüllt | I5: trifft nicht zu | J5: Status | K5: Bemerkung / Schnittstelle | N5: Partner
A6: LIS | B6: Alpitronic | C6: Komponente | D6: Ladeeinrichtung | E6: =IF($D6="","",SUMPRODUCT(ISNUMBER(SEARCH($D6,Anforderungen!$J$7:$J$2000))*(Anforderungen!$B$7:$B$2000<>""))) -> 171 | F6: =IF($D6="","",SUMPRODUCT(ISNUMBER(SEARCH($D6,Anforderungen!$J$7:$J$2000))*(Anforderungen!$K$7:$K$2000="erfasst"))) -> 153 | G6: =IF($D6="","",SUMPRODUCT(ISNUMBER(SEARCH($D6,Anforderungen!$J$7:$J$2000))*(Anforderungen!$K$7:$K$2000="bewertet"))) -> 0 | H6: =IF($D6="","",SUMPRODUCT(ISNUMBER(SEARCH($D6,Anforderungen!$J$7:$J$2000))*(Anforderungen!$K$7:$K$2000="erfüllt"))) -> 0 | I6: =IF($D6="","",SUMPRODUCT(ISNUMBER(SEARCH($D6,Anforderungen!$J$7:$J$2000))*(Anforderungen!$K$7:$K$2000="trifft nicht zu"))) -> 18 | J6: =IF($D6="","",IF($E6=0,"keine Anforderungen",IF($F6>0,"erfasst",IF($G6>0,"bewertet",IF($H6>0,"erfüllt","trifft nicht zu"))))) -> erfasst | N6: Alpitronic
A7: WWL | B7: eRound | C7: Komponente | D7: Abrechnungskomponente | E7: =IF($D7="","",SUMPRODUCT(ISNUMBER(SEARCH($D7,Anforderungen!$J$7:$J$2000))*(Anforderungen!$B$7:$B$2000<>""))) -> 50 | F7: =IF($D7="","",SUMPRODUCT(ISNUMBER(SEARCH($D7,Anforderungen!$J$7:$J$2000))*(Anforderungen!$K$7:$K$2000="erfasst"))) -> 48 | G7: =IF($D7="","",SUMPRODUCT(ISNUMBER(SEARCH($D7,Anforderungen!$J$7:$J$2000))*(Anforderungen!$K$7:$K$2000="bewertet"))) -> 0 | H7: =IF($D7="","",SUMPRODUCT(ISNUMBER(SEARCH($D7,Anforderungen!$J$7:$J$2000))*(Anforderungen!$K$7:$K$2000="erfüllt"))) -> 0 | I7: =IF($D7="","",SUMPRODUCT(ISNUMBER(SEARCH($D7,Anforderungen!$J$7:$J$2000))*(Anforderungen!$K$7:$K$2000="trifft nicht zu"))) -> 2 | J7: =IF($D7="","",IF($E7=0,"keine Anforderungen",IF($F7>0,"erfasst",IF($G7>0,"bewertet",IF($H7>0,"erfüllt","trifft nicht zu"))))) -> erfasst | N7: eRound
A8: WWL | B8: eRound | C8: Komponente | D8: Authentifizierungskomponente | E8: =IF($D8="","",SUMPRODUCT(ISNUMBER(SEARCH($D8,Anforderungen!$J$7:$J$2000))*(Anforderungen!$B$7:$B$2000<>""))) -> 66 | F8: =IF($D8="","",SUMPRODUCT(ISNUMBER(SEARCH($D8,Anforderungen!$J$7:$J$2000))*(Anforderungen!$K$7:$K$2000="erfasst"))) -> 60 | G8: =IF($D8="","",SUMPRODUCT(ISNUMBER(SEARCH($D8,Anforderungen!$J$7:$J$2000))*(Anforderungen!$K$7:$K$2000="bewertet"))) -> 0 | H8: =IF($D8="","",SUMPRODUCT(ISNUMBER(SEARCH($D8,Anforderungen!$J$7:$J$2000))*(Anforderungen!$K$7:$K$2000="erfüllt"))) -> 2 | I8: =IF($D8="","",SUMPRODUCT(ISNUMBER(SEARCH($D8,Anforderungen!$J$7:$J$2000))*(Anforderungen!$K$7:$K$2000="trifft nicht zu"))) -> 4 | J8: =IF($D8="","",IF($E8=0,"keine Anforderungen",IF($F8>0,"erfasst",IF($G8>0,"bewertet",IF($H8>0,"erfüllt","trifft nicht zu"))))) -> erfasst | N8: Reservierungsplattform
A9: WWL | B9: eRound | C9: Komponente | D9: Monitoring | E9: =IF($D9="","",SUMPRODUCT(ISNUMBER(SEARCH($D9,Anforderungen!$J$7:$J$2000))*(Anforderungen!$B$7:$B$2000<>""))) -> 44 | F9: =IF($D9="","",SUMPRODUCT(ISNUMBER(SEARCH($D9,Anforderungen!$J$7:$J$2000))*(Anforderungen!$K$7:$K$2000="erfasst"))) -> 44 | G9: =IF($D9="","",SUMPRODUCT(ISNUMBER(SEARCH($D9,Anforderungen!$J$7:$J$2000))*(Anforderungen!$K$7:$K$2000="bewertet"))) -> 0 | H9: =IF($D9="","",SUMPRODUCT(ISNUMBER(SEARCH($D9,Anforderungen!$J$7:$J$2000))*(Anforderungen!$K$7:$K$2000="erfüllt"))) -> 0 | I9: =IF($D9="","",SUMPRODUCT(ISNUMBER(SEARCH($D9,Anforderungen!$J$7:$J$2000))*(Anforderungen!$K$7:$K$2000="trifft nicht zu"))) -> 0 | J9: =IF($D9="","",IF($E9=0,"keine Anforderungen",IF($F9>0,"erfasst",IF($G9>0,"bewertet",IF($H9>0,"erfüllt","trifft nicht zu"))))) -> erfasst | N9: SCS
A10: WWL | B10: eRound | C10: Komponente | D10: OCPI Buchungskalender | E10: =IF($D10="","",SUMPRODUCT(ISNUMBER(SEARCH($D10,Anforderungen!$J$7:$J$2000))*(Anforderungen!$B$7:$B$2000<>""))) -> 102 | F10: =IF($D10="","",SUMPRODUCT(ISNUMBER(SEARCH($D10,Anforderungen!$J$7:$J$2000))*(Anforderungen!$K$7:$K$2000="erfasst"))) -> 98 | G10: =IF($D10="","",SUMPRODUCT(ISNUMBER(SEARCH($D10,Anforderungen!$J$7:$J$2000))*(Anforderungen!$K$7:$K$2000="bewertet"))) -> 0 | H10: =IF($D10="","",SUMPRODUCT(ISNUMBER(SEARCH($D10,Anforderungen!$J$7:$J$2000))*(Anforderungen!$K$7:$K$2000="erfüllt"))) -> 1 | I10: =IF($D10="","",SUMPRODUCT(ISNUMBER(SEARCH($D10,Anforderungen!$J$7:$J$2000))*(Anforderungen!$K$7:$K$2000="trifft nicht zu"))) -> 3 | J10: =IF($D10="","",IF($E10=0,"keine Anforderungen",IF($F10>0,"erfasst",IF($G10>0,"bewertet",IF($H10>0,"erfüllt","trifft nicht zu"))))) -> erfasst | N10: Schrankenhersteller
A11: SmartInfra | B11: Reservierungsplattform | C11: Komponente | D11: Anbindung | E11: =IF($D11="","",SUMPRODUCT(ISNUMBER(SEARCH($D11,Anforderungen!$J$7:$J$2000))*(Anforderungen!$B$7:$B$2000<>""))) -> 3 | F11: =IF($D11="","",SUMPRODUCT(ISNUMBER(SEARCH($D11,Anforderungen!$J$7:$J$2000))*(Anforderungen!$K$7:$K$2000="erfasst"))) -> 2 | G11: =IF($D11="","",SUMPRODUCT(ISNUMBER(SEARCH($D11,Anforderungen!$J$7:$J$2000))*(Anforderungen!$K$7:$K$2000="bewertet"))) -> 1 | H11: =IF($D11="","",SUMPRODUCT(ISNUMBER(SEARCH($D11,Anforderungen!$J$7:$J$2000))*(Anforderungen!$K$7:$K$2000="erfüllt"))) -> 0 | I11: =IF($D11="","",SUMPRODUCT(ISNUMBER(SEARCH($D11,Anforderungen!$J$7:$J$2000))*(Anforderungen!$K$7:$K$2000="trifft nicht zu"))) -> 0 | J11: =IF($D11="","",IF($E11=0,"keine Anforderungen",IF($F11>0,"erfasst",IF($G11>0,"bewertet",IF($H11>0,"erfüllt","trifft nicht zu"))))) -> erfasst | N11: WWL
A12: SmartInfra | B12: Reservierungsplattform | C12: Komponente | D12: Reservierungsplattform | E12: =IF($D12="","",SUMPRODUCT(ISNUMBER(SEARCH($D12,Anforderungen!$J$7:$J$2000))*(Anforderungen!$B$7:$B$2000<>""))) -> 12 | F12: =IF($D12="","",SUMPRODUCT(ISNUMBER(SEARCH($D12,Anforderungen!$J$7:$J$2000))*(Anforderungen!$K$7:$K$2000="erfasst"))) -> 12 | G12: =IF($D12="","",SUMPRODUCT(ISNUMBER(SEARCH($D12,Anforderungen!$J$7:$J$2000))*(Anforderungen!$K$7:$K$2000="bewertet"))) -> 0 | H12: =IF($D12="","",SUMPRODUCT(ISNUMBER(SEARCH($D12,Anforderungen!$J$7:$J$2000))*(Anforderungen!$K$7:$K$2000="erfüllt"))) -> 0 | I12: =IF($D12="","",SUMPRODUCT(ISNUMBER(SEARCH($D12,Anforderungen!$J$7:$J$2000))*(Anforderungen!$K$7:$K$2000="trifft nicht zu"))) -> 0 | J12: =IF($D12="","",IF($E12=0,"keine Anforderungen",IF($F12>0,"erfasst",IF($G12>0,"bewertet",IF($H12>0,"erfüllt","trifft nicht zu"))))) -> erfasst | N12: Autostrom+
A13: SmartInfra | B13: SCS | C13: Komponente | D13: Belegungsdetektion | E13: =IF($D13="","",SUMPRODUCT(ISNUMBER(SEARCH($D13,Anforderungen!$J$7:$J$2000))*(Anforderungen!$B$7:$B$2000<>""))) -> 5 | F13: =IF($D13="","",SUMPRODUCT(ISNUMBER(SEARCH($D13,Anforderungen!$J$7:$J$2000))*(Anforderungen!$K$7:$K$2000="erfasst"))) -> 4 | G13: =IF($D13="","",SUMPRODUCT(ISNUMBER(SEARCH($D13,Anforderungen!$J$7:$J$2000))*(Anforderungen!$K$7:$K$2000="bewertet"))) -> 0 | H13: =IF($D13="","",SUMPRODUCT(ISNUMBER(SEARCH($D13,Anforderungen!$J$7:$J$2000))*(Anforderungen!$K$7:$K$2000="erfüllt"))) -> 1 | I13: =IF($D13="","",SUMPRODUCT(ISNUMBER(SEARCH($D13,Anforderungen!$J$7:$J$2000))*(Anforderungen!$K$7:$K$2000="trifft nicht zu"))) -> 0 | J13: =IF($D13="","",IF($E13=0,"keine Anforderungen",IF($F13>0,"erfasst",IF($G13>0,"bewertet",IF($H13>0,"erfüllt","trifft nicht zu"))))) -> erfasst | N13: eRound / SCS
A14: SmartInfra | B14: SCS | C14: Komponente | D14: Dynamische Anzeige | E14: =IF($D14="","",SUMPRODUCT(ISNUMBER(SEARCH($D14,Anforderungen!$J$7:$J$2000))*(Anforderungen!$B$7:$B$2000<>""))) -> 12 | F14: =IF($D14="","",SUMPRODUCT(ISNUMBER(SEARCH($D14,Anforderungen!$J$7:$J$2000))*(Anforderungen!$K$7:$K$2000="erfasst"))) -> 10 | G14: =IF($D14="","",SUMPRODUCT(ISNUMBER(SEARCH($D14,Anforderungen!$J$7:$J$2000))*(Anforderungen!$K$7:$K$2000="bewertet"))) -> 0 | H14: =IF($D14="","",SUMPRODUCT(ISNUMBER(SEARCH($D14,Anforderungen!$J$7:$J$2000))*(Anforderungen!$K$7:$K$2000="erfüllt"))) -> 2 | I14: =IF($D14="","",SUMPRODUCT(ISNUMBER(SEARCH($D14,Anforderungen!$J$7:$J$2000))*(Anforderungen!$K$7:$K$2000="trifft nicht zu"))) -> 0 | J14: =IF($D14="","",IF($E14=0,"keine Anforderungen",IF($F14>0,"erfasst",IF($G14>0,"bewertet",IF($H14>0,"erfüllt","trifft nicht zu"))))) -> erfasst | N14: Schrankenhersteller / SCS
A15: SmartInfra | B15: SCS | C15: Komponente | D15: Kennzeichenerfassung | E15: =IF($D15="","",SUMPRODUCT(ISNUMBER(SEARCH($D15,Anforderungen!$J$7:$J$2000))*(Anforderungen!$B$7:$B$2000<>""))) -> 8 | F15: =IF($D15="","",SUMPRODUCT(ISNUMBER(SEARCH($D15,Anforderungen!$J$7:$J$2000))*(Anforderungen!$K$7:$K$2000="erfasst"))) -> 7 | G15: =IF($D15="","",SUMPRODUCT(ISNUMBER(SEARCH($D15,Anforderungen!$J$7:$J$2000))*(Anforderungen!$K$7:$K$2000="bewertet"))) -> 0 | H15: =IF($D15="","",SUMPRODUCT(ISNUMBER(SEARCH($D15,Anforderungen!$J$7:$J$2000))*(Anforderungen!$K$7:$K$2000="erfüllt"))) -> 0 | I15: =IF($D15="","",SUMPRODUCT(ISNUMBER(SEARCH($D15,Anforderungen!$J$7:$J$2000))*(Anforderungen!$K$7:$K$2000="trifft nicht zu"))) -> 1 | J15: =IF($D15="","",IF($E15=0,"keine Anforderungen",IF($F15>0,"erfasst",IF($G15>0,"bewertet",IF($H15>0,"erfüllt","trifft nicht zu"))))) -> erfasst | N15: Schrankenhersteller / SCS / eRound
A16: SmartInfra | B16: SCS | C16: Komponente | D16: Pönalisierungssystem | E16: =IF($D16="","",SUMPRODUCT(ISNUMBER(SEARCH($D16,Anforderungen!$J$7:$J$2000))*(Anforderungen!$B$7:$B$2000<>""))) -> 35 | F16: =IF($D16="","",SUMPRODUCT(ISNUMBER(SEARCH($D16,Anforderungen!$J$7:$J$2000))*(Anforderungen!$K$7:$K$2000="erfasst"))) -> 34 | G16: =IF($D16="","",SUMPRODUCT(ISNUMBER(SEARCH($D16,Anforderungen!$J$7:$J$2000))*(Anforderungen!$K$7:$K$2000="bewertet"))) -> 0 | H16: =IF($D16="","",SUMPRODUCT(ISNUMBER(SEARCH($D16,Anforderungen!$J$7:$J$2000))*(Anforderungen!$K$7:$K$2000="erfüllt"))) -> 0 | I16: =IF($D16="","",SUMPRODUCT(ISNUMBER(SEARCH($D16,Anforderungen!$J$7:$J$2000))*(Anforderungen!$K$7:$K$2000="trifft nicht zu"))) -> 1 | J16: =IF($D16="","",IF($E16=0,"keine Anforderungen",IF($F16>0,"erfasst",IF($G16>0,"bewertet",IF($H16>0,"erfüllt","trifft nicht zu"))))) -> erfasst
A17: SmartInfra | B17: SCS | C17: Komponente | D17: Schrankensteuerung | E17: =IF($D17="","",SUMPRODUCT(ISNUMBER(SEARCH($D17,Anforderungen!$J$7:$J$2000))*(Anforderungen!$B$7:$B$2000<>""))) -> 25 | F17: =IF($D17="","",SUMPRODUCT(ISNUMBER(SEARCH($D17,Anforderungen!$J$7:$J$2000))*(Anforderungen!$K$7:$K$2000="erfasst"))) -> 20 | G17: =IF($D17="","",SUMPRODUCT(ISNUMBER(SEARCH($D17,Anforderungen!$J$7:$J$2000))*(Anforderungen!$K$7:$K$2000="bewertet"))) -> 0 | H17: =IF($D17="","",SUMPRODUCT(ISNUMBER(SEARCH($D17,Anforderungen!$J$7:$J$2000))*(Anforderungen!$K$7:$K$2000="erfüllt"))) -> 4 | I17: =IF($D17="","",SUMPRODUCT(ISNUMBER(SEARCH($D17,Anforderungen!$J$7:$J$2000))*(Anforderungen!$K$7:$K$2000="trifft nicht zu"))) -> 1 | J17: =IF($D17="","",IF($E17=0,"keine Anforderungen",IF($F17>0,"erfasst",IF($G17>0,"bewertet",IF($H17>0,"erfüllt","trifft nicht zu"))))) -> erfasst
A18: AUP | B18: tbd | C18: Komponente | D18: Beschilderung | E18: =IF($D18="","",SUMPRODUCT(ISNUMBER(SEARCH($D18,Anforderungen!$J$7:$J$2000))*(Anforderungen!$B$7:$B$2000<>""))) -> 11 | F18: =IF($D18="","",SUMPRODUCT(ISNUMBER(SEARCH($D18,Anforderungen!$J$7:$J$2000))*(Anforderungen!$K$7:$K$2000="erfasst"))) -> 9 | G18: =IF($D18="","",SUMPRODUCT(ISNUMBER(SEARCH($D18,Anforderungen!$J$7:$J$2000))*(Anforderungen!$K$7:$K$2000="bewertet"))) -> 0 | H18: =IF($D18="","",SUMPRODUCT(ISNUMBER(SEARCH($D18,Anforderungen!$J$7:$J$2000))*(Anforderungen!$K$7:$K$2000="erfüllt"))) -> 0 | I18: =IF($D18="","",SUMPRODUCT(ISNUMBER(SEARCH($D18,Anforderungen!$J$7:$J$2000))*(Anforderungen!$K$7:$K$2000="trifft nicht zu"))) -> 2 | J18: =IF($D18="","",IF($E18=0,"keine Anforderungen",IF($F18>0,"erfasst",IF($G18>0,"bewertet",IF($H18>0,"erfüllt","trifft nicht zu"))))) -> erfasst
A19: SmartInfra | B19: CAME | C19: Komponente | D19: Schrankenanlage | E19: =IF($D19="","",SUMPRODUCT(ISNUMBER(SEARCH($D19,Anforderungen!$J$7:$J$2000))*(Anforderungen!$B$7:$B$2000<>""))) -> 23 | F19: =IF($D19="","",SUMPRODUCT(ISNUMBER(SEARCH($D19,Anforderungen!$J$7:$J$2000))*(Anforderungen!$K$7:$K$2000="erfasst"))) -> 20 | G19: =IF($D19="","",SUMPRODUCT(ISNUMBER(SEARCH($D19,Anforderungen!$J$7:$J$2000))*(Anforderungen!$K$7:$K$2000="bewertet"))) -> 0 | H19: =IF($D19="","",SUMPRODUCT(ISNUMBER(SEARCH($D19,Anforderungen!$J$7:$J$2000))*(Anforderungen!$K$7:$K$2000="erfüllt"))) -> 2 | I19: =IF($D19="","",SUMPRODUCT(ISNUMBER(SEARCH($D19,Anforderungen!$J$7:$J$2000))*(Anforderungen!$K$7:$K$2000="trifft nicht zu"))) -> 1 | J19: =IF($D19="","",IF($E19=0,"keine Anforderungen",IF($F19>0,"erfasst",IF($G19>0,"bewertet",IF($H19>0,"erfüllt","trifft nicht zu"))))) -> erfasst
A20: Zuordnung prüfen | B20: eRound / SCS | C20: Schnittstelle | D20: OCPI Buchungskalender / Abrechnungskomponente / Belegungsdetektion / Pönalisierungssystem | E20: =IF($D20="","",SUMPRODUCT(ISNUMBER(SEARCH("OCPI Buchungskalender",Anforderungen!$J$7:$J$2000))*ISNUMBER(SEARCH("Abrechnungskomponente",Anforderungen!$J$7:$J$2000))*ISNUMBER(SEARCH("Belegungsdetektion",Anforderungen!$J$7:$J$2000))*ISNUMBER(SEARCH("Pönalisierungssystem",Anforderungen!$J$7:$J$2000))*(Anforderungen!$B$7:$B$2000<>""))) -> 1 | F20: =IF($D20="","",SUMPRODUCT(ISNUMBER(SEARCH("OCPI Buchungskalender",Anforderungen!$J$7:$J$2000))*ISNUMBER(SEARCH("Abrechnungskomponente",Anforderungen!$J$7:$J$2000))*ISNUMBER(SEARCH("Belegungsdetektion",Anforderungen!$J$7:$J$2000))*ISNUMBER(SEARCH("Pönalisierungssystem",Anforderungen!$J$7:$J$2000))*(Anforderungen!$K$7:$K$2000="erfasst"))) -> 1 | G20: =IF($D20="","",SUMPRODUCT(ISNUMBER(SEARCH("OCPI Buchungskalender",Anforderungen!$J$7:$J$2000))*ISNUMBER(SEARCH("Abrechnungskomponente",Anforderungen!$J$7:$J$2000))*ISNUMBER(SEARCH("Belegungsdetektion",Anforderungen!$J$7:$J$2000))*ISNUMBER(SEARCH("Pönalisierungssystem",Anforderungen!$J$7:$J$2000))*(Anforderungen!$K$7:$K$2000="bewertet"))) -> 0 | H20: =IF($D20="","",SUMPRODUCT(ISNUMBER(SEARCH("OCPI Buchungskalender",Anforderungen!$J$7:$J$2000))*ISNUMBER(SEARCH("Abrechnungskomponente",Anforderungen!$J$7:$J$2000))*ISNUMBER(SEARCH("Belegungsdetektion",Anforderungen!$J$7:$J$2000))*ISNUMBER(SEARCH("Pönalisierungssystem",Anforderungen!$J$7:$J$2000))*(Anforderungen!$K$7:$K$2000="erfüllt"))) -> 0 | I20: =IF($D20="","",SUMPRODUCT(ISNUMBER(SEARCH("OCPI Buchungskalender",Anforderungen!$J$7:$J$2000))*ISNUMBER(SEARCH("Abrechnungskomponente",Anforderungen!$J$7:$J$2000))*ISNUMBER(SEARCH("Belegungsdetektion",Anforderungen!$J$7:$J$2000))*ISNUMBER(SEARCH("Pönalisierungssystem",Anforderungen!$J$7:$J$2000))*(Anforderungen!$K$7:$K$2000="trifft nicht zu"))) -> 0 | J20: =IF($D20="","",IF($E20=0,"keine Anforderungen",IF($F20>0,"erfasst",IF($G20>0,"bewertet",IF($H20>0,"erfüllt","trifft nicht zu"))))) -> erfasst | K20: Schnittstelle: zählt Anforderungen, die alle genannten Komponenten betreffen.
A21: Zuordnung prüfen | B21: eRound / SCS | C21: Schnittstelle | D21: OCPI Buchungskalender / Dynamische Anzeige | E21: =IF($D21="","",SUMPRODUCT(ISNUMBER(SEARCH("OCPI Buchungskalender",Anforderungen!$J$7:$J$2000))*ISNUMBER(SEARCH("Dynamische Anzeige",Anforderungen!$J$7:$J$2000))*(Anforderungen!$B$7:$B$2000<>""))) -> 5 | F21: =IF($D21="","",SUMPRODUCT(ISNUMBER(SEARCH("OCPI Buchungskalender",Anforderungen!$J$7:$J$2000))*ISNUMBER(SEARCH("Dynamische Anzeige",Anforderungen!$J$7:$J$2000))*(Anforderungen!$K$7:$K$2000="erfasst"))) -> 4 | G21: =IF($D21="","",SUMPRODUCT(ISNUMBER(SEARCH("OCPI Buchungskalender",Anforderungen!$J$7:$J$2000))*ISNUMBER(SEARCH("Dynamische Anzeige",Anforderungen!$J$7:$J$2000))*(Anforderungen!$K$7:$K$2000="bewertet"))) -> 0 | H21: =IF($D21="","",SUMPRODUCT(ISNUMBER(SEARCH("OCPI Buchungskalender",Anforderungen!$J$7:$J$2000))*ISNUMBER(SEARCH("Dynamische Anzeige",Anforderungen!$J$7:$J$2000))*(Anforderungen!$K$7:$K$2000="erfüllt"))) -> 1 | I21: =IF($D21="","",SUMPRODUCT(ISNUMBER(SEARCH("OCPI Buchungskalender",Anforderungen!$J$7:$J$2000))*ISNUMBER(SEARCH("Dynamische Anzeige",Anforderungen!$J$7:$J$2000))*(Anforderungen!$K$7:$K$2000="trifft nicht zu"))) -> 0 | J21: =IF($D21="","",IF($E21=0,"keine Anforderungen",IF($F21>0,"erfasst",IF($G21>0,"bewertet",IF($H21>0,"erfüllt","trifft nicht zu"))))) -> erfasst | K21: Schnittstelle: zählt Anforderungen, die alle genannten Komponenten betreffen.
A22: Zuordnung prüfen | B22: eRound / SCS | C22: Schnittstelle | D22: OCPI Buchungskalender / Kennzeichenerfassung / Pönalisierungssystem | E22: =IF($D22="","",SUMPRODUCT(ISNUMBER(SEARCH("OCPI Buchungskalender",Anforderungen!$J$7:$J$2000))*ISNUMBER(SEARCH("Kennzeichenerfassung",Anforderungen!$J$7:$J$2000))*ISNUMBER(SEARCH("Pönalisierungssystem",Anforderungen!$J$7:$J$2000))*(Anforderungen!$B$7:$B$2000<>""))) -> 2 | F22: =IF($D22="","",SUMPRODUCT(ISNUMBER(SEARCH("OCPI Buchungskalender",Anforderungen!$J$7:$J$2000))*ISNUMBER(SEARCH("Kennzeichenerfassung",Anforderungen!$J$7:$J$2000))*ISNUMBER(SEARCH("Pönalisierungssystem",Anforderungen!$J$7:$J$2000))*(Anforderungen!$K$7:$K$2000="erfasst"))) -> 2 | G22: =IF($D22="","",SUMPRODUCT(ISNUMBER(SEARCH("OCPI Buchungskalender",Anforderungen!$J$7:$J$2000))*ISNUMBER(SEARCH("Kennzeichenerfassung",Anforderungen!$J$7:$J$2000))*ISNUMBER(SEARCH("Pönalisierungssystem",Anforderungen!$J$7:$J$2000))*(Anforderungen!$K$7:$K$2000="bewertet"))) -> 0 | H22: =IF($D22="","",SUMPRODUCT(ISNUMBER(SEARCH("OCPI Buchungskalender",Anforderungen!$J$7:$J$2000))*ISNUMBER(SEARCH("Kennzeichenerfassung",Anforderungen!$J$7:$J$2000))*ISNUMBER(SEARCH("Pönalisierungssystem",Anforderungen!$J$7:$J$2000))*(Anforderungen!$K$7:$K$2000="erfüllt"))) -> 0 | I22: =IF($D22="","",SUMPRODUCT(ISNUMBER(SEARCH("OCPI Buchungskalender",Anforderungen!$J$7:$J$2000))*ISNUMBER(SEARCH("Kennzeichenerfassung",Anforderungen!$J$7:$J$2000))*ISNUMBER(SEARCH("Pönalisierungssystem",Anforderungen!$J$7:$J$2000))*(Anforderungen!$K$7:$K$2000="trifft nicht zu"))) -> 0 | J22: =IF($D22="","",IF($E22=0,"keine Anforderungen",IF($F22>0,"erfasst",IF($G22>0,"bewertet",IF($H22>0,"erfüllt","trifft nicht zu"))))) -> erfasst | K22: Schnittstelle: zählt Anforderungen, die alle genannten Komponenten betreffen.
A23: Zuordnung prüfen | B23: eRound / SCS | C23: Schnittstelle | D23: Authentifizierungskomponente / Schrankensteuerung | E23: =IF($D23="","",SUMPRODUCT(ISNUMBER(SEARCH("Authentifizierungskomponente",Anforderungen!$J$7:$J$2000))*ISNUMBER(SEARCH("Schrankensteuerung",Anforderungen!$J$7:$J$2000))*(Anforderungen!$B$7:$B$2000<>""))) -> 8 | F23: =IF($D23="","",SUMPRODUCT(ISNUMBER(SEARCH("Authentifizierungskomponente",Anforderungen!$J$7:$J$2000))*ISNUMBER(SEARCH("Schrankensteuerung",Anforderungen!$J$7:$J$2000))*(Anforderungen!$K$7:$K$2000="erfasst"))) -> 7 | G23: =IF($D23="","",SUMPRODUCT(ISNUMBER(SEARCH("Authentifizierungskomponente",Anforderungen!$J$7:$J$2000))*ISNUMBER(SEARCH("Schrankensteuerung",Anforderungen!$J$7:$J$2000))*(Anforderungen!$K$7:$K$2000="bewertet"))) -> 0 | H23: =IF($D23="","",SUMPRODUCT(ISNUMBER(SEARCH("Authentifizierungskomponente",Anforderungen!$J$7:$J$2000))*ISNUMBER(SEARCH("Schrankensteuerung",Anforderungen!$J$7:$J$2000))*(Anforderungen!$K$7:$K$2000="erfüllt"))) -> 1 | I23: =IF($D23="","",SUMPRODUCT(ISNUMBER(SEARCH("Authentifizierungskomponente",Anforderungen!$J$7:$J$2000))*ISNUMBER(SEARCH("Schrankensteuerung",Anforderungen!$J$7:$J$2000))*(Anforderungen!$K$7:$K$2000="trifft nicht zu"))) -> 0 | J23: =IF($D23="","",IF($E23=0,"keine Anforderungen",IF($F23>0,"erfasst",IF($G23>0,"bewertet",IF($H23>0,"erfüllt","trifft nicht zu"))))) -> erfasst | K23: Schnittstelle: zählt Anforderungen, die alle genannten Komponenten betreffen.
E24: =IF($D24="","",SUMPRODUCT(ISNUMBER(SEARCH($D24,Anforderungen!$J$7:$J$2000))*(Anforderungen!$B$7:$B$2000<>""))) | F24: =IF($D24="","",SUMPRODUCT(ISNUMBER(SEARCH($D24,Anforderungen!$J$7:$J$2000))*(Anforderungen!$K$7:$K$2000="erfasst"))) | G24: =IF($D24="","",SUMPRODUCT(ISNUMBER(SEARCH($D24,Anforderungen!$J$7:$J$2000))*(Anforderungen!$K$7:$K$2000="bewertet"))) | H24: =IF($D24="","",SUMPRODUCT(ISNUMBER(SEARCH($D24,Anforderungen!$J$7:$J$2000))*(Anforderungen!$K$7:$K$2000="erfüllt"))) | I24: =IF($D24="","",SUMPRODUCT(ISNUMBER(SEARCH($D24,Anforderungen!$J$7:$J$2000))*(Anforderungen!$K$7:$K$2000="trifft nicht zu"))) | J24: =IF($D24="","",IF($E24=0,"keine Anforderungen",IF($F24>0,"erfasst",IF($G24>0,"bewertet",IF($H24>0,"erfüllt","trifft nicht zu")))))
E25: =IF($D25="","",SUMPRODUCT(ISNUMBER(SEARCH($D25,Anforderungen!$J$7:$J$2000))*(Anforderungen!$B$7:$B$2000<>""))) | F25: =IF($D25="","",SUMPRODUCT(ISNUMBER(SEARCH($D25,Anforderungen!$J$7:$J$2000))*(Anforderungen!$K$7:$K$2000="erfasst"))) | G25: =IF($D25="","",SUMPRODUCT(ISNUMBER(SEARCH($D25,Anforderungen!$J$7:$J$2000))*(Anforderungen!$K$7:$K$2000="bewertet"))) | H25: =IF($D25="","",SUMPRODUCT(ISNUMBER(SEARCH($D25,Anforderungen!$J$7:$J$2000))*(Anforderungen!$K$7:$K$2000="erfüllt"))) | I25: =IF($D25="","",SUMPRODUCT(ISNUMBER(SEARCH($D25,Anforderungen!$J$7:$J$2000))*(Anforderungen!$K$7:$K$2000="trifft nicht zu"))) | J25: =IF($D25="","",IF($E25=0,"keine Anforderungen",IF($F25>0,"erfasst",IF($G25>0,"bewertet",IF($H25>0,"erfüllt","trifft nicht zu")))))
E26: =IF($D26="","",SUMPRODUCT(ISNUMBER(SEARCH($D26,Anforderungen!$J$7:$J$2000))*(Anforderungen!$B$7:$B$2000<>""))) | F26: =IF($D26="","",SUMPRODUCT(ISNUMBER(SEARCH($D26,Anforderungen!$J$7:$J$2000))*(Anforderungen!$K$7:$K$2000="erfasst"))) | G26: =IF($D26="","",SUMPRODUCT(ISNUMBER(SEARCH($D26,Anforderungen!$J$7:$J$2000))*(Anforderungen!$K$7:$K$2000="bewertet"))) | H26: =IF($D26="","",SUMPRODUCT(ISNUMBER(SEARCH($D26,Anforderungen!$J$7:$J$2000))*(Anforderungen!$K$7:$K$2000="erfüllt"))) | I26: =IF($D26="","",SUMPRODUCT(ISNUMBER(SEARCH($D26,Anforderungen!$J$7:$J$2000))*(Anforderungen!$K$7:$K$2000="trifft nicht zu"))) | J26: =IF($D26="","",IF($E26=0,"keine Anforderungen",IF($F26>0,"erfasst",IF($G26>0,"bewertet",IF($H26>0,"erfüllt","trifft nicht zu")))))
E27: =IF($D27="","",SUMPRODUCT(ISNUMBER(SEARCH($D27,Anforderungen!$J$7:$J$2000))*(Anforderungen!$B$7:$B$2000<>""))) | F27: =IF($D27="","",SUMPRODUCT(ISNUMBER(SEARCH($D27,Anforderungen!$J$7:$J$2000))*(Anforderungen!$K$7:$K$2000="erfasst"))) | G27: =IF($D27="","",SUMPRODUCT(ISNUMBER(SEARCH($D27,Anforderungen!$J$7:$J$2000))*(Anforderungen!$K$7:$K$2000="bewertet"))) | H27: =IF($D27="","",SUMPRODUCT(ISNUMBER(SEARCH($D27,Anforderungen!$J$7:$J$2000))*(Anforderungen!$K$7:$K$2000="erfüllt"))) | I27: =IF($D27="","",SUMPRODUCT(ISNUMBER(SEARCH($D27,Anforderungen!$J$7:$J$2000))*(Anforderungen!$K$7:$K$2000="trifft nicht zu"))) | J27: =IF($D27="","",IF($E27=0,"keine Anforderungen",IF($F27>0,"erfasst",IF($G27>0,"bewertet",IF($H27>0,"erfüllt","trifft nicht zu")))))
E28: =IF($D28="","",SUMPRODUCT(ISNUMBER(SEARCH($D28,Anforderungen!$J$7:$J$2000))*(Anforderungen!$B$7:$B$2000<>""))) | F28: =IF($D28="","",SUMPRODUCT(ISNUMBER(SEARCH($D28,Anforderungen!$J$7:$J$2000))*(Anforderungen!$K$7:$K$2000="erfasst"))) | G28: =IF($D28="","",SUMPRODUCT(ISNUMBER(SEARCH($D28,Anforderungen!$J$7:$J$2000))*(Anforderungen!$K$7:$K$2000="bewertet"))) | H28: =IF($D28="","",SUMPRODUCT(ISNUMBER(SEARCH($D28,Anforderungen!$J$7:$J$2000))*(Anforderungen!$K$7:$K$2000="erfüllt"))) | I28: =IF($D28="","",SUMPRODUCT(ISNUMBER(SEARCH($D28,Anforderungen!$J$7:$J$2000))*(Anforderungen!$K$7:$K$2000="trifft nicht zu"))) | J28: =IF($D28="","",IF($E28=0,"keine Anforderungen",IF($F28>0,"erfasst",IF($G28>0,"bewertet",IF($H28>0,"erfüllt","trifft nicht zu")))))
E29: =IF($D29="","",SUMPRODUCT(ISNUMBER(SEARCH($D29,Anforderungen!$J$7:$J$2000))*(Anforderungen!$B$7:$B$2000<>""))) | F29: =IF($D29="","",SUMPRODUCT(ISNUMBER(SEARCH($D29,Anforderungen!$J$7:$J$2000))*(Anforderungen!$K$7:$K$2000="erfasst"))) | G29: =IF($D29="","",SUMPRODUCT(ISNUMBER(SEARCH($D29,Anforderungen!$J$7:$J$2000))*(Anforderungen!$K$7:$K$2000="bewertet"))) | H29: =IF($D29="","",SUMPRODUCT(ISNUMBER(SEARCH($D29,Anforderungen!$J$7:$J$2000))*(Anforderungen!$K$7:$K$2000="erfüllt"))) | I29: =IF($D29="","",SUMPRODUCT(ISNUMBER(SEARCH($D29,Anforderungen!$J$7:$J$2000))*(Anforderungen!$K$7:$K$2000="trifft nicht zu"))) | J29: =IF($D29="","",IF($E29=0,"keine Anforderungen",IF($F29>0,"erfasst",IF($G29>0,"bewertet",IF($H29>0,"erfüllt","trifft nicht zu"))))) | N29: tbd
A31: Das Organigramm liegt im eigenen Reiter „Organigramm“. Es rechnet vollständig aus dieser Tabelle.

Sheet Organigramm
A1: Organigramm – Vergabe- und Komponentenstruktur
A2: SmartInfra → Vergabeeinheit → Partner → Art → Komponente. Jede Box ist mit einer Formelzelle in Spalte Z verknüpft und aktualisiert sich automatisch aus dem Reiter „Komponenten“. Gepflegt wird ausschließlich dort.
Z3: Textquellen der Boxen (Formeln – bitte nicht löschen)
Z4: ="SMARTINFRA"&CHAR(10)&COUNTA(Komponenten!$D$6:$D$29)&" Komponenten / Schnittstellen" -> SMARTINFRA 18 Komponenten / Schnittstellen
Z5: =Komponenten!$A6&CHAR(10)&COUNTIF(Komponenten!$A$6:$A$29,Komponenten!$A6)&IF(COUNTIF(Komponenten!$A$6:$A$29,Komponenten!$A6)=1," Komponente"," Komponenten") -> LIS 1 Komponente
Z6: =Komponenten!$A7&CHAR(10)&COUNTIF(Komponenten!$A$6:$A$29,Komponenten!$A7)&IF(COUNTIF(Komponenten!$A$6:$A$29,Komponenten!$A7)=1," Komponente"," Komponenten") -> WWL 4 Komponenten
Z7: =Komponenten!$A11&CHAR(10)&COUNTIF(Komponenten!$A$6:$A$29,Komponenten!$A11)&IF(COUNTIF(Komponenten!$A$6:$A$29,Komponenten!$A11)=1," Komponente"," Komponenten") -> SmartInfra 8 Komponenten
Z8: =Komponenten!$A18&CHAR(10)&COUNTIF(Komponenten!$A$6:$A$29,Komponenten!$A18)&IF(COUNTIF(Komponenten!$A$6:$A$29,Komponenten!$A18)=1," Komponente"," Komponenten") -> AUP 1 Komponente
Z9: =Komponenten!$A20&CHAR(10)&COUNTIF(Komponenten!$A$6:$A$29,Komponenten!$A20)&IF(COUNTIF(Komponenten!$A$6:$A$29,Komponenten!$A20)=1," Komponente"," Komponenten") -> Zuordnung prüfen 4 Komponenten
Z10: =Komponenten!$B6&CHAR(10)&COUNTIFS(Komponenten!$A$6:$A$29,Komponenten!$A6,Komponenten!$B$6:$B$29,Komponenten!$B6)&IF(COUNTIFS(Komponenten!$A$6:$A$29,Komponenten!$A6,Komponenten!$B$6:$B$29,Komponenten!$B6)=1," Komponente"," Komponenten") -> Alpitronic 1 Komponente
Z11: =Komponenten!$B7&CHAR(10)&COUNTIFS(Komponenten!$A$6:$A$29,Komponenten!$A7,Komponenten!$B$6:$B$29,Komponenten!$B7)&IF(COUNTIFS(Komponenten!$A$6:$A$29,Komponenten!$A7,Komponenten!$B$6:$B$29,Komponenten!$B7)=1," Komponente"," Komponenten") -> eRound 4 Komponenten
Z12: =Komponenten!$B11&CHAR(10)&COUNTIFS(Komponenten!$A$6:$A$29,Komponenten!$A11,Komponenten!$B$6:$B$29,Komponenten!$B11)&IF(COUNTIFS(Komponenten!$A$6:$A$29,Komponenten!$A11,Komponenten!$B$6:$B$29,Komponenten!$B11)=1," Komponente"," Komponenten") -> Reservierungsplattform 2 Komponenten
Z13: =Komponenten!$B13&CHAR(10)&COUNTIFS(Komponenten!$A$6:$A$29,Komponenten!$A13,Komponenten!$B$6:$B$29,Komponenten!$B13)&IF(COUNTIFS(Komponenten!$A$6:$A$29,Komponenten!$A13,Komponenten!$B$6:$B$29,Komponenten!$B13)=1," Komponente"," Komponenten") -> SCS 5 Komponenten
